Workbook

Sheet INSTRUCTIONS
A1: DO NOT EDIT MASTER Market Analysis
A13: To Copy this sheet: File -> Make a copy
A17: Rename File with Title: {INSERT CITY}, {INSERT STATE} Market Analysis
A21: Make sure you move file to Shared Drive Sales and into the Market Analysis Folder

Sheet Accounts
A1: =IFERROR(__xludf.DUMMYFUNCTION("if(eq(COUNTA(A2:A199) - COUNTUNIQUE(A2:A199),0),""Accounts"", ""Accounts - Duplicate Found"")"),"Accounts") | B1: Account Type | C1: Contact Created? | D1: Address | E1: Uptown (Yes or No) | F1: Phone Number | G1: Email | H1: URL | I1: Self Parking Rate | J1: Valet Rate | K1: # of Rooms | L1: Parking Reviews % | M1: Parking Reviews # | N1: GM Name | O1: Management Group | P1: Linked Accounts | Q1: Garage Operator | R1: Valet Operator | S1: Sourcing Notes | T1: Location Notes
A2: Aloft Charlotte City Center | B2: Hotel | D2: 210 E Trade Street, Charlotte, NC, 28202 | E2: YES | F2: =17043331999 | H2: https://www.marriott.com/en-us/Hotels/cltul-aloft-charlotte-city-center/overview/ | I2: 30 | J2: 25 | K2: 175 | L2: 0.17 | M2: 156 | N2: Jay Brown | Q2: Preferred | R2: Preferred Parking
A3: Courtyard By Marriott | B3: Hotel | D3: 237 S Tryon St, Charlotte, NC 28202 | E3: YES | F3: (704) 926-5800 | H3: https://www.marriott.com/en-us/Hotels/cltup-courtyard-charlotte-city-center/overview/?scid=f2ae0541-1279-4f24-b197-a979c79310b0 | I3: 30 | K3: 181 | L3: 0.28 | M3: 95 | N3: Eric Knesel | Q3: LAZ | R3: None | T3: poor parking reviews, security maybe an issue
A4: Fairfield Inn & Suites | B4: Hotel | D4: 201 S McDowell St, Charlotte, NC 28204 | E4: YES | F4: (704) 372-7550 | H4: https://www.marriott.com/en-us/Hotels/cltut-fairfield-inn-and-suites-charlotte-uptown/overview/?scid=f2ae0541-1279-4f24-b197-a979c79310b0 | I4: 25 | K4: 196 | L4: 0.38 | M4: 103 | N4: Bill Moore - Left VM | R4: None | T4: Has really easy parking front drive for enterance, own their own parking deck
A5: Hampton Inn Uptown | B5: Hotel | D5: 530 E M.L.K. Jr Blvd, Charlotte, NC 28202 | E5: YES | H5: https://www.hilton.com/en/Hotels/cltsphx-hampton-suites-charlotte-south-park-at-phillips-place/?SEO_id=GMB-AMER-HX-CLTSPHX&y_source=1_MjA4NDc5MC03MTUtbG9jYXRpb24ud2Vic2l0ZQ%3D%3D | I5: 25 | K5: 250 | L5: 0.38 | M5: 156 | R5: None | T5: Valet only there in the evenings on weekends. no morning valet, left message with the AGM Michelle 6/6/23
A6: Hilton Garden Inn (SouthPark) | B6: Hotel | D6: 4808 Sharon Rd, Charlotte, NC 28210 | E6: NO | F6: (704) 362-5080 | H6: https://www.hilton.com/en/Hotels/cltskgi-hilton-garden-inn-charlotte-southpark/?SEO_id=GMB-AMER-GI-CLTSKGI&y_source=1_ODIxMTQxNS03MTUtbG9jYXRpb24ud2Vic2l0ZQ%3D%3D | I6: 10 | K6: 160 | L6: 0.79 | M6: 38 | N6: Tom Payne (Hours are usually 9-5 | R6: None
A7: Hilton/Hilton Garden Inn | B7: Hotel | D7: 508 E M.L.K. Jr Blvd, Charlotte, NC 28202 | E7: YES | F7: (704) 347-5972 | H7: https://www.hilton.com/en/Hotels/cltupgi-hilton-garden-inn-charlotte-uptown/ | I7: 25 | K7: 181 | L7: 0.39 | M7: 115 | R7: None | T7: Left a message with the GM on 6/6/23 letting them know about us and to give us a call back if valet service was of interested, for the Garden inn.
A8: Home2Suites | B8: Hotel | D8: 610 S Caldwell St, Charlotte, NC 28202 | E8: YES | F8: (980) 500-0085 Ext. for GM is 5002 Email for GM: stephanie.parisi@hilton.com NEW GM COMING 5/31/2022 | H8: https://www.hilton.com/en/Hotels/cltowht-home2-suites-charlotte-uptown/?SEO_id=GMB-AMER-HT-CLTOWHT&y_source=1_MTQ3MjI2OTAtNzE1LWxvY2F0aW9uLndlYnNpdGU%3D | I8: 25 | K8: 180 | L8: 0.26 | M8: 101 | N8: Tameka | R8: None | T8: Poor parking reviews
A9: Hilton Charlotte Uptown | B9: Hotel | D9: 222 East Third Street Charlotte NC 20802 | E9: YES | F9: 7043771500 | I9: 24 | J9: 34 | K9: 149 | L9: 0.51 | M9: 224 | R9: PMC
A10: Le Meridien Charlotte | B10: Hotel | D10: 555 S McDowell St Tower, Charlotte, NC 28204 | E10: YES | I10: 25 | J10: 35 | K10: 300 | L10: 0.25 | M10: 162 | T10: Currently No GM or Director of Ops
A11: Sheraton Hotel | B11: Hotel | D11: 555 S McDowell St Tower, Charlotte, NC 28204 | E11: YES | H11: https://www.marriott.com/en-us/Hotels/cltws-sheraton-charlotte-Hotel/overview/ | I11: 25 | J11: 35 | K11: 305 | L11: 0.24 | M11: 157
A12: The Ivey's Hotel | B12: Hotel | D12: 127 N Tryon St, Charlotte, NC 28202 | E12: YES | H12: https://www.theiveysHotel.com/ | J12: 35 | K12: 47 | L12: 0.52 | M12: 89 | Q12: LAZ | R12: PMC
A13: Hyatt Place | B13: Hotel | D13: 222 S Caldwell St, Charlotte NC 28202 | E13: YES | F13: 7042270500 | G13: Check your email/texts for contact updated | H13: tien.ning@hyatt.com | I13: n/a | J13: 38 | K13: 172 | L13: 0.72 | M13: 484 | N13: Tien Ning | R13: PMC | T13: pretty solid valet reviews. maybe bundled services or damage claim pitching
A14: The Dunhill | B14: Hotel | D14: 237 N Tryon St, Charlotte, NC 28202 | E14: YES | F14: (704) 332-4141 GM Ext. 7101 | H14: https://dunhillHotel.com/ | I14: 23 | J14: 38 | K14: 60 | L14: 0.43 | M14: 74 | Q14: LAZ | R14: In House
A15: AC Hotel Residents inn | B15: Hotel | D15: 220 East Trade Street, Suite 1400, Charlotte, NC, 28202 | E15: YES | F15: 7043484002 | G15: rob.cote@marriott.com | H15: https://www.marriott.com/en-us/Hotels/cltad-ac-Hotel-charlotte-city-center/overview/?scid=f2ae0541-1279-4f24-b197-a979c79310b0 | I15: 29 | J15: 40 | K15: 149 | L15: 0.52 | M15: 117 | N15: Rob Cote | Q15: Preferred | R15: PMC
A16: DoubleTree by Hilton Charlotte-Center City | B16: Hotel | D16: 230 N College Street, Charlotte, NC 28202 | E16: YES | I16: 32 | J16: 40 | K16: 187 | L16: 0.36 | M16: 182 | Q16: Preferred | T16: Not interested, Valet owned by brother of Hotel owner. GM Hung up on me when I asked for point of contact.
A17: Omni Hotel | B17: Hotel | D17: 132 E Trade St, Charlotte, NC 28202 | E17: YES | H17: https://www.omniHotels.com/Hotels/charlotte | J17: 40 | K17: 373 | L17: 0.39 | M17: 270 | Q17: LAZ | R17: PMC
A18: SpringHill | B18: Hotel | D18: 311 E 5th St, Charlotte, NC 28202 | E18: YES | F18: shsuptown@sree.com | H18: https://www.marriott.com/en-us/Hotels/cltsd-springhill-suites-charlotte-city-center/overview/?scid=f2ae0541-1279-4f24-b197-a979c79310b0 | I18: Not available | J18: 40 | K18: 195 | L18: 0.38 | M18: 190 | N18: Karen Owens | R18: PMC
A19: Element Charlotte Uptown | B19: Hotel | D19: 650 S Caldwell Street, Charlotte | E19: YES | F19: abethell@midashospitality.com 980-785-1900 | H19: https://www.marriott.com/search/findHotels.mi?pageType=advanced&searchType=NearAddress&destinationAddress.location=Element+Charlotte+Uptown&nst=paid&cid=PAI_GLB0004YXD_GLE000BIM5_GLF000OETA&ppc=ppc&pId=ustbppc&gad_source=1&gclid=CjwKCAjwvr--BhB5EiwAd5YbXnN16LTeyeEMZgiOqVjMxJLbm-3ljbJBxum8-isbcRtiH4LLoomBrRoCZToQAvD_BwE&gclsrc=aw.ds | J19: 42 | K19: 173 | L19: 0.18 | M19: 22 | N19: Ava Bethell | T19: terrible valet reviews, 67% negative. poor schedule, needs staff, annoyed for tips
A20: Hyatt House Charlotte Center City | B20: Hotel | D20: 435 E Trade St, Charlotte, NC 28202 | E20: YES | I20: n/a | J20: 42 | K20: 163 | L20: 0.41 | M20: 217
A21: Homewood Suites by Hilton Charlotte Uptown | B21: Hotel | D21: 508 N College St, Charlotte, NC 28202 | E21: YES | H21: https://www.hilton.com/en/Hotels/cltuchw-homewood-suites-charlotte-uptown-first-ward/?flexibleDates=false&numRooms=1&numAdults=1&numChildren=0&room1ChildAges=&room1AdultAges=&sessionToken=035f1355-cf11-48a0-a093-93e5c0a0926f | J21: 45 | K21: 211 | L21: 0.39 | M21: 79
A22: Embassy Suites by Hilton Charlotte Uptown | B22: Hotel | D22: 401 E M.L.K. Jr Blvd, Charlotte, NC 28202 | E22: YES | G22: mike.masri@hilton.com | H22: https://www.hilton.com/en/Hotels/cltmles-embassy-suites-charlotte-uptown/?SEO_id=GMB-AMER-ES-CLTMLES&y_source=1_OTUwNTM3MC03MTUtbG9jYXRpb24ud2Vic2l0ZQ%3D%3D | J22: 45 | L22: 0.36 | M22: 296 | N22: Mike Masri
A23: The Westin Charlotte | B23: Hotel | D23: 601 S College St, Charlotte, NC 28202 | E23: YES | F23: (704) 375-2600 | G23: Geoffrey.Cousineau @westin.com | H23: https://www.marriott.com/en-us/Hotels/cltcw-the-westin-charlotte/overview/?scid=f2ae0541-1279-4f24-b197-a979c79310b0 | I23: 35 | J23: 45 | K23: 700 | L23: 0.33 | M23: 243 | N23: Geoffrey Cousineau | R23: LAZ | S23: Marinna.tucker@marriott.com
A24: Grand Bohemian Hotel | B24: Hotel | D24: 201 W Trade St, Charlotte, NC 28202 | E24: YES | F24: (704) 372-1877 | G24: hugh.templeman@kesslercollection.com | H24: https://www.kesslercollection.com/bohemian-charlotte/ | I24: unknown | J24: 48 | K24: 254 | L24: 0.65 | M24: 122 | N24: Hugh Templeman | R24: PMC | T24: Wait for new GM
A25: JW Marriott Charlotte | B25: Hotel | D25: 600 S College St, Charlotte, NC 28202 | E25: YES | F25: David.malmberg@whitelodging.com | H25: https://www.marriott.com/en-us/Hotels/cltjw-jw-marriott-charlotte/overview/ | I25: n/a | J25: 48 | K25: 381 | L25: 0.48 | M25: 87 | R25: PMC | T25: Reviews about the valet are mostly terrible.
A26: Kimpton Tryon Park Hotel | B26: Hotel | D26: 303 S Church St, Charlotte, NC 28202 | E26: YES | F26: 7044477662 (Direct line) | H26: https://www.tryonparkHotel.com/ | J26: 48 | K26: 217 | L26: 0.54 | M26: 162 | N26: Yvette Bullock | Q26: Preferred | R26: PMC | T26: $30 4 hours max Valet
A27: Charlotte Marriott City Center | B27: Hotel | D27: 100 W Trade St, Charlotte, NC 28202 | E27: YES | G27: Annette.Crispin@marriott.com | H27: https://www.marriott.com/en-us/Hotels/cltcc-charlotte-marriott-city-center/overview/?scid=f2ae0541-1279-4f24-b197-a979c79310b0 | J27: 48 | K27: 440 | L27: 0.4 | M27: 181 | N27: Annette Crispin | R27: PMC | T27: poor reviews
A28: Ritz Carlton | B28: Hotel | D28: 201 E Trade St, Charlotte, NC 28202 | E28: YES | F28: Karen.Ayad@Ritzcarlton.com | H28: https://www.ritzcarlton.com/en/Hotels/cltrz-the-ritz-carlton-charlotte/overview/ | J28: 50 | K28: 146 | L28: 0.52 | M28: 48 | R28: In House
A29: Kasa FreeMoreWest Charlotte | B29: Hotel | D29: 2109 Morton St, Charlotte, NC 28208 | E29: South End | F29: (704) 368-4082 | H29: https://kasa.com/properties/kasa-freemorewest-charlotte?utm_source=Google&utm_medium=nonpaid&utm_campaign=GMB&utm_term=VisitHotelWebsiteButton&utm_content=BRY&propertyType=&petsAllowed=&parking&bedCount=1&bedroomCount=0&bathroomCount=1&amenities=&adultGuestCount=1&childGuestCount=0&infantGuestCount=0&travelingForBusiness=false
A30: Canopy by Hilton Charlotte Southpark | B30: Hotel | D30: 4905 Barclay Downs Dr, Charlotte, NC 28210 | E30: NO | F30: 704-552-1715 | G30: Gary.colbert@hilton.com, kerisha2113@gmail.com | I30: 15 | N30: Gary Colbert | S30: Left a voicemail and emailed, they used to have valet and are in talks about bringing it back
A31: Courtyard by Marriott Charlotte SouthPark | B31: Hotel | C31: ='Sales Candence'!B75 | E31: NO | F31: 704-552-7333 | I31: 10 | N31: Matthew Wilhelm | S31: not interested at this time, thanked me for introducing myself
A32: Residence Inn by Marriott Charlotte SouthPark | B32: Hotel | C32: ='Sales Candence'!B76 | D32: 6030 Piedmont Row Dr S, Charlotte, NC 28210 | E32: NO | F32: 704-554-7001 | I32: 10 | S32: Couldn't get past front desk
A33: Renaissance Charlotte SouthPark Hotel | B33: Hotel | C33: ='Sales Candence'!B77 | D33: 5501 Carnegie Blvd, Charlotte, NC 28209 | E33: NO | F33: 704-364-8220 | I33: free | N33: James Gratton, area GM 3x hotels | S33: Called got james email, goes by jim supposedly, sent him an email. no paid parking at 3 locaitons when all rest of hotels in area are charging
A34: Charlotte Marriott SouthPark | B34: Hotel | C34: ='Sales Candence'!B78 | D34: 2200 Rexford Rd, Charlotte, NC 28211 | E34: NO | I34: free | N34: James Gratton, area GM 3x hotels
A35: AC Hotel Charlotte SouthPark | B35: Hotel | C35: ='Sales Candence'!B79 | D35: 1824 Roxborough Rd, Charlotte, NC 28211 | E35: NO | G35: jim.gratton@marriott.com | I35: free | N35: James Gratton, area GM 3x hotels
A36: Hyatt Centric Charlotte SouthPark | B36: Hotel | C36: ='Sales Candence'!B80 | D36: 3100 Apex Dr, Charlotte, NC 28211 | E36: NO | F36: =19802997123 | I36: 10
A37: Homewood Suites by Hilton Charlotte/SouthPark | B37: Hotel | C37: ='Sales Candence'!B81 | D37: 4808 Sharon Rd, Charlotte, NC 28210 | E37: NO | F37: =17044424050 | G37: hgihws@chartwellhospitality.com | I37: 10
A38: DoubleTree Suites by Hilton Hotel Charlotte - SouthPark | B38: Hotel | C38: ='Sales Candence'!B82 | D38: 6300 Carnegie Blvd, Charlotte, NC 28211 | E38: NO | I38: 10
A39: UNC Charlotte Marriott Hotel & Conference Center | B39: Hotel | C39: ='Sales Candence'!B83 | D39: 9041 Robert D. Snyder Rd, Charlotte, NC 28262 | E39: NO | F39: =17049788000 | G39: Thomas.Caramucci@unccharlottemarriott.com | J39: 31 | N39: Thomas Caramucci
A40: Steak 48 | B40: Restaurant | D40: 4425 Sharon Rd, Charlotte, NC 28211 | E40: NO | F40: (704) 996-5586 | I40: 0 | J40: 7 | N40: Katie Kathman
A41: The Capital Grille | B41: Restaurant | D41: 201 N Tryon St, Charlotte, NC 28202 | E41: YES | F41: (617) 293-9284 | I41: 11 | J41: 11 | N41: Armin | R41: SOPHI
A42: Morton's Steakhouse | B42: Restaurant | D42: 227 W Trade St Suite 150, Charlotte, NC 28202 | E42: YES | I42: 17 | J42: 15 | N42: Joan | R42: Park Inc | T42: Valet only operating on Friday and Saturday
A43: Church and Union | B43: Restaurant | D43: 127 N Tryon St #8, Charlotte, NC 28202 | E43: YES | F43: 4077330464. pressley@churchandunion.com | I43: 10 | J43: 15 | N43: Matthew Pressley | R43: Park Inc
A44: Fahrenheit CLT | B44: Restaurant | D44: 222 S Caldwell St 21st Floor, Charlotte, NC 28202 | E44: YES | I44: 15 | J44: 17 | R44: Park Inc
A45: STK Steakhouse | B45: Restaurant | D45: 201 S. College St, Charlotte, NC 28202 | E45: YES | I45: 17 | J45: 17 | N45: Vanessa Batista | R45: SOPHI
A46: La Belle | B46: Restaurant | D46: 300 S Tryon St Suite 100, Charlotte, NC 28202 | E46: YES | F46: (980) 345-7867 | I46: 20 | J46: N/A | N46: Chelsea Ball | R46: None
A47: Cajun Queen | B47: Restaurant | D47: 1800 E 7th St, Charlotte, NC 28204 | E47: YES | I47: N/A | J47: N/A | R47: Park Inc
A48: Bernardin's Restaurant At Ratcliffe | B48: Restaurant | D48: 435 S Tryon St Ste 100, Charlotte, NC 28202 | E48: YES | F48: (704) 332-3188 No email available | I48: validated | J48: N/A | N48: James Allen Walker | R48: None | T48: only validate for 1 1/2 hours
A49: Basil | B49: Restaurant | D49: 210 N Church St, Charlotte, NC 28202 | E49: YES | I49: 15 | J49: N/A | R49: None
A50: Haymaker | B50: Restaurant | D50: 225 S Poplar St, Charlotte, NC 28202 | E50: YES | F50: jacque@haymakerclt.com | I50: Closed | J50: N?A | N50: Jacque | R50: None | S50: None but interested in valet | T50: 2 Blocks away form the baseball stadium
A51: McNinch House Restaurant | B51: Restaurant | D51: 511 N Church St, Charlotte, NC 28202 | E51: YES | I51: Free | J51: N/A
A52: Luce Ristorante & Bar | B52: Restaurant | D52: 214 N Tryon St J, Charlotte, NC 28202 | E52: YES | F52: 7044926898. maria@conterestaurangroup.com | I52: 20 | J52: N/A | R52: None | T52: Might have a deal with the truist garage. Thats where they validate from
A53: Fin&Fino | B53: Restaurant | D53: 135 Levine Avenue of the Arts #100, Charlotte, NC 28202 | E53: YES | F53: 7049096295. jon@rarerootshospitality.com | I53: validated | J53: Not Available | N53: Jon Dressler | R53: None
A54: Forchetta | B54: Restaurant | D54: 230 N College St, Charlotte, NC 28202 | E54: YES | F54: 9802143427. george.beattie@hilton.com | I54: Complimentary | J54: Not Available | N54: George Beattie | R54: None
A55: Indaco | B55: Restaurant | D55: 2046 South Blvd, Charlotte, NC 28203 | E55: South End | F55: (704) 741-9004 | I55: Free: Atherton Mill Deck, surface lots | J55: Not Available | N55: Elizabeth Snodgrass | R55: None
A56: Copper Restaurant | B56: Restaurant | D56: 311 East Blvd, Charlotte, NC 28203 | E56: South End | F56: (704) 333-0063 | I56: Complimentary | J56: Not Available | R56: None
A57: Dolce Osteria | B57: Restaurant | D57: 1710 Kenilworth Ave, Charlotte, NC 28203 | E57: NO | F57: 7043330063 | I57: Free lot on site | J57: N/A | R57: None
A58: The Fig Tree Restaurant | B58: Restaurant | D58: 1601 E 7th St, Charlotte, NC 28204 | E58: YES | F58: (704) 332-3322 | I58: Complimentary after 5 | J58: Not Available | N58: Sara Scheidler | R58: None
A59: The Melting Pot | B59: Restaurant | D59: 901 S Kings Dr #140B, Charlotte, NC 28204 | E59: NO | F59: (704) 334-4400 | I59: Free lot on site | J59: N/A | R59: None
A60: The Cellar at Duckworth's | B60: Restaurant | D60: 330 N Tryon St, Charlotte, NC 28202 | E60: YES | F60: 7049992150 | I60: street parking free all day sat-sun | J60: Not Available | N60: Johnathan Baptist | R60: None
A61: Ri Ra | B61: Restaurant | D61: 208 N Tryon St, Charlotte, NC 28202 | E61: YES | F61: (704) 333-5554 | G61: bradypatterson@rira.com | I61: 15 | J61: N/A | N61: Brady Patterson | R61: None
A62: McCormick &Schmick's Seafood &Steaks | B62: Restaurant | D62: 200 S Tryon St, Charlotte, NC 28202 | E62: YES | F62: (704) 377-0201 | I62: Closed | J62: Closed | R62: Closed
A63: Firebirds Wood Fired Grill | B63: Restaurant | D63: 3920 Sharon Rd, Charlotte, NC 28211 | E63: NO | F63: (704) 366-3655 | I63: Free lot on site | J63: N/A | R63: None
A64: Del Frisco's Double Eagle Steakhouse | B64: Restaurant | D64: 4725 Piedmont Row Dr Suite 170, Charlotte, NC 28210 | E64: NO | F64: (704) 552-5502 | I64: Free garage on site | J64: N/A | R64: None
A65: Mariposa | B65: Restaurant | D65: 500 S Tryon St, Charlotte, NC 28202 | E65: YES | I65: 12 | J65: N/A | R65: None
A66: 204 North | B66: Restaurant | D66: 204 N Tryon St, Charlotte, NC 28202 | E66: YES | F66: (704) 910-9891 | I66: no validate | J66: N/A | N66: Katelyn Gearhart and Chris Cooper - Chris@masonjargroup.com | R66: None
A67: Deluxe The Fun Art of Dining | B67: Restaurant | D67: 305 W 4th St, Charlotte, NC 28202 | E67: YES | F67: (980) 237-8042 | I67: $10-$25 | J67: N/A | R67: None
A68: Sea Level NC | B68: Restaurant | D68: 129 E 5th St, Charlotte, NC 28202 | E68: YES | F68: (704) 412-2616 | I68: validate | J68: Not Available | N68: Can't do valet due to truist center garage deal | R68: None | T68: mlight@eat704.com
A69: Red Salt by David Burke | B69: Restaurant | D69: 555 S McDowell St Charlotte, NC 28204 | E69: YES | F69: 704-516-6422 | I69: $5 per hour* | J69: N/A | N69: Steve Johnson | R69: None
A70: Chima Steakhouse | B70: Restaurant | D70: 139 S Tryon St, Charlotte, NC 28202 | E70: YES | F70: (980) 293-1030 | I70: N/A | J70: 15 | N70: Vini | R70: SOPHI
A71: Eddie V's Prime Seafood | B71: Restaurant | D71: 101 S Tryon St Suite 100, Charlotte, NC 28280 (Still Uptown) | E71: YES | F71: Have the card in ym car, just have to find it | I71: $6 per half hour. $30 Max | J71: Complimentary for resturant. Transient $15 first 3 hours. $30 for 3-6 hours | N71: Andrew | R71: Preferred Parking
A72: Dean's Italian Steakhouse | B72: Restaurant | D72: 128 E Stonewall St, Charlotte, NC 28202 | E72: YES | F72: 7044996626 | G72: natalie.shulman@whitelodging.com | J72: $15 she thinks | N72: Natalie Shulman | Q72: LAZ | R72: PMC
A73: Fleming's Prime Steakhouse & Wine Bar | B73: Restaurant | D73: 210 E Trade St Suite C-110, Charlotte, NC 28202 | E73: YES | F73: =17043334266 | I73: $6 per half hour (QCQ) | J73: $17 for guest $13 to resturant | N73: Robert Fritschle | R73: Preferred Parking | S73: Preferred QCQG
A74: 204 kitchen + cocktails | B74: Restaurant | D74: 204 North tryon Street, Charlotte, NC 28202 | E74: YES | F74: =17043333747 | I74: $6 per half hour (QCQ) | J74: $17 for guest $13 to resturant | R74: Preferred Parking | S74: Preferred QCQG
A75: The Palm | B75: Restaurant | D75: 6705-B, Phillips Pl Ct, Charlotte, NC 28210 | E75: NO | F75: (704) 552-7450 | I75: no validation | J75: complimentary | R75: Park Inc
A76: Sullivan's Steakhouse | B76: Restaurant | D76: 1928 South Blvd Suite 200 Suite 200, Charlotte, NC 28203 | E76: South End | F76: (919)833-2888 | I76: No Self-Parking | J76: Complimentary Valet | N76: Christopher Rodgers | R76: Park Inc | T76: free for 2 hours
A77: Aria and Cicchetti | B77: Restaurant | D77: 100 N Tryon St, Charlotte, NC 28202 | E77: YES | F77: =17043768880 | I77: Validated | J77: Complimentary Valet | R77: Park Inc
A78: Dressler's Steakhouse | B78: Restaurant | D78: 1100 Metropolitan Ave #125, Charlotte, NC 28204 | E78: YES | F78: (877) 626-1183 | I78: Free for 4 hours | J78: Complimentary Valet
A79: Ruth's Chris | B79: Restaurant | D79: 222 S Tryon St, Charlotte, NC 28202 | E79: YES | F79: (704) 261-5202 | I79: N/A | J79: 15 | N79: Eric | R79: SOPHI
A80: Ruth's Chris #2 | B80: Restaurant | D80: 6000 Fairview Rd, Charlotte, NC 28210 | E80: NO | F80: (704)-726-3200 | I80: FREE | J80: Valet "temporaliy suspended" | N80: Kristen Brodosi | R80: Park Inc
A81: Oak Steakhouse | B81: Restaurant | D81: 4777 Sharon Rd Suite 125, Charlotte, NC 28210 | E81: NO | F81: =17049548900 | I81: FREE all day | J81: Valet "temporaliy suspended" | R81: None
C84: ='Sales Candence'!B84
C85: ='Sales Candence'!B85
C86: ='Sales Candence'!B86
C87: ='Sales Candence'!B87
C88: ='Sales Candence'!B88
C89: ='Sales Candence'!B89
C90: ='Sales Candence'!B90
C91: ='Sales Candence'!B91
C92: ='Sales Candence'!B92
C93: ='Sales Candence'!B93
C94: ='Sales Candence'!B94
C95: ='Sales Candence'!B95
... C1059: ='Sales Candence'!B1059

Sheet Sales Candence
A1: =Accounts!A1 | B1: Contact Created? | C1: =Accounts!N1 | D1: GM Contact Info | E1: =Accounts!F1 | F1: =Accounts!Q1 | G1: =Accounts!R1 | H1: =Accounts!I1 | I1: =Accounts!J1 | J1: =Accounts!S1 | K1: SALES NOTES | M1: 1 | N1: 2 | O1: 3 | P1: 4 | Q1: 5 | R1: 6 | S1: 7 | T1: 8 | U1: 9 | V1: 10
A2: =Accounts!A2 | B2: TRUE | C2: =Accounts!N2 | E2: =Accounts!F2 | F2: =Accounts!Q2 | G2: =Accounts!R2 | H2: =Accounts!I2 | I2: =Accounts!J2 | J2: =Accounts!S2 | K2: This is the section to write down notes while in calls or meetings. However, make sure to still track in hubspot. | M2: FALSE | N2: FALSE | O2: FALSE | P2: FALSE | Q2: FALSE | R2: FALSE | S2: FALSE | T2: FALSE | U2: FALSE | V2: FALSE
A3: =Accounts!A3 | B3: FALSE | C3: =Accounts!N3 | E3: =Accounts!F3 | F3: =Accounts!Q3 | G3: =Accounts!R3 | H3: =Accounts!I3 | I3: =Accounts!J3 | J3: =Accounts!S3 | K3: ->> Add drop downs instead of check boxes to give more information | M3: FALSE | N3: FALSE | O3: FALSE | P3: FALSE | Q3: FALSE | R3: FALSE | S3: FALSE | T3: FALSE | U3: FALSE | V3: FALSE
A4: =Accounts!A4 | B4: FALSE | C4: =Accounts!N4 | E4: =Accounts!F4 | F4: =Accounts!Q4 | G4: =Accounts!R4 | H4: =Accounts!I4 | I4: =Accounts!J4 | J4: =Accounts!S4 | M4: FALSE | N4: FALSE | O4: FALSE | P4: FALSE | Q4: FALSE | R4: FALSE | S4: FALSE | T4: FALSE | U4: FALSE | V4: FALSE
A5: =Accounts!A5 | B5: FALSE | C5: =Accounts!N5 | E5: =Accounts!F5 | F5: =Accounts!Q5 | G5: =Accounts!R5 | H5: =Accounts!I5 | I5: =Accounts!J5 | J5: =Accounts!S5 | M5: FALSE | N5: FALSE | O5: FALSE | P5: FALSE | Q5: FALSE | R5: FALSE | S5: FALSE | T5: FALSE | U5: FALSE | V5: FALSE
A6: =Accounts!A6 | B6: FALSE | C6: =Accounts!N6 | E6: =Accounts!F6 | F6: =Accounts!Q6 | G6: =Accounts!R6 | H6: =Accounts!I6 | I6: =Accounts!J6 | J6: =Accounts!S6 | M6: FALSE | N6: FALSE | O6: FALSE | P6: FALSE | Q6: FALSE | R6: FALSE | S6: FALSE | T6: FALSE | U6: FALSE | V6: FALSE
A7: =Accounts!A7 | B7: FALSE | C7: =Accounts!N7 | E7: =Accounts!F7 | F7: =Accounts!Q7 | G7: =Accounts!R7 | H7: =Accounts!I7 | I7: =Accounts!J7 | J7: =Accounts!S7 | M7: FALSE | N7: FALSE | O7: FALSE | P7: FALSE | Q7: FALSE | R7: FALSE | S7: FALSE | T7: FALSE | U7: FALSE | V7: FALSE
A8: =Accounts!A8 | B8: FALSE | C8: =Accounts!N8 | E8: =Accounts!F8 | F8: =Accounts!Q8 | G8: =Accounts!R8 | H8: =Accounts!I8 | I8: =Accounts!J8 | J8: =Accounts!S8 | M8: FALSE | N8: FALSE | O8: FALSE | P8: FALSE | Q8: FALSE | R8: FALSE | S8: FALSE | T8: FALSE | U8: FALSE | V8: FALSE
A9: =Accounts!A9 | B9: FALSE | C9: =Accounts!N9 | E9: =Accounts!F9 | F9: =Accounts!Q9 | G9: =Accounts!R9 | H9: =Accounts!I9 | I9: =Accounts!J9 | J9: =Accounts!S9 | M9: FALSE | N9: FALSE | O9: FALSE | P9: FALSE | Q9: FALSE | R9: FALSE | S9: FALSE | T9: FALSE | U9: FALSE | V9: FALSE
A10: =Accounts!A10 | B10: FALSE | C10: =Accounts!N10 | E10: =Accounts!F10 | F10: =Accounts!Q10 | G10: =Accounts!R10 | H10: =Accounts!I10 | I10: =Accounts!J10 | J10: =Accounts!S10 | M10: FALSE | N10: FALSE | O10: FALSE | P10: FALSE | Q10: FALSE | R10: FALSE | S10: FALSE | T10: FALSE | U10: FALSE | V10: FALSE
A11: =Accounts!A11 | B11: FALSE | C11: =Accounts!N11 | E11: =Accounts!F11 | F11: =Accounts!Q11 | G11: =Accounts!R11 | H11: =Accounts!I11 | I11: =Accounts!J11 | J11: =Accounts!S11 | M11: FALSE | N11: FALSE | O11: FALSE | P11: FALSE | Q11: FALSE | R11: FALSE | S11: FALSE | T11: FALSE | U11: FALSE | V11: FALSE
A12: =Accounts!A12 | B12: FALSE | C12: =Accounts!N12 | E12: =Accounts!F12 | F12: =Accounts!Q12 | G12: =Accounts!R12 | H12: =Accounts!I12 | I12: =Accounts!J12 | J12: =Accounts!S12 | M12: FALSE | N12: FALSE | O12: FALSE | P12: FALSE | Q12: FALSE | R12: FALSE | S12: FALSE | T12: FALSE | U12: FALSE | V12: FALSE
A13: =Accounts!A13 | B13: FALSE | C13: =Accounts!N13 | E13: =Accounts!F13 | F13: =Accounts!Q13 | G13: =Accounts!R13 | H13: =Accounts!I13 | I13: =Accounts!J13 | J13: =Accounts!S13 | M13: FALSE | N13: FALSE | O13: FALSE | P13: FALSE | Q13: FALSE | R13: FALSE | S13: FALSE | T13: FALSE | U13: FALSE | V13: FALSE
A14: =Accounts!A14 | B14: FALSE | C14: =Accounts!N14 | E14: =Accounts!F14 | F14: =Accounts!Q14 | G14: =Accounts!R14 | H14: =Accounts!I14 | I14: =Accounts!J14 | J14: =Accounts!S14 | M14: FALSE | N14: FALSE | O14: FALSE | P14: FALSE | Q14: FALSE | R14: FALSE | S14: FALSE | T14: FALSE | U14: FALSE | V14: FALSE
A15: =Accounts!A15 | B15: FALSE | C15: =Accounts!N15 | E15: =Accounts!F15 | F15: =Accounts!Q15 | G15: =Accounts!R15 | H15: =Accounts!I15 | I15: =Accounts!J15 | J15: =Accounts!S15 | M15: FALSE | N15: FALSE | O15: FALSE | P15: FALSE | Q15: FALSE | R15: FALSE | S15: FALSE | T15: FALSE | U15: FALSE | V15: FALSE
... A75: =Accounts!A75 | B75: FALSE | C75: =Accounts!N75 | E75: =Accounts!F75 | F75: =Accounts!Q75 | G75: =Accounts!R75 | H75: =Accounts!I75 | I75: =Accounts!J75 | J75: =Accounts!S75 | M75: FALSE | N75: FALSE | O75: FALSE | P75: FALSE | Q75: FALSE | R75: FALSE | S75: FALSE | T75: FALSE | U75: FALSE | V75: FALSE
A76: =Accounts!A76 | B76: FALSE | C76: =Accounts!N77 | E76: =Accounts!F76 | F76: =Accounts!Q76 | G76: =Accounts!R76 | H76: =Accounts!I76 | I76: =Accounts!J76 | J76: =Accounts!S76 | M76: FALSE | N76: FALSE | O76: FALSE | P76: FALSE | Q76: FALSE | R76: FALSE | S76: FALSE | T76: FALSE | U76: FALSE | V76: FALSE
A77: =Accounts!A77 | B77: FALSE | C77: =#REF! | E77: =Accounts!F77 | F77: =Accounts!Q77 | G77: =Accounts!R77 | H77: =Accounts!I77 | I77: =Accounts!J77 | J77: =Accounts!S77 | M77: FALSE | N77: FALSE | O77: FALSE | P77: FALSE | Q77: FALSE | R77: FALSE | S77: FALSE | T77: FALSE | U77: FALSE | V77: FALSE
A78: =Accounts!A78 | B78: FALSE | C78: =Accounts!N78 | E78: =Accounts!F78 | F78: =Accounts!Q78 | G78: =Accounts!R78 | H78: =Accounts!I78 | I78: =Accounts!J78 | J78: =Accounts!S78 | M78: FALSE | N78: FALSE | O78: FALSE | P78: FALSE | Q78: FALSE | R78: FALSE | S78: FALSE | T78: FALSE | U78: FALSE | V78: FALSE
A79: =Accounts!A79 | B79: FALSE | C79: =Accounts!N79 | E79: =Accounts!F79 | F79: =Accounts!Q79 | G79: =Accounts!R79 | H79: =Accounts!I79 | I79: =Accounts!J79 | J79: =Accounts!S79 | M79: FALSE | N79: FALSE | O79: FALSE | P79: FALSE | Q79: FALSE | R79: FALSE | S79: FALSE | T79: FALSE | U79: FALSE | V79: FALSE
A80: =Accounts!A80 | B80: FALSE | C80: =Accounts!N80 | E80: =Accounts!F80 | F80: =Accounts!Q80 | G80: =Accounts!R80 | H80: =Accounts!I80 | I80: =Accounts!J80 | J80: =Accounts!S80 | M80: FALSE | N80: FALSE | O80: FALSE | P80: FALSE | Q80: FALSE | R80: FALSE | S80: FALSE | T80: FALSE | U80: FALSE | V80: FALSE
A81: =Accounts!A81 | B81: FALSE | C81: =Accounts!N81 | E81: =Accounts!F81 | F81: =Accounts!Q81 | G81: =Accounts!R81 | H81: =Accounts!I81 | I81: =Accounts!J81 | J81: =Accounts!S81 | M81: FALSE | N81: FALSE | O81: FALSE | P81: FALSE | Q81: FALSE | R81: FALSE | S81: FALSE | T81: FALSE | U81: FALSE | V81: FALSE
A82: =Accounts!A82 | B82: FALSE | C82: =Accounts!N82 | E82: =Accounts!F82 | F82: =Accounts!Q82 | G82: =Accounts!R82 | H82: =Accounts!I82 | I82: =Accounts!J82 | J82: =Accounts!S82 | M82: FALSE | N82: FALSE | O82: FALSE | P82: FALSE | Q82: FALSE | R82: FALSE | S82: FALSE | T82: FALSE | U82: FALSE | V82: FALSE
A83: =Accounts!A83 | B83: FALSE | C83: =Accounts!N83 | E83: =Accounts!F83 | F83: =Accounts!Q83 | G83: =Accounts!R83 | H83: =Accounts!I83 | I83: =Accounts!J83 | J83: =Accounts!S83 | M83: FALSE | N83: FALSE | O83: FALSE | P83: FALSE | Q83: FALSE | R83: FALSE | S83: FALSE | T83: FALSE | U83: FALSE | V83: FALSE
A84: =Accounts!A84 | B84: FALSE | C84: =Accounts!N84 | E84: =Accounts!F84 | F84: =Accounts!Q84 | G84: =Accounts!R84 | H84: =Accounts!I84 | I84: =Accounts!J84 | J84: =Accounts!S84 | M84: FALSE | N84: FALSE | O84: FALSE | P84: FALSE | Q84: FALSE | R84: FALSE | S84: FALSE | T84: FALSE | U84: FALSE | V84: FALSE
A85: =Accounts!A85 | B85: FALSE | C85: =Accounts!N85 | E85: =Accounts!F85 | F85: =Accounts!Q85 | G85: =Accounts!R85 | H85: =Accounts!I85 | I85: =Accounts!J85 | J85: =Accounts!S85 | M85: FALSE | N85: FALSE | O85: FALSE | P85: FALSE | Q85: FALSE | R85: FALSE | S85: FALSE | T85: FALSE | U85: FALSE | V85: FALSE
A86: =Accounts!A86 | B86: FALSE | C86: =Accounts!N86 | E86: =Accounts!F86 | F86: =Accounts!Q86 | G86: =Accounts!R86 | H86: =Accounts!I86 | I86: =Accounts!J86 | J86: =Accounts!S86 | M86: FALSE | N86: FALSE | O86: FALSE | P86: FALSE | Q86: FALSE | R86: FALSE | S86: FALSE | T86: FALSE | U86: FALSE | V86: FALSE
A87: =Accounts!A87 | B87: FALSE | C87: =Accounts!N87 | E87: =Accounts!F87 | F87: =Accounts!Q87 | G87: =Accounts!R87 | H87: =Accounts!I87 | I87: =Accounts!J87 | J87: =Accounts!S87 | M87: FALSE | N87: FALSE | O87: FALSE | P87: FALSE | Q87: FALSE | R87: FALSE | S87: FALSE | T87: FALSE | U87: FALSE | V87: FALSE
A88: =Accounts!A88 | B88: FALSE | C88: =Accounts!N88 | E88: =Accounts!F88 | F88: =Accounts!Q88 | G88: =Accounts!R88 | H88: =Accounts!I88 | I88: =Accounts!J88 | J88: =Accounts!S88 | M88: FALSE | N88: FALSE | O88: FALSE | P88: FALSE | Q88: FALSE | R88: FALSE | S88: FALSE | T88: FALSE | U88: FALSE | V88: FALSE
A89: =Accounts!A89 | B89: FALSE | C89: =Accounts!N89 | E89: =Accounts!F89 | F89: =Accounts!Q89 | G89: =Accounts!R89 | H89: =Accounts!I89 | I89: =Accounts!J89 | J89: =Accounts!S89 | M89: FALSE | N89: FALSE | O89: FALSE | P89: FALSE | Q89: FALSE | R89: FALSE | S89: FALSE | T89: FALSE | U89: FALSE | V89: FALSE
... A1000: =Accounts!A1000 | B1000: FALSE | C1000: =Accounts!N1000 | E1000: =Accounts!F1000 | F1000: =Accounts!Q1000 | G1000: =Accounts!R1000 | H1000: =Accounts!I1000 | I1000: =Accounts!J1000 | J1000: =Accounts!S1000 | M1000: FALSE | N1000: FALSE | O1000: FALSE | P1000: FALSE | Q1000: FALSE | R1000: FALSE | S1000: FALSE | T1000: FALSE | U1000: FALSE | V1000: FALSE
B1001: FALSE | C1001: =Accounts!N1001 | E1001: =Accounts!F1001 | F1001: =Accounts!Q1001 | G1001: =Accounts!R1001 | H1001: =Accounts!I1001 | I1001: =Accounts!J1001 | J1001: =Accounts!S1001 | M1001: FALSE | N1001: FALSE | O1001: FALSE | P1001: FALSE | Q1001: FALSE | R1001: FALSE | S1001: FALSE | T1001: FALSE | U1001: FALSE | V1001: FALSE
B1002: FALSE | C1002: =Accounts!N1002 | E1002: =Accounts!F1002 | F1002: =Accounts!Q1002 | G1002: =Accounts!R1002 | H1002: =Accounts!I1002 | I1002: =Accounts!J1002 | J1002: =Accounts!S1002 | M1002: FALSE | N1002: FALSE | O1002: FALSE | P1002: FALSE | Q1002: FALSE | R1002: FALSE | S1002: FALSE | T1002: FALSE | U1002: FALSE | V1002: FALSE
B1003: FALSE | C1003: =Accounts!N1003 | E1003: =Accounts!F1003 | F1003: =Accounts!Q1003 | G1003: =Accounts!R1003 | H1003: =Accounts!I1003 | I1003: =Accounts!J1003 | J1003: =Accounts!S1003 | M1003: FALSE | N1003: FALSE | O1003: FALSE | P1003: FALSE | Q1003: FALSE | R1003: FALSE | S1003: FALSE | T1003: FALSE | U1003: FALSE | V1003: FALSE
B1004: FALSE | C1004: =Accounts!N1004 | E1004: =Accounts!F1004 | F1004: =Accounts!Q1004 | G1004: =Accounts!R1004 | H1004: =Accounts!I1004 | I1004: =Accounts!J1004 | J1004: =Accounts!S1004 | M1004: FALSE | N1004: FALSE | O1004: FALSE | P1004: FALSE | Q1004: FALSE | R1004: FALSE | S1004: FALSE | T1004: FALSE | U1004: FALSE | V1004: FALSE
B1005: FALSE | C1005: =Accounts!N1005 | E1005: =Accounts!F1005 | F1005: =Accounts!Q1005 | G1005: =Accounts!R1005 | H1005: =Accounts!I1005 | I1005: =Accounts!J1005 | J1005: =Accounts!S1005 | M1005: FALSE | N1005: FALSE | O1005: FALSE | P1005: FALSE | Q1005: FALSE | R1005: FALSE | S1005: FALSE | T1005: FALSE | U1005: FALSE | V1005: FALSE
B1006: FALSE | C1006: =Accounts!N1006 | E1006: =Accounts!F1006 | F1006: =Accounts!Q1006 | G1006: =Accounts!R1006 | H1006: =Accounts!I1006 | I1006: =Accounts!J1006 | J1006: =Accounts!S1006 | M1006: FALSE | N1006: FALSE | O1006: FALSE | P1006: FALSE | Q1006: FALSE | R1006: FALSE | S1006: FALSE | T1006: FALSE | U1006: FALSE | V1006: FALSE
B1007: FALSE | C1007: =Accounts!N1007 | E1007: =Accounts!F1007 | F1007: =Accounts!Q1007 | G1007: =Accounts!R1007 | H1007: =Accounts!I1007 | I1007: =Accounts!J1007 | J1007: =Accounts!S1007 | M1007: FALSE | N1007: FALSE | O1007: FALSE | P1007: FALSE | Q1007: FALSE | R1007: FALSE | S1007: FALSE | T1007: FALSE | U1007: FALSE | V1007: FALSE
B1008: FALSE | C1008: =Accounts!N1008 | E1008: =Accounts!F1008 | F1008: =Accounts!Q1008 | G1008: =Accounts!R1008 | H1008: =Accounts!I1008 | I1008: =Accounts!J1008 | J1008: =Accounts!S1008 | M1008: FALSE | N1008: FALSE | O1008: FALSE | P1008: FALSE | Q1008: FALSE | R1008: FALSE | S1008: FALSE | T1008: FALSE | U1008: FALSE | V1008: FALSE
B1009: FALSE | C1009: =Accounts!N1009 | E1009: =Accounts!F1009 | F1009: =Accounts!Q1009 | G1009: =Accounts!R1009 | H1009: =Accounts!I1009 | I1009: =Accounts!J1009 | J1009: =Accounts!S1009 | M1009: FALSE | N1009: FALSE | O1009: FALSE | P1009: FALSE | Q1009: FALSE | R1009: FALSE | S1009: FALSE | T1009: FALSE | U1009: FALSE | V1009: FALSE
B1010: FALSE | C1010: =Accounts!N1010 | E1010: =Accounts!F1010 | F1010: =Accounts!Q1010 | G1010: =Accounts!R1010 | H1010: =Accounts!I1010 | I1010: =Accounts!J1010 | J1010: =Accounts!S1010 | M1010: FALSE | N1010: FALSE | O1010: FALSE | P1010: FALSE | Q1010: FALSE | R1010: FALSE | S1010: FALSE | T1010: FALSE | U1010: FALSE | V1010: FALSE
B1011: FALSE | C1011: =Accounts!N1011 | E1011: =Accounts!F1011 | F1011: =Accounts!Q1011 | G1011: =Accounts!R1011 | H1011: =Accounts!I1011 | I1011: =Accounts!J1011 | J1011: =Accounts!S1011 | M1011: FALSE | N1011: FALSE | O1011: FALSE | P1011: FALSE | Q1011: FALSE | R1011: FALSE | S1011: FALSE | T1011: FALSE | U1011: FALSE | V1011: FALSE
B1012: FALSE | C1012: =Accounts!N1012 | E1012: =Accounts!F1012 | F1012: =Accounts!Q1012 | G1012: =Accounts!R1012 | H1012: =Accounts!I1012 | I1012: =Accounts!J1012 | J1012: =Accounts!S1012 | M1012: FALSE | N1012: FALSE | O1012: FALSE | P1012: FALSE | Q1012: FALSE | R1012: FALSE | S1012: FALSE | T1012: FALSE | U1012: FALSE | V1012: FALSE
... B1059: FALSE | C1059: =Accounts!N1059 | E1059: =Accounts!F1059 | F1059: =Accounts!Q1059 | G1059: =Accounts!R1059 | H1059: =Accounts!I1059 | I1059: =Accounts!J1059 | J1059: =Accounts!S1059 | M1059: FALSE | N1059: FALSE | O1059: FALSE | P1059: FALSE | Q1059: FALSE | R1059: FALSE | S1059: FALSE | T1059: FALSE | U1059: FALSE | V1059: FALSE

Sheet Parking
A1: Loaction ID | B1: Location Name | C1: Location Type | D1: Address | E1: # Spaces | F1: Unreserved Monthly Rate | G1: Operator | H1: Point of Contact | I1: POC Number | J1: URL | K1: Notes | L1: PARCs Equipment Notes
B2: Charlotte Marriott City Center | C2: Underground | D2: 100 W Trade St | E2: 320 | F2: N/A | G2: Preferred | I2: (704)-333-9000 | K2: Customer parking only;
B3: Avenue Condominium | C3: Covered | D3: 210 N Church St | E3: N/A | F3: N/A | G3: N/A | J3: N/A
B4: IVEY's Garage | C4: Garage | D4: 120 N Church St | E4: 226 | F4: N/A | G4: LAZ | J4: https://lazparking.com/local/charlotte-nc/ivey-garage | K4: Monthly parking only
B5: Fifth-Third Center | C5: Garage | D5: 201 N Tryon St | E5: 930 | F5: N/A | G5: LAZ | J5: https://www.lazparking.com/local/charlotte-nc/fifth-third
B6: Discovery Place Science | C6: Garage | D6: 220 W 6th St | E6: 316 | F6: N/A | G6: Discovery Place | J6: https://science.discoveryplace.org/plan#parking | K6: Visitor Parking Only
B7: 401 W Pine St | C7: Lot | D7: 401 W Pine St | E7: 115 | F7: 135 | G7: Preferred | J7: https://www.preferredparking.com/dailyparking_clt/default.aspx
B8: The VUE Charlotte | C8: Garage | D8: 410 W 5th St | E8: N/A | F8: 250 | G8: The VUE | I8: (704)-333-2533 | K8: Free validation
B9: 309 W Trade St | C9: Lot | D9: 309 W Trade St | E9: 255 | F9: 190 | G9: Preferred | J9: https://www.preferredparking.com/dailyparking_clt/default.aspx | K9: Open all day Mon-Sat; No parking 6am-12N on Sunday
B10: 401 N. Tryon Garage | C10: Underground | D10: 401 N Tryon St | E10: 1101 | F10: N/A | G10: LAZ | J10: https://www.lazparking.com/local/charlotte-nc/401-north-tryon
B11: 101 Independance Center Parking Facility | C11: Underground | D11: 101 N Tryon St | E11: 320 | F11: N/A | G11: LAZ | J11: https://www.lazparking.com/local/charlotte-nc/101-independence-center | K11: On-sight car wash!
B12: 123 S Church St | C12: Garage | D12: 123 S Church St | E12: 275 | F12: 205 | G12: Preferred | J12: N/A | K12: Maximum stay 2 days
B13: Carillon Garage | C13: Garage | D13: 160 S Poplar St | E13: 832 | F13: N/A | G13: SP Plus Corparation | I13: (980)-224-1065
B14: 124 S Poplar St | C14: Lot | D14: 124 S Poplar St | E14: 105 | F14: 169 | G14: Preferred | J14: https://www.preferredparking.com/dailyparking_clt/default.aspx
B15: Auto Park | C15: Lot | D15: 206 S Church St | E15: 40 | F15: N/A | G15: Preferred | J15: https://www.preferredparking.com/dailyparking_clt/default.aspx
B16: Auto Park | C16: Garage | D16: 206 S Church St | E16: 690 | F16: 185 | G16: Preferred | J16: https://www.preferredparking.com/dailyparking_clt/default.aspx
B17: 208 S Poplar St | C17: Lot | D17: 208 S Poplar St | E17: 160 | F17: 169 | G17: Preferred | J17: https://www.preferredparking.com/dailyparking_clt/default.aspx
B18: 400 South Tryon Street Garage | C18: Garage | D18: 400 S Tryon St | E18: 495 | F18: N/A | G18: Preferred | J18: https://www.preferredparking.com/dailyparking_clt/default.aspx
B19: 330 South Tryon Street Garage | C19: Garage | D19: 330 S Tryon St | E19: 250 | F19: 198 | G19: Preferred | J19: https://www.preferredparking.com/dailyparking_clt/default.aspx
B20: 300 South Tryon Street Garage | C20: Garage | D20: 300 S Tryon St | E20: 408 | F20: N/A | G20: Preferred | J20: https://www.preferredparking.com/dailyparking_clt/default.aspx
B21: 230 South Tryon Street Garage | C21: Garage | D21: 100 W Third St | E21: 670 | F21: N/A | G21: Spectrum Parking LLC | I21: (704)-358-1000
B22: 228 S Church St | C22: Lot | D22: 228 S Church St | E22: 35 | F22: N/A | G22: Preferred | J22: https://www.preferredparking.com/dailyparking_clt/default.aspx
B23: First Citizens Bank Plaza Garage | C23: Garage | D23: 205 S Church St | E23: 697 | F23: 195 | G23: Preferred | J23: https://www.preferredparking.com/dailyparking_clt/default.aspx
B24: 121 West Trade | C24: Garage | D24: 121 W Trade St | E24: 264 | F24: N/A | G24: Preferred | J24: https://www.preferredparking.com/dailyparking_clt/default.aspx
B25: Epicentre Parking / Queen City Quarter | C25: Garage | D25: 101 S College St | E25: 982 | F25: 179 | G25: Preferred | J25: https://www.preferredparking.com/dailyparking_clt/default.aspx
B26: Bank of America Plaza (One South At the Plaza) | C26: Garage | D26: 101 S Tryon St | E26: 459 | F26: 200 | G26: LAZ | J26: https://go.lazparking.com/subnow?l=351&start=2023-11-15T22:00:00.000Z
B27: 300 S. Brevard Garage | C27: Garage | D27: 300 S. Brevard St. | E27: 720 | F27: $75/$173 | G27: Preferred | J27: https://www.preferredparking.com/dailyparking_clt/default.aspx
B28: 402 E 3rd St | C28: Lot | D28: 402 E 3rd St | E28: 45 | F28: $150 | G28: Preferred | J28: https://www.preferredparking.com/dailyparking_clt/default.aspx
B29: 415 E. 4th St | C29: Lot | D29: 415 E 4th St | E29: 29 | F29: 140 | G29: Preferred | J29: https://www.preferredparking.com/dailyparking_clt/default.aspx
B30: 402 E 4th St | C30: Lot | D30: 402 E 4th St | E30: 180 | F30: 150 | G30: Preferred | J30: https://www.preferredparking.com/dailyparking_clt/default.aspx
B31: Location #20 | C31: Lot | D31: 210 S Brevard St | E31: 380 | F31: 160 | G31: Preferred | J31: https://www.preferredparking.com/dailyparking_clt/default.aspx
B32: Preferred Parking Lot #406 | C32: Lot | D32: 407 E 4th St | E32: 180 | F32: 150 | G32: Preferred | J32: https://www.preferredparking.com/dailyparking_clt/default.aspx
B33: 426 E Trade St | C33: Lot | D33: 426 E Trade St | E33: 47 | F33: 150 | G33: Preferred | J33: https://www.preferredparking.com/dailyparking_clt/default.aspx
B34: Charlotte Plaza | C34: Garage | D34: 201 S College St | E34: 980 | F34: 175 | G34: Charlotte | J34: https://parking.com/charlotte/parking-near/35.22462560/-80.84200160/306-e-4th-st/?lot_id=20383&showListOnly=1&view=daily&facility&valet&general=&displayFullCity=0&start=2023-12-28T14%3A00&stop=2023-12-28T14%3A30&sw=35.21071788363375,-80.86408062727335&ne=35.2381351005086,-80.8207577726999 | K34: 5pm to 4am 10 sat-sun allday untill 4 am 10
B35: One Wells Fargo Center Parking Garage | C35: Garage | D35: 301 S College St | E35: 1119 | F35: $165/$205 | G35: CK Parking | I35: (704)-342-9030 | K35: Customer parking only
B36: Two Wells Fargo Center Parking Garage | C36: Garage | D36: 301 S Tryon St | E36: 525 | F36: 152 | G36: CK Parking | I36: (704)-944-1830
B37: Omni Charlotte | C37: Garage | D37: 132 E Trade St | E37: N/A | F37: N/A | G37: In-house | I37: (704)-377-0400
B38: 237 S Tryon Garage | C38: Garage | D38: 237 S Tryon St | E38: 689 | F38: 195 | G38: Preferred | J38: https://www.preferredparking.com/dailyparking_clt/default.aspx
B39: 200 S College St | C39: Garage | D39: 200 S College St | E39: 1500 | F39: 200 | G39: LAZ | J39: https://www.lazparking.com/local/charlotte--nc/bbt-center | K39: $17 early bird mon-fri 8am out 3pm
B40: Bank of America Center Garage | C40: Garage | D40: 150 N College St | E40: 1200 | F40: N/A | G40: LAZ | I40: (704)-331-0055
B41: Hyatt House Charlotte | C41: Garage | D41: 435 E Trade St | E41: N/A | F41: N/A | G41: In-house | J41: https://www.hyatt.com/hyatt-house/en-US/cltxd-hyatt-house-charlotte-center-city/Hotel-info
B42: 424 N College St | C42: Lot | D42: 424 N College St | E42: 103 | F42: N/A | G42: Preferred | J42: https://www.preferredparking.com/dailyparking_clt/default.aspx
B43: 219 E 7th St | C43: Lot | D43: 219 E 7th St | E43: 233 | F43: N/A | G43: Preferred | J43: https://www.preferredparking.com/dailyparking_clt/default.aspx
B44: Truist Center | C44: Covered | D44: 214 N Tryon St | E44: 1400 | F44: N/A | G44: Preferred | J44: https://www.preferredparking.com/dailyparking_clt/default.aspx
B45: Seventh Street Station | C45: Garage | D45: 225 E 6th St | E45: 1600 | F45: N/A | G45: LAZ | I45: (704)-344-8446
B46: ImaginOn: The Joe & Joan Martin Center | C46: Underground | D46: 311 E 6th St | E46: N/A | F46: N/A | G46: Preferred | J46: https://www.preferredparking.com/dailyparking_clt/default.aspx | K46: Refer to parkopedia page: too much info
B47: City Center Green | C47: Garage | D47: 350 E 6th St | E47: 1380 | F47: 120 | G47: City Center Green LLC | I47: (704) 716-9876
B48: 418 E 6th St | C48: Lot | D48: 418 E 6th St | E48: 84 | F48: N/A | G48: Southland Parking | I48: (704)-451-7846
B49: SpringHill Suites Charlotte City Center | C49: Garage | D49: 311 E 5th St | E49: 1380 | F49: N/A | G49: Parking Management | I49: (704)-439-8100 | K49: Valet & Customer Only
B50: Wake Forest University Charlotte Center Garage | C50: Garage | D50: 209 E 5th St | E50: 801 | F50: 170 | G50: Preferred | J50: https://www.preferredparking.com/dailyparking_clt/default.aspx
B51: Design Center Garage | C51: Garage | D51: 240 Hawkins St. South End
B52: 300 South Brevard Garage | C52: Garage | D52: 300 S. Brevard St
B53: Hyatt place Garage | C53: Garage | D53: 222 S Caldwell st | E53: N/A
B54: JW Marriott's Garage | C54: garage | D54: 122 E Brooklyn Village
B55: Element/Home2 garage | C55: Garage | D55: 400 E Brooklyn Village | E55: n/a
B56: Sheraton Garage | C56: Garage | D56: 555 S McDowell St | E56: 1390
B57: City Center Green | C57: Garage | D57: 316 E 6th St | E57: 1380
B58: Harvey B Gantt center | C58: Garage | D58: 615 S College

Sheet RevenueForecasting
A1: Account | B1: Account Type | C1: Valet Operator | D1: # of Rooms | E1: Occupancy Rate | F1: Forecast | G1: Valet Conversion Rate | H1: Estimated Daily Valet Count | I1: Estimated Daily Revenue | J1: Estimated Annual Revenue | K1: Estimate Net Operating Income Annually | L1: Total Daily Rev | M1: Total Annual Rev | N1: Total Annual NOI
A2: =Accounts!A2 | B2: Restaurant | D2: =Accounts!K2 | E2: 0.6 | F2: =Accounts!K2*E2 | G2: 0.4 | H2: =F2*G2 | I2: =if(or(eq(Accounts!J2,"No Valet"),eq(Accounts!J2,"Has Valet")), H2 * AVERAGE(Accounts!J$2:J$36),H2*Accounts!J2) | J2: =iferror(I2*360,"") | K2: =J2*0.1 | L2: =sum(I2:I72) | M2: =sum(J2:J72) | N2: =sum(K2:K72)
A3: =Accounts!A3 | B3: Hotel | C3: Preferred Parking | D3: =Accounts!K3 | E3: 0.6 | F3: =Accounts!K3*E3 | G3: 0.4 | H3: =F3*G3 | I3: =if(or(eq(Accounts!J3,"No Valet"),eq(Accounts!J3,"Has Valet")), H3 * AVERAGE(Accounts!J$2:J$36),H3*Accounts!J3) | J3: =iferror(I3*360,"") | K3: =J3*0.2 | M3: =sum(J3:J72) | N3: =sum(K3:K72)*2
A4: =Accounts!A4 | B4: Hotel | C4: None | D4: =Accounts!K4 | E4: 0.6 | F4: =Accounts!K4*E4 | G4: 0.4 | H4: =F4*G4 | I4: =H4*40 | J4: =iferror(I4*360,"") | K4: =J4*0.2
A5: =Accounts!A5 | B5: Restaurant | C5: SOPHI | D5: =Accounts!K5 | E5: 0.6 | F5: =Accounts!K5*E5 | G5: 0.4 | H5: =F5*G5 | I5: =if(or(eq(Accounts!J5,"No Valet"),eq(Accounts!J5,"Has Valet")), H5 * AVERAGE(Accounts!J$2:J$36),H5*Accounts!J5) | J5: 100000 | K5: =J5*0.25
A6: =Accounts!A6 | B6: Restaurant | C6: Park Inc | D6: =Accounts!K6 | E6: 0.6 | F6: =Accounts!K6*E6 | G6: 0.4 | H6: =F6*G6 | I6: =if(or(eq(Accounts!J6,"No Valet"),eq(Accounts!J6,"Has Valet")), H6 * AVERAGE(Accounts!J$2:J$36),H6*Accounts!J6) | J6: 150000 | K6: =J6*0.25
A7: =Accounts!A7 | B7: Hotel | C7: None | D7: =Accounts!K7 | E7: 0.6 | F7: =Accounts!K7*E7 | G7: 0.4 | H7: =F7*G7 | I7: =H7*40 | J7: =iferror(I7*360,"") | K7: =J7*0.1
A8: =Accounts!A8 | B8: Restaurant | C8: Park Inc | D8: =Accounts!K8 | E8: 0.6 | F8: =Accounts!K8*E8 | G8: 0.4 | H8: =F8*G8 | I8: =if(or(eq(Accounts!J8,"No Valet"),eq(Accounts!J8,"Has Valet")), H8 * AVERAGE(Accounts!J$2:J$36),H8*Accounts!J8) | J8: 150000 | K8: =J8*0.25
A9: =Accounts!A9 | B9: Hotel | C9: None | D9: =Accounts!K9 | E9: 0.6 | F9: =Accounts!K9*E9 | G9: 0.4 | H9: =F9*G9 | I9: =H9*40 | J9: =iferror(I9*360,"") | K9: =J9*0.1
A10: =Accounts!A10 | B10: Restaurant | C10: Park Inc | D10: =Accounts!K10 | E10: 0.6 | F10: =Accounts!K10*E10 | G10: 0.4 | H10: =F10*G10 | I10: =if(or(eq(Accounts!J10,"No Valet"),eq(Accounts!J10,"Has Valet")), H10 * AVERAGE(Accounts!J$2:J$36),H10*Accounts!J10) | J10: 150000 | K10: =J10*0.25
A11: =Accounts!A11 | B11: Hotel | C11: None | D11: =Accounts!K11 | E11: 0.6 | F11: =Accounts!K11*E11 | G11: 0.4 | H11: =F11*G11 | I11: =H11*40 | J11: =iferror(I11*360,"") | K11: =J11*0.1
A12: =Accounts!A12 | B12: Hotel | C12: None | D12: =Accounts!K12 | E12: 0.6 | F12: =Accounts!K12*E12 | G12: 0.4 | H12: =F12*G12 | I12: =H12*40 | J12: =iferror(I12*360,"") | K12: =J12*0.1
A13: =Accounts!A13 | B13: Hotel | C13: None | D13: =Accounts!K13 | E13: 0.6 | F13: =Accounts!K13*E13 | G13: 0.4 | H13: =F13*G13 | I13: =H13*40 | J13: =iferror(I13*360,"") | K13: =J13*0.1
A14: =Accounts!A14 | B14: Restaurant | C14: SOPHI | D14: =Accounts!K14 | E14: 0.6 | F14: =Accounts!K14*E14 | G14: 0.4 | H14: =F14*G14 | I14: =if(or(eq(Accounts!J14,"No Valet"),eq(Accounts!J14,"Has Valet")), H14 * AVERAGE(Accounts!J$2:J$36),H14*Accounts!J14) | J14: 150000 | K14: =J14*0.25
A15: =Accounts!A15 | B15: Hotel | C15: PMC | D15: =Accounts!K15 | E15: 0.6 | F15: =Accounts!K15*E15 | G15: 0.4 | H15: =F15*G15 | I15: =if(or(eq(Accounts!J15,"No Valet"),eq(Accounts!J15,"Has Valet")), H15 * AVERAGE(Accounts!J$2:J$36),H15*Accounts!J15) | J15: =iferror(I15*360,"") | K15: =J15*0.1
A16: =Accounts!A16 | B16: Hotel | D16: =Accounts!K16 | E16: 0.6 | F16: =Accounts!K16*E16 | G16: 0.4 | H16: =F16*G16 | I16: =if(or(eq(Accounts!J16,"No Valet"),eq(Accounts!J16,"Has Valet")), H16 * AVERAGE(Accounts!J$2:J$36),H16*Accounts!J16) | J16: =iferror(I16*360,"") | K16: =J16*0.1
A17: =Accounts!A17 | B17: Hotel | D17: =Accounts!K17 | E17: 0.6 | F17: =Accounts!K17*E17 | G17: 0.4 | H17: =F17*G17 | I17: =if(or(eq(Accounts!J17,"No Valet"),eq(Accounts!J17,"Has Valet")), H17 * AVERAGE(Accounts!J$2:J$36),H17*Accounts!J17) | J17: =iferror(I17*360,"") | K17: =J17*0.1
A18: =Accounts!A18 | B18: Hotel | C18: PMC | D18: =Accounts!K18 | E18: 0.6 | F18: =Accounts!K18*E18 | G18: 0.4 | H18: =F18*G18 | I18: =if(or(eq(Accounts!J18,"No Valet"),eq(Accounts!J18,"Has Valet")), H18 * AVERAGE(Accounts!J$2:J$36),H18*Accounts!J18) | J18: =iferror(I18*360,"") | K18: =J18*0.1
A19: =Accounts!A19 | B19: Hotel | C19: PMC | D19: =Accounts!K19 | E19: 0.6 | F19: =Accounts!K19*E19 | G19: 0.4 | H19: =F19*G19 | I19: =if(or(eq(Accounts!J19,"No Valet"),eq(Accounts!J19,"Has Valet")), H19 * AVERAGE(Accounts!J$2:J$36),H19*Accounts!J19) | J19: =iferror(I19*360,"") | K19: =J19*0.1
A20: =Accounts!A20 | B20: Hotel | C20: In House | D20: =Accounts!K20 | E20: 0.6 | F20: =Accounts!K20*E20 | G20: 0.4 | H20: =F20*G20 | I20: =if(or(eq(Accounts!J20,"No Valet"),eq(Accounts!J20,"Has Valet")), H20 * AVERAGE(Accounts!J$2:J$36),H20*Accounts!J20) | J20: =iferror(I20*360,"") | K20: =J20*0.1
A21: =Accounts!A21 | B21: Hotel | C21: PMC | D21: =Accounts!K21 | E21: 0.6 | F21: =Accounts!K21*E21 | G21: 0.4 | H21: =F21*G21 | I21: =if(or(eq(Accounts!J21,"No Valet"),eq(Accounts!J21,"Has Valet")), H21 * AVERAGE(Accounts!J$2:J$36),H21*Accounts!J21) | J21: =iferror(I21*360,"") | K21: =J21*0.1
A22: =Accounts!A22 | B22: Hotel | D22: =Accounts!K22 | E22: 0.6 | F22: =Accounts!K22*E22 | G22: 0.4 | H22: =F22*G22 | I22: =if(or(eq(Accounts!J22,"No Valet"),eq(Accounts!J22,"Has Valet")), H22 * AVERAGE(Accounts!J$2:J$36),H22*Accounts!J22) | J22: =iferror(I22*360,"") | K22: =J22*0.1
A23: =Accounts!A23 | B23: Hotel | C23: PMC | D23: =Accounts!K23 | E23: 0.6 | F23: =Accounts!K23*E23 | G23: 0.4 | H23: =F23*G23 | I23: =if(or(eq(Accounts!J23,"No Valet"),eq(Accounts!J23,"Has Valet")), H23 * AVERAGE(Accounts!J$2:J$36),H23*Accounts!J23) | J23: =iferror(I23*360,"") | K23: =J23*0.1
A24: =Accounts!A24 | B24: Restaurant | C24: None | D24: =Accounts!K24 | E24: 0.6 | F24: =Accounts!K24*E24 | G24: 0.4 | H24: =F24*G24 | I24: =if(or(eq(Accounts!J24,"No Valet"),eq(Accounts!J24,"Has Valet")), H24 * AVERAGE(Accounts!J$2:J$36),H24*Accounts!J24) | J24: 100000 | K24: =J24*0.1
A25: =Accounts!A25 | B25: Restaurant | C25: Park Inc | D25: =Accounts!K25 | E25: 0.6 | F25: =Accounts!K25*E25 | G25: 0.4 | H25: =F25*G25 | I25: =if(or(eq(Accounts!J25,"No Valet"),eq(Accounts!J25,"Has Valet")), H25 * AVERAGE(Accounts!J$2:J$36),H25*Accounts!J25) | J25: 150000 | K25: =J25*0.25
A26: =Accounts!A26 | B26: Hotel | C26: PMC | D26: =Accounts!K26 | E26: 0.6 | F26: =Accounts!K26*E26 | G26: 0.4 | H26: =F26*G26 | I26: =if(or(eq(Accounts!J26,"No Valet"),eq(Accounts!J26,"Has Valet")), H26 * AVERAGE(Accounts!J$2:J$36),H26*Accounts!J26) | J26: =iferror(I26*360,"") | K26: =J26*0.1
A27: =Accounts!A27 | B27: Restaurant | C27: None | D27: =Accounts!K27 | E27: 0.6 | F27: =Accounts!K27*E27 | G27: 0.4 | H27: =F27*G27 | I27: =if(or(eq(Accounts!J27,"No Valet"),eq(Accounts!J27,"Has Valet")), H27 * AVERAGE(Accounts!J$2:J$36),H27*Accounts!J27) | J27: 100000 | K27: =J27*0.1
A28: =Accounts!A28 | B28: Restaurant | C28: None | D28: =Accounts!K28 | E28: 0.6 | F28: =Accounts!K28*E28 | G28: 0.4 | H28: =F28*G28 | I28: =if(or(eq(Accounts!J28,"No Valet"),eq(Accounts!J28,"Has Valet")), H28 * AVERAGE(Accounts!J$2:J$36),H28*Accounts!J28) | J28: 100000 | K28: =J28*0.1
A29: =Accounts!A29 | B29: Restaurant | C29: None | D29: =Accounts!K29 | E29: 0.6 | F29: =Accounts!K29*E29 | G29: 0.4 | H29: =F29*G29 | I29: =if(or(eq(Accounts!J29,"No Valet"),eq(Accounts!J29,"Has Valet")), H29 * AVERAGE(Accounts!J$2:J$36),H29*Accounts!J29) | J29: 100000 | K29: =J29*0.1
A30: =Accounts!A30 | B30: Restaurant | D30: =Accounts!K30 | E30: 0.6 | F30: =Accounts!K30*E30 | G30: 0.4 | H30: =F30*G30 | I30: =if(or(eq(Accounts!J30,"No Valet"),eq(Accounts!J30,"Has Valet")), H30 * AVERAGE(Accounts!J$2:J$36),H30*Accounts!J30) | J30: =iferror(I30*360,"") | K30: =J30*0.1
A31: =Accounts!A31 | B31: Restaurant | C31: None | D31: =Accounts!K31 | E31: 0.6 | F31: =Accounts!K31*E31 | G31: 0.4 | H31: =F31*G31 | I31: =if(or(eq(Accounts!J31,"No Valet"),eq(Accounts!J31,"Has Valet")), H31 * AVERAGE(Accounts!J$2:J$36),H31*Accounts!J31) | J31: 100000 | K31: =J31*0.1
A32: =Accounts!A32 | B32: Restaurant | C32: None | D32: =Accounts!K32 | E32: 0.6 | F32: =Accounts!K32*E32 | G32: 0.4 | H32: =F32*G32 | I32: =if(or(eq(Accounts!J32,"No Valet"),eq(Accounts!J32,"Has Valet")), H32 * AVERAGE(Accounts!J$2:J$36),H32*Accounts!J32) | J32: 100000 | K32: =J32*0.1
A33: =Accounts!A33 | B33: Restaurant | C33: None | D33: =Accounts!K33 | E33: 0.6 | F33: =Accounts!K33*E33 | G33: 0.4 | H33: =F33*G33 | I33: =if(or(eq(Accounts!J33,"No Valet"),eq(Accounts!J33,"Has Valet")), H33 * AVERAGE(Accounts!J$2:J$36),H33*Accounts!J33) | J33: 100000 | K33: =J33*0.1
A34: =Accounts!A34 | B34: Hotel | D34: =Accounts!K34 | E34: 0.6 | F34: =Accounts!K34*E34 | G34: 0.4 | H34: =F34*G34 | I34: =if(or(eq(Accounts!J34,"No Valet"),eq(Accounts!J34,"Has Valet")), H34 * AVERAGE(Accounts!J$2:J$36),H34*Accounts!J34) | J34: =iferror(I34*360,"") | K34: =J34*0.1
A35: =Accounts!A35 | B35: Restaurant | C35: None | D35: =Accounts!K35 | E35: 0.6 | F35: =Accounts!K35*E35 | G35: 0.4 | H35: =F35*G35 | I35: =if(or(eq(Accounts!J35,"No Valet"),eq(Accounts!J35,"Has Valet")), H35 * AVERAGE(Accounts!J$2:J$36),H35*Accounts!J35) | J35: 100000 | K35: =J35*0.1
A36: =Accounts!A36 | B36: Restaurant | C36: None | D36: =Accounts!K36 | E36: 0.6 | F36: =Accounts!K36*E36 | G36: 0.4 | H36: =F36*G36 | I36: =if(or(eq(Accounts!J36,"No Valet"),eq(Accounts!J36,"Has Valet")), H36 * AVERAGE(Accounts!J$2:J$36),H36*Accounts!J36) | J36: 100000 | K36: =J36*0.1
A37: =Accounts!A37 | B37: Restaurant | C37: None | D37: =Accounts!K37 | E37: 0.6 | F37: =Accounts!K37*E37 | G37: 0.4 | H37: =F37*G37 | I37: =if(or(eq(Accounts!J37,"No Valet"),eq(Accounts!J37,"Has Valet")), H37 * AVERAGE(Accounts!J$2:J$36),H37*Accounts!J37) | J37: 100000 | K37: =J37*0.1
A38: =Accounts!A38 | B38: Restaurant | C38: None | D38: =Accounts!K38 | E38: 0.6 | F38: =Accounts!K38*E38 | G38: 0.4 | H38: =F38*G38 | I38: =if(or(eq(Accounts!J38,"No Valet"),eq(Accounts!J38,"Has Valet")), H38 * AVERAGE(Accounts!J$2:J$36),H38*Accounts!J38) | J38: 100000 | K38: =J38*0.1
A39: =Accounts!A39 | B39: Hotel | D39: =Accounts!K39 | E39: 0.6 | F39: =Accounts!K39*E39 | G39: 0.4 | H39: =F39*G39 | I39: =if(or(eq(Accounts!J39,"No Valet"),eq(Accounts!J39,"Has Valet")), H39 * AVERAGE(Accounts!J$2:J$36),H39*Accounts!J39) | J39: =iferror(I39*360,"") | K39: =J39*0.1
A40: =Accounts!A40 | B40: Restaurant | C40: None | D40: =Accounts!K40 | E40: 0.6 | F40: =Accounts!K40*E40 | G40: 0.4 | H40: =F40*G40 | I40: =if(or(eq(Accounts!J40,"No Valet"),eq(Accounts!J40,"Has Valet")), H40 * AVERAGE(Accounts!J$2:J$36),H40*Accounts!J40) | J40: 100000 | K40: =J40*0.1
A41: =Accounts!A41 | B41: Restaurant | C41: None | D41: =Accounts!K41 | E41: 0.6 | F41: =Accounts!K41*E41 | G41: 0.4 | H41: =F41*G41 | I41: =if(or(eq(Accounts!J41,"No Valet"),eq(Accounts!J41,"Has Valet")), H41 * AVERAGE(Accounts!J$2:J$36),H41*Accounts!J41) | J41: 100000 | K41: =J41*0.1
A42: =Accounts!A42 | B42: Restaurant | C42: None | D42: =Accounts!K42 | E42: 0.6 | F42: =Accounts!K42*E42 | G42: 0.4 | H42: =F42*G42 | I42: =if(or(eq(Accounts!J42,"No Valet"),eq(Accounts!J42,"Has Valet")), H42 * AVERAGE(Accounts!J$2:J$36),H42*Accounts!J42) | J42: 100000 | K42: =J42*0.1
A43: =Accounts!A43 | B43: Hotel | D43: =Accounts!K43 | E43: 0.6 | F43: =Accounts!K43*E43 | G43: 0.4 | H43: =F43*G43 | I43: =if(or(eq(Accounts!J43,"No Valet"),eq(Accounts!J43,"Has Valet")), H43 * AVERAGE(Accounts!J$2:J$36),H43*Accounts!J43) | J43: =iferror(I43*360,"") | K43: =J43*0.1
A44: =Accounts!A44 | B44: Hotel | D44: =Accounts!K44 | E44: 0.6 | F44: =Accounts!K44*E44 | G44: 0.4 | H44: =F44*G44 | I44: =if(or(eq(Accounts!J44,"No Valet"),eq(Accounts!J44,"Has Valet")), H44 * AVERAGE(Accounts!J$2:J$36),H44*Accounts!J44) | J44: =iferror(I44*360,"") | K44: =J44*0.1
A45: =Accounts!A45 | B45: Hotel | C45: LAZ | D45: =Accounts!K45 | E45: 0.6 | F45: =Accounts!K45*E45 | G45: 0.4 | H45: =F45*G45 | I45: =if(or(eq(Accounts!J45,"No Valet"),eq(Accounts!J45,"Has Valet")), H45 * AVERAGE(Accounts!J$2:J$36),H45*Accounts!J45) | J45: =iferror(I45*360,"") | K45: =J45*0.1
A46: =Accounts!A46 | B46: Restaurant | C46: Closed | D46: =Accounts!K46 | E46: 0.6 | F46: =Accounts!K46*E46 | G46: 0.4 | H46: =F46*G46 | I46: =if(or(eq(Accounts!J46,"No Valet"),eq(Accounts!J46,"Has Valet")), H46 * AVERAGE(Accounts!J$2:J$36),H46*Accounts!J46) | J46: =iferror(I46*360,"") | K46: =J46*0.1
A47: =Accounts!A47 | B47: Restaurant | C47: None | D47: =Accounts!K47 | E47: 0.6 | F47: =Accounts!K47*E47 | G47: 0.4 | H47: =F47*G47 | I47: =if(or(eq(Accounts!J47,"No Valet"),eq(Accounts!J47,"Has Valet")), H47 * AVERAGE(Accounts!J$2:J$36),H47*Accounts!J47) | J47: 100000 | K47: =J47*0.1
A48: =Accounts!A48 | B48: Restaurant | C48: None | D48: =Accounts!K48 | E48: 0.6 | F48: =Accounts!K48*E48 | G48: 0.4 | H48: =F48*G48 | I48: =if(or(eq(Accounts!J48,"No Valet"),eq(Accounts!J48,"Has Valet")), H48 * AVERAGE(Accounts!J$2:J$36),H48*Accounts!J48) | J48: 100000 | K48: =J48*0.1
A49: =Accounts!A49 | B49: Hotel | C49: PMC | D49: =Accounts!K49 | E49: 0.6 | F49: =Accounts!K49*E49 | G49: 0.4 | H49: =F49*G49 | I49: =if(or(eq(Accounts!J49,"No Valet"),eq(Accounts!J49,"Has Valet")), H49 * AVERAGE(Accounts!J$2:J$36),H49*Accounts!J49) | J49: =iferror(I49*360,"") | K49: =J49*0.1
A50: =Accounts!A50 | B50: Hotel | C50: PMC | D50: =Accounts!K50 | E50: 0.6 | F50: =Accounts!K50*E50 | G50: 0.4 | H50: =F50*G50 | I50: =if(or(eq(Accounts!J50,"No Valet"),eq(Accounts!J50,"Has Valet")), H50 * AVERAGE(Accounts!J$2:J$36),H50*Accounts!J50) | J50: =iferror(I50*360,"") | K50: =J50*0.1
A51: =Accounts!A51 | B51: Hotel | C51: PMC | D51: =Accounts!K51 | E51: 0.6 | F51: =Accounts!K51*E51 | G51: 0.4 | H51: =F51*G51 | I51: =if(or(eq(Accounts!J51,"No Valet"),eq(Accounts!J51,"Has Valet")), H51 * AVERAGE(Accounts!J$2:J$36),H51*Accounts!J51) | J51: =iferror(I51*360,"") | K51: =J51*0.1
A52: =Accounts!A52 | B52: Restaurant | C52: None | D52: =Accounts!K52 | E52: 0.6 | F52: =Accounts!K52*E52 | G52: 0.4 | H52: =F52*G52 | I52: =if(or(eq(Accounts!J52,"No Valet"),eq(Accounts!J52,"Has Valet")), H52 * AVERAGE(Accounts!J$2:J$36),H52*Accounts!J52) | J52: 100000 | K52: =J52*0.1
A53: =Accounts!A53 | B53: Hotel | C53: PMC | D53: 446 | E53: 0.6 | F53: =D53*E53 | G53: 0.4 | H53: =F53*G53 | I53: =if(or(eq(Accounts!J53,"No Valet"),eq(Accounts!J53,"Has Valet")), H53 * AVERAGE(Accounts!J$2:J$36),H53*Accounts!J53) | J53: =iferror(I53*360,"") | K53: =J53*0.1
A54: =Accounts!A54 | B54: Restaurant | C54: None | D54: =Accounts!K54 | E54: 0.6 | F54: =Accounts!K54*E54 | G54: 0.4 | H54: =F54*G54 | I54: =if(or(eq(Accounts!J54,"No Valet"),eq(Accounts!J54,"Has Valet")), H54 * AVERAGE(Accounts!J$2:J$36),H54*Accounts!J54) | J54: 100000 | K54: =J54*0.1
A55: =Accounts!A55 | B55: Restaurant | C55: None | D55: =Accounts!K55 | E55: 0.6 | F55: =Accounts!K55*E55 | G55: 0.4 | H55: =F55*G55 | I55: =if(or(eq(Accounts!J55,"No Valet"),eq(Accounts!J55,"Has Valet")), H55 * AVERAGE(Accounts!J$2:J$36),H55*Accounts!J55) | J55: 100000 | K55: =J55*0.1
A56: =Accounts!A56 | B56: Restaurant | C56: None | D56: =Accounts!K56 | E56: 0.6 | F56: =Accounts!K56*E56 | G56: 0.4 | H56: =F56*G56 | I56: =if(or(eq(Accounts!J56,"No Valet"),eq(Accounts!J56,"Has Valet")), H56 * AVERAGE(Accounts!J$2:J$36),H56*Accounts!J56) | J56: 100000 | K56: =J56*0.1
A57: =Accounts!A57 | B57: Restaurant | C57: None | D57: =Accounts!K57 | E57: 0.6 | F57: =Accounts!K57*E57 | G57: 0.4 | H57: =F57*G57 | I57: =if(or(eq(Accounts!J57,"No Valet"),eq(Accounts!J57,"Has Valet")), H57 * AVERAGE(Accounts!J$2:J$36),H57*Accounts!J57) | J57: 100000 | K57: =J57*0.1
A58: =Accounts!A58 | B58: Restaurant | C58: SOPHI | D58: =Accounts!K58 | E58: 0.6 | F58: =Accounts!K58*E58 | G58: 0.4 | H58: =F58*G58 | I58: =if(or(eq(Accounts!J58,"No Valet"),eq(Accounts!J58,"Has Valet")), H58 * AVERAGE(Accounts!J$2:J$36),H58*Accounts!J58) | J58: 225000 | K58: =J58*0.25
A59: =Accounts!A59 | B59: Hotel | C59: In House | D59: =Accounts!K59 | E59: 0.6 | F59: =Accounts!K59*E59 | G59: 0.4 | H59: =F59*G59 | I59: =if(or(eq(Accounts!J59,"No Valet"),eq(Accounts!J59,"Has Valet")), H59 * AVERAGE(Accounts!J$2:J$36),H59*Accounts!J59) | J59: =iferror(I59*360,"") | K59: =J59*0.1
A60: =Accounts!A60 | B60: Restaurant | C60: Preferred Parking | D60: =Accounts!K60 | E60: 0.6 | F60: =Accounts!K60*E60 | G60: 0.4 | H60: =F60*G60 | I60: =if(or(eq(Accounts!J60,"No Valet"),eq(Accounts!J60,"Has Valet")), H60 * AVERAGE(Accounts!J$2:J$36),H60*Accounts!J60) | J60: 225000 | K60: =J60*0.25
A61: =Accounts!A61 | B61: Restaurant | C61: PMC | D61: =Accounts!K61 | E61: 0.6 | F61: =Accounts!K61*E61 | G61: 0.4 | H61: =F61*G61 | I61: =if(or(eq(Accounts!J61,"No Valet"),eq(Accounts!J61,"Has Valet")), H61 * AVERAGE(Accounts!J$2:J$36),H61*Accounts!J61) | J61: 100000 | K61: =J61*0.25
A62: =Accounts!A62 | B62: Restaurant | C62: Preferred Parking | D62: =Accounts!K62 | E62: 0.6 | F62: =Accounts!K62*E62 | G62: 0.4 | H62: =F62*G62 | I62: =if(or(eq(Accounts!J62,"No Valet"),eq(Accounts!J62,"Has Valet")), H62 * AVERAGE(Accounts!J$2:J$36),H62*Accounts!J62) | J62: 100000 | K62: =J62*0.25
A63: =Accounts!A63 | D63: =Accounts!K53 | E63: 0.6 | F63: =Accounts!K53*E63 | G63: 0.4 | H63: =F63*G63 | I63: =if(or(eq(Accounts!J63,"No Valet"),eq(Accounts!J63,"Has Valet")), H63 * AVERAGE(Accounts!J$2:J$36),H63*Accounts!J63) | J63: =iferror(I63*360,"") | K63: =J63*0.1
A64: =Accounts!A64 | D64: =Accounts!K64 | E64: 0.6 | F64: =Accounts!K64*E64 | G64: 0.4 | H64: =F64*G64 | I64: =if(or(eq(Accounts!J64,"No Valet"),eq(Accounts!J64,"Has Valet")), H64 * AVERAGE(Accounts!J$2:J$36),H64*Accounts!J64) | J64: =iferror(I64*360,"") | K64: =J64*0.1
A65: =Accounts!A65 | B65: Restaurant | C65: Preferred Parking | D65: =Accounts!K65 | E65: 0.6 | F65: =Accounts!K65*E65 | G65: 0.4 | H65: =F65*G65 | I65: =if(or(eq(Accounts!J65,"No Valet"),eq(Accounts!J65,"Has Valet")), H65 * AVERAGE(Accounts!J$2:J$36),H65*Accounts!J65) | J65: 100000 | K65: =J65*0.25
A66: =Accounts!A66 | B66: Restaurant | C66: Park Inc | D66: =Accounts!K66 | E66: 0.6 | F66: =Accounts!K66*E66 | G66: 0.4 | H66: =F66*G66 | I66: =if(or(eq(Accounts!J66,"No Valet"),eq(Accounts!J66,"Has Valet")), H66 * AVERAGE(Accounts!J$2:J$36),H66*Accounts!J66) | J66: 100000 | K66: =J66*0.25
A67: =Accounts!A67 | B67: Restaurant | C67: Park Inc | D67: =Accounts!K67 | E67: 0.6 | F67: =Accounts!K67*E67 | G67: 0.4 | H67: =F67*G67 | I67: =if(or(eq(Accounts!J67,"No Valet"),eq(Accounts!J67,"Has Valet")), H67 * AVERAGE(Accounts!J$2:J$36),H67*Accounts!J67) | J67: 100000 | K67: =J67*0.25
A68: =Accounts!A68 | B68: Restaurant | C68: Park Inc | D68: =Accounts!K68 | E68: 0.6 | F68: =Accounts!K68*E68 | G68: 0.4 | H68: =F68*G68 | I68: =if(or(eq(Accounts!J68,"No Valet"),eq(Accounts!J68,"Has Valet")), H68 * AVERAGE(Accounts!J$2:J$36),H68*Accounts!J68) | J68: 100000 | K68: =J68*0.25
A69: =Accounts!A69 | B69: Restaurant | D69: =Accounts!K69 | E69: 0.6 | F69: =Accounts!K69*E69 | G69: 0.4 | H69: =F69*G69 | I69: =if(or(eq(Accounts!J69,"No Valet"),eq(Accounts!J69,"Has Valet")), H69 * AVERAGE(Accounts!J$2:J$36),H69*Accounts!J69) | J69: =iferror(I69*360,"") | K69: =J69*0.1
A70: =Accounts!A70 | B70: Restaurant | C70: SOPHI | D70: =Accounts!K70 | E70: 0.6 | F70: =Accounts!K70*E70 | G70: 0.4 | H70: =F70*G70 | I70: =if(or(eq(Accounts!J70,"No Valet"),eq(Accounts!J70,"Has Valet")), H70 * AVERAGE(Accounts!J$2:J$36),H70*Accounts!J70) | J70: 100000 | K70: =J70*0.25
A71: =Accounts!A71 | B71: Restaurant | C71: Park Inc | D71: =Accounts!K71 | E71: 0.6 | F71: =Accounts!K71*E71 | G71: 0.4 | H71: =F71*G71 | I71: =if(or(eq(Accounts!J71,"No Valet"),eq(Accounts!J71,"Has Valet")), H71 * AVERAGE(Accounts!J$2:J$36),H71*Accounts!J71) | J71: 75000 | K71: =J71*0.25
A72: =Accounts!A72 | B72: Restaurant | C72: None | D72: =Accounts!K72 | E72: 0.6 | F72: =Accounts!K72*E72 | G72: 0.4 | H72: =F72*G72 | I72: =if(or(eq(Accounts!J72,"No Valet"),eq(Accounts!J72,"Has Valet")), H72 * AVERAGE(Accounts!J$2:J$36),H72*Accounts!J72) | J72: 100000 | K72: =J72*0.1
A73: =Accounts!A73 | B73: Hotel | D73: =Accounts!K73 | E73: 0.6 | F73: =Accounts!K73*E73 | G73: 0.4 | H73: =F73*G73 | I73: =if(or(eq(Accounts!J73,"No Valet"),eq(Accounts!J73,"Has Valet")), H73 * AVERAGE(Accounts!J$2:J$36),H73*Accounts!J73) | J73: =iferror(I73*360,"") | K73: =J73*0.1
A74: =Accounts!A74 | D74: =Accounts!K74
A75: =Accounts!A75 | D75: =Accounts!K75
A76: =Accounts!A76 | D76: =Accounts!K76
A77: =Accounts!A77 | D77: =Accounts!K77
A78: =Accounts!A78 | D78: =Accounts!K78
A79: =Accounts!A79 | D79: =Accounts!K79
A80: =Accounts!A80 | D80: =Accounts!K80
A81: =Accounts!A81 | D81: =Accounts!K81
A82: =Accounts!A82 | D82: =Accounts!K82
A83: =Accounts!A83 | D83: =Accounts!K83
A84: =Accounts!A84 | D84: =Accounts!K84
A85: =Accounts!A85 | D85: =Accounts!K85
... A267: =Accounts!A267 | D267: =Accounts!K267
A268: =Accounts!A268 | D268: =Accounts!K268 | E268: 0.6 | F268: =Accounts!K268*E268 | G268: 0.4 | H268: =F268*G268 | I268: =if(or(eq(Accounts!J268,"No Valet"),eq(Accounts!J268,"Has Valet")), H268 * AVERAGE(Accounts!J$2:J$36),H268*Accounts!J268) | J268: =iferror(I268*360,"") | K268: =J268*0.1
A269: =Accounts!A269 | D269: =Accounts!K269 | E269: 0.6 | F269: =Accounts!K269*E269 | G269: 0.4 | H269: =F269*G269 | I269: =if(or(eq(Accounts!J269,"No Valet"),eq(Accounts!J269,"Has Valet")), H269 * AVERAGE(Accounts!J$2:J$36),H269*Accounts!J269) | J269: =iferror(I269*360,"") | K269: =J269*0.1
A270: =Accounts!A270 | D270: =Accounts!K270 | E270: 0.6 | F270: =Accounts!K270*E270 | G270: 0.4 | H270: =F270*G270 | I270: =if(or(eq(Accounts!J270,"No Valet"),eq(Accounts!J270,"Has Valet")), H270 * AVERAGE(Accounts!J$2:J$36),H270*Accounts!J270) | J270: =iferror(I270*360,"") | K270: =J270*0.1
A271: =Accounts!A271 | D271: =Accounts!K271 | E271: 0.6 | F271: =Accounts!K271*E271 | G271: 0.4 | H271: =F271*G271 | I271: =if(or(eq(Accounts!J271,"No Valet"),eq(Accounts!J271,"Has Valet")), H271 * AVERAGE(Accounts!J$2:J$36),H271*Accounts!J271) | J271: =iferror(I271*360,"") | K271: =J271*0.1
A272: =Accounts!A272 | D272: =Accounts!K272 | E272: 0.6 | F272: =Accounts!K272*E272 | G272: 0.4 | H272: =F272*G272 | I272: =if(or(eq(Accounts!J272,"No Valet"),eq(Accounts!J272,"Has Valet")), H272 * AVERAGE(Accounts!J$2:J$36),H272*Accounts!J272) | J272: =iferror(I272*360,"") | K272: =J272*0.1
A273: =Accounts!A273 | D273: =Accounts!K273 | E273: 0.6 | F273: =Accounts!K273*E273 | G273: 0.4 | H273: =F273*G273 | I273: =if(or(eq(Accounts!J273,"No Valet"),eq(Accounts!J273,"Has Valet")), H273 * AVERAGE(Accounts!J$2:J$36),H273*Accounts!J273) | J273: =iferror(I273*360,"") | K273: =J273*0.1
A274: =Accounts!A274 | D274: =Accounts!K274 | E274: 0.6 | F274: =Accounts!K274*E274 | G274: 0.4 | H274: =F274*G274 | I274: =if(or(eq(Accounts!J274,"No Valet"),eq(Accounts!J274,"Has Valet")), H274 * AVERAGE(Accounts!J$2:J$36),H274*Accounts!J274) | J274: =iferror(I274*360,"") | K274: =J274*0.1
A275: =Accounts!A275 | D275: =Accounts!K275 | E275: 0.6 | F275: =Accounts!K275*E275 | G275: 0.4 | H275: =F275*G275 | I275: =if(or(eq(Accounts!J275,"No Valet"),eq(Accounts!J275,"Has Valet")), H275 * AVERAGE(Accounts!J$2:J$36),H275*Accounts!J275) | J275: =iferror(I275*360,"") | K275: =J275*0.1
A276: =Accounts!A276 | D276: =Accounts!K276 | E276: 0.6 | F276: =Accounts!K276*E276 | G276: 0.4 | H276: =F276*G276 | I276: =if(or(eq(Accounts!J276,"No Valet"),eq(Accounts!J276,"Has Valet")), H276 * AVERAGE(Accounts!J$2:J$36),H276*Accounts!J276) | J276: =iferror(I276*360,"") | K276: =J276*0.1
A277: =Accounts!A277 | D277: =Accounts!K277 | E277: 0.6 | F277: =Accounts!K277*E277 | G277: 0.4 | H277: =F277*G277 | I277: =if(or(eq(Accounts!J277,"No Valet"),eq(Accounts!J277,"Has Valet")), H277 * AVERAGE(Accounts!J$2:J$36),H277*Accounts!J277) | J277: =iferror(I277*360,"") | K277: =J277*0.1
A278: =Accounts!A278 | D278: =Accounts!K278 | E278: 0.6 | F278: =Accounts!K278*E278 | G278: 0.4 | H278: =F278*G278 | I278: =if(or(eq(Accounts!J278,"No Valet"),eq(Accounts!J278,"Has Valet")), H278 * AVERAGE(Accounts!J$2:J$36),H278*Accounts!J278) | J278: =iferror(I278*360,"") | K278: =J278*0.1
A279: =Accounts!A279 | D279: =Accounts!K279 | E279: 0.6 | F279: =Accounts!K279*E279 | G279: 0.4 | H279: =F279*G279 | I279: =if(or(eq(Accounts!J279,"No Valet"),eq(Accounts!J279,"Has Valet")), H279 * AVERAGE(Accounts!J$2:J$36),H279*Accounts!J279) | J279: =iferror(I279*360,"") | K279: =J279*0.1
... A1060: =Accounts!A1060 | D1060: =Accounts!K1060 | E1060: 0.6 | F1060: =Accounts!K1060*E1060 | G1060: 0.4 | H1060: =F1060*G1060 | I1060: =if(or(eq(Accounts!J1060,"No Valet"),eq(Accounts!J1060,"Has Valet")), H1060 * AVERAGE(Accounts!J$2:J$36),H1060*Accounts!J1060) | J1060: =iferror(I1060*360,"") | K1060: =J1060*0.1

Sheet Analysis
A1: SOPHI's MARKET SCORE | B1: =G2 | C1: TAM | D1: SAM | E1: SOM | G1: Total | H1: Location | I1: Connections | J1: Garage | K1: Growth | L1: capacity | M1: cash flow | O1: Connection 3 | P1: Volume 2 170 + 2 100 + 1 | Q1: Location Downtown 1 Far -1 | R1: High End | S1: Garage Connection 2 location 1 | T1: Valet & Paid Self Park | U1: Points | V1: Priority
C2: =SUM(RevenueForecasting!J:J) | D2: =SUMIF(#REF!,1,RevenueForecasting!J2:J36) | E2: =D2/SUM(#REF!) | G2: =SUM(H2:L2)*2 & " /100" | H2: 7 | I2: 0 | J2: 8 | K2: 7
C3: sum of predicted revenues | D3: Guess of locations that I could see being interested in introducing valet | E3: SAM / # of locations in SAM. Representing 1 Hotel landed
C4: all valet, all parking contracts, additional services, bell etc | D4: realistically obtained | E4: going to get | H4: 257 miles | I4: locations? 0/7 | J4: public? 8/8 | K4: Population? 2/4 | L4: personal bandwidth 0/4 | M4: costs
H5: SB X | I5: 1 connection -> 5 2+ connections -> 7 | J5: yes or no | K5: small city, medium city, large city, metropolis
H6: CH | I6: employees? 3 | J6: connection? 2 | K6: Events Space? 4 | L6: hire 0/3
A7: Average Self Park | B7: Average Valet | I7: # of possible employees | J7: yes or no | K7: # of markets
A8: =AVERAGE(Accounts!I:I) | B8: =AVERAGE(Accounts!J:J) | H8: 0 -> 1000+ | K8: Parking? 2 | L8: management 0/3
H9: 3 -> 700 - 1000 | K9: reducing, steady, increasing
H10: 5 -> 500 - 700
H11: 7 -> 250 - 500
H12: 10 -> 0 - 250

Sheet Detail2-PMC-Hotel
A1: Accounts | B1: Account Type | C1: Contact Created? | D1: Address | E1: Phone Number | F1: Email | G1: URL | H1: Self Parking Rate | I1: Valet Rate | J1: # of Rooms | K1: Parking Reviews % | L1: Parking Reviews # | M1: GM Name | N1: Management Group | O1: Linked Accounts | P1: Garage Operator | Q1: Valet Operator | R1: Sourcing Notes | S1: Location Notes
A2: Hilton Charlotte Uptown | B2: Hotel | D2: 222 East vThird Street Charlotte NC 20802 | E2: 7043771500 | H2: 24 | I2: 34 | J2: 149 | K2: 0.51 | L2: 224 | Q2: PMC
A3: The Ivey's Hotel | B3: Hotel | D3: 127 N Tryon St, Charlotte, NC 28202 | G3: https://www.theiveysHotel.com/ | I3: 35 | J3: 47 | K3: 0.52 | L3: 89 | P3: LAZ | Q3: PMC
A4: Hyatt Place | B4: Hotel | D4: 222 S Caldwell St, Charlotte NC 28202 | E4: 7042270500 | F4: Check your email/texts for contact updated | G4: tien.ning@hyatt.com | H4: n/a | I4: 38 | J4: 172 | K4: 0.72 | L4: 484 | M4: Tien Ning | Q4: PMC | S4: pretty solid valet reviews. maybe bundled services or damage claim pitching
A5: AC Hotel Residents inn | B5: Hotel | D5: 220 East Trade Street, Suite 1400, Charlotte, NC, 28202 | E5: 7043484002 | F5: rob.cote@marriott.com | G5: https://www.marriott.com/en-us/Hotels/cltad-ac-Hotel-charlotte-city-center/overview/?scid=f2ae0541-1279-4f24-b197-a979c79310b0 | H5: 29 | I5: 40 | J5: 149 | K5: 0.52 | L5: 117 | M5: Rob Cote | P5: Preferred | Q5: PMC
A6: Omni Hotel | B6: Hotel | D6: 132 E Trade St, Charlotte, NC 28202 | G6: https://www.omniHotels.com/Hotels/charlotte | I6: 40 | J6: 373 | K6: 0.39 | L6: 270 | P6: LAZ | Q6: PMC
A7: SpringHill | B7: Hotel | D7: 311 E 5th St, Charlotte, NC 28202 | E7: shsuptown@sree.com | G7: https://www.marriott.com/en-us/Hotels/cltsd-springhill-suites-charlotte-city-center/overview/?scid=f2ae0541-1279-4f24-b197-a979c79310b0 | H7: Not available | I7: 40 | J7: 195 | K7: 0.38 | L7: 190 | M7: Karen Owens | Q7: PMC
A8: Grand Bohemian Hotel | B8: Hotel | D8: 201 W Trade St, Charlotte, NC 28202 | E8: (704) 372-1877 | F8: hugh.templeman@kesslercollection.com | G8: https://www.kesslercollection.com/bohemian-charlotte/ | H8: unknown | I8: 48 | J8: 254 | K8: 0.65 | L8: 122 | M8: Hugh Templeman | Q8: PMC | S8: Wait for new GM
A9: JW Marriott Charlotte | B9: Hotel | D9: 600 S College St, Charlotte, NC 28202 | E9: David.malmberg@whitelodging.com | G9: https://www.marriott.com/en-us/Hotels/cltjw-jw-marriott-charlotte/overview/ | H9: n/a | I9: 48 | J9: 381 | K9: 0.48 | L9: 87 | Q9: PMC | S9: Reviews about the valet are mostly terrible.
A10: Kimpton Tryon Park Hotel | B10: Hotel | D10: 303 S Church St, Charlotte, NC 28202 | E10: 7044477662 (Direct line) | G10: https://www.tryonparkHotel.com/ | I10: 48 | J10: 217 | K10: 0.54 | L10: 162 | M10: Yvette Bullock | P10: Preferred | Q10: PMC | S10: $30 4 hours max Valet
A11: Charlotte Marriott City Center | B11: Hotel | D11: 100 W Trade St, Charlotte, NC 28202 | F11: jennifer.correa@marriott.com | G11: https://www.marriott.com/en-us/Hotels/cltcc-charlotte-marriott-city-center/overview/?scid=f2ae0541-1279-4f24-b197-a979c79310b0 | I11: 48 | J11: 440 | K11: 0.4 | L11: 181 | M11: Jennifer Correa | Q11: PMC | S11: poor reviews

Sheet TAM_Conservative
A1: Account | B1: Account Type | C1: TAM Class | D1: Rooms/Beds | E1: Seats | F1: Occupancy % | G1: Turnover | H1: Valet Conv % | I1: Valet Rate | J1: Op Days | K1: Peak Mod | L1: Daily Rev | M1: TAM | N1: TAM Status | O1: Notes / Source
A2: Aloft Charlotte City Center | B2: Hotel | C2: Hotel — Downtown Select-Service | D2: 175 | F2: 0.6 | H2: 0.25 | I2: 25 | J2: 360 | L2: 656.25 | M2: 236250 | N2: Active TAM | O2: Auto-class: downtown + select-service flag. Occ 60% flat (refine w/STR).
A3: Courtyard By Marriott | B3: Hotel | C3: Hotel — Downtown Select-Service | D3: 181 | F3: 0.6 | H3: 0.25 | J3: 360 | N3: No Valet / TAM = $0 | O3: Hotel has no valet (rate field: None). Auto-class: downtown + select-service flag. Qualitative pipeline only.
A4: Fairfield Inn & Suites | B4: Hotel | C4: Hotel — Downtown Select-Service | D4: 196 | F4: 0.6 | H4: 0.25 | J4: 360 | N4: No Valet / TAM = $0 | O4: Hotel has no valet (rate field: None). Auto-class: downtown + select-service flag. Qualitative pipeline only.
A5: Hampton Inn Uptown | B5: Hotel | C5: Hotel — Downtown Select-Service | D5: 250 | F5: 0.6 | H5: 0.25 | J5: 360 | N5: No Valet / TAM = $0 | O5: Hotel has no valet (rate field: None). Auto-class: downtown + select-service flag. Qualitative pipeline only.
A6: Hilton Garden Inn (SouthPark) | B6: Hotel | C6: Hotel — Suburban/Airport | D6: 160 | F6: 0.6 | H6: 0.15 | J6: 360 | N6: No Valet / TAM = $0 | O6: Hotel has no valet (rate field: None). Auto-class: not downtown (by flag or name). Qualitative pipeline only.
A7: Hilton/Hilton Garden Inn | B7: Hotel | C7: Hotel — Downtown Select-Service | D7: 181 | F7: 0.6 | H7: 0.25 | J7: 360 | N7: No Valet / TAM = $0 | O7: Hotel has no valet (rate field: None). Auto-class: downtown full-service <300 rooms. Qualitative pipeline only.
A8: Home2Suites | B8: Hotel | C8: Hotel — Downtown Select-Service | D8: 180 | F8: 0.6 | H8: 0.25 | J8: 360 | N8: No Valet / TAM = $0 | O8: Hotel has no valet (rate field: None). Auto-class: downtown + select-service flag. Qualitative pipeline only.
A9: Hilton Charlotte Uptown | B9: Hotel | C9: Hotel — Downtown Select-Service | D9: 149 | F9: 0.6 | H9: 0.25 | I9: 34 | J9: 360 | L9: 759.9 | M9: 273564 | N9: Active TAM | O9: Auto-class: downtown full-service <300 rooms. Occ 60% flat (refine w/STR).
A10: Le Meridien Charlotte | B10: Hotel | C10: Hotel — Downtown+Convention | D10: 300 | F10: 0.6 | H10: 0.4 | I10: 35 | J10: 360 | L10: 2520 | M10: 907200 | N10: Active TAM | O10: Auto-class: downtown + 300 rooms. Occ 60% flat (refine w/STR).
A11: Sheraton Hotel | B11: Hotel | C11: Hotel — Downtown+Convention | D11: 305 | F11: 0.6 | H11: 0.4 | I11: 35 | J11: 360 | L11: 2562 | M11: 922320 | N11: Active TAM | O11: Auto-class: downtown + 305 rooms. Occ 60% flat (refine w/STR).
A12: The Ivey's Hotel | B12: Hotel | C12: Hotel — Downtown Select-Service | D12: 47 | F12: 0.6 | H12: 0.25 | I12: 35 | J12: 360 | L12: 246.75 | M12: 88830 | N12: Active TAM | O12: Auto-class: downtown full-service <300 rooms. Occ 60% flat (refine w/STR).
A13: Hyatt Place | B13: Hotel | C13: Hotel — Downtown Select-Service | D13: 172 | F13: 0.6 | H13: 0.25 | I13: 38 | J13: 360 | L13: 980.4 | M13: 352944 | N13: Active TAM | O13: Auto-class: downtown + select-service flag. Occ 60% flat (refine w/STR).
A14: The Dunhill | B14: Hotel | C14: Hotel — Downtown Select-Service | D14: 60 | F14: 0.6 | H14: 0.25 | I14: 38 | J14: 360 | L14: 342 | M14: 123120 | N14: Active TAM | O14: Auto-class: downtown full-service <300 rooms. Occ 60% flat (refine w/STR).
A15: AC Hotel Residents inn | B15: Hotel | C15: Hotel — Downtown Select-Service | D15: 149 | F15: 0.6 | H15: 0.25 | I15: 40 | J15: 360 | L15: 894 | M15: 321840 | N15: Active TAM | O15: Auto-class: downtown + select-service flag. Occ 60% flat (refine w/STR).
A16: DoubleTree by Hilton Charlotte-Center City | B16: Hotel | C16: Hotel — Downtown Select-Service | D16: 187 | F16: 0.6 | H16: 0.25 | I16: 40 | J16: 360 | L16: 1122 | M16: 403920 | N16: Active TAM | O16: Auto-class: downtown full-service <300 rooms. Occ 60% flat (refine w/STR).
A17: Omni Hotel | B17: Hotel | C17: Hotel — Downtown+Convention | D17: 373 | F17: 0.6 | H17: 0.4 | I17: 40 | J17: 360 | L17: 3580.8 | M17: 1289088 | N17: Active TAM | O17: Auto-class: downtown + 373 rooms. Occ 60% flat (refine w/STR).
A18: SpringHill | B18: Hotel | C18: Hotel — Downtown Select-Service | D18: 195 | F18: 0.6 | H18: 0.25 | I18: 40 | J18: 360 | L18: 1170 | M18: 421200 | N18: Active TAM | O18: Auto-class: downtown + select-service flag. Occ 60% flat (refine w/STR).
A19: Element Charlotte Uptown | B19: Hotel | C19: Hotel — Downtown Select-Service | D19: 173 | F19: 0.6 | H19: 0.25 | I19: 42 | J19: 360 | L19: 1089.9 | M19: 392364 | N19: Active TAM | O19: Auto-class: downtown + select-service flag. Occ 60% flat (refine w/STR).
A20: Hyatt House Charlotte Center City | B20: Hotel | C20: Hotel — Downtown Select-Service | D20: 163 | F20: 0.6 | H20: 0.25 | I20: 42 | J20: 360 | L20: 1026.9 | M20: 369684 | N20: Active TAM | O20: Auto-class: downtown + select-service flag. Occ 60% flat (refine w/STR).
A21: Homewood Suites by Hilton Charlotte Uptown | B21: Hotel | C21: Hotel — Downtown Select-Service | D21: 211 | F21: 0.6 | H21: 0.25 | I21: 45 | J21: 360 | L21: 1424.25 | M21: 512730 | N21: Active TAM | O21: Auto-class: downtown + select-service flag. Occ 60% flat (refine w/STR).
A22: Embassy Suites by Hilton Charlotte Uptown | B22: Hotel | C22: Hotel — Downtown Select-Service | F22: 0.6 | H22: 0.25 | I22: 45 | J22: 360 | N22: Active TAM | O22: Auto-class: downtown full-service <300 rooms. Occ 60% flat (refine w/STR).
A23: The Westin Charlotte | B23: Hotel | C23: Hotel — Downtown+Convention | D23: 700 | F23: 0.6 | H23: 0.4 | I23: 45 | J23: 360 | L23: 7560 | M23: 2721600 | N23: Active TAM | O23: Auto-class: downtown + 700 rooms (>=400). Occ 60% flat (refine w/STR).
A24: Grand Bohemian Hotel | B24: Hotel | C24: Hotel — Downtown Select-Service | D24: 254 | F24: 0.6 | H24: 0.25 | I24: 48 | J24: 360 | L24: 1828.8 | M24: 658368 | N24: Active TAM | O24: Auto-class: downtown full-service <300 rooms. Occ 60% flat (refine w/STR).
A25: JW Marriott Charlotte | B25: Hotel | C25: Hotel — Downtown+Convention | D25: 381 | F25: 0.6 | H25: 0.4 | I25: 48 | J25: 360 | L25: 4389.12 | M25: 1580083.2 | N25: Active TAM | O25: Auto-class: downtown + 381 rooms. Occ 60% flat (refine w/STR).
A26: Kimpton Tryon Park Hotel | B26: Hotel | C26: Hotel — Downtown Select-Service | D26: 217 | F26: 0.6 | H26: 0.25 | I26: 48 | J26: 360 | L26: 1562.4 | M26: 562464 | N26: Active TAM | O26: Auto-class: downtown full-service <300 rooms. Occ 60% flat (refine w/STR).
A27: Charlotte Marriott City Center | B27: Hotel | C27: Hotel — Downtown+Convention | D27: 440 | F27: 0.6 | H27: 0.4 | I27: 48 | J27: 360 | L27: 5068.8 | M27: 1824768 | N27: Active TAM | O27: Auto-class: downtown + 440 rooms (>=400). Occ 60% flat (refine w/STR).
A28: Ritz Carlton | B28: Hotel | C28: Hotel — Downtown Select-Service | D28: 146 | F28: 0.6 | H28: 0.25 | I28: 50 | J28: 360 | L28: 1095 | M28: 394200 | N28: Active TAM | O28: Auto-class: downtown full-service <300 rooms. Occ 60% flat (refine w/STR).
A29: Kasa FreeMoreWest Charlotte | B29: Hotel | C29: Hotel — Suburban/Airport | F29: 0.6 | H29: 0.15 | J29: 360 | N29: No Valet / TAM = $0 | O29: Hotel has no valet (rate field: None). Auto-class: not downtown (by flag or name). Qualitative pipeline only.
A30: Canopy by Hilton Charlotte Southpark | B30: Hotel | C30: Hotel — Suburban/Airport | F30: 0.6 | H30: 0.15 | J30: 360 | N30: No Valet / TAM = $0 | O30: Hotel has no valet (rate field: None). Auto-class: not downtown (by flag or name). Qualitative pipeline only.
A31: Courtyard by Marriott Charlotte SouthPark | B31: Hotel | C31: Hotel — Suburban/Airport | F31: 0.6 | H31: 0.15 | J31: 360 | N31: No Valet / TAM = $0 | O31: Hotel has no valet (rate field: None). Auto-class: not downtown (by flag or name). Qualitative pipeline only.
A32: Residence Inn by Marriott Charlotte SouthPark | B32: Hotel | C32: Hotel — Suburban/Airport | F32: 0.6 | H32: 0.15 | J32: 360 | N32: No Valet / TAM = $0 | O32: Hotel has no valet (rate field: None). Auto-class: not downtown (by flag or name). Qualitative pipeline only.
A33: Renaissance Charlotte SouthPark Hotel | B33: Hotel | C33: Hotel — Suburban/Airport | F33: 0.6 | H33: 0.15 | J33: 360 | N33: No Valet / TAM = $0 | O33: Hotel has no valet (rate field: None). Auto-class: not downtown (by flag or name). Qualitative pipeline only.
A34: Charlotte Marriott SouthPark | B34: Hotel | C34: Hotel — Suburban/Airport | F34: 0.6 | H34: 0.15 | J34: 360 | N34: No Valet / TAM = $0 | O34: Hotel has no valet (rate field: None). Auto-class: not downtown (by flag or name). Qualitative pipeline only.
A35: AC Hotel Charlotte SouthPark | B35: Hotel | C35: Hotel — Suburban/Airport | F35: 0.6 | H35: 0.15 | J35: 360 | N35: No Valet / TAM = $0 | O35: Hotel has no valet (rate field: None). Auto-class: not downtown (by flag or name). Qualitative pipeline only.
A36: Hyatt Centric Charlotte SouthPark | B36: Hotel | C36: Hotel — Suburban/Airport | F36: 0.6 | H36: 0.15 | J36: 360 | N36: No Valet / TAM = $0 | O36: Hotel has no valet (rate field: None). Auto-class: not downtown (by flag or name). Qualitative pipeline only.
A37: Homewood Suites by Hilton Charlotte/SouthPark | B37: Hotel | C37: Hotel — Suburban/Airport | F37: 0.6 | H37: 0.15 | J37: 360 | N37: No Valet / TAM = $0 | O37: Hotel has no valet (rate field: None). Auto-class: not downtown (by flag or name). Qualitative pipeline only.
A38: DoubleTree Suites by Hilton Hotel Charlotte - SouthPark | B38: Hotel | C38: Hotel — Suburban/Airport | F38: 0.6 | H38: 0.15 | J38: 360 | N38: No Valet / TAM = $0 | O38: Hotel has no valet (rate field: None). Auto-class: not downtown (by flag or name). Qualitative pipeline only.
A39: UNC Charlotte Marriott Hotel & Conference Center | B39: Hotel | C39: Hotel — Suburban/Airport | F39: 0.6 | H39: 0.15 | I39: 31 | J39: 360 | N39: Active TAM | O39: Auto-class: not downtown (by flag or name). Occ 60% flat (refine w/STR).
A40: Steak 48 | B40: Restaurant | C40: Restaurant — Steakhouse — flagship | E40: 300 | G40: 1.5 | H40: 0.125 | I40: 7 | J40: 250 | K40: 1.08 | L40: 843.75 | M40: 227812.5 | N40: Active TAM (MED confidence) | O40: Charlotte uptown location, active paid valet $7 on file | industry brand avg (Steak 48 flagship ~280-320 seats)
A41: The Capital Grille | B41: Restaurant | C41: Restaurant — Steakhouse | E41: 250 | G41: 1.5 | H41: 0.125 | I41: 11 | J41: 250 | K41: 1.08 | L41: 703.125 | M41: 189843.75 | N41: Active TAM (MED confidence) | O41: SOPHI current operator (+1.0 lift) | Darden brand std ~240-260 seats
A42: Morton's Steakhouse | B42: Restaurant | C42: Restaurant — Steakhouse | E42: 200 | G42: 1.5 | H42: 0.125 | I42: 15 | J42: 250 | K42: 1.08 | L42: 562.5 | M42: 151875 | N42: Active TAM (MED confidence) | O42: Park Inc current valet at $15 | Landry brand std ~180-220 seats
A43: Church and Union | B43: Restaurant | C43: Restaurant — Excluded | I43: 15 | N43: EXCLUDED — no active valet / not eligible | O43: Not in eligible FD universe (steakhouse/fine dining with active independent valet)
A44: Fahrenheit CLT | B44: Restaurant | C44: Restaurant — Upscale rooftop | E44: 225 | G44: 1.5 | H44: 0.125 | I44: 17 | J44: 250 | K44: 1.08 | L44: 632.8125 | M44: 170859.38 | N44: Active TAM (LOW confidence) | O44: Park Inc valet at $17 | independent rooftop estimate
A45: STK Steakhouse | B45: Restaurant | C45: Restaurant — Steakhouse — modern | E45: 275 | G45: 1.5 | H45: 0.125 | I45: 17 | J45: 250 | K45: 1.08 | L45: 773.4375 | M45: 208828.12 | N45: Active TAM (MED confidence) | O45: SOPHI current operator (+1.0 lift) | ONE Group brand std ~260-290 seats
A46: La Belle | B46: Restaurant | C46: Restaurant — Excluded | N46: EXCLUDED — no active valet / not eligible | O46: Not in eligible FD universe (steakhouse/fine dining with active independent valet)
A47: Cajun Queen | B47: Restaurant | C47: Restaurant — Excluded | N47: EXCLUDED — no active valet / not eligible | O47: Not in eligible FD universe (steakhouse/fine dining with active independent valet)
A48: Bernardin's Restaurant At Ratcliffe | B48: Restaurant | C48: Restaurant — Excluded | N48: EXCLUDED — no active valet / not eligible | O48: Not in eligible FD universe (steakhouse/fine dining with active independent valet)
A49: Basil | B49: Restaurant | C49: Restaurant — Excluded | N49: EXCLUDED — no active valet / not eligible | O49: Not in eligible FD universe (steakhouse/fine dining with active independent valet)
A50: Haymaker | B50: Restaurant | C50: Restaurant — Excluded | N50: EXCLUDED — no active valet / not eligible | O50: Not in eligible FD universe (steakhouse/fine dining with active independent valet)
A51: McNinch House Restaurant | B51: Restaurant | C51: Restaurant — Excluded | N51: EXCLUDED — no active valet / not eligible | O51: Not in eligible FD universe (steakhouse/fine dining with active independent valet)
A52: Luce Ristorante & Bar | B52: Restaurant | C52: Restaurant — Excluded | N52: EXCLUDED — no active valet / not eligible | O52: Not in eligible FD universe (steakhouse/fine dining with active independent valet)
A53: Fin&Fino | B53: Restaurant | C53: Restaurant — Excluded | N53: EXCLUDED — no active valet / not eligible | O53: Not in eligible FD universe (steakhouse/fine dining with active independent valet)
A54: Forchetta | B54: Restaurant | C54: Restaurant — Excluded | N54: EXCLUDED — no active valet / not eligible | O54: Not in eligible FD universe (steakhouse/fine dining with active independent valet)
A55: Indaco | B55: Restaurant | C55: Restaurant — Excluded | N55: EXCLUDED — no active valet / not eligible | O55: Not in eligible FD universe (steakhouse/fine dining with active independent valet)
A56: Copper Restaurant | B56: Restaurant | C56: Restaurant — Excluded | N56: EXCLUDED — no active valet / not eligible | O56: Not in eligible FD universe (steakhouse/fine dining with active independent valet)
A57: Dolce Osteria | B57: Restaurant | C57: Restaurant — Excluded | N57: EXCLUDED — no active valet / not eligible | O57: Not in eligible FD universe (steakhouse/fine dining with active independent valet)
... A63: Firebirds Wood Fired Grill | B63: Restaurant | C63: Restaurant — Excluded | N63: EXCLUDED — no active valet / not eligible | O63: Not in eligible FD universe (steakhouse/fine dining with active independent valet)
A64: Del Frisco's Double Eagle Steakhouse | B64: Restaurant | C64: Restaurant — Steakhouse — flagship | E64: 400 | G64: 1.5 | H64: 0.125 | J64: 250 | K64: 1.08 | L64: 1125 | M64: 303750 | N64: Active TAM (MED confidence) | O64: Uptown Charlotte — no active valet listed in workbook, but flag for outreach | brand std flagship ~380-450 seats
A65: Mariposa | B65: Restaurant | C65: Restaurant — Excluded | N65: EXCLUDED — no active valet / not eligible | O65: Not in eligible FD universe (steakhouse/fine dining with active independent valet)
A66: 204 North | B66: Restaurant | C66: Restaurant — Excluded | N66: EXCLUDED — no active valet / not eligible | O66: Not in eligible FD universe (steakhouse/fine dining with active independent valet)
A67: Deluxe The Fun Art of Dining | B67: Restaurant | C67: Restaurant — Excluded | N67: EXCLUDED — no active valet / not eligible | O67: Not in eligible FD universe (steakhouse/fine dining with active independent valet)
A68: Sea Level NC | B68: Restaurant | C68: Restaurant — Excluded | N68: EXCLUDED — no active valet / not eligible | O68: Not in eligible FD universe (steakhouse/fine dining with active independent valet)
A69: Red Salt by David Burke | B69: Restaurant | C69: Restaurant — Excluded | N69: EXCLUDED — no active valet / not eligible | O69: Not in eligible FD universe (steakhouse/fine dining with active independent valet)
A70: Chima Steakhouse | B70: Restaurant | C70: Restaurant — Brazilian steakhouse | E70: 220 | G70: 1.5 | H70: 0.125 | I70: 15 | J70: 250 | K70: 1.08 | L70: 618.75 | M70: 167062.5 | N70: Active TAM (MED confidence) | O70: SOPHI current operator (+1.0 lift) | brand std ~200-240 seats
A71: Eddie V's Prime Seafood | B71: Restaurant | C71: Restaurant — Seafood — upscale | E71: 250 | G71: 1.5 | H71: 0.125 | I71: 25 | J71: 250 | K71: 1.08 | L71: 703.125 | M71: 189843.75 | N71: Active TAM (MED confidence) | O71: Complimentary to restaurant, paid transient $15 first 3h, Preferred Parking op | Darden brand std ~230-270
A72: Dean's Italian Steakhouse | B72: Restaurant | C72: Restaurant — Italian steakhouse | E72: 200 | G72: 1.5 | H72: 0.125 | J72: 250 | K72: 1.08 | L72: 562.5 | M72: 151875 | N72: Active TAM (LOW confidence) | O72: PMC current valet at ~$15 | default fine-dining estimate
A73: Fleming's Prime Steakhouse & Wine Bar | B73: Restaurant | C73: Restaurant — Steakhouse | E73: 175 | G73: 1.5 | H73: 0.125 | J73: 250 | K73: 1.08 | L73: 492.1875 | M73: 132890.62 | N73: Active TAM (MED confidence) | O73: Preferred Parking valet at $17 | Bloomin' Brands std ~160-190 seats
A74: 204 kitchen + cocktails | B74: Restaurant | C74: Restaurant — Excluded | N74: EXCLUDED — no active valet / not eligible | O74: Not in eligible FD universe (steakhouse/fine dining with active independent valet)
A75: The Palm | B75: Restaurant | C75: Restaurant — Excluded | I75: 25 | N75: EXCLUDED — no active valet / not eligible | O75: Not in eligible FD universe (steakhouse/fine dining with active independent valet)
A76: Sullivan's Steakhouse | B76: Restaurant | C76: Restaurant — Excluded | I76: 25 | N76: EXCLUDED — no active valet / not eligible | O76: Not in eligible FD universe (steakhouse/fine dining with active independent valet)
A77: Aria and Cicchetti | B77: Restaurant | C77: Restaurant — Excluded | I77: 25 | N77: EXCLUDED — no active valet / not eligible | O77: Not in eligible FD universe (steakhouse/fine dining with active independent valet)
A78: Dressler's Steakhouse | B78: Restaurant | C78: Restaurant — Excluded | I78: 25 | N78: EXCLUDED — no active valet / not eligible | O78: Not in eligible FD universe (steakhouse/fine dining with active independent valet)
A79: Ruth's Chris | B79: Restaurant | C79: Restaurant — Steakhouse | E79: 250 | G79: 1.5 | H79: 0.125 | I79: 15 | J79: 250 | K79: 1.08 | L79: 703.125 | M79: 189843.75 | N79: Active TAM (MED confidence) | O79: SOPHI current operator (+1.0 lift) | Darden brand std ~240-260 seats
A80: Ruth's Chris #2 | B80: Restaurant | C80: Restaurant — Excluded | N80: EXCLUDED — no active valet / not eligible | O80: Not in eligible FD universe (steakhouse/fine dining with active independent valet)
A81: Oak Steakhouse | B81: Restaurant | C81: Restaurant — Steakhouse | E81: 175 | G81: 1.5 | H81: 0.125 | J81: 250 | K81: 1.08 | L81: 492.1875 | M81: 132890.62 | N81: Active TAM (LOW confidence) | O81: Workbook flags 'valet temporarily suspended' — include as pipeline | Indigo Road brand avg

Sheet TAM_Summary
A1: Charlotte — Conservative TAM Summary
A3: Account Type | B3: # Accounts | C3: TAM | D3: Status
A4: Hotel | B4: 38 | C4: 14356537 | D4: Active TAM
A5: Restaurant | B5: 12 | C5: 2217375 | D5: Active TAM
A6: TOTAL | B6: 50 | C6: 16573912
A8: HOTEL BREAKDOWN BY CLASS
A9: Class | B9: # Hotels | C9: Conv %
A10: Downtown+Convention | B10: 6 | C10: 0.4
A11: Downtown Select-Service | B11: 20 | C11: 0.25
A12: Resort | B12: 0 | C12: 0.5
A13: Suburban/Airport | B13: 12 | C13: 0.15
A15: RESTAURANTS WITH ACTIVE TAM
A16: Restaurant | B16: Seats | C16: TAM
A17: Del Frisco's Double Eagle Steakhouse | B17: 400 | C17: 303750
A18: Steak 48 | B18: 300 | C18: 227812.5
A19: STK Steakhouse | B19: 275 | C19: 208828.12
A20: The Capital Grille | B20: 250 | C20: 189843.75
A21: Eddie V's Prime Seafood | B21: 250 | C21: 189843.75
A22: Ruth's Chris | B22: 250 | C22: 189843.75
A23: Fahrenheit CLT | B23: 225 | C23: 170859.38
A24: Chima Steakhouse | B24: 220 | C24: 167062.5
A25: Morton's Steakhouse | B25: 200 | C25: 151875
A26: Dean's Italian Steakhouse | B26: 200 | C26: 151875
A27: Fleming's Prime Steakhouse & Wine Bar | B27: 175 | C27: 132890.62
A28: Oak Steakhouse | B28: 175 | C28: 132890.62

Sheet TAM_Methodology
A1: SOPHI CONSERVATIVE TAM METHODOLOGY
A3: Replaces original RevenueForecasting formulas. Hospitals / Venues / Airports now qualitative only.
A5: HOTEL FORMULA
A6: TAM = Rooms × Occupancy × Valet Conversion (tiered) × Valet Rate × 360 days
A7: Occupancy: 60% flat across all hotels
A8: ⚠️ FLAG: Refine with STR actuals per-submarket before finalizing fundraise model
A9: Valet Conversion by archetype (auto-classified — review recommended):
A10: Downtown+Convention: 40%
A11: Downtown Select-Service: 25%
A12: Resort: 50%
A13: Suburban/Airport: 15%
A14: Operating Days: 360 (captures soft-closures / transition days)
... A35: 4. Hospital/venue/airport TAM dropped to $0 → build IU Health-benchmarked KPI proxy

Sheet WAS_Scoring_v2
A1: Account | B1: Type | C1: Downtown | D1: Rooms | E1: Valet Op (incumbent) | F1: Valet Rate | G1: Est. Annual Rev (TAM) | H1: Fit (25%) | I1: Size (25%) | J1: Owner Base (20%) | K1: Addr (15%) | L1: Adj (15%) | M1: Rel Lift | N1: Rel Tag | O1: WAS Raw | P1: WAS Final | Q1: Tier | R1: Y1 % | S1: Y2 % | T1: Y3 % | U1: Y4 % | V1: Y5 % | W1: Y1 Rev | X1: Y2 Rev | Y1: Y3 Rev | Z1: Y4 Rev | AA1: Y5 Rev
A2: Aloft Charlotte City Center | B2: Hotel | C2: YES | D2: 175 | E2: Preferred Parking | F2: 25 | G2: 236250 | H2: 4 | I2: 1 | J2: 2 | K2: 3 | L2: 4 | M2: 0.3 | N2: Brand familiarity (current): Marriott_family | O2: 2.7 | P2: 3 | Q2: C — Opportunistic | R2: 0.11 | S2: 0.20375 | T2: 0.365625 | U2: 0.48375 | V2: 0.5625 | W2: 25987.5 | X2: 48135.938 | Y2: 86378.906 | Z2: 114285.94 | AA2: 132890.62
A3: Courtyard By Marriott | B3: Hotel | C3: YES | D3: 181 | E3: None | G3: 0 | H3: 4 | I3: 1 | J3: 3 | K3: 3 | L3: 4 | M3: 0.3 | N3: Brand familiarity (current): Marriott_family | O3: 2.9 | P3: 3.2 | Q3: C — Opportunistic | R3: 0.11 | S3: 0.20375 | T3: 0.365625 | U3: 0.48375 | V3: 0.5625 | W3: 0 | X3: 0 | Y3: 0 | Z3: 0 | AA3: 0
A4: Fairfield Inn & Suites | B4: Hotel | C4: YES | D4: 196 | E4: None | G4: 0 | H4: 4 | I4: 1 | J4: 2 | K4: 3 | L4: 4 | M4: 0.3 | N4: Brand familiarity (current): Marriott_family | O4: 2.7 | P4: 3 | Q4: C — Opportunistic | R4: 0.11 | S4: 0.20375 | T4: 0.365625 | U4: 0.48375 | V4: 0.5625 | W4: 0 | X4: 0 | Y4: 0 | Z4: 0 | AA4: 0
A5: Hampton Inn Uptown | B5: Hotel | C5: YES | D5: 250 | E5: None | G5: 0 | H5: 4 | I5: 1 | J5: 3 | K5: 3 | L5: 4 | M5: 0.15 | N5: Brand familiarity (historical): Hilton_family | O5: 2.9 | P5: 3.05 | Q5: C — Opportunistic | R5: 0.11 | S5: 0.20375 | T5: 0.365625 | U5: 0.48375 | V5: 0.5625 | W5: 0 | X5: 0 | Y5: 0 | Z5: 0 | AA5: 0
A6: Hilton Garden Inn (SouthPark) | B6: Hotel | C6: NO | D6: 160 | E6: None | G6: 0 | H6: 3 | I6: 1 | J6: 3 | K6: 3 | L6: 2 | M6: 0.15 | N6: Brand familiarity (historical): Hilton_family | O6: 2.35 | P6: 2.5 | Q6: C — Opportunistic | R6: 0.11 | S6: 0.20375 | T6: 0.365625 | U6: 0.48375 | V6: 0.5625 | W6: 0 | X6: 0 | Y6: 0 | Z6: 0 | AA6: 0
A7: Hilton/Hilton Garden Inn | B7: Hotel | C7: YES | D7: 181 | E7: None | G7: 0 | H7: 4 | I7: 1 | J7: 3 | K7: 3 | L7: 4 | M7: 0.15 | N7: Brand familiarity (historical): Hilton_family | O7: 2.9 | P7: 3.05 | Q7: C — Opportunistic | R7: 0.11 | S7: 0.20375 | T7: 0.365625 | U7: 0.48375 | V7: 0.5625 | W7: 0 | X7: 0 | Y7: 0 | Z7: 0 | AA7: 0
A8: Home2Suites | B8: Hotel | C8: YES | D8: 180 | E8: None | G8: 0 | H8: 4 | I8: 1 | J8: 2 | K8: 3 | L8: 4 | M8: 0 | O8: 2.7 | P8: 2.7 | Q8: C — Opportunistic | R8: 0.11 | S8: 0.20375 | T8: 0.365625 | U8: 0.48375 | V8: 0.5625 | W8: 0 | X8: 0 | Y8: 0 | Z8: 0 | AA8: 0
A9: Hilton Charlotte Uptown | B9: Hotel | C9: YES | D9: 149 | E9: PMC | F9: 34 | G9: 273564 | H9: 3 | I9: 2 | J9: 3 | K9: 3 | L9: 4 | M9: 0.15 | N9: Brand familiarity (historical): Hilton_family | O9: 2.9 | P9: 3.05 | Q9: C — Opportunistic | R9: 0.11 | S9: 0.20375 | T9: 0.365625 | U9: 0.48375 | V9: 0.5625 | W9: 30092.04 | X9: 55738.665 | Y9: 100021.84 | Z9: 132336.58 | AA9: 153879.75
A10: Le Meridien Charlotte | B10: Hotel | C10: YES | D10: 300 | F10: 35 | G10: 907200 | H10: 5 | I10: 3 | J10: 2 | K10: 4 | L10: 4 | M10: 0 | O10: 3.6 | P10: 3.6 | Q10: B — Core | R10: 0.275 | S10: 0.43625 | T10: 0.690625 | U10: 0.87625 | V10: 1 | W10: 249480 | X10: 395766 | Y10: 626535 | Z10: 794934 | AA10: 907200
A11: Sheraton Hotel | B11: Hotel | C11: YES | D11: 305 | F11: 35 | G11: 922320 | H11: 5 | I11: 3 | J11: 3 | K11: 4 | L11: 4 | M11: 0.3 | N11: Brand familiarity (current): Marriott_family | O11: 3.8 | P11: 4.1 | Q11: B — Core | R11: 0.275 | S11: 0.43625 | T11: 0.690625 | U11: 0.87625 | V11: 1 | W11: 253638 | X11: 402362.1 | Y11: 636977.25 | Z11: 808182.9 | AA11: 922320
A12: The Ivey's Hotel | B12: Hotel | C12: YES | D12: 47 | E12: PMC | F12: 35 | G12: 88830 | H12: 2 | I12: 1 | J12: 2 | K12: 3 | L12: 4 | M12: 0 | O12: 2.2 | P12: 2.2 | Q12: D — Deprioritized | R12: 0 | S12: 0.027 | T12: 0.0825 | U12: 0.123 | V12: 0.15 | W12: 0 | X12: 2398.41 | Y12: 7328.475 | Z12: 10926.09 | AA12: 13324.5
A13: Hyatt Place | B13: Hotel | C13: YES | D13: 172 | E13: PMC | F13: 38 | G13: 352944 | H13: 4 | I13: 2 | J13: 3 | K13: 3 | L13: 4 | M13: 0 | O13: 3.15 | P13: 3.15 | Q13: C — Opportunistic | R13: 0.11 | S13: 0.20375 | T13: 0.365625 | U13: 0.48375 | V13: 0.5625 | W13: 38823.84 | X13: 71912.34 | Y13: 129045.15 | Z13: 170736.66 | AA13: 198531
A14: The Dunhill | B14: Hotel | C14: YES | D14: 60 | E14: In House | F14: 38 | G14: 123120 | H14: 2 | I14: 1 | J14: 2 | K14: 5 | L14: 4 | M14: 0 | O14: 2.5 | P14: 2.5 | Q14: C — Opportunistic | R14: 0.11 | S14: 0.20375 | T14: 0.365625 | U14: 0.48375 | V14: 0.5625 | W14: 13543.2 | X14: 25085.7 | Y14: 45015.75 | Z14: 59559.3 | AA14: 69255
A15: AC Hotel Residents inn | B15: Hotel | C15: YES | D15: 149 | E15: PMC | F15: 40 | G15: 321840 | H15: 3 | I15: 2 | J15: 2 | K15: 3 | L15: 4 | M15: 0 | O15: 2.7 | P15: 2.7 | Q15: C — Opportunistic | R15: 0.11 | S15: 0.20375 | T15: 0.365625 | U15: 0.48375 | V15: 0.5625 | W15: 35402.4 | X15: 65574.9 | Y15: 117672.75 | Z15: 155690.1 | AA15: 181035
A16: DoubleTree by Hilton Charlotte-Center City | B16: Hotel | C16: YES | D16: 187 | F16: 40 | G16: 403920 | H16: 4 | I16: 2 | J16: 3 | K16: 4 | L16: 4 | M16: 0.15 | N16: Brand familiarity (historical): Hilton_family | O16: 3.3 | P16: 3.45 | Q16: C — Opportunistic | R16: 0.11 | S16: 0.20375 | T16: 0.365625 | U16: 0.48375 | V16: 0.5625 | W16: 44431.2 | X16: 82298.7 | Y16: 147683.25 | Z16: 195396.3 | AA16: 227205
A17: Omni Hotel | B17: Hotel | C17: YES | D17: 373 | E17: PMC | F17: 40 | G17: 1289088 | H17: 5 | I17: 3 | J17: 2 | K17: 3 | L17: 4 | M17: 0 | O17: 3.45 | P17: 3.45 | Q17: C — Opportunistic | R17: 0.11 | S17: 0.20375 | T17: 0.365625 | U17: 0.48375 | V17: 0.5625 | W17: 141799.68 | X17: 262651.68 | Y17: 471322.8 | Z17: 623596.32 | AA17: 725112
A18: SpringHill | B18: Hotel | C18: YES | D18: 195 | E18: PMC | F18: 40 | G18: 421200 | H18: 4 | I18: 2 | J18: 2 | K18: 3 | L18: 4 | M18: 0 | O18: 2.95 | P18: 2.95 | Q18: C — Opportunistic | R18: 0.11 | S18: 0.20375 | T18: 0.365625 | U18: 0.48375 | V18: 0.5625 | W18: 46332 | X18: 85819.5 | Y18: 154001.25 | Z18: 203755.5 | AA18: 236925
A19: Element Charlotte Uptown | B19: Hotel | C19: YES | D19: 173 | F19: 42 | G19: 392364 | H19: 4 | I19: 2 | J19: 2 | K19: 4 | L19: 4 | M19: 0 | O19: 3.1 | P19: 3.1 | Q19: C — Opportunistic | R19: 0.11 | S19: 0.20375 | T19: 0.365625 | U19: 0.48375 | V19: 0.5625 | W19: 43160.04 | X19: 79944.165 | Y19: 143458.09 | Z19: 189806.08 | AA19: 220704.75
A20: Hyatt House Charlotte Center City | B20: Hotel | C20: YES | D20: 163 | F20: 42 | G20: 369684 | H20: 4 | I20: 2 | J20: 3 | K20: 4 | L20: 4 | M20: 0 | O20: 3.3 | P20: 3.3 | Q20: C — Opportunistic | R20: 0.11 | S20: 0.20375 | T20: 0.365625 | U20: 0.48375 | V20: 0.5625 | W20: 40665.24 | X20: 75323.115 | Y20: 135165.71 | Z20: 178834.64 | AA20: 207947.25
A21: Homewood Suites by Hilton Charlotte Uptown | B21: Hotel | C21: YES | D21: 211 | F21: 45 | G21: 512730 | H21: 4 | I21: 2 | J21: 3 | K21: 4 | L21: 4 | M21: 0.15 | N21: Brand familiarity (historical): Hilton_family | O21: 3.3 | P21: 3.45 | Q21: C — Opportunistic | R21: 0.11 | S21: 0.20375 | T21: 0.365625 | U21: 0.48375 | V21: 0.5625 | W21: 56400.3 | X21: 104468.74 | Y21: 187466.91 | Z21: 248033.14 | AA21: 288410.62
A22: Embassy Suites by Hilton Charlotte Uptown | B22: Hotel | C22: YES | D22: 0 | F22: 45 | G22: 0 | H22: 2 | I22: 1 | J22: 3 | K22: 4 | L22: 4 | M22: 0.15 | N22: Brand familiarity (historical): Hilton_family | O22: 2.55 | P22: 2.7 | Q22: C — Opportunistic | R22: 0.11 | S22: 0.20375 | T22: 0.365625 | U22: 0.48375 | V22: 0.5625 | W22: 0 | X22: 0 | Y22: 0 | Z22: 0 | AA22: 0
A23: The Westin Charlotte | B23: Hotel | C23: YES | D23: 700 | E23: LAZ | F23: 45 | G23: 2721600 | H23: 5 | I23: 5 | J23: 3 | K23: 2 | L23: 4 | M23: 0.3 | N23: Brand familiarity (current): Marriott_family | O23: 4 | P23: 4.3 | Q23: B — Core | R23: 0.275 | S23: 0.43625 | T23: 0.690625 | U23: 0.87625 | V23: 1 | W23: 748440 | X23: 1187298 | Y23: 1879605 | Z23: 2384802 | AA23: 2721600
A24: Grand Bohemian Hotel | B24: Hotel | C24: YES | D24: 254 | E24: PMC | F24: 48 | G24: 658368 | H24: 4 | I24: 2 | J24: 2 | K24: 3 | L24: 4 | M24: 0 | O24: 2.95 | P24: 2.95 | Q24: C — Opportunistic | R24: 0.11 | S24: 0.20375 | T24: 0.365625 | U24: 0.48375 | V24: 0.5625 | W24: 72420.48 | X24: 134142.48 | Y24: 240715.8 | Z24: 318485.52 | AA24: 370332
A25: JW Marriott Charlotte | B25: Hotel | C25: YES | D25: 381 | E25: PMC | F25: 48 | G25: 1580083.2 | H25: 5 | I25: 4 | J25: 3 | K25: 3 | L25: 4 | M25: 0.3 | N25: Brand familiarity (current): Marriott_family | O25: 3.9 | P25: 4.2 | Q25: B — Core | R25: 0.275 | S25: 0.43625 | T25: 0.690625 | U25: 0.87625 | V25: 1 | W25: 434522.88 | X25: 689311.3 | Y25: 1091245 | Z25: 1384547.9 | AA25: 1580083.2
A26: Kimpton Tryon Park Hotel | B26: Hotel | C26: YES | D26: 217 | E26: PMC | F26: 48 | G26: 562464 | H26: 4 | I26: 2 | J26: 3 | K26: 3 | L26: 4 | M26: 0 | O26: 3.15 | P26: 3.15 | Q26: C — Opportunistic | R26: 0.11 | S26: 0.20375 | T26: 0.365625 | U26: 0.48375 | V26: 0.5625 | W26: 61871.04 | X26: 114602.04 | Y26: 205650.9 | Z26: 272091.96 | AA26: 316386
A27: Charlotte Marriott City Center | B27: Hotel | C27: YES | D27: 440 | E27: PMC | F27: 48 | G27: 1824768 | H27: 5 | I27: 4 | J27: 3 | K27: 3 | L27: 4 | M27: 0.3 | N27: Brand familiarity (current): Marriott_family | O27: 3.9 | P27: 4.2 | Q27: B — Core | R27: 0.275 | S27: 0.43625 | T27: 0.690625 | U27: 0.87625 | V27: 1 | W27: 501811.2 | X27: 796055.04 | Y27: 1260230.4 | Z27: 1598953 | AA27: 1824768
A28: Ritz Carlton | B28: Hotel | C28: YES | D28: 146 | E28: In House | F28: 50 | G28: 394200 | H28: 3 | I28: 2 | J28: 2 | K28: 5 | L28: 4 | M28: 0 | O28: 3 | P28: 3 | Q28: C — Opportunistic | R28: 0.11 | S28: 0.20375 | T28: 0.365625 | U28: 0.48375 | V28: 0.5625 | W28: 43362 | X28: 80318.25 | Y28: 144129.38 | Z28: 190694.25 | AA28: 221737.5
A29: Kasa FreeMoreWest Charlotte | B29: Hotel | C29: NO | D29: 0 | G29: 0 | H29: 2 | I29: 1 | J29: 2 | K29: 4 | L29: 2 | M29: 0 | O29: 2.05 | P29: 2.05 | Q29: D — Deprioritized | R29: 0 | S29: 0.027 | T29: 0.0825 | U29: 0.123 | V29: 0.15 | W29: 0 | X29: 0 | Y29: 0 | Z29: 0 | AA29: 0
A30: Canopy by Hilton Charlotte Southpark | B30: Hotel | C30: NO | D30: 0 | G30: 0 | H30: 2 | I30: 1 | J30: 3 | K30: 4 | L30: 2 | M30: 0.15 | N30: Brand familiarity (historical): Hilton_family | O30: 2.25 | P30: 2.4 | Q30: D — Deprioritized | R30: 0 | S30: 0.027 | T30: 0.0825 | U30: 0.123 | V30: 0.15 | W30: 0 | X30: 0 | Y30: 0 | Z30: 0 | AA30: 0
A31: Courtyard by Marriott Charlotte SouthPark | B31: Hotel | C31: NO | D31: 0 | G31: 0 | H31: 2 | I31: 1 | J31: 3 | K31: 4 | L31: 2 | M31: 0.3 | N31: Brand familiarity (current): Marriott_family | O31: 2.25 | P31: 2.55 | Q31: C — Opportunistic | R31: 0.11 | S31: 0.20375 | T31: 0.365625 | U31: 0.48375 | V31: 0.5625 | W31: 0 | X31: 0 | Y31: 0 | Z31: 0 | AA31: 0
A32: Residence Inn by Marriott Charlotte SouthPark | B32: Hotel | C32: NO | D32: 0 | G32: 0 | H32: 2 | I32: 1 | J32: 3 | K32: 4 | L32: 2 | M32: 0.3 | N32: Brand familiarity (current): Marriott_family | O32: 2.25 | P32: 2.55 | Q32: C — Opportunistic | R32: 0.11 | S32: 0.20375 | T32: 0.365625 | U32: 0.48375 | V32: 0.5625 | W32: 0 | X32: 0 | Y32: 0 | Z32: 0 | AA32: 0
A33: Renaissance Charlotte SouthPark Hotel | B33: Hotel | C33: NO | D33: 0 | G33: 0 | H33: 2 | I33: 1 | J33: 3 | K33: 4 | L33: 2 | M33: 0.3 | N33: Brand familiarity (current): Marriott_family | O33: 2.25 | P33: 2.55 | Q33: C — Opportunistic | R33: 0.11 | S33: 0.20375 | T33: 0.365625 | U33: 0.48375 | V33: 0.5625 | W33: 0 | X33: 0 | Y33: 0 | Z33: 0 | AA33: 0
A34: Charlotte Marriott SouthPark | B34: Hotel | C34: NO | D34: 0 | G34: 0 | H34: 2 | I34: 1 | J34: 3 | K34: 4 | L34: 2 | M34: 0.3 | N34: Brand familiarity (current): Marriott_family | O34: 2.25 | P34: 2.55 | Q34: C — Opportunistic | R34: 0.11 | S34: 0.20375 | T34: 0.365625 | U34: 0.48375 | V34: 0.5625 | W34: 0 | X34: 0 | Y34: 0 | Z34: 0 | AA34: 0
A35: AC Hotel Charlotte SouthPark | B35: Hotel | C35: NO | D35: 0 | G35: 0 | H35: 2 | I35: 1 | J35: 2 | K35: 4 | L35: 2 | M35: 0 | O35: 2.05 | P35: 2.05 | Q35: D — Deprioritized | R35: 0 | S35: 0.027 | T35: 0.0825 | U35: 0.123 | V35: 0.15 | W35: 0 | X35: 0 | Y35: 0 | Z35: 0 | AA35: 0
A36: Hyatt Centric Charlotte SouthPark | B36: Hotel | C36: NO | D36: 0 | G36: 0 | H36: 2 | I36: 1 | J36: 3 | K36: 4 | L36: 2 | M36: 0 | O36: 2.25 | P36: 2.25 | Q36: D — Deprioritized | R36: 0 | S36: 0.027 | T36: 0.0825 | U36: 0.123 | V36: 0.15 | W36: 0 | X36: 0 | Y36: 0 | Z36: 0 | AA36: 0
A37: Homewood Suites by Hilton Charlotte/SouthPark | B37: Hotel | C37: NO | D37: 0 | G37: 0 | H37: 2 | I37: 1 | J37: 3 | K37: 4 | L37: 2 | M37: 0.15 | N37: Brand familiarity (historical): Hilton_family | O37: 2.25 | P37: 2.4 | Q37: D — Deprioritized | R37: 0 | S37: 0.027 | T37: 0.0825 | U37: 0.123 | V37: 0.15 | W37: 0 | X37: 0 | Y37: 0 | Z37: 0 | AA37: 0
A38: DoubleTree Suites by Hilton Hotel Charlotte - SouthPark | B38: Hotel | C38: NO | D38: 0 | G38: 0 | H38: 2 | I38: 1 | J38: 3 | K38: 4 | L38: 2 | M38: 0.15 | N38: Brand familiarity (historical): Hilton_family | O38: 2.25 | P38: 2.4 | Q38: D — Deprioritized | R38: 0 | S38: 0.027 | T38: 0.0825 | U38: 0.123 | V38: 0.15 | W38: 0 | X38: 0 | Y38: 0 | Z38: 0 | AA38: 0
A39: UNC Charlotte Marriott Hotel & Conference Center | B39: Hotel | C39: NO | D39: 0 | F39: 31 | G39: 0 | H39: 2 | I39: 1 | J39: 3 | K39: 4 | L39: 2 | M39: 0.3 | N39: Brand familiarity (current): Marriott_family | O39: 2.25 | P39: 2.55 | Q39: C — Opportunistic | R39: 0.11 | S39: 0.20375 | T39: 0.365625 | U39: 0.48375 | V39: 0.5625 | W39: 0 | X39: 0 | Y39: 0 | Z39: 0 | AA39: 0
A40: Steak 48 | B40: Restaurant | C40: NO | D40: 0 | F40: 7 | G40: 227812.5 | H40: 3 | I40: 1 | J40: 2 | K40: 4 | L40: 2 | M40: 0 | O40: 2.3 | P40: 2.3 | Q40: D — Deprioritized | R40: 0 | S40: 0.027 | T40: 0.0825 | U40: 0.123 | V40: 0.15 | W40: 0 | X40: 6150.9375 | Y40: 18794.531 | Z40: 28020.938 | AA40: 34171.875
A41: The Capital Grille | B41: Restaurant | C41: YES | D41: 0 | E41: SOPHI | F41: 11 | G41: 189843.75 | H41: 3 | I41: 1 | J41: 2 | K41: 3 | L41: 4 | M41: 1 | N41: Current operator: Darden | O41: 2.45 | P41: 3.45 | Q41: C — Opportunistic | R41: 0.11 | S41: 0.20375 | T41: 0.365625 | U41: 0.48375 | V41: 0.5625 | W41: 20882.812 | X41: 38680.664 | Y41: 69411.621 | Z41: 91836.914 | AA41: 106787.11
A42: Morton's Steakhouse | B42: Restaurant | C42: YES | D42: 0 | E42: Park Inc | F42: 15 | G42: 151875 | H42: 3 | I42: 1 | J42: 2 | K42: 3 | L42: 4 | M42: 0 | O42: 2.45 | P42: 2.45 | Q42: D — Deprioritized | R42: 0 | S42: 0.027 | T42: 0.0825 | U42: 0.123 | V42: 0.15 | W42: 0 | X42: 4100.625 | Y42: 12529.688 | Z42: 18680.625 | AA42: 22781.25
A43: Church and Union | B43: Restaurant | C43: YES | D43: 0 | E43: Park Inc | F43: 15 | G43: 0 | H43: 3 | I43: 1 | J43: 2 | K43: 3 | L43: 4 | M43: 0 | O43: 2.45 | P43: 2.45 | Q43: D — Deprioritized | R43: 0 | S43: 0.027 | T43: 0.0825 | U43: 0.123 | V43: 0.15 | W43: 0 | X43: 0 | Y43: 0 | Z43: 0 | AA43: 0
A44: Fahrenheit CLT | B44: Restaurant | C44: YES | D44: 0 | E44: Park Inc | F44: 17 | G44: 170859.38 | H44: 3 | I44: 1 | J44: 2 | K44: 3 | L44: 4 | M44: 0 | O44: 2.45 | P44: 2.45 | Q44: D — Deprioritized | R44: 0 | S44: 0.027 | T44: 0.0825 | U44: 0.123 | V44: 0.15 | W44: 0 | X44: 4613.2031 | Y44: 14095.898 | Z44: 21015.703 | AA44: 25628.906
A45: STK Steakhouse | B45: Restaurant | C45: YES | D45: 0 | E45: SOPHI | F45: 17 | G45: 208828.12 | H45: 3 | I45: 1 | J45: 2 | K45: 3 | L45: 4 | M45: 1 | N45: Current operator: The ONE Group | O45: 2.45 | P45: 3.45 | Q45: C — Opportunistic | R45: 0.11 | S45: 0.20375 | T45: 0.365625 | U45: 0.48375 | V45: 0.5625 | W45: 22971.094 | X45: 42548.73 | Y45: 76352.783 | Z45: 101020.61 | AA45: 117465.82
A46: La Belle | B46: Restaurant | C46: YES | D46: 0 | E46: None | F46: N/A | G46: 0 | H46: 3 | I46: 1 | J46: 2 | K46: 3 | L46: 4 | M46: 0 | O46: 2.45 | P46: 2.45 | Q46: D — Deprioritized | R46: 0 | S46: 0.027 | T46: 0.0825 | U46: 0.123 | V46: 0.15 | W46: 0 | X46: 0 | Y46: 0 | Z46: 0 | AA46: 0
A47: Cajun Queen | B47: Restaurant | C47: YES | D47: 0 | E47: Park Inc | F47: N/A | G47: 0 | H47: 3 | I47: 1 | J47: 2 | K47: 3 | L47: 4 | M47: 0 | O47: 2.45 | P47: 2.45 | Q47: D — Deprioritized | R47: 0 | S47: 0.027 | T47: 0.0825 | U47: 0.123 | V47: 0.15 | W47: 0 | X47: 0 | Y47: 0 | Z47: 0 | AA47: 0
A48: Bernardin's Restaurant At Ratcliffe | B48: Restaurant | C48: YES | D48: 0 | E48: None | F48: N/A | G48: 0 | H48: 3 | I48: 1 | J48: 2 | K48: 3 | L48: 4 | M48: 0 | O48: 2.45 | P48: 2.45 | Q48: D — Deprioritized | R48: 0 | S48: 0.027 | T48: 0.0825 | U48: 0.123 | V48: 0.15 | W48: 0 | X48: 0 | Y48: 0 | Z48: 0 | AA48: 0
A49: Basil | B49: Restaurant | C49: YES | D49: 0 | E49: None | F49: N/A | G49: 0 | H49: 3 | I49: 1 | J49: 2 | K49: 3 | L49: 4 | M49: 0 | O49: 2.45 | P49: 2.45 | Q49: D — Deprioritized | R49: 0 | S49: 0.027 | T49: 0.0825 | U49: 0.123 | V49: 0.15 | W49: 0 | X49: 0 | Y49: 0 | Z49: 0 | AA49: 0
A50: Haymaker | B50: Restaurant | C50: YES | D50: 0 | E50: None | F50: N?A | G50: 0 | H50: 3 | I50: 1 | J50: 2 | K50: 3 | L50: 4 | M50: 0 | O50: 2.45 | P50: 2.45 | Q50: D — Deprioritized | R50: 0 | S50: 0.027 | T50: 0.0825 | U50: 0.123 | V50: 0.15 | W50: 0 | X50: 0 | Y50: 0 | Z50: 0 | AA50: 0
A51: McNinch House Restaurant | B51: Restaurant | C51: YES | D51: 0 | F51: N/A | G51: 0 | H51: 3 | I51: 1 | J51: 2 | K51: 4 | L51: 4 | M51: 0 | O51: 2.6 | P51: 2.6 | Q51: C — Opportunistic | R51: 0.11 | S51: 0.20375 | T51: 0.365625 | U51: 0.48375 | V51: 0.5625 | W51: 0 | X51: 0 | Y51: 0 | Z51: 0 | AA51: 0
A52: Luce Ristorante & Bar | B52: Restaurant | C52: YES | D52: 0 | E52: None | F52: N/A | G52: 0 | H52: 3 | I52: 1 | J52: 2 | K52: 3 | L52: 4 | M52: 0 | O52: 2.45 | P52: 2.45 | Q52: D — Deprioritized | R52: 0 | S52: 0.027 | T52: 0.0825 | U52: 0.123 | V52: 0.15 | W52: 0 | X52: 0 | Y52: 0 | Z52: 0 | AA52: 0
A53: Fin&Fino | B53: Restaurant | C53: YES | D53: 0 | E53: None | F53: Not Available | G53: 0 | H53: 3 | I53: 1 | J53: 2 | K53: 3 | L53: 4 | M53: 0 | O53: 2.45 | P53: 2.45 | Q53: D — Deprioritized | R53: 0 | S53: 0.027 | T53: 0.0825 | U53: 0.123 | V53: 0.15 | W53: 0 | X53: 0 | Y53: 0 | Z53: 0 | AA53: 0
A54: Forchetta | B54: Restaurant | C54: YES | D54: 0 | E54: None | F54: Not Available | G54: 0 | H54: 3 | I54: 1 | J54: 2 | K54: 3 | L54: 4 | M54: 0 | O54: 2.45 | P54: 2.45 | Q54: D — Deprioritized | R54: 0 | S54: 0.027 | T54: 0.0825 | U54: 0.123 | V54: 0.15 | W54: 0 | X54: 0 | Y54: 0 | Z54: 0 | AA54: 0
A55: Indaco | B55: Restaurant | C55: NO | D55: 0 | E55: None | F55: Not Available | G55: 0 | H55: 3 | I55: 1 | J55: 2 | K55: 3 | L55: 2 | M55: 0 | O55: 2.15 | P55: 2.15 | Q55: D — Deprioritized | R55: 0 | S55: 0.027 | T55: 0.0825 | U55: 0.123 | V55: 0.15 | W55: 0 | X55: 0 | Y55: 0 | Z55: 0 | AA55: 0
A56: Copper Restaurant | B56: Restaurant | C56: NO | D56: 0 | E56: None | F56: Not Available | G56: 0 | H56: 3 | I56: 1 | J56: 2 | K56: 3 | L56: 2 | M56: 0 | O56: 2.15 | P56: 2.15 | Q56: D — Deprioritized | R56: 0 | S56: 0.027 | T56: 0.0825 | U56: 0.123 | V56: 0.15 | W56: 0 | X56: 0 | Y56: 0 | Z56: 0 | AA56: 0
A57: Dolce Osteria | B57: Restaurant | C57: NO | D57: 0 | E57: None | F57: N/A | G57: 0 | H57: 3 | I57: 1 | J57: 2 | K57: 3 | L57: 2 | M57: 0 | O57: 2.15 | P57: 2.15 | Q57: D — Deprioritized | R57: 0 | S57: 0.027 | T57: 0.0825 | U57: 0.123 | V57: 0.15 | W57: 0 | X57: 0 | Y57: 0 | Z57: 0 | AA57: 0
A58: The Fig Tree Restaurant | B58: Restaurant | C58: YES | D58: 0 | E58: None | F58: Not Available | G58: 0 | H58: 3 | I58: 1 | J58: 2 | K58: 3 | L58: 4 | M58: 0 | O58: 2.45 | P58: 2.45 | Q58: D — Deprioritized | R58: 0 | S58: 0.027 | T58: 0.0825 | U58: 0.123 | V58: 0.15 | W58: 0 | X58: 0 | Y58: 0 | Z58: 0 | AA58: 0
A59: The Melting Pot | B59: Restaurant | C59: NO | D59: 0 | E59: None | F59: N/A | G59: 0 | H59: 3 | I59: 1 | J59: 2 | K59: 3 | L59: 2 | M59: 0 | O59: 2.15 | P59: 2.15 | Q59: D — Deprioritized | R59: 0 | S59: 0.027 | T59: 0.0825 | U59: 0.123 | V59: 0.15 | W59: 0 | X59: 0 | Y59: 0 | Z59: 0 | AA59: 0
A60: The Cellar at Duckworth's | B60: Restaurant | C60: YES | D60: 0 | E60: None | F60: Not Available | G60: 0 | H60: 3 | I60: 1 | J60: 2 | K60: 3 | L60: 4 | M60: 0 | O60: 2.45 | P60: 2.45 | Q60: D — Deprioritized | R60: 0 | S60: 0.027 | T60: 0.0825 | U60: 0.123 | V60: 0.15 | W60: 0 | X60: 0 | Y60: 0 | Z60: 0 | AA60: 0
A61: Ri Ra | B61: Restaurant | C61: YES | D61: 0 | E61: None | F61: N/A | G61: 0 | H61: 3 | I61: 1 | J61: 2 | K61: 3 | L61: 4 | M61: 0 | O61: 2.45 | P61: 2.45 | Q61: D — Deprioritized | R61: 0 | S61: 0.027 | T61: 0.0825 | U61: 0.123 | V61: 0.15 | W61: 0 | X61: 0 | Y61: 0 | Z61: 0 | AA61: 0
A62: McCormick &Schmick's Seafood &Steaks | B62: Restaurant | C62: YES | D62: 0 | E62: Closed | F62: Closed | G62: 0 | H62: 3 | I62: 1 | J62: 2 | K62: 3 | L62: 4 | M62: 0 | O62: 2.45 | P62: 2.45 | Q62: D — Deprioritized | R62: 0 | S62: 0.027 | T62: 0.0825 | U62: 0.123 | V62: 0.15 | W62: 0 | X62: 0 | Y62: 0 | Z62: 0 | AA62: 0
A63: Firebirds Wood Fired Grill | B63: Restaurant | C63: NO | D63: 0 | E63: None | F63: N/A | G63: 0 | H63: 3 | I63: 1 | J63: 2 | K63: 3 | L63: 2 | M63: 0 | O63: 2.15 | P63: 2.15 | Q63: D — Deprioritized | R63: 0 | S63: 0.027 | T63: 0.0825 | U63: 0.123 | V63: 0.15 | W63: 0 | X63: 0 | Y63: 0 | Z63: 0 | AA63: 0
... A69: Red Salt by David Burke | B69: Restaurant | C69: YES | D69: 0 | E69: None | F69: N/A | G69: 0 | H69: 3 | I69: 1 | J69: 2 | K69: 3 | L69: 4 | M69: 0 | O69: 2.45 | P69: 2.45 | Q69: D — Deprioritized | R69: 0 | S69: 0.027 | T69: 0.0825 | U69: 0.123 | V69: 0.15 | W69: 0 | X69: 0 | Y69: 0 | Z69: 0 | AA69: 0
A70: Chima Steakhouse | B70: Restaurant | C70: YES | D70: 0 | E70: SOPHI | F70: 15 | G70: 167062.5 | H70: 3 | I70: 1 | J70: 2 | K70: 3 | L70: 4 | M70: 0 | O70: 2.45 | P70: 2.45 | Q70: D — Deprioritized | R70: 0 | S70: 0.027 | T70: 0.0825 | U70: 0.123 | V70: 0.15 | W70: 0 | X70: 4510.6875 | Y70: 13782.656 | Z70: 20548.688 | AA70: 25059.375
A71: Eddie V's Prime Seafood | B71: Restaurant | C71: YES | D71: 0 | E71: Preferred Parking | F71: Complimentary for resturant. Transient $15 first 3 hours. $30 for 3-6 hours | G71: 189843.75 | H71: 3 | I71: 1 | J71: 2 | K71: 3 | L71: 4 | M71: 1 | N71: Current operator: Darden | O71: 2.45 | P71: 3.45 | Q71: C — Opportunistic | R71: 0.11 | S71: 0.20375 | T71: 0.365625 | U71: 0.48375 | V71: 0.5625 | W71: 20882.812 | X71: 38680.664 | Y71: 69411.621 | Z71: 91836.914 | AA71: 106787.11
A72: Dean's Italian Steakhouse | B72: Restaurant | C72: YES | D72: 0 | E72: PMC | F72: $15 she thinks | G72: 151875 | H72: 3 | I72: 1 | J72: 2 | K72: 3 | L72: 4 | M72: 0 | O72: 2.45 | P72: 2.45 | Q72: D — Deprioritized | R72: 0 | S72: 0.027 | T72: 0.0825 | U72: 0.123 | V72: 0.15 | W72: 0 | X72: 4100.625 | Y72: 12529.688 | Z72: 18680.625 | AA72: 22781.25
A73: Fleming's Prime Steakhouse & Wine Bar | B73: Restaurant | C73: YES | D73: 0 | E73: Preferred Parking | F73: $17 for guest $13 to resturant | G73: 132890.62 | H73: 3 | I73: 1 | J73: 2 | K73: 3 | L73: 4 | M73: 0 | O73: 2.45 | P73: 2.45 | Q73: D — Deprioritized | R73: 0 | S73: 0.027 | T73: 0.0825 | U73: 0.123 | V73: 0.15 | W73: 0 | X73: 3588.0469 | Y73: 10963.477 | Z73: 16345.547 | AA73: 19933.594
A74: 204 kitchen + cocktails | B74: Restaurant | C74: YES | D74: 0 | E74: Preferred Parking | F74: $17 for guest $13 to resturant | G74: 0 | H74: 3 | I74: 1 | J74: 2 | K74: 3 | L74: 4 | M74: 0 | O74: 2.45 | P74: 2.45 | Q74: D — Deprioritized | R74: 0 | S74: 0.027 | T74: 0.0825 | U74: 0.123 | V74: 0.15 | W74: 0 | X74: 0 | Y74: 0 | Z74: 0 | AA74: 0
A75: The Palm | B75: Restaurant | C75: NO | D75: 0 | E75: Park Inc | F75: complimentary | G75: 0 | H75: 3 | I75: 1 | J75: 2 | K75: 3 | L75: 2 | M75: 0 | O75: 2.15 | P75: 2.15 | Q75: D — Deprioritized | R75: 0 | S75: 0.027 | T75: 0.0825 | U75: 0.123 | V75: 0.15 | W75: 0 | X75: 0 | Y75: 0 | Z75: 0 | AA75: 0
A76: Sullivan's Steakhouse | B76: Restaurant | C76: NO | D76: 0 | E76: Park Inc | F76: Complimentary Valet | G76: 0 | H76: 3 | I76: 1 | J76: 2 | K76: 3 | L76: 2 | M76: 0 | O76: 2.15 | P76: 2.15 | Q76: D — Deprioritized | R76: 0 | S76: 0.027 | T76: 0.0825 | U76: 0.123 | V76: 0.15 | W76: 0 | X76: 0 | Y76: 0 | Z76: 0 | AA76: 0
A77: Aria and Cicchetti | B77: Restaurant | C77: YES | D77: 0 | E77: Park Inc | F77: Complimentary Valet | G77: 0 | H77: 3 | I77: 1 | J77: 2 | K77: 3 | L77: 4 | M77: 0 | O77: 2.45 | P77: 2.45 | Q77: D — Deprioritized | R77: 0 | S77: 0.027 | T77: 0.0825 | U77: 0.123 | V77: 0.15 | W77: 0 | X77: 0 | Y77: 0 | Z77: 0 | AA77: 0
A78: Dressler's Steakhouse | B78: Restaurant | C78: YES | D78: 0 | F78: Complimentary Valet | G78: 0 | H78: 3 | I78: 1 | J78: 2 | K78: 4 | L78: 4 | M78: 0 | O78: 2.6 | P78: 2.6 | Q78: C — Opportunistic | R78: 0.11 | S78: 0.20375 | T78: 0.365625 | U78: 0.48375 | V78: 0.5625 | W78: 0 | X78: 0 | Y78: 0 | Z78: 0 | AA78: 0
A79: Ruth's Chris | B79: Restaurant | C79: YES | D79: 0 | E79: SOPHI | F79: 15 | G79: 189843.75 | H79: 3 | I79: 1 | J79: 2 | K79: 3 | L79: 4 | M79: 1 | N79: Current operator: Darden | O79: 2.45 | P79: 3.45 | Q79: C — Opportunistic | R79: 0.11 | S79: 0.20375 | T79: 0.365625 | U79: 0.48375 | V79: 0.5625 | W79: 20882.812 | X79: 38680.664 | Y79: 69411.621 | Z79: 91836.914 | AA79: 106787.11
A80: Ruth's Chris #2 | B80: Restaurant | C80: NO | D80: 0 | E80: Park Inc | F80: Valet "temporaliy suspended" | G80: 0 | H80: 3 | I80: 1 | J80: 2 | K80: 3 | L80: 2 | M80: 1 | N80: Current operator: Darden | O80: 2.15 | P80: 3.15 | Q80: C — Opportunistic | R80: 0.11 | S80: 0.20375 | T80: 0.365625 | U80: 0.48375 | V80: 0.5625 | W80: 0 | X80: 0 | Y80: 0 | Z80: 0 | AA80: 0
A81: Oak Steakhouse | B81: Restaurant | C81: NO | D81: 0 | E81: None | F81: Valet "temporaliy suspended" | G81: 132890.62 | H81: 3 | I81: 1 | J81: 2 | K81: 3 | L81: 2 | M81: 0 | O81: 2.15 | P81: 2.15 | Q81: D — Deprioritized | R81: 0 | S81: 0.027 | T81: 0.0825 | U81: 0.123 | V81: 0.15 | W81: 0 | X81: 3588.0469 | Y81: 10963.477 | Z81: 16345.547 | AA81: 19933.594

Sheet SOM_Summary_v2
A1: Charlotte — WAS v2 SOM Projection (state = WARM)
A2: Cold/Warm curves · S-curve ramp · Diversification multiplier · Relationship ledger
A4: Tier | B4: # Accts | C4: Total TAM | D4: Y1 | E4: Y2 | F4: Y3 | G4: Y4 | H4: Y5
A5: A — Beachhead | B5: 0 | C5: 0 | D5: 0 | E5: 0 | F5: 0 | G5: 0 | H5: 0
A6: B — Core | B6: 5 | C6: 7955971.2 | D6: 2187892.1 | E6: 3470792.4 | F6: 5494592.6 | G6: 6971419.8 | H6: 7955971.2
A7: C — Opportunistic | B7: 33 | C7: 7090095.4 | D7: 779910.49 | E7: 1444606.9 | F7: 2592316.1 | G7: 3429833.6 | H7: 3988178.6
A8: D — Deprioritized | B8: 42 | C8: 1527845.6 | D8: 0 | E8: 41251.832 | F8: 126047.26 | G8: 187925.01 | H8: 229176.84
A9: TOTAL (uncapped) | B9: 80 | C9: 16573912 | D9: 2967802.6 | E9: 4956651.2 | F9: 8212956 | G9: 10589178 | H9: 12173327
A11: CAPACITY-CAPPED SOM (single CM, 10 new accts/yr)
A12: Tier A+B, ranked by Y1 rev, cumulative 10/yr signing pace
B13: Accts Signed | D13: Y1 SOM | E13: Y2 SOM | F13: Y3 SOM | G13: Y4 SOM | H13: Y5 SOM
B14: End Y1: 10 | D14: 2566715.6
B15: End Y2: 20 | E15: 4812952.3
B16: End Y3: 30 | F16: 8086908.7
B17: End Y4: 38 | G17: 10401253
B18: End Y5: 38 | H18: 11944150
A20: BY ACCOUNT TYPE (uncapped)
A21: Type | B21: Count | C21: TAM | D21: Y1 | E21: Y3 | F21: Y5
A22: Hotel | B22: 38 | C22: 14356537 | D22: 2882183 | E22: 7809649.6 | F22: 11519647
A23: Restaurant | B23: 42 | C23: 2217375 | D23: 85619.531 | E23: 403306.44 | F23: 653679.49

Sheet Methodology_v2
A1: WAS v2 METHODOLOGY — SOPHI MOBILITY
A3: Market state: WARM (Warm = ≥3 current SOPHI anchor accounts in-market)
A5: CONVERSION CURVES (Y1 rate → Y5 rate per tier)
A6: Cold — A: 40% → 95%
A7: B: 8% → 75%
A8: C: 2% → 40%
A9: D: 0% → 10%
A10: Warm — A: 60% → 95%
A11: B: 25% → 80%
A12: C: 10% → 45%
A13: D: 0% → 15%
A15: S-CURVE ANNUAL RAMP (fraction of Y5-Y1 captured per year)
... A33: Source: config/relationships.yaml
