Workbook

Sheet INSTRUCTIONS
A1: DO NOT EDIT MASTER Market Analysis
A3: 2026 Denver, CO Market Analysis
A5: Sophi Mobility - Automated Valet Parking Services
A7: Generated: March 19, 2026
A9: Sheet Descriptions:
A11: Accounts | B11: Master list of all target accounts - hotels, restaurants, hospitals, event venues, airport
A12: Sales Cadence | B12: Outreach tracking with 11-touch sales cadence for each account
A13: To Copy this sheet: File -> Make a copy | B13: Inventory of public parking garages and lots with operators and rates
A14: RevenueForecasting | B14: Revenue model: rooms × occupancy × valet conversion × rate = annual revenue/NOI
A15: Analysis | B15: TAM/SAM/SOM market sizing, market score, and prioritization matrix
A16: Market Notes | B16: Key market data, rate benchmarks, tourism stats, and competitive landscape

Sheet Accounts
A1: Accounts | B1: Account Type | C1: Contact Created? | D1: Address | E1: Downtown (Yes or No) | F1: Phone Number | G1: Email | H1: URL | I1: Self Parking Rate | J1: Valet Rate | K1: # of Rooms/Beds | L1: Parking Reviews % | M1: Parking Reviews # | N1: GM Name | O1: Management Group | P1: Linked Accounts | Q1: Garage Operator | R1: Valet Operator | S1: Sourcing Notes | T1: Location Notes
A2: Le Méridien Denver Downtown | B2: Hotel | C2: False | D2: 1475 California St, Denver, CO 80202 | E2: YES | F2: (303) 893-1888 | H2: https://www.marriott.com/en-us/hotels/denmd-le-meridien-denver-downtown/overview/ | J2: 72 | K2: 272 | N2: Ebrahim Ansari | O2: White Lodging | Q2: Marriott | S2: upper-upscale | T2: White Lodging managed. Shares GM with AC Hotel Denver Downtown. Valet-only parking.
A3: The Ritz-Carlton, Denver | B3: Hotel | C3: False | D3: 1881 Curtis Street, Denver, CO 80202 | E3: YES | F3: (303) 312-3800 | H3: https://www.ritzcarlton.com/en/hotels/denrz-the-ritz-carlton-denver/overview/ | J3: 72 | K3: 205 | N3: Brad Mills | O3: Marriott International | S3: luxury | T3: Denver's premier luxury Marriott property.
A4: AC Hotel Denver Downtown | B4: Hotel | C4: False | D4: 750 15th St, Denver, CO 80202 | E4: NO | F4: (303) 825-2888 | H4: https://www.marriott.com/en-us/hotels/denac-ac-hotel-denver-downtown/overview/ | J4: 72 | K4: 223 | N4: Ebrahim Ansari | O4: White Lodging | Q4: Towne Park | R4: Towne Park | S4: upscale | T4: White Lodging managed. Towne Park valet. Shares GM with Le Méridien.
A5: Embassy Suites by Hilton Denver Downtown Convention Center | B5: Hotel | C5: False | D5: 1420 Stout St, Denver, CO 80202 | E5: NO | F5: (303) 592-1000 | H5: https://www.hilton.com/en/hotels/deneses-embassy-suites-denver-downtown-convention-center/ | J5: 70 | K5: 403 | N5: Ed Decker | O5: Sage Hospitality | R5: SP+ | S5: upper-upscale | T5: Valet only - no self-park on site. Updated 2026 rate: $70/night. SP+ operates valet per reviews.
A6: Aloft Denver Downtown | B6: Hotel | C6: False | D6: 800 15th St, Denver, CO 80202 | E6: NO | F6: (303) 623-3063 | H6: https://www.marriott.com/en-us/hotels/dendw-aloft-denver-downtown/overview/ | J6: 68 | K6: 140 | Q6: LAZ | R6: LAZ | S6: upscale | T6: Aloft Marriott brand. LAZ operates parking/valet.
A7: Sheraton Denver Downtown Hotel | B7: Hotel | C7: False | D7: 1550 Court Place, Denver, CO 80202 | E7: YES | F7: (303) 893-3333 | H7: https://www.marriott.com/en-us/hotels/dends-sheraton-denver-downtown-hotel/overview/ | I7: 57 | J7: 67 | K7: 1238 | N7: Tony Dunn | S7: upper-upscale | T7: Largest hotel in Denver by rooms. 139,165 sq ft meeting space. Updated 2026 rates: self $57, valet $67.
A8: Hyatt Regency Denver at Colorado Convention Center | B8: Hotel | C8: False | D8: 650 15th St, Denver, CO 80202 | E8: NO | F8: (303) 436-1234 | H8: https://www.hyatt.com/hyatt-regency/en-US/dencc-hyatt-regency-denver-at-colorado-convention-center | I8: 64 | J8: 67 | K8: 1100 | N8: Gregory Leonard | S8: upper-upscale | T8: 1,100 rooms - second largest hotel in Denver. Adjacent to Colorado Convention Center. 2026 valet rate: $67 overnight per Hyatt website.
A9: The Jacquard, Autograph Collection | B9: Hotel | C9: False | D9: 222 Milwaukee St, Denver, CO 80206 | E9: NO | F9: (303) 515-2000 | H9: https://www.marriott.com/en-us/hotels/dencr-the-jacquard-autograph-collection/overview/ | I9: 65 | J9: 65 | K9: 198 | N9: Thomas Lloyd | R9: Pro Park | S9: upper-upscale | T9: Boutique upscale hotel in Cherry Creek shopping district.
A10: Four Seasons Hotel Denver | B10: Hotel | C10: False | D10: 1111 14th St, Denver, CO 80202 | E10: YES | F10: (303) 389-3000 | H10: https://www.fourseasons.com/denver/ | J10: 65 | K10: 239 | N10: Thierry Kennel | O10: Four Seasons Hotels and Resorts | Q10: Four Seasons | R10: In House | S10: luxury | T10: Only 5-star luxury hotel in Denver. Valet operated in-house.
A11: The Brown Palace Hotel and Spa, Autograph Collection | B11: Hotel | C11: False | D11: 321 17th St, Denver, CO 80202 | E11: YES | F11: (303) 297-3111 | H11: https://www.marriott.com/en-us/hotels/denak-the-brown-palace-hotel-and-spa-autograph-collection/overview/ | J11: 65 | K11: 241 | N11: George Hanna | S11: luxury | T11: Denver's most iconic historic luxury hotel (1892). Michelin One Key 2024. Autograph Collection.
A12: Thompson Denver, by Hyatt | B12: Hotel | C12: False | D12: 1616 Market St, Denver, CO 80202 | E12: YES | F12: (303) 572-1321 | H12: https://www.hyatt.com/thompson-hotels/denth-thompson-denver | J12: 64 | K12: 216 | N12: Julian Tucker | O12: McWhinney | S12: luxury | T12: Boutique luxury hotel in LoDo. Chez Maggy restaurant, rooftop lounge.
A13: Grand Hyatt Denver | B13: Hotel | C13: False | D13: 1750 Welton St, Denver, CO 80202 | E13: YES | F13: (303) 295-1234 | H13: https://www.hyatt.com/grand-hyatt/en-US/denrd-grand-hyatt-denver | I13: 50 | J13: 64 | K13: 516 | N13: Greg Leonard | S13: upper-upscale | T13: 516-room Grand Hyatt near 16th Street Mall, Coors Field, Ball Arena.
A14: Hyatt Place Denver/Downtown | B14: Hotel | C14: False | D14: 440 14th St, Denver, CO 80202 | E14: NO | F14: (303) 893-2900 | H14: https://www.hyatt.com/hyatt-place/en-US/denzd-hyatt-place-denver-downtown | J14: 64 | K14: 248 | N14: Kimberly Gagnon | O14: White Lodging | Q14: Towne Park | R14: Towne Park | S14: upscale | T14: White Lodging managed. Towne Park operates valet. Shares address with Hyatt House.
A15: Populus | B15: Hotel | C15: False | D15: 240 14th St, Denver, CO 80202 | E15: NO | F15: (303) 800-4240 | H15: https://populusdenver.com/ | J15: 64 | K15: 265 | N15: George Prine | O15: Aparium Hotel Group | S15: upper-upscale | T15: Opened October 2024. First carbon-positive hotel in the US. 13-story aspen-inspired architecture. Aparium managed.
A16: Hilton Denver City Center | B16: Hotel | C16: False | D16: 1701 California St, Denver, CO 80202 | E16: YES | F16: (303) 297-1300 | H16: https://www.hilton.com/en/hotels/dencyhh-hilton-denver-city-center/ | J16: 64 | K16: 613 | N16: Mike Case | O16: Sage Hospitality | S16: upper-upscale | T16: Large full-service Hilton in downtown financial district. Sage Hospitality managed (as of Dec 2024).
A17: Halcyon, a hotel in Cherry Creek | B17: Hotel | C17: False | D17: 245 Columbine St, Denver, CO 80206 | E17: NO | F17: (720) 772-5000 | H17: https://www.halcyonhotelcherrycreek.com/ | J17: 60 | K17: 154 | N17: McClinton Heil | S17: luxury | T17: Boutique luxury hotel in Cherry Creek.
A18: Hampton Inn & Suites Denver Downtown-Convention Center | B18: Hotel | C18: False | D18: 550 15th St, Denver, CO 80202 | E18: NO | F18: (303) 623-5900 | H18: https://www.hilton.com/en/hotels/dencvhx-hampton-suites-denver-downtown-convention-center/ | J18: 60 | K18: 120 | Q18: Parking Management | S18: upper-midscale | T18: Shares block with Homewood Suites at 550 15th.
A19: Tru by Hilton Denver Downtown Convention Center | B19: Hotel | C19: False | D19: 801 15th St, Denver, CO 80202 | E19: NO | F19: (303) 753-1201 | H19: https://www.hilton.com/en/hotels/dencsru-tru-denver-downtown-convention-center/ | J19: 60 | K19: 176 | N19: Kara van Beek | S19: midscale | T19: Tru by Hilton brand. Shares GM with Home2 Suites at same address.
A20: Home2 Suites by Hilton Denver Downtown Convention Center | B20: Hotel | C20: False | D20: 801 15th St, Denver, CO 80202 | E20: NO | F20: (303) 759-1301 | H20: https://www.hilton.com/en/hotels/dentiht-home2-suites-denver-downtown-convention-center/ | J20: 60 | K20: 206 | N20: Kara van Beek | S20: upper-midscale | T20: Shares address and GM with Tru by Hilton.
A21: Homewood Suites by Hilton Denver Downtown-Convention Center | B21: Hotel | C21: False | D21: 550 15th St, Denver, CO 80202 | E21: NO | F21: (303) 534-7800 | H21: https://www.hilton.com/en/hotels/dendchw-homewood-suites-denver-downtown-convention-center-co/ | J21: 60 | K21: 182 | S21: upper-midscale | T21: Shares block with Hampton Inn at 550 15th. Recent renovation.
A22: Hotel Clio, a Luxury Collection Hotel, Denver Cherry Creek | B22: Hotel | C22: False | D22: 150 Clayton Ln, Denver, CO 80206 | E22: NO | F22: (303) 316-2700 | H22: https://www.marriott.com/en-us/hotels/denld-hotel-clio-a-luxury-collection-hotel-denver-cherry-creek/overview/ | J22: 59 | K22: 199 | N22: Marc Blackford | O22: Sage Hospitality | R22: Pro Park | S22: luxury | T22: Formerly JW Marriott Denver Cherry Creek. Rebranded to Luxury Collection.
A23: Clayton Hotel & Members Club | B23: Hotel | C23: False | D23: 233 Clayton St, Denver, CO 80206 | E23: NO | F23: (303) 551-1600 | H23: https://claytondenver.com/ | J23: 59 | K23: 63 | N23: Alison Mitchell | O23: Aparium Hotel Group | S23: luxury | T23: Boutique luxury members club hotel in Cherry Creek. Aparium managed.
A24: The Slate Hotel Denver Downtown, Tapestry by Hilton | B24: Hotel | C24: False | D24: 1250 Welton St, Denver, CO 80204 | E24: YES | F24: (303) 292-5000 | H24: https://www.hilton.com/en/hotels/denvrup-the-slate-hotel-denver-downtown/ | J24: 59 | K24: 251 | N24: Kirby Kiner | O24: Stonebridge Companies | Q24: Parkwell | S24: upscale | T24: Tapestry Collection by Hilton. Stonebridge managed. Parkwell operates garage.
A25: Kimpton Hotel Monaco Denver | B25: Hotel | C25: False | D25: 1717 Champa St, Denver, CO 80202 | E25: YES | F25: (303) 296-1717 | H25: https://www.monaco-denver.com/ | J25: 59 | K25: 189 | N25: Kevin Panzano | O25: IHG / Kimpton | Q25: Towne Park | R25: Towne Park | S25: upper-upscale | T25: Kimpton flagship downtown. Towne Park operates valet. Panzano Italian restaurant on site.
A26: Magnolia Hotel Denver, a Tribute Portfolio Hotel | B26: Hotel | C26: False | D26: 818 17th St, Denver, CO 80202 | E26: YES | F26: (303) 607-9000 | H26: https://www.marriott.com/en-us/hotels/denmg-magnolia-hotel-denver-a-tribute-portfolio-hotel/overview/ | J26: 59 | K26: 297 | N26: James Ancona | Q26: Marriott | S26: upscale | T26: Tribute Portfolio by Marriott in historic downtown building.
A27: Hyatt Centric Downtown Denver | B27: Hotel | C27: False | D27: 1776 Champa St, Denver, CO 80202 | E27: YES | F27: (303) 529-2340 | H27: https://www.hyatt.com/hyatt-centric/en-US/denct-hyatt-centric-downtown-denver | J27: 59 | K27: 264 | N27: Michael Galligan | S27: upscale | T27: 264 rooms per TripAdvisor. Rooftop bar. Valet-only at $59/night.
A28: Hotel Indigo Denver Downtown-Union Station | B28: Hotel | C28: False | D28: 1801 Wewatta St, Denver, CO 80202 | E28: NO | F28: (303) 623-4422 | H28: https://www.ihg.com/hotelindigo/hotels/us/en/denver/denws/hoteldetail | I28: 45 | J28: 55 | K28: 180 | N28: Michael Keytel | O28: Sage Hospitality | Q28: Intercontinental | S28: upscale | T28: IHG boutique brand. Steps from Union Station.
A29: Hotel Teatro | B29: Hotel | C29: False | D29: 1100 14th St, Denver, CO 80202 | E29: NO | F29: (888) 727-1200 | H29: https://www.hotelteatro.com/ | J29: 55 | K29: 111 | N29: Courtney Griffith | O29: Sage Hospitality | Q29: LAZ | R29: LAZ | S29: upper-upscale | T29: Boutique luxury theater district hotel. LAZ likely operates valet per garage operator pattern. Sold June 2024.
A30: Kimpton Claret Hotel | B30: Hotel | C30: False | D30: 6985 E. Chenango Ave, Denver, CO 80237 | E30: NO | F30: (983) 999-0310 | H30: https://www.clarethotel.com/ | J30: 55 | K30: 190 | N30: Keith Siebenaler | O30: IHG / Kimpton | S30: upper-upscale | T30: Opened July 2024. 19-story Kimpton with rooftop Halo Bar. 190 rooms. $55/night valet. Near Belleview Station.
A31: Apiary Hotel Belleview Station | B31: Hotel | C31: False | D31: 4855 S Quebec, Suite 150, Denver, CO 80237 | E31: NO | F31: (720) 791-4700 | H31: https://www.apiaryhotel.com/ | J31: 55 | K31: 175 | O31: Marriott / Residence Inn | S31: upscale | T31: Opened January 2026. Boutique Residence Inn-affiliated extended stay. 175 suites with kitchenettes. Near DTC and Belleview Station lightrail. Valet $55/night.
A32: The Art Hotel Denver, Curio Collection by Hilton | B32: Hotel | C32: False | D32: 1201 Broadway, Denver, CO 80203 | E32: NO | F32: (303) 572-8000 | H32: https://www.hilton.com/en/hotels/denrtqq-the-art-hotel-denver/ | J32: 54 | K32: 165 | N32: Dorian Phillips | S32: upscale | T32: Near Denver Art Museum. Curio Collection by Hilton. Valet-only parking.
A33: The Westin Denver Downtown | B33: Hotel | C33: False | D33: 1672 Lawrence St, Denver, CO 80202 | E33: NO | F33: (303) 572-9100 | H33: https://www.marriott.com/en-us/hotels/denwi-the-westin-denver-downtown/overview/ | I33: 40 | J33: 54 | K33: 432 | N33: Jerry Caliguire | S33: upper-upscale | T33: Full-service Westin in LoDo. Large conference hotel.
A34: The Westin Denver International Airport | B34: Hotel | C34: False | D34: 8300 Peña Boulevard, Denver, CO 80249 | E34: NO | F34: (303) 317-1800 | H34: https://www.marriott.com/en-us/hotels/denaw-the-westin-denver-international-airport/overview/ | I34: 54 | J34: 54 | K34: 519 | O34: Marriott International | Q34: Pro Park | R34: Pro Park | S34: upper-upscale | T34: Only hotel connected to DIA terminal. 519 rooms. Pro Park is exclusive valet at DIA. Hotel guests $54/night; airport guests $59. After 5 days: $35/night.
A35: The Maven Hotel at Dairy Block | B35: Hotel | C35: False | D35: 1850 Wazee St, Denver, CO 80202 | E35: NO | F35: (720) 460-2727 | H35: https://www.themavenhotel.com/ | J35: 53 | K35: 172 | N35: Jennifer Cottingias | O35: Sage Hospitality | Q35: Sage Hospitality | S35: upscale | T35: Part of the Dairy Block mixed-use development. Sage operates garage.
A36: Catbird Hotel | B36: Hotel | C36: False | D36: 3770 Walnut St, Denver, CO 80205 | E36: NO | F36: (720) 990-5555 | H36: https://www.catbirdhotel.com/ | I36: 34 | J36: 52 | K36: 165 | O36: Sage Hospitality | S36: upscale | T36: Boutique lifestyle hotel in River North Arts District.
A37: Limelight Denver | B37: Hotel | C37: False | D37: 2020 Little Raven St, Denver, CO 80202 | E37: NO | F37: (303) 323-0024 | H37: https://limelighthotels.com/denver | J37: 50 | K37: 200 | N37: Kim Corrigan | O37: Aspen Hospitality | S37: upscale | T37: Formerly Kimpton Hotel Born. Rebranded 2023. Near Union Station. Aspen Hospitality flagship urban property.
A38: The Crawford Hotel | B38: Hotel | C38: False | D38: 1701 Wynkoop St, Denver, CO 80202 | E38: NO | F38: (720) 460-3700 | H38: https://thecrawfordhotel.com/ | J38: 50 | K38: 112 | O38: Sage Hospitality | S38: upper-upscale | T38: Historic hotel inside Denver Union Station. $11M renovation completed July 2024. Michelin One Key designation 2024.
A39: Warwick Denver | B39: Hotel | C39: False | D39: 1776 Grant St, Denver, CO 80203 | E39: NO | F39: (303) 861-2000 | H39: https://www.warwickhotels.com/warwick-denver | I39: 50 | J39: 50 | K39: 216 | N39: Chad Hansen | Q39: SP Plus Corporation | R39: SP+ | S39: upscale | T39: Independent European chain. SP+ operates both self-park and valet.
A40: Moxy Denver Cherry Creek | B40: Hotel | C40: False | D40: 2401 E. 2nd Ave, Denver, CO 80206 | E40: NO | F40: (720) 707-3247 | H40: https://www.marriott.com/en-us/hotels/denox-moxy-denver-cherry-creek/overview/ | J40: 49 | K40: 140 | N40: Emily Jackson | O40: Sage Hospitality | S40: upscale | T40: Trendy Marriott Moxy brand in Cherry Creek.
A41: SpringHill Suites Denver Downtown | B41: Hotel | C41: False | D41: 1190 Auraria Parkway, Denver, CO 80204 | E41: NO | F41: (303) 825-7000 | H41: https://www.marriott.com/en-us/hotels/densd-springhill-suites-denver-downtown/overview/ | J41: 49 | K41: 150 | N41: Ryan Kensinger | O41: Sage Hospitality | S41: upper-midscale | T41: Near Auraria Campus. Extended stay suites.
A42: Hilton Garden Inn Denver Union Station | B42: Hotel | C42: False | D42: 1999 Chestnut Pl, Denver, CO 80202 | E42: YES | F42: (720) 643-1999 | H42: https://www.hilton.com/en/hotels/denungi-hilton-garden-inn-denver-union-station/ | J42: 49 | K42: 223 | S42: upscale | T42: Hilton Garden Inn near Union Station transit hub.
A43: Gaylord Rockies Resort & Convention Center | B43: Hotel | C43: False | D43: 6700 North Gaylord Rockies Blvd, Aurora, CO 80019 | E43: NO | F43: (720) 452-6900 | H43: https://www.marriott.com/en-us/hotels/dengr-gaylord-rockies-resort-and-convention-center/overview/ | I43: 33 | J43: 48 | K43: 1501 | N43: Suzy Hart | O43: Marriott International / Gaylord Hotels | S43: upper-upscale | T43: Largest resort in Colorado. 1,501 rooms. Near DIA. Arapahoe Springs water park. Self-park $33, valet $48 daily (2026 rates). Suzy Hart is GM since 2020.
A44: The Rally Hotel at McGregor Square | B44: Hotel | C44: False | D44: 1600 20th St, Denver, CO 80202 | E44: NO | F44: (303) 623-8500 | H44: https://www.therallyhotelatmcgregorsquare.com/ | J44: 46 | K44: 182 | N44: Maria DeLibero | O44: Sage Hospitality | S44: upscale | T44: Part of McGregor Square development adjacent to Coors Field.
A45: Hampton Inn & Suites Denver-Downtown | B45: Hotel | C45: False | D45: 1845 Sherman St, Denver, CO 80203 | E45: NO | F45: (303) 864-8000 | H45: https://www.hilton.com/en/hotels/dendthx-hampton-suites-denver-downtown/ | J45: 45 | K45: 156 | S45: upper-midscale | T45: Hampton near Capitol Hill neighborhood.
A46: Renaissance Denver Downtown City Center Hotel | B46: Hotel | C46: False | D46: 918 17th St, Denver, CO 80202 | E46: YES | F46: (303) 312-9100 | H46: https://www.marriott.com/en-us/hotels/denrn-renaissance-denver-downtown-city-center-hotel/overview/ | J46: 43 | K46: 230 | N46: Brian Leiker | O46: Stonebridge Companies | S46: upper-upscale | T46: Stonebridge managed Renaissance on 17th Street financial district.
A47: Hyatt House Denver/Downtown | B47: Hotel | C47: False | D47: 440 14th St, Denver, CO 80202 | E47: NO | F47: (303) 893-3100 | H47: https://www.hyatt.com/hyatt-house/en-US/denxd-hyatt-house-denver-downtown | J47: 42 | K47: 113 | S47: upscale | T47: Extended-stay Hyatt House at 440 14th. Shares address with Hyatt Place. Valet ~$42/night per reviews.
A48: The Oxford Hotel | B48: Hotel | C48: False | D48: 1600 17th St, Denver, CO 80202 | E48: YES | F48: (303) 628-5400 | H48: https://www.theoxfordhotel.com/ | J48: 40 | K48: 80 | O48: Sage Hospitality | R48: In House | S48: upper-upscale | T48: Historic landmark LoDo hotel. Denver's most historic hotel; valet operated in-house.
A49: Benson Hotel & Faculty Club | B49: Hotel | C49: False | D49: 13025 E Montview Blvd, Aurora, CO 80045 | E49: NO | F49: (720) 627-5958 | H49: https://thebensonhotel.com/ | I49: 22 | J49: 39 | K49: 106 | S49: upscale | T49: Faculty club hotel at University of Colorado Anschutz Medical Campus.
A50: The Ramble Hotel | B50: Hotel | C50: False | D50: 1280 25th St, Denver, CO 80205 | E50: NO | F50: (720) 996-6300 | H50: https://www.theramblehotel.com/ | J50: 35 | K50: 50 | N50: Andrew Guerra | S50: upper-upscale | T50: Boutique 50-room hotel in RiNo. At the threshold of valet worthiness by room count.
A51: Denver Marriott Tech Center | B51: Hotel | C51: False | D51: 4900 S. Syracuse Street, Denver, CO 80237 | E51: NO | F51: (303) 779-1100 | H51: https://www.marriott.com/en-us/hotels/dentc-denver-marriott-tech-center/overview/ | I51: 20 | J51: 25 | K51: 605 | N51: Jeff Bolton | O51: Sage Hospitality | S51: upper-upscale | T51: 605-room full-service Marriott in DTC. Sage Hospitality managed. Jeff Bolton is GM (as of March 2023+). Official hotel of Denver Summit FC.
A52: Hyatt Regency Denver Tech Center | B52: Hotel | C52: False | D52: 7800 E Tufts Ave, Denver, CO 80237 | E52: NO | F52: (303) 779-1234 | H52: https://www.hyatt.com/hyatt-regency/en-US/denve-hyatt-regency-denver-tech-center | I52: 15 | J52: 25 | K52: 451 | S52: upper-upscale | T52: 451 rooms in DTC. 30,000 sq ft meeting space. Near Belleview light rail. Self-park $15, valet $25 per historical rates (may have increased).
A53: Renaissance Denver Hotel & Conference Center | B53: Hotel | C53: False | D53: 3801 Quebec Street, Denver, CO 80207 | E53: NO | F53: (303) 399-7500 | H53: https://www.marriott.com/en-us/hotels/densa-renaissance-denver-hotel-and-conference-center/overview/ | I53: 21 | J53: 19 | K53: 399 | S53: upper-upscale | T53: 399 rooms. Between downtown and DIA near I-70/Quebec. Valet $19 (lower-cost market). Self-park $21. Covered 5-floor garage.
A54: DoubleTree by Hilton Hotel Denver | B54: Hotel | C54: False | D54: 3203 Quebec St, Denver, CO 80207 | E54: NO | F54: (303) 321-3333 | H54: https://www.hilton.com/en/hotels/rldv-dt-doubletree-denver/ | I54: 18 | J54: No Valet | K54: 561 | N54: Cheryl Biggins | S54: upscale | T54: Large full-service DoubleTree near I-70 / Quebec. Completed $18M renovation 2024.
A55: Courtyard Denver Central Park | B55: Hotel | C55: False | D55: 7415 E 41st Ave, Denver, CO 80216 | E55: NO | F55: (303) 333-3303 | H55: https://www.marriott.com/en-us/hotels/denca-courtyard-denver-central-park/overview/ | I55: 5 | J55: No Valet | K55: 146 | N55: Chris Davis | O55: Sage Hospitality | S55: upscale | T55: Near Central Park neighborhood.
A56: Hampton Inn & Suites Denver-Speer Boulevard | B56: Hotel | C56: False | D56: 2728 Zuni St, Denver, CO 80211 | E56: NO | F56: (303) 825-0500 | H56: https://www.hilton.com/en/hotels/densphi-hampton-inn-suites-denver-speer-boulevard/ | I56: Free | J56: No Valet | K56: 153 | S56: upper-midscale | T56: Free parking. Limited valet potential.
A57: Drury Inn & Suites Denver Central Park | B57: Hotel | C57: False | D57: 4550 N. Central Park Blvd, Denver, CO 80238 | E57: NO | F57: (303) 373-2313 | H57: https://www.druryhotels.com/locations/denver-co/drury-inn-and-suites-denver-central-park/ | I57: Free | J57: No Valet | K57: 209 | O57: Drury Hotels | S57: upper-midscale | T57: Drury-managed. Free parking. Rooms corrected from erroneous 1479 in original data.
A58: Cambria Hotel Denver Downtown RiNo | B58: Hotel | C58: False | D58: 3601 Brighton Blvd, Denver, CO 80216 | E58: NO | F58: (720) 806-7251 | H58: https://www.choicehotels.com/colorado/denver/cambria-hotels/co482 | I58: 20 | J58: No Valet | K58: 153 | N58: Phyllis Meyer | S58: upscale | T58: Opened September 2024. Choice Hotels Cambria brand in RiNo.
A59: The Source Hotel | B59: Hotel | C59: False | D59: 3330 Brighton Blvd, Denver, CO 80216 | E59: NO | F59: (720) 409-1200 | H59: https://www.thesourcehotel.com/ | I59: 24 | J59: No Valet | K59: 100 | N59: HC Noll | O59: Stockdale Capital Partners | Q59: LAZ | S59: upscale | T59: Boutique hotel attached to The Source food hall in RiNo. LAZ manages garage.
A60: the Curtis Denver - a DoubleTree by Hilton Hotel | B60: Hotel | C60: False | D60: 1405 Curtis Street, Denver, CO 80202 | E60: YES | F60: (303) 571-0300 | H60: https://www.hilton.com/en/hotels/denchdt-the-curtis-denver/ | I60: 45 | J60: No Valet | K60: 336 | N60: Lizzie Raudenbush | O60: Sage Hospitality | Q60: Hilton | S60: upscale | T60: Pop culture-themed DoubleTree. Self-park only - no valet. Prospect for valet upgrade.
A61: Courtyard Denver Downtown | B61: Hotel | C61: False | D61: 934 16th St, Denver, CO 80202 | E61: NO | F61: (303) 571-1114 | H61: https://www.marriott.com/en-us/hotels/dencd-courtyard-denver-downtown/overview/ | I61: 46 | J61: No Valet | K61: 177 | N61: Craig | O61: Sage Hospitality | Q61: Marriott | S61: upscale | T61: On 16th Street Mall. Self-park only at $46/night.
A62: Hyatt Regency Aurora-Denver Conference Center | B62: Hotel | C62: False | D62: 13200 E 14th Pl, Aurora, CO 80011 | E62: NO | F62: (303) 365-1234 | H62: https://www.hyatt.com/hyatt-regency/en-US/denhy-hyatt-regency-aurora-denver-conference-center | K62: 249 | N62: Daniel Benton | S62: upper-upscale | T62: Full-service Hyatt Regency near Anschutz Medical Campus and Veterans Hospital.
A63: Sonesta Denver Downtown | B63: Hotel | C63: False | D63: 1450 Glenarm Pl, Denver, CO 80202 | E63: YES | F63: (303) 573-1450 | H63: https://www.sonesta.com/sonesta-hotels-resorts/co/denver/sonesta-denver-downtown | I63: 47 | J63: No Valet | K63: 380 | N63: Jason Polland | S63: upper-upscale | T63: Large downtown full-service hotel. No valet currently - good prospect.
A64: Vīb Hotel by Best Western Denver RiNo | B64: Hotel | C64: False | D64: 3560 Brighton Blvd, Denver, CO 80216 | E64: NO | F64: (720) 844-3100 | H64: https://www.bestwestern.com/en_US/book/hotels-in-denver/v%C4%ABb-hotel-by-best-western-denver-rino/propertyCode.06199.html | I64: 15 | J64: No Valet | K64: 140 | O64: TWC Management | S64: midscale | T64: Best Western Vib lifestyle brand in RiNo.
A65: Element Denver Downtown East | B65: Hotel | C65: False | D65: 1314 Elati St, Denver, CO 80204 | E65: NO | F65: (720) 614-5555 | H65: https://www.marriott.com/en-us/hotels/dened-element-denver-downtown-east/overview/ | I65: 35 | J65: No Valet | K65: 157 | N65: Alexa | S65: upscale | T65: Extended stay Marriott Element brand.
A66: DoubleTree by Hilton Hotel Denver Tech Center | B66: Hotel | C66: False | D66: 7801 East Orchard Rd, Greenwood Village, CO 80111 | E66: NO | F66: (303) 779-6161 | H66: https://www.hilton.com/en/hotels/denewdt-doubletree-denver-tech-center/ | I66: Free | J66: No Valet | K66: 305 | S66: upscale | T66: Free self-parking. No valet. Prospect for valet program. Near Oracle, Deloitte. Free shuttle.
A67: Embassy Suites by Hilton Denver Tech Center | B67: Hotel | C67: False | D67: 10250 East Costilla Avenue, Centennial, CO 80112 | E67: NO | F67: (855) 605-0319 | H67: https://www.hilton.com/en/hotels/dentces-embassy-suites-denver-tech-center/ | I67: 20 | J67: No Valet | K67: 236 | S67: upper-upscale | T67: 236 rooms. No valet available. Self-park $20/day. Near Inverness Business Park, TopGolf. Good prospect for valet.
A68: The Inverness Denver, a Hilton Golf & Spa Resort | B68: Hotel | C68: False | D68: 200 Inverness Drive West, Englewood, CO 80112 | E68: NO | F68: (303) 799-5800 | H68: https://www.hilton.com/en/hotels/denirhh-the-inverness-denver-a-hilton-golf-and-spa-resort/ | I68: Free | J68: Free (included in resort fee) | K68: 302 | R68: In House | S68: upper-upscale | T68: Full resort with 18-hole golf, spa. 302 rooms. Valet included in resort fee. Valet operated in-house.
A69: Embassy Suites by Hilton Denver Tech Center North | B69: Hotel | C69: False | D69: 7525 East Hampden Ave, Denver, CO 80231 | E69: NO | F69: (303) 696-6644 | H69: https://www.hilton.com/en/hotels/deneses-embassy-suites-denver-tech-center-north/ | I69: Free | J69: No Valet | K69: 205 | S69: upper-upscale | T69: 205 rooms (sold April 2024). Near Cherry Creek, Aurora, DTC North. Free parking. Good valet prospect.
A70: Denver Marriott South at Park Meadows | B70: Hotel | C70: False | D70: 10345 Park Meadows Drive, Lone Tree, CO 80124 | E70: NO | F70: (303) 925-0004 | H70: https://www.marriott.com/en-us/hotels/denms-denver-marriott-south-at-park-meadows/overview/ | I70: 12 | J70: No Valet | K70: 279 | S70: upper-upscale | T70: Full-service Marriott near Park Meadows Mall. 279 committable rooms. No valet - strong prospect.
A71: Hilton Garden Inn Denver Tech Center | B71: Hotel | C71: False | D71: 7675 East Union Ave., Denver, CO 80237 | E71: NO | F71: (303) 770-7800 | H71: https://www.hilton.com/en/hotels/dentrgi-hilton-garden-inn-denver-tech-center/ | I71: 14 | J71: No Valet | K71: 180 | S71: upscale | T71: 180 rooms (sold Jan 2024). Near Belleview Station lightrail. Self-park $14/day. No valet - prospect.
A72: DoubleTree by Hilton Hotel Denver - Aurora | B72: Hotel | C72: False | D72: 3203 N. Peoria St, Aurora, CO 80010 | E72: NO | F72: (303) 371-0800 | H72: https://www.hilton.com/en/hotels/denitdt-doubletree-denver-aurora/ | I72: Free | J72: No Valet | K72: 248 | S72: upscale | T72: Free parking and free airport shuttle. Near I-225 and I-70. 14,000 sq ft event space.
A73: Crowne Plaza Denver Airport Convention Center | B73: Hotel | C73: False | D73: 15500 East 40th Ave, Denver, CO 80239 | E73: NO | F73: (303) 371-9494 | H73: https://www.ihg.com/crowneplaza/hotels/us/en/denver/denap/hoteldetail | I73: 10 | J73: No Valet | K73: 255 | O73: IHG | S73: upscale | T73: 255 rooms. 24/7 airport shuttle. Near DIA. Sold June 2024. Park and fly hotel. Note: reported as closed in some reviews - verify status.
A74: Courtyard Denver Downtown West (Stadium Area) | B74: Hotel | C74: False | D74: 1800 Federal Blvd, Denver, CO 80204 | E74: NO | F74: (720) 617-0700 | H74: https://www.marriott.com/en-us/hotels/dencs-courtyard-denver-downtown-west/overview/ | I74: 49 | J74: No Valet | K74: 118 | S74: upscale | T74: Opened January 2025. Adjacent to Empower Field at Mile High. 118 rooms. Panoramic city views, rooftop event space. Self-park $49/night.
A75: Urban Cowboy Denver | B75: Hotel | C75: False | D75: 1665 Grant St, Denver, CO 80203 | E75: NO | H75: https://www.urbancowboy.com/denver/ | I75: Free | J75: No Valet | K75: 9 | O75: Urban Cowboy Hotels | S75: luxury | T75: Opened October 2024. Boutique hotel in historic George Schleier Mansion (1886). 9 rooms - below valet threshold but notable new luxury opening. Wood-fire pizza restaurant.
A76: Hyatt Place Denver/Cherry Creek | B76: Hotel | C76: False | D76: 4150 East Mississippi Avenue, Glendale, CO 80246 | E76: NO | F76: (303) 782-9300 | H76: https://www.hyatt.com/hyatt-place/en-US/dengc-hyatt-place-denver-cherry-creek | I76: Free | J76: No Valet | K76: 133 | S76: upscale | T76: Near Cherry Creek and University of Denver. Free parking.
A77: Hyatt Place Denver Tech Center | B77: Hotel | C77: False | D77: 8300 East Crescent Parkway, Greenwood Village, CO 80111 | E77: NO | F77: (303) 804-0700 | H77: https://www.hyatt.com/hyatt-place/en-US/denzt-hyatt-place-denver-tech-center | I77: Free | J77: No Valet | K77: 126 | S77: upscale | T77: In DTC Greenwood Village. Free parking. Near Park Meadows Mall.
A78: Hyatt Place Denver Airport | B78: Hotel | C78: False | D78: 16250 East 40th Avenue, Aurora, CO 80011 | E78: NO | F78: (720) 875-2200 | H78: https://www.hyatt.com/hyatt-place/en-US/denza-hyatt-place-denver-airport | I78: Free | J78: No Valet | K78: 127 | S78: upscale | T78: Free parking and free airport shuttle. Near Gateway Park business district.
A79: Hyatt Place Peña Station / Denver Airport | B79: Hotel | C79: False | D79: 6110 North Panasonic Way, Denver, CO 80249 | E79: NO | F79: (720) 484-9300 | H79: https://www.hyatt.com/hyatt-place/en-US/denps-hyatt-place-pena-station-denver-airport | I79: Free | J79: No Valet | K79: 150 | S79: upscale | T79: Near DIA at Peña Station development. Free parking.
A80: Aloft Denver Airport at Gateway Park | B80: Hotel | C80: False | D80: 16470 East 40th Circle, Aurora, CO 80011 | E80: NO | F80: (303) 371-9500 | H80: https://www.marriott.com/en-us/hotels/denia-aloft-denver-airport-at-gateway-park/overview/ | I80: 16 | J80: No Valet | K80: 136 | S80: upscale | T80: Self-park $16/day. Airport area. SpotHero lists as cheapest airport parking option ($4-6/day for guests).
A81: Four Points by Sheraton Englewood Centennial Airport | B81: Hotel | C81: False | D81: 7770 South Peoria Street, Englewood, CO 80112 | E81: NO | F81: (720) 500-5750 | H81: https://www.marriott.com/en-us/hotels/deneu-four-points-englewood-centennial-airport/overview/ | I81: Free | J81: No Valet | K81: 132 | S81: upscale | T81: New hotel (opened 2025, renovated June 2025). Near Centennial Airport and DTC. Free parking.
A82: Mint House Denver - Downtown Union Station | B82: Hotel | C82: False | D82: 1777 Chestnut Place, Denver, CO 80202 | E82: YES | F82: (855) 972-9090 | H82: https://minthouse.com/denver/downtown-union-station/ | J82: No Valet | K82: 40 | O82: Mint House | S82: upscale | T82: Tech-forward apartment-hotel hybrid near Union Station. Small property.
A83: Sonder at Skyline | B83: Hotel | C83: False | D83: 2602 Bryant St, Denver, CO 80211 | E83: NO | F83: (617) 300-0956 | H83: https://www.sonder.com/destinations/denver/skyline/ | I83: 30 | J83: No Valet | K83: 93 | O83: Sonder | S83: upscale | T83: Opened April 2024. 93 apartment-style rooms at Highland/LoHi border.
A84: Hyatt House Denver Tech Center | B84: Hotel | C84: False | D84: 9280 E. Costilla Avenue, Englewood, CO 80112 | E84: NO | F84: (303) 799-2000 | H84: https://www.hyatt.com/hyatt-house/en-US/denyh-hyatt-house-denver-tech-center | I84: Free | J84: No Valet | K84: 128 | S84: upscale | T84: Extended-stay Hyatt House in DTC. Free parking. Near I-25.
A85: Springhill Suites by Marriott Denver Airport at Gateway Park | B85: Hotel | C85: False | D85: 18350 E 68th Ave, Denver, CO 80249 | E85: NO | F85: (720) 458-5000 | H85: https://www.marriott.com/en-us/hotels/densg-springhill-suites-denver-airport-at-gateway-park/overview/ | I85: Free | J85: No Valet | K85: 124 | S85: upper-midscale | T85: New hotel near DIA Gateway Park. Marriott new build.
A86: Hyatt House Denver Aurora Anschutz Medical Campus | B86: Hotel | C86: False | D86: 12230 E. Colfax Ave., Aurora, CO 80011 | E86: NO | F86: (303) 344-9600 | H86: https://www.hyatt.com/hyatt-house/en-US/denau-hyatt-house-denver-aurora-anschutz-medical-campus | I86: Free | J86: No Valet | K86: 124 | S86: upscale | T86: Extended-stay Hyatt House near Anschutz Medical Campus. 8 miles from downtown.
A87: Home2 Suites by Hilton Denver Central Park | B87: Hotel | C87: False | D87: 6675 N. Gaylord Rockies Blvd, Denver, CO 80238 | E87: NO | F87: (303) 373-2200 | H87: https://www.hilton.com/en/hotels/dennfht-home2-suites-denver-central-park/ | I87: Free | J87: No Valet | K87: 117 | S87: upper-midscale | T87: Free parking. Extended stay suites in Central Park neighborhood.
A88: The Capital Grille - Denver | B88: Restaurant | C88: False | D88: 1450 Larimer Street, Denver, CO 80202 | F88: (303) 539-2500 | H88: https://www.thecapitalgrille.com/locations/co/denver/denver/8018 | I88: Validated parking available in nearby garages | J88: Complimentary valet (free) for private dining; standard valet available at front | O88: Darden Restaurants | R88: Unknown (Darden Restaurants brand) | S88: Fine Dining - Steakhouse | T88: Valet directly out front on Larimer Street at 15th. LoDo / Larimer Square location. $50+ avg check.
A89: Ocean Prime - Denver (Larimer Square) | B89: Restaurant | C89: False | D89: 1465 Larimer Street, Denver, CO 80202 | F89: (303) 825-3663 | H89: https://ocean-prime.com/locations-menus/denver-larimer-square/ | I89: $15 with validation in nearby garage | J89: $25 valet or $15 validated at host desk | O89: Cameron Mitchell Restaurants | R89: Cameron Mitchell Restaurants | S89: Fine Dining - Seafood/Steakhouse | T89: LoDo / Larimer Square. Corner of 15th and Larimer. Avg check $50+. Valet confirmed via OpenTable.
A90: Ruth's Chris Steak House - Denver | B90: Restaurant | C90: False | D90: 707 15th Street, Denver, CO 80202 | F90: (303) 825-0713 | H90: https://www.ruthschris.com/restaurant-locations/denver/ | I90: Nearby public garages; Embassy Suites valet nearby at $185/month | J90: Available (rate not published) | O90: Ruth's Hospitality Group (Dine Brands) | R90: Ruth's Hospitality Group | S90: Fine Dining - Steakhouse | T90: Downtown Denver / CBD. Valet confirmed via OpenTable and TripAdvisor. Avg check $75+.
A91: STK Steakhouse Denver | B91: Restaurant | C91: False | D91: 1550 Market Street, Denver, CO 80202 | F91: (720) 597-8010 | H91: https://stksteakhouse.com/en-us/location/denver/ | I91: Free garage parking for lunch patrons until 4 PM. Market Station Valet Only Garage nearby at ~$23. | J91: No Valet | O91: ONE Group Hospitality | R91: ONE Group Hospitality | S91: Fine Dining - Steakhouse | T91: LoDo near Market Street and Union Station. Guests directed to nearby LoDo garages. Strong candidate for valet program. Avg check $60+.
A92: Guard & Grace | B92: Restaurant | C92: False | D92: 1801 California Street, Denver, CO 80202 | F92: (720) 328-0550 | H92: https://www.guardandgrace.com | I92: 1801 California St. Garage adjacent | O92: TAG Restaurant Group | R92: Chef/Owner Troy Guard (TAG Restaurant Group) | S92: Fine Dining - Modern Steakhouse | T92: 9,000 sq ft steakhouse in heart of downtown Denver. One of Denver's largest patios. Strong candidate for valet. Avg check $60+.
A93: Elway's Downtown | B93: Restaurant | C93: False | D93: 1881 Curtis Street, Denver, CO 80202 | F93: (303) 312-3107 | H93: https://www.elways.com/downtown-home/ | I93: Ritz-Carlton valet at approx. $400/month | J93: Via Ritz-Carlton Denver hotel valet (adjacent) | O93: John Elway Enterprises | R93: John Elway Enterprises / Ritz-Carlton hotel valet | S93: Fine Dining - Steakhouse | T93: Located at The Ritz-Carlton, Denver. Breakfast, lunch, and dinner. Hotel valet accessible. Avg check $60+.
A94: Elway's Cherry Creek | B94: Restaurant | C94: False | D94: 2500 E 1st Avenue, Denver, CO 80206 | F94: (303) 399-5353 | H94: https://www.elways.com/cherry-creek-home/ | I94: Validated parking in adjacent garage | J94: Not confirmed, parking available and validated | O94: John Elway Enterprises | R94: John Elway Enterprises | S94: Fine Dining - Steakhouse | T94: Cherry Creek location. TripAdvisor notes 'Parking Available, Validated Parking'. Strong candidate for valet program. Avg check $60+.
A95: Shanahan's Steakhouse | B95: Restaurant | C95: False | D95: 5085 S Syracuse Street, Denver, CO 80237 | F95: (303) 770-7300 | H95: https://www.shanahanssteakhouse.com | I95: Private parking lot on-site | J95: Available (rate not published) | O95: Shanahan's Restaurant Group | R95: Shanahan's Restaurant Group | S95: Fine Dining - Steakhouse | T95: SE Denver/DTC area. TripAdvisor confirms 'Valet Parking, Validated Parking'. #1 steakhouse in Denver per Zagat. Avg check $75+.
A96: Del Frisco's Double Eagle Steakhouse | B96: Restaurant | C96: False | D96: 8100 E Orchard Road, Denver, CO 80111 | F96: (303) 796-0100 | H96: https://www.delfriscos.com/location/del-friscos-double-eagle-steakhouse-denver-co/ | I96: Private parking lot on-site | J96: Available (own parking lot and valet service) | O96: Del Frisco's Restaurant Group | R96: Del Frisco's Restaurant Group / Lone Star Funds | S96: Fine Dining - Steakhouse | T96: Greenwood Village / DTC. Yelp reviewer confirms own parking lot and valet service. Avg check $70+.
A97: Del Frisco's Grille - Cherry Creek | B97: Restaurant | C97: False | D97: 100 St Paul Street, Suite 140, Denver, CO 80206 | F97: (303) 320-8529 | H97: https://www.delfriscosgrille.com/location/del-friscos-grille-cherry-creek-co/ | I97: Complimentary parking in attached garage | J97: No Valet | O97: Del Frisco's Restaurant Group | R97: Del Frisco's Restaurant Group | S97: Upscale Casual - Bar & Grill | T97: Cherry Creek location. Complimentary parking in attached garage — not currently using valet. Avg check $40-60.
A98: Tavernetta | B98: Restaurant | C98: False | D98: 1889 Sixteenth Street, Denver, CO 80202 | F98: (720) 605-1889 | H98: https://www.tavernettadenver.com | I98: $10 with validation at Park Union Station Garage (1881 16th St) | J98: $15 with restaurant validation at Limelight Hotel (1600 Wewatta St) | O98: Frasca Hospitality Group (Chef Lachlan Mackinnon-Patterson, MS Bobby Stuckey) | R98: Frasca Hospitality Group / Limelight Hotel valet | S98: Fine Dining - Italian | T98: Union Station neighborhood. James Beard Award-winning team. Valet confirmed at Limelight Hotel ($15 with validation). Avg check $70+.
A99: Sunday Vinyl | B99: Restaurant | C99: False | D99: 1803 16th Street Mall, Denver, CO 80202 | F99: (720) 738-1803 | H99: https://sundayvinyldenver.com | I99: Street parking and nearby garages along 16th Street Mall | O99: Frasca Hospitality Group | R99: Frasca Hospitality Group | S99: Upscale - European Wine Bar & Restaurant | T99: LoDo / 16th Street Mall. Part of Frasca Hospitality Group. European-inspired wine bar with full menu. Strong candidate if volumes justify valet.
A100: Frasca Food and Wine | B100: Restaurant | C100: False | D100: 1738 Pearl Street, Boulder, CO 80302 | F100: (303) 442-6966 | H100: https://www.frascafoodandwine.com | I100: Public garage at 15th and Pearl St | J100: No Valet | O100: Frasca Hospitality Group | R100: Frasca Hospitality Group | S100: Fine Dining - Italian (Friuli) | T100: Boulder, CO (not Denver). Michelin-starred. No valet offered — website confirms parking at public garage. Included for completeness as flagship Frasca brand.
...

Sheet Sales Cadence
A1: Accounts | B1: Contact Created? | C1: GM Name | D1: GM Contact Info | E1: Phone Number | F1: Garage Operator | G1: Valet Operator | H1: Self Parking Rate | I1: Valet Rate | J1: Sourcing Notes | K1: SALES NOTES | M1: 1. LinkedIn | N1: 2. Cold Call | O1: 3. In Person Visit | P1: 4. First Email | Q1: 5. Cold Call | R1: 6. Second Follow Up Email | S1: 7. Cold Call | T1: 8. 2nd In Person Visit | U1: 9. Cold Call + VM | V1: 10. Video Email - Owner | W1: 11. 3rd Email - Temp Check
A2: Le Méridien Denver Downtown | B2: False | C2: Ebrahim Ansari | E2: (303) 893-1888 | F2: Marriott | I2: 72 | J2: upper-upscale | M2: False | N2: False | O2: False | P2: False | Q2: False | R2: False | S2: False | T2: False | U2: False | V2: False | W2: False
A3: The Ritz-Carlton, Denver | B3: False | C3: Brad Mills | E3: (303) 312-3800 | I3: 72 | J3: luxury | M3: False | N3: False | O3: False | P3: False | Q3: False | R3: False | S3: False | T3: False | U3: False | V3: False | W3: False
A4: AC Hotel Denver Downtown | B4: False | C4: Ebrahim Ansari | E4: (303) 825-2888 | F4: Towne Park | G4: Towne Park | I4: 72 | J4: upscale | M4: False | N4: False | O4: False | P4: False | Q4: False | R4: False | S4: False | T4: False | U4: False | V4: False | W4: False
A5: Embassy Suites by Hilton Denver Downtown Convention Center | B5: False | C5: Ed Decker | E5: (303) 592-1000 | G5: SP+ | I5: 70 | J5: upper-upscale | M5: False | N5: False | O5: False | P5: False | Q5: False | R5: False | S5: False | T5: False | U5: False | V5: False | W5: False
A6: Aloft Denver Downtown | B6: False | E6: (303) 623-3063 | F6: LAZ | G6: LAZ | I6: 68 | J6: upscale | M6: False | N6: False | O6: False | P6: False | Q6: False | R6: False | S6: False | T6: False | U6: False | V6: False | W6: False
A7: Sheraton Denver Downtown Hotel | B7: False | C7: Tony Dunn | E7: (303) 893-3333 | H7: 57 | I7: 67 | J7: upper-upscale | M7: False | N7: False | O7: False | P7: False | Q7: False | R7: False | S7: False | T7: False | U7: False | V7: False | W7: False
A8: Hyatt Regency Denver at Colorado Convention Center | B8: False | C8: Gregory Leonard | E8: (303) 436-1234 | H8: 64 | I8: 67 | J8: upper-upscale | M8: False | N8: False | O8: False | P8: False | Q8: False | R8: False | S8: False | T8: False | U8: False | V8: False | W8: False
A9: The Jacquard, Autograph Collection | B9: False | C9: Thomas Lloyd | E9: (303) 515-2000 | G9: Pro Park | H9: 65 | I9: 65 | J9: upper-upscale | M9: False | N9: False | O9: False | P9: False | Q9: False | R9: False | S9: False | T9: False | U9: False | V9: False | W9: False
A10: Four Seasons Hotel Denver | B10: False | C10: Thierry Kennel | E10: (303) 389-3000 | F10: Four Seasons | G10: In House | I10: 65 | J10: luxury | M10: False | N10: False | O10: False | P10: False | Q10: False | R10: False | S10: False | T10: False | U10: False | V10: False | W10: False
A11: The Brown Palace Hotel and Spa, Autograph Collection | B11: False | C11: George Hanna | E11: (303) 297-3111 | I11: 65 | J11: luxury | M11: False | N11: False | O11: False | P11: False | Q11: False | R11: False | S11: False | T11: False | U11: False | V11: False | W11: False
A12: Thompson Denver, by Hyatt | B12: False | C12: Julian Tucker | E12: (303) 572-1321 | I12: 64 | J12: luxury | M12: False | N12: False | O12: False | P12: False | Q12: False | R12: False | S12: False | T12: False | U12: False | V12: False | W12: False
A13: Grand Hyatt Denver | B13: False | C13: Greg Leonard | E13: (303) 295-1234 | H13: 50 | I13: 64 | J13: upper-upscale | M13: False | N13: False | O13: False | P13: False | Q13: False | R13: False | S13: False | T13: False | U13: False | V13: False | W13: False
A14: Hyatt Place Denver/Downtown | B14: False | C14: Kimberly Gagnon | E14: (303) 893-2900 | F14: Towne Park | G14: Towne Park | I14: 64 | J14: upscale | M14: False | N14: False | O14: False | P14: False | Q14: False | R14: False | S14: False | T14: False | U14: False | V14: False | W14: False
A15: Populus | B15: False | C15: George Prine | E15: (303) 800-4240 | I15: 64 | J15: upper-upscale | M15: False | N15: False | O15: False | P15: False | Q15: False | R15: False | S15: False | T15: False | U15: False | V15: False | W15: False
A16: Hilton Denver City Center | B16: False | C16: Mike Case | E16: (303) 297-1300 | I16: 64 | J16: upper-upscale | M16: False | N16: False | O16: False | P16: False | Q16: False | R16: False | S16: False | T16: False | U16: False | V16: False | W16: False
A17: Halcyon, a hotel in Cherry Creek | B17: False | C17: McClinton Heil | E17: (720) 772-5000 | I17: 60 | J17: luxury | M17: False | N17: False | O17: False | P17: False | Q17: False | R17: False | S17: False | T17: False | U17: False | V17: False | W17: False
A18: Hampton Inn & Suites Denver Downtown-Convention Center | B18: False | E18: (303) 623-5900 | F18: Parking Management | I18: 60 | J18: upper-midscale | M18: False | N18: False | O18: False | P18: False | Q18: False | R18: False | S18: False | T18: False | U18: False | V18: False | W18: False
A19: Tru by Hilton Denver Downtown Convention Center | B19: False | C19: Kara van Beek | E19: (303) 753-1201 | I19: 60 | J19: midscale | M19: False | N19: False | O19: False | P19: False | Q19: False | R19: False | S19: False | T19: False | U19: False | V19: False | W19: False
A20: Home2 Suites by Hilton Denver Downtown Convention Center | B20: False | C20: Kara van Beek | E20: (303) 759-1301 | I20: 60 | J20: upper-midscale | M20: False | N20: False | O20: False | P20: False | Q20: False | R20: False | S20: False | T20: False | U20: False | V20: False | W20: False
A21: Homewood Suites by Hilton Denver Downtown-Convention Center | B21: False | E21: (303) 534-7800 | I21: 60 | J21: upper-midscale | M21: False | N21: False | O21: False | P21: False | Q21: False | R21: False | S21: False | T21: False | U21: False | V21: False | W21: False
A22: Hotel Clio, a Luxury Collection Hotel, Denver Cherry Creek | B22: False | C22: Marc Blackford | E22: (303) 316-2700 | G22: Pro Park | I22: 59 | J22: luxury | M22: False | N22: False | O22: False | P22: False | Q22: False | R22: False | S22: False | T22: False | U22: False | V22: False | W22: False
A23: Clayton Hotel & Members Club | B23: False | C23: Alison Mitchell | E23: (303) 551-1600 | I23: 59 | J23: luxury | M23: False | N23: False | O23: False | P23: False | Q23: False | R23: False | S23: False | T23: False | U23: False | V23: False | W23: False
A24: The Slate Hotel Denver Downtown, Tapestry by Hilton | B24: False | C24: Kirby Kiner | E24: (303) 292-5000 | F24: Parkwell | I24: 59 | J24: upscale | M24: False | N24: False | O24: False | P24: False | Q24: False | R24: False | S24: False | T24: False | U24: False | V24: False | W24: False
A25: Kimpton Hotel Monaco Denver | B25: False | C25: Kevin Panzano | E25: (303) 296-1717 | F25: Towne Park | G25: Towne Park | I25: 59 | J25: upper-upscale | M25: False | N25: False | O25: False | P25: False | Q25: False | R25: False | S25: False | T25: False | U25: False | V25: False | W25: False
A26: Magnolia Hotel Denver, a Tribute Portfolio Hotel | B26: False | C26: James Ancona | E26: (303) 607-9000 | F26: Marriott | I26: 59 | J26: upscale | M26: False | N26: False | O26: False | P26: False | Q26: False | R26: False | S26: False | T26: False | U26: False | V26: False | W26: False
A27: Hyatt Centric Downtown Denver | B27: False | C27: Michael Galligan | E27: (303) 529-2340 | I27: 59 | J27: upscale | M27: False | N27: False | O27: False | P27: False | Q27: False | R27: False | S27: False | T27: False | U27: False | V27: False | W27: False
A28: Hotel Indigo Denver Downtown-Union Station | B28: False | C28: Michael Keytel | E28: (303) 623-4422 | F28: Intercontinental | H28: 45 | I28: 55 | J28: upscale | M28: False | N28: False | O28: False | P28: False | Q28: False | R28: False | S28: False | T28: False | U28: False | V28: False | W28: False
A29: Hotel Teatro | B29: False | C29: Courtney Griffith | E29: (888) 727-1200 | F29: LAZ | G29: LAZ | I29: 55 | J29: upper-upscale | M29: False | N29: False | O29: False | P29: False | Q29: False | R29: False | S29: False | T29: False | U29: False | V29: False | W29: False
A30: Kimpton Claret Hotel | B30: False | C30: Keith Siebenaler | E30: (983) 999-0310 | I30: 55 | J30: upper-upscale | M30: False | N30: False | O30: False | P30: False | Q30: False | R30: False | S30: False | T30: False | U30: False | V30: False | W30: False
A31: Apiary Hotel Belleview Station | B31: False | E31: (720) 791-4700 | I31: 55 | J31: upscale | M31: False | N31: False | O31: False | P31: False | Q31: False | R31: False | S31: False | T31: False | U31: False | V31: False | W31: False
A32: The Art Hotel Denver, Curio Collection by Hilton | B32: False | C32: Dorian Phillips | E32: (303) 572-8000 | I32: 54 | J32: upscale | M32: False | N32: False | O32: False | P32: False | Q32: False | R32: False | S32: False | T32: False | U32: False | V32: False | W32: False
A33: The Westin Denver Downtown | B33: False | C33: Jerry Caliguire | E33: (303) 572-9100 | H33: 40 | I33: 54 | J33: upper-upscale | M33: False | N33: False | O33: False | P33: False | Q33: False | R33: False | S33: False | T33: False | U33: False | V33: False | W33: False
A34: The Westin Denver International Airport | B34: False | E34: (303) 317-1800 | F34: Pro Park | G34: Pro Park | H34: 54 | I34: 54 | J34: upper-upscale | M34: False | N34: False | O34: False | P34: False | Q34: False | R34: False | S34: False | T34: False | U34: False | V34: False | W34: False
A35: The Maven Hotel at Dairy Block | B35: False | C35: Jennifer Cottingias | E35: (720) 460-2727 | F35: Sage Hospitality | I35: 53 | J35: upscale | M35: False | N35: False | O35: False | P35: False | Q35: False | R35: False | S35: False | T35: False | U35: False | V35: False | W35: False
A36: Catbird Hotel | B36: False | E36: (720) 990-5555 | H36: 34 | I36: 52 | J36: upscale | M36: False | N36: False | O36: False | P36: False | Q36: False | R36: False | S36: False | T36: False | U36: False | V36: False | W36: False
A37: Limelight Denver | B37: False | C37: Kim Corrigan | E37: (303) 323-0024 | I37: 50 | J37: upscale | M37: False | N37: False | O37: False | P37: False | Q37: False | R37: False | S37: False | T37: False | U37: False | V37: False | W37: False
A38: The Crawford Hotel | B38: False | E38: (720) 460-3700 | I38: 50 | J38: upper-upscale | M38: False | N38: False | O38: False | P38: False | Q38: False | R38: False | S38: False | T38: False | U38: False | V38: False | W38: False
A39: Warwick Denver | B39: False | C39: Chad Hansen | E39: (303) 861-2000 | F39: SP Plus Corporation | G39: SP+ | H39: 50 | I39: 50 | J39: upscale | M39: False | N39: False | O39: False | P39: False | Q39: False | R39: False | S39: False | T39: False | U39: False | V39: False | W39: False
A40: Moxy Denver Cherry Creek | B40: False | C40: Emily Jackson | E40: (720) 707-3247 | I40: 49 | J40: upscale | M40: False | N40: False | O40: False | P40: False | Q40: False | R40: False | S40: False | T40: False | U40: False | V40: False | W40: False
A41: SpringHill Suites Denver Downtown | B41: False | C41: Ryan Kensinger | E41: (303) 825-7000 | I41: 49 | J41: upper-midscale | M41: False | N41: False | O41: False | P41: False | Q41: False | R41: False | S41: False | T41: False | U41: False | V41: False | W41: False
A42: Hilton Garden Inn Denver Union Station | B42: False | E42: (720) 643-1999 | I42: 49 | J42: upscale | M42: False | N42: False | O42: False | P42: False | Q42: False | R42: False | S42: False | T42: False | U42: False | V42: False | W42: False
A43: Gaylord Rockies Resort & Convention Center | B43: False | C43: Suzy Hart | E43: (720) 452-6900 | H43: 33 | I43: 48 | J43: upper-upscale | M43: False | N43: False | O43: False | P43: False | Q43: False | R43: False | S43: False | T43: False | U43: False | V43: False | W43: False
A44: The Rally Hotel at McGregor Square | B44: False | C44: Maria DeLibero | E44: (303) 623-8500 | I44: 46 | J44: upscale | M44: False | N44: False | O44: False | P44: False | Q44: False | R44: False | S44: False | T44: False | U44: False | V44: False | W44: False
A45: Hampton Inn & Suites Denver-Downtown | B45: False | E45: (303) 864-8000 | I45: 45 | J45: upper-midscale | M45: False | N45: False | O45: False | P45: False | Q45: False | R45: False | S45: False | T45: False | U45: False | V45: False | W45: False
A46: Renaissance Denver Downtown City Center Hotel | B46: False | C46: Brian Leiker | E46: (303) 312-9100 | I46: 43 | J46: upper-upscale | M46: False | N46: False | O46: False | P46: False | Q46: False | R46: False | S46: False | T46: False | U46: False | V46: False | W46: False
A47: Hyatt House Denver/Downtown | B47: False | E47: (303) 893-3100 | I47: 42 | J47: upscale | M47: False | N47: False | O47: False | P47: False | Q47: False | R47: False | S47: False | T47: False | U47: False | V47: False | W47: False
A48: The Oxford Hotel | B48: False | E48: (303) 628-5400 | G48: In House | I48: 40 | J48: upper-upscale | M48: False | N48: False | O48: False | P48: False | Q48: False | R48: False | S48: False | T48: False | U48: False | V48: False | W48: False
A49: Benson Hotel & Faculty Club | B49: False | E49: (720) 627-5958 | H49: 22 | I49: 39 | J49: upscale | M49: False | N49: False | O49: False | P49: False | Q49: False | R49: False | S49: False | T49: False | U49: False | V49: False | W49: False
A50: The Ramble Hotel | B50: False | C50: Andrew Guerra | E50: (720) 996-6300 | I50: 35 | J50: upper-upscale | M50: False | N50: False | O50: False | P50: False | Q50: False | R50: False | S50: False | T50: False | U50: False | V50: False | W50: False
A51: Denver Marriott Tech Center | B51: False | C51: Jeff Bolton | E51: (303) 779-1100 | H51: 20 | I51: 25 | J51: upper-upscale | M51: False | N51: False | O51: False | P51: False | Q51: False | R51: False | S51: False | T51: False | U51: False | V51: False | W51: False
A52: Hyatt Regency Denver Tech Center | B52: False | E52: (303) 779-1234 | H52: 15 | I52: 25 | J52: upper-upscale | M52: False | N52: False | O52: False | P52: False | Q52: False | R52: False | S52: False | T52: False | U52: False | V52: False | W52: False
A53: Renaissance Denver Hotel & Conference Center | B53: False | E53: (303) 399-7500 | H53: 21 | I53: 19 | J53: upper-upscale | M53: False | N53: False | O53: False | P53: False | Q53: False | R53: False | S53: False | T53: False | U53: False | V53: False | W53: False
A54: DoubleTree by Hilton Hotel Denver | B54: False | C54: Cheryl Biggins | E54: (303) 321-3333 | H54: 18 | I54: No Valet | J54: upscale | M54: False | N54: False | O54: False | P54: False | Q54: False | R54: False | S54: False | T54: False | U54: False | V54: False | W54: False
A55: Courtyard Denver Central Park | B55: False | C55: Chris Davis | E55: (303) 333-3303 | H55: 5 | I55: No Valet | J55: upscale | M55: False | N55: False | O55: False | P55: False | Q55: False | R55: False | S55: False | T55: False | U55: False | V55: False | W55: False
A56: Hampton Inn & Suites Denver-Speer Boulevard | B56: False | E56: (303) 825-0500 | H56: Free | I56: No Valet | J56: upper-midscale | M56: False | N56: False | O56: False | P56: False | Q56: False | R56: False | S56: False | T56: False | U56: False | V56: False | W56: False
A57: Drury Inn & Suites Denver Central Park | B57: False | E57: (303) 373-2313 | H57: Free | I57: No Valet | J57: upper-midscale | M57: False | N57: False | O57: False | P57: False | Q57: False | R57: False | S57: False | T57: False | U57: False | V57: False | W57: False
A58: Cambria Hotel Denver Downtown RiNo | B58: False | C58: Phyllis Meyer | E58: (720) 806-7251 | H58: 20 | I58: No Valet | J58: upscale | M58: False | N58: False | O58: False | P58: False | Q58: False | R58: False | S58: False | T58: False | U58: False | V58: False | W58: False
A59: The Source Hotel | B59: False | C59: HC Noll | E59: (720) 409-1200 | F59: LAZ | H59: 24 | I59: No Valet | J59: upscale | M59: False | N59: False | O59: False | P59: False | Q59: False | R59: False | S59: False | T59: False | U59: False | V59: False | W59: False
A60: the Curtis Denver - a DoubleTree by Hilton Hotel | B60: False | C60: Lizzie Raudenbush | E60: (303) 571-0300 | F60: Hilton | H60: 45 | I60: No Valet | J60: upscale | M60: False | N60: False | O60: False | P60: False | Q60: False | R60: False | S60: False | T60: False | U60: False | V60: False | W60: False
A61: Courtyard Denver Downtown | B61: False | C61: Craig | E61: (303) 571-1114 | F61: Marriott | H61: 46 | I61: No Valet | J61: upscale | M61: False | N61: False | O61: False | P61: False | Q61: False | R61: False | S61: False | T61: False | U61: False | V61: False | W61: False
A62: Hyatt Regency Aurora-Denver Conference Center | B62: False | C62: Daniel Benton | E62: (303) 365-1234 | J62: upper-upscale | M62: False | N62: False | O62: False | P62: False | Q62: False | R62: False | S62: False | T62: False | U62: False | V62: False | W62: False
A63: Sonesta Denver Downtown | B63: False | C63: Jason Polland | E63: (303) 573-1450 | H63: 47 | I63: No Valet | J63: upper-upscale | M63: False | N63: False | O63: False | P63: False | Q63: False | R63: False | S63: False | T63: False | U63: False | V63: False | W63: False
A64: Vīb Hotel by Best Western Denver RiNo | B64: False | E64: (720) 844-3100 | H64: 15 | I64: No Valet | J64: midscale | M64: False | N64: False | O64: False | P64: False | Q64: False | R64: False | S64: False | T64: False | U64: False | V64: False | W64: False
A65: Element Denver Downtown East | B65: False | C65: Alexa | E65: (720) 614-5555 | H65: 35 | I65: No Valet | J65: upscale | M65: False | N65: False | O65: False | P65: False | Q65: False | R65: False | S65: False | T65: False | U65: False | V65: False | W65: False
A66: DoubleTree by Hilton Hotel Denver Tech Center | B66: False | E66: (303) 779-6161 | H66: Free | I66: No Valet | J66: upscale | M66: False | N66: False | O66: False | P66: False | Q66: False | R66: False | S66: False | T66: False | U66: False | V66: False | W66: False
A67: Embassy Suites by Hilton Denver Tech Center | B67: False | E67: (855) 605-0319 | H67: 20 | I67: No Valet | J67: upper-upscale | M67: False | N67: False | O67: False | P67: False | Q67: False | R67: False | S67: False | T67: False | U67: False | V67: False | W67: False
A68: The Inverness Denver, a Hilton Golf & Spa Resort | B68: False | E68: (303) 799-5800 | G68: In House | H68: Free | I68: Free (included in resort fee) | J68: upper-upscale | M68: False | N68: False | O68: False | P68: False | Q68: False | R68: False | S68: False | T68: False | U68: False | V68: False | W68: False
A69: Embassy Suites by Hilton Denver Tech Center North | B69: False | E69: (303) 696-6644 | H69: Free | I69: No Valet | J69: upper-upscale | M69: False | N69: False | O69: False | P69: False | Q69: False | R69: False | S69: False | T69: False | U69: False | V69: False | W69: False
A70: Denver Marriott South at Park Meadows | B70: False | E70: (303) 925-0004 | H70: 12 | I70: No Valet | J70: upper-upscale | M70: False | N70: False | O70: False | P70: False | Q70: False | R70: False | S70: False | T70: False | U70: False | V70: False | W70: False
A71: Hilton Garden Inn Denver Tech Center | B71: False | E71: (303) 770-7800 | H71: 14 | I71: No Valet | J71: upscale | M71: False | N71: False | O71: False | P71: False | Q71: False | R71: False | S71: False | T71: False | U71: False | V71: False | W71: False
A72: DoubleTree by Hilton Hotel Denver - Aurora | B72: False | E72: (303) 371-0800 | H72: Free | I72: No Valet | J72: upscale | M72: False | N72: False | O72: False | P72: False | Q72: False | R72: False | S72: False | T72: False | U72: False | V72: False | W72: False
A73: Crowne Plaza Denver Airport Convention Center | B73: False | E73: (303) 371-9494 | H73: 10 | I73: No Valet | J73: upscale | M73: False | N73: False | O73: False | P73: False | Q73: False | R73: False | S73: False | T73: False | U73: False | V73: False | W73: False
A74: Courtyard Denver Downtown West (Stadium Area) | B74: False | E74: (720) 617-0700 | H74: 49 | I74: No Valet | J74: upscale | M74: False | N74: False | O74: False | P74: False | Q74: False | R74: False | S74: False | T74: False | U74: False | V74: False | W74: False
A75: Urban Cowboy Denver | B75: False | H75: Free | I75: No Valet | J75: luxury | M75: False | N75: False | O75: False | P75: False | Q75: False | R75: False | S75: False | T75: False | U75: False | V75: False | W75: False
A76: Hyatt Place Denver/Cherry Creek | B76: False | E76: (303) 782-9300 | H76: Free | I76: No Valet | J76: upscale | M76: False | N76: False | O76: False | P76: False | Q76: False | R76: False | S76: False | T76: False | U76: False | V76: False | W76: False
A77: Hyatt Place Denver Tech Center | B77: False | E77: (303) 804-0700 | H77: Free | I77: No Valet | J77: upscale | M77: False | N77: False | O77: False | P77: False | Q77: False | R77: False | S77: False | T77: False | U77: False | V77: False | W77: False
A78: Hyatt Place Denver Airport | B78: False | E78: (720) 875-2200 | H78: Free | I78: No Valet | J78: upscale | M78: False | N78: False | O78: False | P78: False | Q78: False | R78: False | S78: False | T78: False | U78: False | V78: False | W78: False
A79: Hyatt Place Peña Station / Denver Airport | B79: False | E79: (720) 484-9300 | H79: Free | I79: No Valet | J79: upscale | M79: False | N79: False | O79: False | P79: False | Q79: False | R79: False | S79: False | T79: False | U79: False | V79: False | W79: False
A80: Aloft Denver Airport at Gateway Park | B80: False | E80: (303) 371-9500 | H80: 16 | I80: No Valet | J80: upscale | M80: False | N80: False | O80: False | P80: False | Q80: False | R80: False | S80: False | T80: False | U80: False | V80: False | W80: False
A81: Four Points by Sheraton Englewood Centennial Airport | B81: False | E81: (720) 500-5750 | H81: Free | I81: No Valet | J81: upscale | M81: False | N81: False | O81: False | P81: False | Q81: False | R81: False | S81: False | T81: False | U81: False | V81: False | W81: False
A82: Mint House Denver - Downtown Union Station | B82: False | E82: (855) 972-9090 | I82: No Valet | J82: upscale | M82: False | N82: False | O82: False | P82: False | Q82: False | R82: False | S82: False | T82: False | U82: False | V82: False | W82: False
A83: Sonder at Skyline | B83: False | E83: (617) 300-0956 | H83: 30 | I83: No Valet | J83: upscale | M83: False | N83: False | O83: False | P83: False | Q83: False | R83: False | S83: False | T83: False | U83: False | V83: False | W83: False
A84: Hyatt House Denver Tech Center | B84: False | E84: (303) 799-2000 | H84: Free | I84: No Valet | J84: upscale | M84: False | N84: False | O84: False | P84: False | Q84: False | R84: False | S84: False | T84: False | U84: False | V84: False | W84: False
A85: Springhill Suites by Marriott Denver Airport at Gateway Park | B85: False | E85: (720) 458-5000 | H85: Free | I85: No Valet | J85: upper-midscale | M85: False | N85: False | O85: False | P85: False | Q85: False | R85: False | S85: False | T85: False | U85: False | V85: False | W85: False
A86: Hyatt House Denver Aurora Anschutz Medical Campus | B86: False | E86: (303) 344-9600 | H86: Free | I86: No Valet | J86: upscale | M86: False | N86: False | O86: False | P86: False | Q86: False | R86: False | S86: False | T86: False | U86: False | V86: False | W86: False
A87: Home2 Suites by Hilton Denver Central Park | B87: False | E87: (303) 373-2200 | H87: Free | I87: No Valet | J87: upper-midscale | M87: False | N87: False | O87: False | P87: False | Q87: False | R87: False | S87: False | T87: False | U87: False | V87: False | W87: False
A88: The Capital Grille - Denver | B88: False | E88: (303) 539-2500 | G88: Unknown (Darden Restaurants brand) | H88: Validated parking available in nearby garages | I88: Complimentary valet (free) for private dining; standard valet available at front | J88: Fine Dining - Steakhouse | M88: False | N88: False | O88: False | P88: False | Q88: False | R88: False | S88: False | T88: False | U88: False | V88: False | W88: False
A89: Ocean Prime - Denver (Larimer Square) | B89: False | E89: (303) 825-3663 | G89: Cameron Mitchell Restaurants | H89: $15 with validation in nearby garage | I89: $25 valet or $15 validated at host desk | J89: Fine Dining - Seafood/Steakhouse | M89: False | N89: False | O89: False | P89: False | Q89: False | R89: False | S89: False | T89: False | U89: False | V89: False | W89: False
A90: Ruth's Chris Steak House - Denver | B90: False | E90: (303) 825-0713 | G90: Ruth's Hospitality Group | H90: Nearby public garages; Embassy Suites valet nearby at $185/month | I90: Available (rate not published) | J90: Fine Dining - Steakhouse | M90: False | N90: False | O90: False | P90: False | Q90: False | R90: False | S90: False | T90: False | U90: False | V90: False | W90: False
A91: STK Steakhouse Denver | B91: False | E91: (720) 597-8010 | G91: ONE Group Hospitality | H91: Free garage parking for lunch patrons until 4 PM. Market Station Valet Only Garage nearby at ~$23. | I91: No Valet | J91: Fine Dining - Steakhouse | M91: False | N91: False | O91: False | P91: False | Q91: False | R91: False | S91: False | T91: False | U91: False | V91: False | W91: False
A92: Guard & Grace | B92: False | E92: (720) 328-0550 | G92: Chef/Owner Troy Guard (TAG Restaurant Group) | H92: 1801 California St. Garage adjacent | J92: Fine Dining - Modern Steakhouse | M92: False | N92: False | O92: False | P92: False | Q92: False | R92: False | S92: False | T92: False | U92: False | V92: False | W92: False
A93: Elway's Downtown | B93: False | E93: (303) 312-3107 | G93: John Elway Enterprises / Ritz-Carlton hotel valet | H93: Ritz-Carlton valet at approx. $400/month | I93: Via Ritz-Carlton Denver hotel valet (adjacent) | J93: Fine Dining - Steakhouse | M93: False | N93: False | O93: False | P93: False | Q93: False | R93: False | S93: False | T93: False | U93: False | V93: False | W93: False
A94: Elway's Cherry Creek | B94: False | E94: (303) 399-5353 | G94: John Elway Enterprises | H94: Validated parking in adjacent garage | I94: Not confirmed, parking available and validated | J94: Fine Dining - Steakhouse | M94: False | N94: False | O94: False | P94: False | Q94: False | R94: False | S94: False | T94: False | U94: False | V94: False | W94: False
A95: Shanahan's Steakhouse | B95: False | E95: (303) 770-7300 | G95: Shanahan's Restaurant Group | H95: Private parking lot on-site | I95: Available (rate not published) | J95: Fine Dining - Steakhouse | M95: False | N95: False | O95: False | P95: False | Q95: False | R95: False | S95: False | T95: False | U95: False | V95: False | W95: False
A96: Del Frisco's Double Eagle Steakhouse | B96: False | E96: (303) 796-0100 | G96: Del Frisco's Restaurant Group / Lone Star Funds | H96: Private parking lot on-site | I96: Available (own parking lot and valet service) | J96: Fine Dining - Steakhouse | M96: False | N96: False | O96: False | P96: False | Q96: False | R96: False | S96: False | T96: False | U96: False | V96: False | W96: False
A97: Del Frisco's Grille - Cherry Creek | B97: False | E97: (303) 320-8529 | G97: Del Frisco's Restaurant Group | H97: Complimentary parking in attached garage | I97: No Valet | J97: Upscale Casual - Bar & Grill | M97: False | N97: False | O97: False | P97: False | Q97: False | R97: False | S97: False | T97: False | U97: False | V97: False | W97: False
A98: Tavernetta | B98: False | E98: (720) 605-1889 | G98: Frasca Hospitality Group / Limelight Hotel valet | H98: $10 with validation at Park Union Station Garage (1881 16th St) | I98: $15 with restaurant validation at Limelight Hotel (1600 Wewatta St) | J98: Fine Dining - Italian | M98: False | N98: False | O98: False | P98: False | Q98: False | R98: False | S98: False | T98: False | U98: False | V98: False | W98: False
A99: Sunday Vinyl | B99: False | E99: (720) 738-1803 | G99: Frasca Hospitality Group | H99: Street parking and nearby garages along 16th Street Mall | J99: Upscale - European Wine Bar & Restaurant | M99: False | N99: False | O99: False | P99: False | Q99: False | R99: False | S99: False | T99: False | U99: False | V99: False | W99: False
A100: Frasca Food and Wine | B100: False | E100: (303) 442-6966 | G100: Frasca Hospitality Group | H100: Public garage at 15th and Pearl St | I100: No Valet | J100: Fine Dining - Italian (Friuli) | M100: False | N100: False | O100: False | P100: False | Q100: False | R100: False | S100: False | T100: False | U100: False | V100: False | W100: False
...

Sheet Parking
A1: Location ID | B1: Location Name | C1: Location Type | D1: Address | E1: # Spaces | F1: Unreserved Monthly Rate | G1: Operator | H1: Point of Contact | I1: POC Number | J1: URL | K1: Notes | L1: PARCs Equipment Notes
A2: 1 | B2: Denver Place Garage | C2: Garage | D2: 999 18th St, Denver, CO | E2: 1200 | F2: 235 | G2: ABM Parking
A3: 2 | B3: 16th Street Center Garage | C3: Garage | D3: 16th & Champa St, Denver, CO | E3: 800 | F3: 200 | G3: LAZ Parking
A4: 3 | B4: Tabor Center Garage | C4: Garage | D4: 1200 17th St, Denver, CO | E4: 1500 | F4: 225 | G4: SP+/Metropolis
A5: 4 | B5: Republic Plaza Garage | C5: Underground | D5: 370 17th St, Denver, CO | E5: 900 | F5: 250 | G5: SP+/Metropolis
A6: 5 | B6: Cherry Creek Shopping Center | C6: Garage | D6: 3000 E 1st Ave, Denver, CO | E6: 5700 | G6: Denison Parking | K6: Free for shoppers
A7: 6 | B7: Clayton Lane Garages | C7: Garage | D7: 225 Clayton Ln, Denver, CO | E7: 1200 | F7: 200 | G7: LAZ Parking | K7: Cherry Creek district
A8: 7 | B8: Union Station Block A | C8: Garage | D8: 1660 Wynkoop St, Denver, CO | E8: 500 | F8: 200 | G8: Interstate Parking | K8: LoDo area
A9: 8 | B9: LoDo Towers Garage | C9: Garage | D9: 1755 Wazee St, Denver, CO | E9: 400 | F9: 195 | G9: Interstate Parking | K9: Security robot deployed
A10: 9 | B10: Civic Center Park Garage | C10: Underground | D10: 101 W 14th Ave, Denver, CO | E10: 1100 | F10: 175 | G10: City of Denver
A11: 10 | B11: Convention Center Garage | C11: Garage | D11: 700 14th St, Denver, CO | E11: 2000 | F11: 210 | G11: City of Denver | K11: Adjacent to Colorado Convention Center
A12: 11 | B12: Ball Arena Lots | C12: Surface Lots | D12: 1000 Chopper Cir, Denver, CO | E12: 3000 | G12: LAZ Parking | K12: Event parking $35-$70
A13: 12 | B13: Coors Field Lots | C13: Surface Lots | D13: 2001 Blake St, Denver, CO | E13: 5000 | G13: SP+/Metropolis | K13: Game day parking $18-$35
A14: 13 | B14: Sheraton Denver Garage | C14: Garage | D14: 249 15th St, Denver, CO | E14: 800 | F14: 235 | G14: Propark Mobility | K14: Hotel/public parking
A15: 14 | B15: Hyatt Regency Garage | C15: Garage | D15: 650 15th St, Denver, CO | E15: 1000 | F15: 220 | G15: Propark Mobility | K15: Convention center adjacent
A16: 15 | B16: McGregor Square Garage | C16: Garage | D16: 1901 Wazee St, Denver, CO | E16: 500 | F16: 210 | G16: SP+/Metropolis | K16: Near Coors Field, Rally Hotel
A17: 16 | B17: DIA East Garage | C17: Garage | D17: Peña Blvd, Denver, CO | E17: 12000 | G17: LAZ Parking | K17: $30/day, $210/week
A18: 17 | B18: DIA West Garage | C18: Garage | D18: Peña Blvd, Denver, CO | E18: 12000 | G18: LAZ Parking | K18: $30/day, $210/week
A19: 18 | B19: DIA Economy East | C19: Surface Lot | D19: Peña Blvd, Denver, CO | E19: 8000 | G19: LAZ Parking | K19: $18/day
A20: 19 | B20: DIA Economy West | C20: Surface Lot | D20: Peña Blvd, Denver, CO | E20: 8000 | G20: LAZ Parking | K20: $18/day
A21: 20 | B21: DIA Pikes Peak Shuttle | C21: Surface Lot | D21: Peña Blvd, Denver, CO | E21: 5000 | G21: LAZ Parking | K21: $8/day shuttle

Sheet RevenueForecasting
A1: Account | B1: Account Type | C1: Valet Operator | D1: # of Rooms/Beds | E1: Occupancy Rate | F1: Forecast | G1: Valet Conversion Rate | H1: Estimated Daily Valet Count | I1: Estimated Daily Revenue | J1: Estimated Annual Revenue | K1: Estimate Net Operating Income Annually | L1: Total Daily Rev | M1: Total Annual Rev | N1: Total Annual NOI
A2: Le Méridien Denver Downtown | B2: Hotel | D2: 272 | E2: 0.6 | F2: =D2*E2 | G2: 0.4 | H2: =F2*G2 | I2: =H2*Accounts!J2 | J2: =I2*360 | K2: =J2*0.1 | L2: =SUM(I2:I136) | M2: =SUM(J2:J136) | N2: =SUM(K2:K136)
A3: The Ritz-Carlton, Denver | B3: Hotel | D3: 205 | E3: 0.6 | F3: =D3*E3 | G3: 0.4 | H3: =F3*G3 | I3: =H3*Accounts!J3 | J3: =I3*360 | K3: =J3*0.1
A4: AC Hotel Denver Downtown | B4: Hotel | C4: Towne Park | D4: 223 | E4: 0.6 | F4: =D4*E4 | G4: 0.4 | H4: =F4*G4 | I4: =H4*Accounts!J4 | J4: =I4*360 | K4: =J4*0.1
A5: Embassy Suites by Hilton Denver Downtown Convention Center | B5: Hotel | C5: SP+ | D5: 403 | E5: 0.6 | F5: =D5*E5 | G5: 0.4 | H5: =F5*G5 | I5: =H5*Accounts!J5 | J5: =I5*360 | K5: =J5*0.1
A6: Aloft Denver Downtown | B6: Hotel | C6: LAZ | D6: 140 | E6: 0.6 | F6: =D6*E6 | G6: 0.4 | H6: =F6*G6 | I6: =H6*Accounts!J6 | J6: =I6*360 | K6: =J6*0.1
A7: Sheraton Denver Downtown Hotel | B7: Hotel | D7: 1238 | E7: 0.6 | F7: =D7*E7 | G7: 0.4 | H7: =F7*G7 | I7: =H7*Accounts!J7 | J7: =I7*360 | K7: =J7*0.1
A8: Hyatt Regency Denver at Colorado Convention Center | B8: Hotel | D8: 1100 | E8: 0.6 | F8: =D8*E8 | G8: 0.4 | H8: =F8*G8 | I8: =H8*Accounts!J8 | J8: =I8*360 | K8: =J8*0.1
A9: The Jacquard, Autograph Collection | B9: Hotel | C9: Pro Park | D9: 198 | E9: 0.6 | F9: =D9*E9 | G9: 0.4 | H9: =F9*G9 | I9: =H9*Accounts!J9 | J9: =I9*360 | K9: =J9*0.1
A10: Four Seasons Hotel Denver | B10: Hotel | C10: In House | D10: 239 | E10: 0.6 | F10: =D10*E10 | G10: 0.4 | H10: =F10*G10 | I10: =H10*Accounts!J10 | J10: =I10*360 | K10: =J10*0.1
A11: The Brown Palace Hotel and Spa, Autograph Collection | B11: Hotel | D11: 241 | E11: 0.6 | F11: =D11*E11 | G11: 0.4 | H11: =F11*G11 | I11: =H11*Accounts!J11 | J11: =I11*360 | K11: =J11*0.1
A12: Thompson Denver, by Hyatt | B12: Hotel | D12: 216 | E12: 0.6 | F12: =D12*E12 | G12: 0.4 | H12: =F12*G12 | I12: =H12*Accounts!J12 | J12: =I12*360 | K12: =J12*0.1
A13: Grand Hyatt Denver | B13: Hotel | D13: 516 | E13: 0.6 | F13: =D13*E13 | G13: 0.4 | H13: =F13*G13 | I13: =H13*Accounts!J13 | J13: =I13*360 | K13: =J13*0.1
A14: Hyatt Place Denver/Downtown | B14: Hotel | C14: Towne Park | D14: 248 | E14: 0.6 | F14: =D14*E14 | G14: 0.4 | H14: =F14*G14 | I14: =H14*Accounts!J14 | J14: =I14*360 | K14: =J14*0.1
A15: Populus | B15: Hotel | D15: 265 | E15: 0.6 | F15: =D15*E15 | G15: 0.4 | H15: =F15*G15 | I15: =H15*Accounts!J15 | J15: =I15*360 | K15: =J15*0.1
A16: Hilton Denver City Center | B16: Hotel | D16: 613 | E16: 0.6 | F16: =D16*E16 | G16: 0.4 | H16: =F16*G16 | I16: =H16*Accounts!J16 | J16: =I16*360 | K16: =J16*0.1
A17: Halcyon, a hotel in Cherry Creek | B17: Hotel | D17: 154 | E17: 0.6 | F17: =D17*E17 | G17: 0.4 | H17: =F17*G17 | I17: =H17*Accounts!J17 | J17: =I17*360 | K17: =J17*0.1
A18: Hampton Inn & Suites Denver Downtown-Convention Center | B18: Hotel | D18: 120 | E18: 0.6 | F18: =D18*E18 | G18: 0.4 | H18: =F18*G18 | I18: =H18*Accounts!J18 | J18: =I18*360 | K18: =J18*0.1
A19: Tru by Hilton Denver Downtown Convention Center | B19: Hotel | D19: 176 | E19: 0.6 | F19: =D19*E19 | G19: 0.4 | H19: =F19*G19 | I19: =H19*Accounts!J19 | J19: =I19*360 | K19: =J19*0.1
A20: Home2 Suites by Hilton Denver Downtown Convention Center | B20: Hotel | D20: 206 | E20: 0.6 | F20: =D20*E20 | G20: 0.4 | H20: =F20*G20 | I20: =H20*Accounts!J20 | J20: =I20*360 | K20: =J20*0.1
A21: Homewood Suites by Hilton Denver Downtown-Convention Center | B21: Hotel | D21: 182 | E21: 0.6 | F21: =D21*E21 | G21: 0.4 | H21: =F21*G21 | I21: =H21*Accounts!J21 | J21: =I21*360 | K21: =J21*0.1
A22: Hotel Clio, a Luxury Collection Hotel, Denver Cherry Creek | B22: Hotel | C22: Pro Park | D22: 199 | E22: 0.6 | F22: =D22*E22 | G22: 0.4 | H22: =F22*G22 | I22: =H22*Accounts!J22 | J22: =I22*360 | K22: =J22*0.1
A23: Clayton Hotel & Members Club | B23: Hotel | D23: 63 | E23: 0.6 | F23: =D23*E23 | G23: 0.4 | H23: =F23*G23 | I23: =H23*Accounts!J23 | J23: =I23*360 | K23: =J23*0.1
A24: The Slate Hotel Denver Downtown, Tapestry by Hilton | B24: Hotel | D24: 251 | E24: 0.6 | F24: =D24*E24 | G24: 0.4 | H24: =F24*G24 | I24: =H24*Accounts!J24 | J24: =I24*360 | K24: =J24*0.1
A25: Kimpton Hotel Monaco Denver | B25: Hotel | C25: Towne Park | D25: 189 | E25: 0.6 | F25: =D25*E25 | G25: 0.4 | H25: =F25*G25 | I25: =H25*Accounts!J25 | J25: =I25*360 | K25: =J25*0.1
A26: Magnolia Hotel Denver, a Tribute Portfolio Hotel | B26: Hotel | D26: 297 | E26: 0.6 | F26: =D26*E26 | G26: 0.4 | H26: =F26*G26 | I26: =H26*Accounts!J26 | J26: =I26*360 | K26: =J26*0.1
A27: Hyatt Centric Downtown Denver | B27: Hotel | D27: 264 | E27: 0.6 | F27: =D27*E27 | G27: 0.4 | H27: =F27*G27 | I27: =H27*Accounts!J27 | J27: =I27*360 | K27: =J27*0.1
A28: Hotel Indigo Denver Downtown-Union Station | B28: Hotel | D28: 180 | E28: 0.6 | F28: =D28*E28 | G28: 0.4 | H28: =F28*G28 | I28: =H28*Accounts!J28 | J28: =I28*360 | K28: =J28*0.1
A29: Hotel Teatro | B29: Hotel | C29: LAZ | D29: 111 | E29: 0.6 | F29: =D29*E29 | G29: 0.4 | H29: =F29*G29 | I29: =H29*Accounts!J29 | J29: =I29*360 | K29: =J29*0.1
A30: Kimpton Claret Hotel | B30: Hotel | D30: 190 | E30: 0.6 | F30: =D30*E30 | G30: 0.4 | H30: =F30*G30 | I30: =H30*Accounts!J30 | J30: =I30*360 | K30: =J30*0.1
A31: Apiary Hotel Belleview Station | B31: Hotel | D31: 175 | E31: 0.6 | F31: =D31*E31 | G31: 0.4 | H31: =F31*G31 | I31: =H31*Accounts!J31 | J31: =I31*360 | K31: =J31*0.1
A32: The Art Hotel Denver, Curio Collection by Hilton | B32: Hotel | D32: 165 | E32: 0.6 | F32: =D32*E32 | G32: 0.4 | H32: =F32*G32 | I32: =H32*Accounts!J32 | J32: =I32*360 | K32: =J32*0.1
A33: The Westin Denver Downtown | B33: Hotel | D33: 432 | E33: 0.6 | F33: =D33*E33 | G33: 0.4 | H33: =F33*G33 | I33: =H33*Accounts!J33 | J33: =I33*360 | K33: =J33*0.1
A34: The Westin Denver International Airport | B34: Hotel | C34: Pro Park | D34: 519 | E34: 0.6 | F34: =D34*E34 | G34: 0.4 | H34: =F34*G34 | I34: =H34*Accounts!J34 | J34: =I34*360 | K34: =J34*0.1
A35: The Maven Hotel at Dairy Block | B35: Hotel | D35: 172 | E35: 0.6 | F35: =D35*E35 | G35: 0.4 | H35: =F35*G35 | I35: =H35*Accounts!J35 | J35: =I35*360 | K35: =J35*0.1
A36: Catbird Hotel | B36: Hotel | D36: 165 | E36: 0.6 | F36: =D36*E36 | G36: 0.4 | H36: =F36*G36 | I36: =H36*Accounts!J36 | J36: =I36*360 | K36: =J36*0.1
A37: Limelight Denver | B37: Hotel | D37: 200 | E37: 0.6 | F37: =D37*E37 | G37: 0.4 | H37: =F37*G37 | I37: =H37*Accounts!J37 | J37: =I37*360 | K37: =J37*0.1
A38: The Crawford Hotel | B38: Hotel | D38: 112 | E38: 0.6 | F38: =D38*E38 | G38: 0.4 | H38: =F38*G38 | I38: =H38*Accounts!J38 | J38: =I38*360 | K38: =J38*0.1
A39: Warwick Denver | B39: Hotel | C39: SP+ | D39: 216 | E39: 0.6 | F39: =D39*E39 | G39: 0.4 | H39: =F39*G39 | I39: =H39*Accounts!J39 | J39: =I39*360 | K39: =J39*0.1
A40: Moxy Denver Cherry Creek | B40: Hotel | D40: 140 | E40: 0.6 | F40: =D40*E40 | G40: 0.4 | H40: =F40*G40 | I40: =H40*Accounts!J40 | J40: =I40*360 | K40: =J40*0.1
A41: SpringHill Suites Denver Downtown | B41: Hotel | D41: 150 | E41: 0.6 | F41: =D41*E41 | G41: 0.4 | H41: =F41*G41 | I41: =H41*Accounts!J41 | J41: =I41*360 | K41: =J41*0.1
A42: Hilton Garden Inn Denver Union Station | B42: Hotel | D42: 223 | E42: 0.6 | F42: =D42*E42 | G42: 0.4 | H42: =F42*G42 | I42: =H42*Accounts!J42 | J42: =I42*360 | K42: =J42*0.1
A43: Gaylord Rockies Resort & Convention Center | B43: Hotel | D43: 1501 | E43: 0.6 | F43: =D43*E43 | G43: 0.4 | H43: =F43*G43 | I43: =H43*Accounts!J43 | J43: =I43*360 | K43: =J43*0.1
A44: The Rally Hotel at McGregor Square | B44: Hotel | D44: 182 | E44: 0.6 | F44: =D44*E44 | G44: 0.4 | H44: =F44*G44 | I44: =H44*Accounts!J44 | J44: =I44*360 | K44: =J44*0.1
A45: Hampton Inn & Suites Denver-Downtown | B45: Hotel | D45: 156 | E45: 0.6 | F45: =D45*E45 | G45: 0.4 | H45: =F45*G45 | I45: =H45*Accounts!J45 | J45: =I45*360 | K45: =J45*0.1
A46: Renaissance Denver Downtown City Center Hotel | B46: Hotel | D46: 230 | E46: 0.6 | F46: =D46*E46 | G46: 0.4 | H46: =F46*G46 | I46: =H46*Accounts!J46 | J46: =I46*360 | K46: =J46*0.1
A47: Hyatt House Denver/Downtown | B47: Hotel | D47: 113 | E47: 0.6 | F47: =D47*E47 | G47: 0.4 | H47: =F47*G47 | I47: =H47*Accounts!J47 | J47: =I47*360 | K47: =J47*0.1
A48: The Oxford Hotel | B48: Hotel | C48: In House | D48: 80 | E48: 0.6 | F48: =D48*E48 | G48: 0.4 | H48: =F48*G48 | I48: =H48*Accounts!J48 | J48: =I48*360 | K48: =J48*0.1
A49: Benson Hotel & Faculty Club | B49: Hotel | D49: 106 | E49: 0.6 | F49: =D49*E49 | G49: 0.4 | H49: =F49*G49 | I49: =H49*Accounts!J49 | J49: =I49*360 | K49: =J49*0.1
A50: The Ramble Hotel | B50: Hotel | D50: 50 | E50: 0.6 | F50: =D50*E50 | G50: 0.4 | H50: =F50*G50 | I50: =H50*Accounts!J50 | J50: =I50*360 | K50: =J50*0.1
A51: Denver Marriott Tech Center | B51: Hotel | D51: 605 | E51: 0.6 | F51: =D51*E51 | G51: 0.4 | H51: =F51*G51 | I51: =H51*Accounts!J51 | J51: =I51*360 | K51: =J51*0.1
A52: Hyatt Regency Denver Tech Center | B52: Hotel | D52: 451 | E52: 0.6 | F52: =D52*E52 | G52: 0.4 | H52: =F52*G52 | I52: =H52*Accounts!J52 | J52: =I52*360 | K52: =J52*0.1
A53: Renaissance Denver Hotel & Conference Center | B53: Hotel | D53: 399 | E53: 0.6 | F53: =D53*E53 | G53: 0.4 | H53: =F53*G53 | I53: =H53*Accounts!J53 | J53: =I53*360 | K53: =J53*0.1
A54: DoubleTree by Hilton Hotel Denver | B54: Hotel | D54: 561 | E54: 0.6 | F54: =D54*E54 | G54: 0.4 | H54: =F54*G54 | I54: 0 | J54: =I54*360 | K54: =J54*0.1
A55: Courtyard Denver Central Park | B55: Hotel | D55: 146 | E55: 0.6 | F55: =D55*E55 | G55: 0.4 | H55: =F55*G55 | I55: 0 | J55: =I55*360 | K55: =J55*0.1
A56: Hampton Inn & Suites Denver-Speer Boulevard | B56: Hotel | D56: 153 | E56: 0.6 | F56: =D56*E56 | G56: 0.4 | H56: =F56*G56 | I56: 0 | J56: =I56*360 | K56: =J56*0.1
A57: Drury Inn & Suites Denver Central Park | B57: Hotel | D57: 209 | E57: 0.6 | F57: =D57*E57 | G57: 0.4 | H57: =F57*G57 | I57: 0 | J57: =I57*360 | K57: =J57*0.1
A58: Cambria Hotel Denver Downtown RiNo | B58: Hotel | D58: 153 | E58: 0.6 | F58: =D58*E58 | G58: 0.4 | H58: =F58*G58 | I58: 0 | J58: =I58*360 | K58: =J58*0.1
A59: The Source Hotel | B59: Hotel | D59: 100 | E59: 0.6 | F59: =D59*E59 | G59: 0.4 | H59: =F59*G59 | I59: 0 | J59: =I59*360 | K59: =J59*0.1
A60: the Curtis Denver - a DoubleTree by Hilton Hotel | B60: Hotel | D60: 336 | E60: 0.6 | F60: =D60*E60 | G60: 0.4 | H60: =F60*G60 | I60: 0 | J60: =I60*360 | K60: =J60*0.1
A61: Courtyard Denver Downtown | B61: Hotel | D61: 177 | E61: 0.6 | F61: =D61*E61 | G61: 0.4 | H61: =F61*G61 | I61: 0 | J61: =I61*360 | K61: =J61*0.1
A62: Hyatt Regency Aurora-Denver Conference Center | B62: Hotel | D62: 249 | E62: 0.6 | F62: =D62*E62 | G62: 0.4 | H62: =F62*G62 | I62: 0 | J62: =I62*360 | K62: =J62*0.1
A63: Sonesta Denver Downtown | B63: Hotel | D63: 380 | E63: 0.6 | F63: =D63*E63 | G63: 0.4 | H63: =F63*G63 | I63: 0 | J63: =I63*360 | K63: =J63*0.1
A64: Vīb Hotel by Best Western Denver RiNo | B64: Hotel | D64: 140 | E64: 0.6 | F64: =D64*E64 | G64: 0.4 | H64: =F64*G64 | I64: 0 | J64: =I64*360 | K64: =J64*0.1
A65: Element Denver Downtown East | B65: Hotel | D65: 157 | E65: 0.6 | F65: =D65*E65 | G65: 0.4 | H65: =F65*G65 | I65: 0 | J65: =I65*360 | K65: =J65*0.1
... A67: Embassy Suites by Hilton Denver Tech Center | B67: Hotel | D67: 236 | E67: 0.6 | F67: =D67*E67 | G67: 0.4 | H67: =F67*G67 | I67: 0 | J67: =I67*360 | K67: =J67*0.1
A68: The Inverness Denver, a Hilton Golf & Spa Resort | B68: Hotel | C68: In House | D68: 302 | E68: 0.6 | F68: =D68*E68 | G68: 0.4 | H68: =F68*G68 | I68: 0 | J68: =I68*360 | K68: =J68*0.1
A69: Embassy Suites by Hilton Denver Tech Center North | B69: Hotel | D69: 205 | E69: 0.6 | F69: =D69*E69 | G69: 0.4 | H69: =F69*G69 | I69: 0 | J69: =I69*360 | K69: =J69*0.1
A70: Denver Marriott South at Park Meadows | B70: Hotel | D70: 279 | E70: 0.6 | F70: =D70*E70 | G70: 0.4 | H70: =F70*G70 | I70: 0 | J70: =I70*360 | K70: =J70*0.1
A71: Hilton Garden Inn Denver Tech Center | B71: Hotel | D71: 180 | E71: 0.6 | F71: =D71*E71 | G71: 0.4 | H71: =F71*G71 | I71: 0 | J71: =I71*360 | K71: =J71*0.1
A72: DoubleTree by Hilton Hotel Denver - Aurora | B72: Hotel | D72: 248 | E72: 0.6 | F72: =D72*E72 | G72: 0.4 | H72: =F72*G72 | I72: 0 | J72: =I72*360 | K72: =J72*0.1
A73: Crowne Plaza Denver Airport Convention Center | B73: Hotel | D73: 255 | E73: 0.6 | F73: =D73*E73 | G73: 0.4 | H73: =F73*G73 | I73: 0 | J73: =I73*360 | K73: =J73*0.1
A74: Courtyard Denver Downtown West (Stadium Area) | B74: Hotel | D74: 118 | E74: 0.6 | F74: =D74*E74 | G74: 0.4 | H74: =F74*G74 | I74: 0 | J74: =I74*360 | K74: =J74*0.1
A75: Urban Cowboy Denver | B75: Hotel | D75: 9 | E75: 0.6 | F75: =D75*E75 | G75: 0.4 | H75: =F75*G75 | I75: 0 | J75: =I75*360 | K75: =J75*0.1
A76: Hyatt Place Denver/Cherry Creek | B76: Hotel | D76: 133 | E76: 0.6 | F76: =D76*E76 | G76: 0.4 | H76: =F76*G76 | I76: 0 | J76: =I76*360 | K76: =J76*0.1
A77: Hyatt Place Denver Tech Center | B77: Hotel | D77: 126 | E77: 0.6 | F77: =D77*E77 | G77: 0.4 | H77: =F77*G77 | I77: 0 | J77: =I77*360 | K77: =J77*0.1
A78: Hyatt Place Denver Airport | B78: Hotel | D78: 127 | E78: 0.6 | F78: =D78*E78 | G78: 0.4 | H78: =F78*G78 | I78: 0 | J78: =I78*360 | K78: =J78*0.1
A79: Hyatt Place Peña Station / Denver Airport | B79: Hotel | D79: 150 | E79: 0.6 | F79: =D79*E79 | G79: 0.4 | H79: =F79*G79 | I79: 0 | J79: =I79*360 | K79: =J79*0.1
A80: Aloft Denver Airport at Gateway Park | B80: Hotel | D80: 136 | E80: 0.6 | F80: =D80*E80 | G80: 0.4 | H80: =F80*G80 | I80: 0 | J80: =I80*360 | K80: =J80*0.1
... A87: Home2 Suites by Hilton Denver Central Park | B87: Hotel | D87: 117 | E87: 0.6 | F87: =D87*E87 | G87: 0.4 | H87: =F87*G87 | I87: 0 | J87: =I87*360 | K87: =J87*0.1
A88: The Capital Grille - Denver | B88: Restaurant | C88: Unknown (Darden Restaurants brand) | D88: 100 | E88: 0.6 | F88: =D88*E88 | G88: 0.4 | H88: =F88*G88 | I88: 0 | J88: =I88*360 | K88: =J88*0.1
A89: Ocean Prime - Denver (Larimer Square) | B89: Restaurant | C89: Cameron Mitchell Restaurants | D89: 100 | E89: 0.6 | F89: =D89*E89 | G89: 0.4 | H89: =F89*G89 | I89: 0 | J89: =I89*360 | K89: =J89*0.1
A90: Ruth's Chris Steak House - Denver | B90: Restaurant | C90: Ruth's Hospitality Group | D90: 100 | E90: 0.6 | F90: =D90*E90 | G90: 0.4 | H90: =F90*G90 | I90: 0 | J90: =I90*360 | K90: =J90*0.1
A91: STK Steakhouse Denver | B91: Restaurant | C91: ONE Group Hospitality | D91: 100 | E91: 0.6 | F91: =D91*E91 | G91: 0.4 | H91: =F91*G91 | I91: 0 | J91: =I91*360 | K91: =J91*0.1
A92: Guard & Grace | B92: Restaurant | C92: Chef/Owner Troy Guard (TAG Restaurant Group) | D92: 100 | E92: 0.6 | F92: =D92*E92 | G92: 0.4 | H92: =F92*G92 | I92: 0 | J92: =I92*360 | K92: =J92*0.1
A93: Elway's Downtown | B93: Restaurant | C93: John Elway Enterprises / Ritz-Carlton hotel valet | D93: 100 | E93: 0.6 | F93: =D93*E93 | G93: 0.4 | H93: =F93*G93 | I93: 0 | J93: =I93*360 | K93: =J93*0.1
A94: Elway's Cherry Creek | B94: Restaurant | C94: John Elway Enterprises | D94: 100 | E94: 0.6 | F94: =D94*E94 | G94: 0.4 | H94: =F94*G94 | I94: 0 | J94: =I94*360 | K94: =J94*0.1
A95: Shanahan's Steakhouse | B95: Restaurant | C95: Shanahan's Restaurant Group | D95: 100 | E95: 0.6 | F95: =D95*E95 | G95: 0.4 | H95: =F95*G95 | I95: 0 | J95: =I95*360 | K95: =J95*0.1
A96: Del Frisco's Double Eagle Steakhouse | B96: Restaurant | C96: Del Frisco's Restaurant Group / Lone Star Funds | D96: 100 | E96: 0.6 | F96: =D96*E96 | G96: 0.4 | H96: =F96*G96 | I96: 0 | J96: =I96*360 | K96: =J96*0.1
A97: Del Frisco's Grille - Cherry Creek | B97: Restaurant | C97: Del Frisco's Restaurant Group | D97: 100 | E97: 0.6 | F97: =D97*E97 | G97: 0.4 | H97: =F97*G97 | I97: 0 | J97: =I97*360 | K97: =J97*0.1
A98: Tavernetta | B98: Restaurant | C98: Frasca Hospitality Group / Limelight Hotel valet | D98: 100 | E98: 0.6 | F98: =D98*E98 | G98: 0.4 | H98: =F98*G98 | I98: 0 | J98: =I98*360 | K98: =J98*0.1
A99: Sunday Vinyl | B99: Restaurant | C99: Frasca Hospitality Group | D99: 100 | E99: 0.6 | F99: =D99*E99 | G99: 0.4 | H99: =F99*G99 | I99: 0 | J99: =I99*360 | K99: =J99*0.1
... A121: St. Anthony Hospital (CommonSpirit/Centura) | B121: Hospital | C121: CommonSpirit Health (Centura Health) | D121: 100 | E121: 0.6 | F121: =D121*E121 | G121: 0.4 | H121: =F121*G121 | I121: 0 | J121: =I121*360 | K121: =J121*0.1
A122: Colorado Convention Center | B122: Event Venue | E122: 0.6 | F122: =D122*E122 | G122: 0.4 | H122: =F122*G122 | I122: 0 | J122: =I122*360 | K122: =J122*0.1
A123: Denver Performing Arts Complex (DPAC) / Bellco Theatre | B123: Event Venue | E123: 0.6 | F123: =D123*E123 | G123: 0.4 | H123: =F123*G123 | I123: 0 | J123: =I123*360 | K123: =J123*0.1
A124: Ellie Caulkins Opera House | B124: Event Venue | E124: 0.6 | F124: =D124*E124 | G124: 0.4 | H124: =F124*G124 | I124: 0 | J124: =I124*360 | K124: =J124*0.1
A125: Boettcher Concert Hall | B125: Event Venue | E125: 0.6 | F125: =D125*E125 | G125: 0.4 | H125: =F125*G125 | I125: 0 | J125: =I125*360 | K125: =J125*0.1
A126: Ball Arena | B126: Event Venue | E126: 0.6 | F126: =D126*E126 | G126: 0.4 | H126: =F126*G126 | I126: 0 | J126: =I126*360 | K126: =J126*0.1
A127: Empower Field at Mile High | B127: Event Venue | E127: 0.6 | F127: =D127*E127 | G127: 0.4 | H127: =F127*G127 | I127: 0 | J127: =I127*360 | K127: =J127*0.1
A128: Coors Field | B128: Event Venue | E128: 0.6 | F128: =D128*E128 | G128: 0.4 | H128: =F128*G128 | I128: 0 | J128: =I128*360 | K128: =J128*0.1
...

Sheet Analysis
A1: SOPHI's MARKET SCORE | C1: TAM | D1: SAM | E1: SOM | G1: Total | H1: Location | I1: Connections | J1: Garage | K1: Growth | L1: Capacity | M1: Cash Flow | O1: Connection 3 | P1: Volume 2 170 + 2 100 + 1 | Q1: Location Downtown 1 Far -1 | R1: High End | S1: Garage Connection 2 location 1 | T1: Valet & Paid Self Park | U1: Points | V1: Priority
C2: =RevenueForecasting!M2
C3: Sum of all predicted valet revenues | D3: Locations likely to adopt valet/switch providers | E3: SAM / # of SAM locations (1 location landed)
C4: All valet, parking contracts, additional services | D4: Realistically obtainable | E4: Going to get (Year 1 target) | H4: 0 miles | I4: locations? 0/7 | J4: public? 8/8 | K4: Population? 4/4 | L4: personal bandwidth 0/4 | M4: costs
H5: DEN | I5: 1 connection -> 5 2+ connections -> 7 | J5: yes or no | K5: small city, medium city, large city, metropolis
I6: employees? 3 | J6: connection? 2 | K6: Events Space? 4 | L6: hire 0/3
A7: Average Self Park | B7: Average Valet | I7: # of possible employees | J7: yes or no | K7: # of markets
A8: 32.53 | B8: 54.77
A10: DENVER MARKET KEY METRICS
A12: Metro Population | C12: ~2.97 million (2025)
A13: City of Denver Population | C13: ~720,000 (2024)
A14: Annual Visitors | C14: 37.1 million (2024)
A15: Overnight Visitors | C15: 19.8 million (2024)
A16: Visitor Spending | C16: $10.3 billion (2024)
A17: DEN Passengers | C17: 82.4 million (2025 record)
A18: Hotels in Denver | C18: 169 properties
A19: Hotel Rooms | C19: 26,460 rooms
A20: Downtown Hotels | C20: 52 properties, ~12,944 rooms
A21: Downtown Occupancy | C21: 66.8% (2025)
A22: Downtown ADR | C22: $207.74 (2025)
A23: Convention Center Impact | C23: $1B+ economic impact (2025 record)
... A26: Global AVP Market | C26: $793M (2025), 32.7% CAGR to $5.6B by 2034

Sheet Market Notes
A1: Denver, CO Market Notes - 2026
A3: MAJOR PARKING OPERATORS IN DENVER
A4: Operator | B4: Focus | C4: Key Denver Locations | D4: Notes
A5: Propark Mobility | B5: Dominant hotel valet operator | C5: 12+ hotel locations incl. Hyatt Regency, Sheraton, Thompson, Westin DEN | D5: Also operates Canopy Airport Parking (4,500 spaces, LEED Gold)
A6: SP+/Metropolis | B6: Largest national operator (4,000+ locations) | C6: Coors Field lots, Cherry Creek, multiple downtown garages | D6: Merged with REEF Technology in $1.5B acquisition (May 2024)
A7: LAZ Parking | B7: Airport & entertainment venues | C7: DEN Airport (5-year contract Feb 2024), Clayton Lane, Ball Arena | D7: Largest airport parking operation in North America
A8: ABM Parking | B8: Commercial office | C8: Denver Place Garage (999 18th St) | D8: Broad client type coverage
A9: Interstate Parking | B9: Downtown LoDo focus | C9: 6 downtown facilities incl. Union Station Block A | D9: Uses Knightscope security robots
A10: Reimagined Parking (REEF/Impark) | B10: Cherry Creek district | C10: Multiple Cherry Creek North garages | D10: Operates under Impark/Lanier/Republic brands
A11: Denison Parking | B11: Retail/shopping | C11: Cherry Creek Shopping Center (5,700 spaces) | D11: Local operator
A12: Great West Parking | B12: Cherry Creek valet | C12: Cherry Creek commercial properties | D12: Local valet specialist
A13: Pro Park | B13: Hotel valet | C13: Jacquard, Hotel Clio | D13: Boutique hotel focus
A16: PARKING RATE BENCHMARKS - 2026
A17: Downtown Self-Park (Daily) | B17: $10-$35/day (lots $10-$15, garages $23-$35)
A18: Downtown Self-Park (Monthly) | B18: $155-$235 typical unreserved
A19: Hotel Valet (Luxury) | B19: $65-$72/night (Ritz-Carlton $72, Four Seasons $65, Le Méridien $72)
A20: Hotel Valet (Upscale) | B20: $50-$64/night (Thompson $64, Sheraton $67, Hyatt Regency $67)
A21: Hotel Valet (Upper-Midscale) | B21: $39-$49/night (SpringHill $49, Hilton Garden Inn $49)
A22: Cherry Creek Daily | B22: $15-$36/day (M-F max)
A23: Cherry Creek Monthly | B23: $140-$235 unreserved
A24: Event Parking (Ball Arena) | B24: $35-$95 depending on event/lot
A25: Event Parking (Coors Field) | B25: $18-$35
A26: DIA Garage | B26: $30/day, $210/week
A27: DIA Economy | B27: $18/day
A28: DIA Shuttle | B28: $8/day
A29: Rate Trend | B29: Increasing: DIA raised 25% (May 2025); downtown rates up modestly YoY
A32: COMPETITIVE LANDSCAPE & OPPORTUNITY
A33: • No automated valet operators currently in Denver - Sophi Mobility would be first-mover
A34: • Propark Mobility is dominant hotel valet player with 12+ hotel contracts
A35: • PMC Valet (similar to Charlotte) is NOT a major presence in Denver
A36: • Waymo autonomous ride-hail targeting Denver for 2026 launch - creates tech-forward awareness
A37: • Knightscope security robots already deployed in downtown garages (Interstate Parking)
A38: • Global AVP (Automated Valet Parking) market: $793M (2025), growing 32.7% CAGR to $5.6B by 2034
A39: • DEN Airport is 3rd busiest in North America - massive parking revenue opportunity
A40: • Convention center had record $1B+ economic impact in 2025 - strong event-driven demand
A41: • Denver hotel construction pipeline: several new properties opened 2024-2026 (Populus, Kimpton Claret, Apiary)

Sheet TAM_Conservative
A1: Account | B1: Account Type | C1: TAM Class | D1: Rooms/Beds | E1: Seats | F1: Occupancy % | G1: Turnover | H1: Valet Conv % | I1: Valet Rate | J1: Op Days | K1: Peak Mod | L1: Daily Rev | M1: TAM | N1: TAM Status | O1: Notes / Source
A2: Le Méridien Denver Downtown | B2: Hotel | C2: Hotel — Downtown Select-Service | D2: 272 | F2: 0.6 | H2: 0.25 | I2: 72 | J2: 360 | L2: 2937.6 | M2: 1057536 | N2: Active TAM | O2: Auto-class: downtown full-service <300 rooms. Occ 60% flat (refine w/STR).
A3: The Ritz-Carlton, Denver | B3: Hotel | C3: Hotel — Downtown Select-Service | D3: 205 | F3: 0.6 | H3: 0.25 | I3: 72 | J3: 360 | L3: 2214 | M3: 797040 | N3: Active TAM | O3: Auto-class: downtown full-service <300 rooms. Occ 60% flat (refine w/STR).
A4: AC Hotel Denver Downtown | B4: Hotel | C4: Hotel — Downtown Select-Service | D4: 223 | F4: 0.6 | H4: 0.25 | I4: 72 | J4: 360 | L4: 2408.4 | M4: 867024 | N4: Active TAM | O4: Auto-class: downtown + select-service flag [name-inferred downtown; workbook flag=No]. Occ 60% flat (refine w/STR).
A5: Embassy Suites by Hilton Denver Downtown Convention Center | B5: Hotel | C5: Hotel — Downtown+Convention | D5: 403 | F5: 0.6 | H5: 0.4 | I5: 70 | J5: 360 | L5: 6770.4 | M5: 2437344 | N5: Active TAM | O5: Auto-class: convention keyword in name. Occ 60% flat (refine w/STR).
A6: Aloft Denver Downtown | B6: Hotel | C6: Hotel — Downtown Select-Service | D6: 140 | F6: 0.6 | H6: 0.25 | I6: 68 | J6: 360 | L6: 1428 | M6: 514080 | N6: Active TAM | O6: Auto-class: downtown + select-service flag [name-inferred downtown; workbook flag=No]. Occ 60% flat (refine w/STR).
A7: Sheraton Denver Downtown Hotel | B7: Hotel | C7: Hotel — Downtown+Convention | D7: 1238 | F7: 0.6 | H7: 0.4 | I7: 67 | J7: 360 | L7: 19907.04 | M7: 7166534.4 | N7: Active TAM | O7: Auto-class: downtown + 1238 rooms (>=400). Occ 60% flat (refine w/STR).
A8: Hyatt Regency Denver at Colorado Convention Center | B8: Hotel | C8: Hotel — Downtown+Convention | D8: 1100 | F8: 0.6 | H8: 0.4 | I8: 67 | J8: 360 | L8: 17688 | M8: 6367680 | N8: Active TAM | O8: Auto-class: convention keyword in name. Occ 60% flat (refine w/STR).
A9: The Jacquard, Autograph Collection | B9: Hotel | C9: Hotel — Suburban/Airport | D9: 198 | F9: 0.6 | H9: 0.15 | I9: 65 | J9: 360 | L9: 1158.3 | M9: 416988 | N9: Active TAM | O9: Auto-class: not downtown (by flag or name). Occ 60% flat (refine w/STR).
A10: Four Seasons Hotel Denver | B10: Hotel | C10: Hotel — Downtown Select-Service | D10: 239 | F10: 0.6 | H10: 0.25 | I10: 65 | J10: 360 | L10: 2330.25 | M10: 838890 | N10: Active TAM | O10: Auto-class: downtown full-service <300 rooms. Occ 60% flat (refine w/STR).
A11: The Brown Palace Hotel and Spa, Autograph Collection | B11: Hotel | C11: Hotel — Resort | D11: 241 | F11: 0.6 | H11: 0.5 | I11: 65 | J11: 360 | L11: 4699.5 | M11: 1691820 | N11: Active TAM | O11: Auto-class: resort keyword: 'spa'. Occ 60% flat (refine w/STR).
A12: Thompson Denver, by Hyatt | B12: Hotel | C12: Hotel — Downtown Select-Service | D12: 216 | F12: 0.6 | H12: 0.25 | I12: 64 | J12: 360 | L12: 2073.6 | M12: 746496 | N12: Active TAM | O12: Auto-class: downtown full-service <300 rooms. Occ 60% flat (refine w/STR).
A13: Grand Hyatt Denver | B13: Hotel | C13: Hotel — Downtown+Convention | D13: 516 | F13: 0.6 | H13: 0.4 | I13: 64 | J13: 360 | L13: 7925.76 | M13: 2853273.6 | N13: Active TAM | O13: Auto-class: downtown + 516 rooms (>=400). Occ 60% flat (refine w/STR).
... A53: Renaissance Denver Hotel & Conference Center | B53: Hotel | C53: Hotel — Suburban/Airport | D53: 399 | F53: 0.6 | H53: 0.15 | I53: 19 | J53: 360 | L53: 682.29 | M53: 245624.4 | N53: Active TAM | O53: Auto-class: not downtown (by flag or name). Occ 60% flat (refine w/STR).
A54: DoubleTree by Hilton Hotel Denver | B54: Hotel | C54: Hotel — Suburban/Airport | D54: 561 | F54: 0.6 | H54: 0.15 | J54: 360 | N54: No Valet / TAM = $0 | O54: Hotel has no valet (rate field: 'No Valet'). Auto-class: not downtown (by flag or name). Qualitative pipeline only.
A55: Courtyard Denver Central Park | B55: Hotel | C55: Hotel — Suburban/Airport | D55: 146 | F55: 0.6 | H55: 0.15 | J55: 360 | N55: No Valet / TAM = $0 | O55: Hotel has no valet (rate field: 'No Valet'). Auto-class: not downtown (by flag or name). Qualitative pipeline only.
A56: Hampton Inn & Suites Denver-Speer Boulevard | B56: Hotel | C56: Hotel — Suburban/Airport | D56: 153 | F56: 0.6 | H56: 0.15 | J56: 360 | N56: No Valet / TAM = $0 | O56: Hotel has no valet (rate field: 'No Valet'). Auto-class: not downtown (by flag or name). Qualitative pipeline only.
A57: Drury Inn & Suites Denver Central Park | B57: Hotel | C57: Hotel — Suburban/Airport | D57: 209 | F57: 0.6 | H57: 0.15 | J57: 360 | N57: No Valet / TAM = $0 | O57: Hotel has no valet (rate field: 'No Valet'). Auto-class: not downtown (by flag or name). Qualitative pipeline only.
A58: Cambria Hotel Denver Downtown RiNo | B58: Hotel | C58: Hotel — Downtown Select-Service | D58: 153 | F58: 0.6 | H58: 0.25 | J58: 360 | N58: No Valet / TAM = $0 | O58: Hotel has no valet (rate field: 'No Valet'). Auto-class: downtown full-service <300 rooms [name-inferred downtown]. Qualitative pipeline only.
A59: The Source Hotel | B59: Hotel | C59: Hotel — Suburban/Airport | D59: 100 | F59: 0.6 | H59: 0.15 | J59: 360 | N59: No Valet / TAM = $0 | O59: Hotel has no valet (rate field: 'No Valet'). Auto-class: not downtown (by flag or name). Qualitative pipeline only.
A60: the Curtis Denver - a DoubleTree by Hilton Hotel | B60: Hotel | C60: Hotel — Downtown+Convention | D60: 336 | F60: 0.6 | H60: 0.4 | J60: 360 | N60: No Valet / TAM = $0 | O60: Hotel has no valet (rate field: 'No Valet'). Auto-class: downtown + 336 rooms. Qualitative pipeline only.
A61: Courtyard Denver Downtown | B61: Hotel | C61: Hotel — Downtown Select-Service | D61: 177 | F61: 0.6 | H61: 0.25 | J61: 360 | N61: No Valet / TAM = $0 | O61: Hotel has no valet (rate field: 'No Valet'). Auto-class: downtown + select-service flag [name-inferred downtown; workbook flag=No]. Qualitative pipeline only.
A62: Hyatt Regency Aurora-Denver Conference Center | B62: Hotel | C62: Hotel — Suburban/Airport | D62: 249 | F62: 0.6 | H62: 0.15 | J62: 360 | N62: No Valet / TAM = $0 | O62: Hotel has no valet (rate field: 0). Auto-class: not downtown (by flag or name). Qualitative pipeline only.
A63: Sonesta Denver Downtown | B63: Hotel | C63: Hotel — Downtown+Convention | D63: 380 | F63: 0.6 | H63: 0.4 | J63: 360 | N63: No Valet / TAM = $0 | O63: Hotel has no valet (rate field: 'No Valet'). Auto-class: downtown + 380 rooms. Qualitative pipeline only.
A64: Vīb Hotel by Best Western Denver RiNo | B64: Hotel | C64: Hotel — Downtown Select-Service | D64: 140 | F64: 0.6 | H64: 0.25 | J64: 360 | N64: No Valet / TAM = $0 | O64: Hotel has no valet (rate field: 'No Valet'). Auto-class: downtown + select-service flag [name-inferred downtown; workbook flag=No]. Qualitative pipeline only.
A65: Element Denver Downtown East | B65: Hotel | C65: Hotel — Downtown Select-Service | D65: 157 | F65: 0.6 | H65: 0.25 | J65: 360 | N65: No Valet / TAM = $0 | O65: Hotel has no valet (rate field: 'No Valet'). Auto-class: downtown + select-service flag [name-inferred downtown; workbook flag=No]. Qualitative pipeline only.
... A87: Home2 Suites by Hilton Denver Central Park | B87: Hotel | C87: Hotel — Suburban/Airport | D87: 117 | F87: 0.6 | H87: 0.15 | J87: 360 | N87: No Valet / TAM = $0 | O87: Hotel has no valet (rate field: 'No Valet'). Auto-class: not downtown (by flag or name). Qualitative pipeline only.
A88: The Capital Grille - Denver | B88: Restaurant | C88: Restaurant — Excluded | N88: EXCLUDED — no active valet / not eligible | O88: Not in eligible FD universe (steakhouse/fine dining with active independent valet)
A89: Ocean Prime - Denver (Larimer Square) | B89: Restaurant | C89: Restaurant — Seafood Steakhouse | E89: 225 | G89: 1.5 | H89: 0.125 | J89: 250 | K89: 1.08 | L89: 843.75 | M89: 227812.5 | N89: Active TAM (MEDIUM confidence) | O89: Ocean Prime brand-standard 200-250; 234 private dining seats across rooms confirmed. | [Ocean Prime](https://ocean-prime.com/locations-menus/denver-larimer-square/), [EventUp](https://eventup.com/venue/ocean-prime-larimer-square/)
A90: Ruth's Chris Steak House - Denver | B90: Restaurant | C90: Restaurant — Steakhouse | E90: 275 | G90: 1.5 | H90: 0.125 | J90: 250 | K90: 1.08 | L90: 1031.25 | M90: 278437.5 | N90: Active TAM (MEDIUM confidence) | O90: Brand-standard Ruth's Chris 250-300. Address note: 1445 Market closed 2009, current location 707 15th St. | [Brand standard benchmark; PRNewswire](https://www.prnewswire.com/news-releases/denver-welcomes-ruths-chris-steak-house-to-the-mile-high-city-242296641.html)
A91: STK Steakhouse Denver | B91: Restaurant | C91: Restaurant — Excluded | N91: EXCLUDED — no active valet / not eligible | O91: Not in eligible FD universe (steakhouse/fine dining with active independent valet)
A92: Guard & Grace | B92: Restaurant | C92: Restaurant — Excluded | N92: EXCLUDED — no active valet / not eligible | O92: Not in eligible FD universe (steakhouse/fine dining with active independent valet)
A93: Elway's Downtown | B93: Restaurant | C93: Restaurant — Excluded | N93: EXCLUDED — no active valet / not eligible | O93: Not in eligible FD universe (steakhouse/fine dining with active independent valet)
A94: Elway's Cherry Creek | B94: Restaurant | C94: Restaurant — Excluded | N94: EXCLUDED — no active valet / not eligible | O94: Not in eligible FD universe (steakhouse/fine dining with active independent valet)
A95: Shanahan's Steakhouse | B95: Restaurant | C95: Restaurant — Steakhouse | E95: 200 | G95: 1.5 | H95: 0.125 | J95: 250 | K95: 1.08 | L95: 750 | M95: 202500 | N95: Active TAM (LOW confidence) | O95: No published dining-room count. 200 seats is steakhouse default; private dining 72 confirmed. | [Shanahan's private dining](https://www.shanahanssteakhouse.com/private-dining)
A96: Del Frisco's Double Eagle Steakhouse | B96: Restaurant | C96: Restaurant — Steakhouse | E96: 450 | G96: 1.5 | H96: 0.125 | J96: 250 | K96: 1.08 | L96: 1687.5 | M96: 455625 | N96: Active TAM (HIGH confidence) | O96: Published 450 seats post-2018 renovation. Largest of the 7. | [303 Magazine](https://303magazine.com/2018/11/del-friscos-double-eagle-steak-house-new-menu/)
A97: Del Frisco's Grille - Cherry Creek | B97: Restaurant | C97: Restaurant — Excluded | N97: EXCLUDED — no active valet / not eligible | O97: Not in eligible FD universe (steakhouse/fine dining with active independent valet)
A98: Tavernetta | B98: Restaurant | C98: Restaurant — Excluded | N98: EXCLUDED — no active valet / not eligible | O98: Not in eligible FD universe (steakhouse/fine dining with active independent valet)
A99: Sunday Vinyl | B99: Restaurant | C99: Restaurant — Excluded | N99: EXCLUDED — no active valet / not eligible | O99: Not in eligible FD universe (steakhouse/fine dining with active independent valet)
A100: Frasca Food and Wine | B100: Restaurant | C100: Restaurant — Excluded | N100: EXCLUDED — no active valet / not eligible | O100: Not in eligible FD universe (steakhouse/fine dining with active independent valet)
A101: Rioja | B101: Restaurant | C101: Restaurant — Excluded | N101: EXCLUDED — no active valet / not eligible | O101: Not in eligible FD universe (steakhouse/fine dining with active independent valet)
A102: Barolo Grill | B102: Restaurant | C102: Restaurant — Excluded | N102: EXCLUDED — no active valet / not eligible | O102: Not in eligible FD universe (steakhouse/fine dining with active independent valet)
A103: Mizuna | B103: Restaurant | C103: Restaurant — Fine Dining (boutique) | E103: 79 | G103: 1.5 | H103: 0.125 | J103: 250 | K103: 1.08 | L103: 296.25 | M103: 79987.5 | N103: Active TAM (HIGH confidence) | O103: 55 dining + 24 private = 79 published. Smallest of the 7; boutique chef-driven fine dining. | [Cvent](https://www.cvent.com/venues/denver/restaurant/mizuna/venue-1a94c9f1-8d62-4ccd-b90f-bb633aa3d6e4)
A104: Wildflower | B104: Restaurant | C104: Restaurant — Excluded | N104: EXCLUDED — no active valet / not eligible | O104: Not in eligible FD universe (steakhouse/fine dining with active independent valet)
A105: Le Colonial Denver | B105: Restaurant | C105: Restaurant — French-Vietnamese Fine Dining | E105: 220 | G105: 1.5 | H105: 0.125 | J105: 250 | K105: 1.08 | L105: 825 | M105: 222750 | N105: Active TAM (LOW confidence) | O105: Research computed 400 from 6K sqft gross (includes kitchen/bar/aisles). Realistic FD dining ~200-240. | [Meetings + Events](https://meetingsmags.com/colorado/co_news/le-colonial-debuts-in-denver/)
A106: Water Grill Denver | B106: Restaurant | C106: Restaurant — Seafood | E106: 346 | G106: 1.5 | H106: 0.125 | J106: 250 | K106: 1.08 | L106: 1297.5 | M106: 350325 | N106: Active TAM (HIGH confidence) | O106: 240 dining + 70 private + 36 bar = 346 — fully published. | [City Lifestyle](https://citylifestyle.com/articles/lodos-up-and-coming-water-grill), [Water Grill](https://www.watergrill.com/denver)
A107: Corinne Denver | B107: Restaurant | C107: Restaurant — Excluded | N107: EXCLUDED — no active valet / not eligible | O107: Not in eligible FD universe (steakhouse/fine dining with active independent valet)
A108: Salt Water Social | B108: Restaurant | C108: Restaurant — Excluded | N108: EXCLUDED — no active valet / not eligible | O108: Not in eligible FD universe (steakhouse/fine dining with active independent valet)
A109: Alma Fonda Fina | B109: Restaurant | C109: Restaurant — Excluded | N109: EXCLUDED — no active valet / not eligible | O109: Not in eligible FD universe (steakhouse/fine dining with active independent valet)
A110: UCHealth University of Colorado Hospital | B110: Hospital | C110: Hospital — Qualitative | N110: PIPELINE ONLY | O110: Hospital deals are RFP/profit-share; excluded from TAM until IU Health benchmark formalized
A111: Denver Health Medical Center | B111: Hospital | C111: Hospital — Qualitative | N111: PIPELINE ONLY | O111: Hospital deals are RFP/profit-share; excluded from TAM until IU Health benchmark formalized
A112: National Jewish Health | B112: Hospital | C112: Hospital — Qualitative | N112: PIPELINE ONLY | O112: Hospital deals are RFP/profit-share; excluded from TAM until IU Health benchmark formalized
A113: Rose Medical Center (HCA HealthONE Rose) | B113: Hospital | C113: Hospital — Qualitative | N113: PIPELINE ONLY | O113: Hospital deals are RFP/profit-share; excluded from TAM until IU Health benchmark formalized
A114: Presbyterian/St. Luke's Medical Center (HCA HealthONE PSL) | B114: Hospital | C114: Hospital — Qualitative | N114: PIPELINE ONLY | O114: Hospital deals are RFP/profit-share; excluded from TAM until IU Health benchmark formalized
A115: Swedish Medical Center (HCA HealthONE Swedish) | B115: Hospital | C115: Hospital — Qualitative | N115: PIPELINE ONLY | O115: Hospital deals are RFP/profit-share; excluded from TAM until IU Health benchmark formalized
A116: Sky Ridge Medical Center (HCA HealthONE Sky Ridge) | B116: Hospital | C116: Hospital — Qualitative | N116: PIPELINE ONLY | O116: Hospital deals are RFP/profit-share; excluded from TAM until IU Health benchmark formalized
A117: AdventHealth Porter (formerly Porter Adventist Hospital) | B117: Hospital | C117: Hospital — Qualitative | N117: PIPELINE ONLY | O117: Hospital deals are RFP/profit-share; excluded from TAM until IU Health benchmark formalized
A118: Children's Hospital Colorado (Anschutz Campus) | B118: Hospital | C118: Hospital — Qualitative | N118: PIPELINE ONLY | O118: Hospital deals are RFP/profit-share; excluded from TAM until IU Health benchmark formalized
... A136: Denver International Airport (DEN) | B136: Airport | C136: Airport — Excluded | N136: EXCLUDED | O136: Airport parking = authority RFP, not hotel-style valet; strategic only

Sheet TAM_Summary
A1: Denver — Conservative TAM Summary
A3: Account Type | B3: # Accounts | C3: TAM | D3: Status
A4: Hotel | B4: 86 | C4: 57469500 | D4: Active TAM
A5: Restaurant | B5: 7 | C5: 1817437.5 | D5: Active TAM
A6: Hospital | B6: 12 | C6: 0 | D6: Qualitative pipeline only
A7: Event Venue | B7: 14 | C7: 0 | D7: Qualitative pipeline only
A8: Airport | B8: 1 | C8: 0 | D8: Qualitative pipeline only
A9: TOTAL | B9: 120 | C9: 59286937
A11: HOTEL BREAKDOWN BY CLASS
A12: Class | B12: # Hotels | C12: Conv %
A13: Downtown+Convention | B13: 13 | C13: 0.4
A14: Downtown Select-Service | B14: 32 | C14: 0.25
A15: Resort | B15: 3 | C15: 0.5
A16: Suburban/Airport | B16: 38 | C16: 0.15
A18: RESTAURANTS WITH ACTIVE TAM
A19: Restaurant | B19: Seats | C19: TAM
A20: Del Frisco's Double Eagle Steakhouse | B20: 450 | C20: 455625
A21: Water Grill Denver | B21: 346 | C21: 350325
A22: Ruth's Chris Steak House - Denver | B22: 275 | C22: 278437.5
A23: Ocean Prime - Denver (Larimer Square) | B23: 225 | C23: 227812.5
A24: Le Colonial Denver | B24: 220 | C24: 222750
A25: Shanahan's Steakhouse | B25: 200 | C25: 202500
A26: Mizuna | B26: 79 | C26: 79987.5

Sheet TAM_Methodology
A1: SOPHI CONSERVATIVE TAM METHODOLOGY
A3: Replaces original RevenueForecasting formulas. Hospitals / Venues / Airports now qualitative only.
A5: HOTEL FORMULA
A6: TAM = Rooms × Occupancy × Valet Conversion (tiered) × Valet Rate × 360 days
A7: Occupancy: 60% flat across all hotels
A8: ⚠️ FLAG: Refine with STR actuals per-submarket before finalizing fundraise model
A9: Valet Conversion by archetype (auto-classified — review recommended):
A10: Downtown+Convention: 40%
A11: Downtown Select-Service: 25%
A12: Resort: 50%
A13: Suburban/Airport: 15%
A14: Operating Days: 360 (captures soft-closures / transition days)
... A35: 4. Hospital/venue/airport TAM dropped to $0 → build IU Health-benchmarked KPI proxy

Sheet WAS_Scoring_v2
A1: Account | B1: Type | C1: Downtown | D1: Rooms | E1: Valet Op (incumbent) | F1: Valet Rate | G1: Est. Annual Rev (TAM) | H1: Fit (25%) | I1: Size (25%) | J1: Owner Base (20%) | K1: Addr (15%) | L1: Adj (15%) | M1: Rel Lift | N1: Rel Tag | O1: WAS Raw | P1: WAS Final | Q1: Tier | R1: Y1 % | S1: Y2 % | T1: Y3 % | U1: Y4 % | V1: Y5 % | W1: Y1 Rev | X1: Y2 Rev | Y1: Y3 Rev | Z1: Y4 Rev | AA1: Y5 Rev
A2: Le Méridien Denver Downtown | B2: Hotel | C2: YES | D2: 272 | F2: 72 | G2: 1057536 | H2: 4 | I2: 3 | J2: 2 | K2: 4 | L2: 4 | M2: 0 | O2: 3.35 | P2: 3.35 | Q2: C — Opportunistic | R2: 0.02 | S2: 0.09724 | T2: 0.28625 | U2: 0.4145 | V2: 0.5 | W2: 21150.72 | X2: 102834.8 | Y2: 302719.68 | Z2: 438348.67 | AA2: 528768
A3: The Ritz-Carlton, Denver | B3: Hotel | C3: YES | D3: 205 | F3: 72 | G3: 797040 | H3: 4 | I3: 3 | J3: 3 | K3: 4 | L3: 4 | M3: 0 | O3: 3.55 | P3: 3.55 | Q3: B — Core | R3: 0.08 | S3: 0.22066 | T3: 0.560625 | U3: 0.78675 | V3: 0.9375 | W3: 63763.2 | X3: 175874.85 | Y3: 446840.55 | Z3: 627071.22 | AA3: 747225
A4: AC Hotel Denver Downtown | B4: Hotel | C4: NO | D4: 223 | E4: Towne Park | F4: 72 | G4: 867024 | H4: 3 | I4: 3 | J4: 2 | K4: 2 | L4: 2 | M4: 0 | O4: 2.5 | P4: 2.5 | Q4: C — Opportunistic | R4: 0.02 | S4: 0.09724 | T4: 0.28625 | U4: 0.4145 | V4: 0.5 | W4: 17340.48 | X4: 84309.414 | Y4: 248185.62 | Z4: 359381.45 | AA4: 433512
A5: Embassy Suites by Hilton Denver Downtown Convention Center | B5: Hotel | C5: NO | D5: 403 | E5: SP+ | F5: 70 | G5: 2437344 | H5: 4 | I5: 4 | J5: 3 | K5: 2 | L5: 2 | M5: 0.15 | N5: Brand familiarity (historical): Hilton_family | O5: 3.2 | P5: 3.35 | Q5: C — Opportunistic | R5: 0.02 | S5: 0.09724 | T5: 0.28625 | U5: 0.4145 | V5: 0.5 | W5: 48746.88 | X5: 237007.33 | Y5: 697689.72 | Z5: 1010279.1 | AA5: 1218672
A6: Aloft Denver Downtown | B6: Hotel | C6: NO | D6: 140 | E6: LAZ | F6: 68 | G6: 514080 | H6: 3 | I6: 2 | J6: 2 | K6: 2 | L6: 2 | M6: 0.3 | N6: Brand familiarity (current): Marriott_family | O6: 2.25 | P6: 2.55 | Q6: C — Opportunistic | R6: 0.02 | S6: 0.09724 | T6: 0.28625 | U6: 0.4145 | V6: 0.5 | W6: 10281.6 | X6: 49989.139 | Y6: 147155.4 | Z6: 213086.16 | AA6: 257040
A7: Sheraton Denver Downtown Hotel | B7: Hotel | C7: YES | D7: 1238 | F7: 67 | G7: 7166534.4 | H7: 5 | I7: 5 | J7: 3 | K7: 4 | L7: 4 | M7: 0.3 | N7: Brand familiarity (current): Marriott_family | O7: 4.3 | P7: 4.6 | Q7: A — Beachhead | R7: 0.4 | S7: 0.499 | T7: 0.7025 | U7: 0.851 | V7: 0.95 | W7: 2866613.8 | X7: 3576100.7 | Y7: 5034490.4 | Z7: 6098720.8 | AA7: 6808207.7
A8: Hyatt Regency Denver at Colorado Convention Center | B8: Hotel | C8: NO | D8: 1100 | F8: 67 | G8: 6367680 | H8: 5 | I8: 5 | J8: 3 | K8: 4 | L8: 2 | M8: 0 | O8: 4 | P8: 4 | Q8: B — Core | R8: 0.08 | S8: 0.22066 | T8: 0.560625 | U8: 0.78675 | V8: 0.9375 | W8: 509414.4 | X8: 1405092.3 | Y8: 3569880.6 | Z8: 5009772.2 | AA8: 5969700
A9: The Jacquard, Autograph Collection | B9: Hotel | C9: NO | D9: 198 | E9: Pro Park | F9: 65 | G9: 416988 | H9: 3 | I9: 2 | J9: 3 | K9: 3 | L9: 2 | M9: 0.3 | N9: Brand familiarity (current): Marriott_family | O9: 2.6 | P9: 2.9 | Q9: C — Opportunistic | R9: 0.02 | S9: 0.09724 | T9: 0.28625 | U9: 0.4145 | V9: 0.5 | W9: 8339.76 | X9: 40547.913 | Y9: 119362.82 | Z9: 172841.53 | AA9: 208494
A10: Four Seasons Hotel Denver | B10: Hotel | C10: YES | D10: 239 | E10: In House | F10: 65 | G10: 838890 | H10: 4 | I10: 3 | J10: 3 | K10: 5 | L10: 4 | M10: 0 | O10: 3.7 | P10: 3.7 | Q10: B — Core | R10: 0.08 | S10: 0.22066 | T10: 0.560625 | U10: 0.78675 | V10: 0.9375 | W10: 67111.2 | X10: 185109.47 | Y10: 470302.71 | Z10: 659996.71 | AA10: 786459.38
A11: The Brown Palace Hotel and Spa, Autograph Collection | B11: Hotel | C11: YES | D11: 241 | F11: 65 | G11: 1691820 | H11: 4 | I11: 4 | J11: 3 | K11: 4 | L11: 4 | M11: 0.3 | N11: Brand familiarity (current): Marriott_family | O11: 3.8 | P11: 4.1 | Q11: B — Core | R11: 0.08 | S11: 0.22066 | T11: 0.560625 | U11: 0.78675 | V11: 0.9375 | W11: 135345.6 | X11: 373317 | Y11: 948476.59 | Z11: 1331039.4 | AA11: 1586081.2
A12: Thompson Denver, by Hyatt | B12: Hotel | C12: YES | D12: 216 | F12: 64 | G12: 746496 | H12: 4 | I12: 2 | J12: 3 | K12: 4 | L12: 4 | M12: 0 | O12: 3.3 | P12: 3.3 | Q12: C — Opportunistic | R12: 0.02 | S12: 0.09724 | T12: 0.28625 | U12: 0.4145 | V12: 0.5 | W12: 14929.92 | X12: 72589.271 | Y12: 213684.48 | Z12: 309422.59 | AA12: 373248
A13: Grand Hyatt Denver | B13: Hotel | C13: YES | D13: 516 | F13: 64 | G13: 2853273.6 | H13: 5 | I13: 5 | J13: 3 | K13: 4 | L13: 4 | M13: 0 | O13: 4.3 | P13: 4.3 | Q13: B — Core | R13: 0.08 | S13: 0.22066 | T13: 0.560625 | U13: 0.78675 | V13: 0.9375 | W13: 228261.89 | X13: 629603.35 | Y13: 1599616.5 | Z13: 2244813 | AA13: 2674944
A14: Hyatt Place Denver/Downtown | B14: Hotel | C14: NO | D14: 248 | E14: Towne Park | F14: 64 | G14: 857088 | H14: 3 | I14: 3 | J14: 3 | K14: 2 | L14: 2 | M14: 0 | O14: 2.7 | P14: 2.7 | Q14: C — Opportunistic | R14: 0.02 | S14: 0.09724 | T14: 0.28625 | U14: 0.4145 | V14: 0.5 | W14: 17141.76 | X14: 83343.237 | Y14: 245341.44 | Z14: 355262.98 | AA14: 428544
A15: Populus | B15: Hotel | C15: NO | D15: 265 | F15: 64 | G15: 915840 | H15: 4 | I15: 3 | J15: 2 | K15: 4 | L15: 2 | M15: 0 | O15: 3.05 | P15: 3.05 | Q15: C — Opportunistic | R15: 0.02 | S15: 0.09724 | T15: 0.28625 | U15: 0.4145 | V15: 0.5 | W15: 18316.8 | X15: 89056.282 | Y15: 262159.2 | Z15: 379615.68 | AA15: 457920
A16: Hilton Denver City Center | B16: Hotel | C16: YES | D16: 613 | F16: 64 | G16: 3389644.8 | H16: 5 | I16: 5 | J16: 3 | K16: 4 | L16: 4 | M16: 0.15 | N16: Brand familiarity (historical): Hilton_family | O16: 4.3 | P16: 4.45 | Q16: B — Core | R16: 0.08 | S16: 0.22066 | T16: 0.560625 | U16: 0.78675 | V16: 0.9375 | W16: 271171.58 | X16: 747959.02 | Y16: 1900319.6 | Z16: 2666803 | AA16: 3177792
A17: Halcyon, a hotel in Cherry Creek | B17: Hotel | C17: NO | D17: 154 | F17: 60 | G17: 299376 | H17: 3 | I17: 2 | J17: 2 | K17: 4 | L17: 2 | M17: 0 | O17: 2.55 | P17: 2.55 | Q17: C — Opportunistic | R17: 0.02 | S17: 0.09724 | T17: 0.28625 | U17: 0.4145 | V17: 0.5 | W17: 5987.52 | X17: 29111.322 | Y17: 85696.38 | Z17: 124091.35 | AA17: 149688
A18: Hampton Inn & Suites Denver Downtown-Convention Center | B18: Hotel | C18: NO | D18: 120 | F18: 60 | G18: 622080 | H18: 3 | I18: 2 | J18: 3 | K18: 4 | L18: 2 | M18: 0.15 | N18: Brand familiarity (historical): Hilton_family | O18: 2.75 | P18: 2.9 | Q18: C — Opportunistic | R18: 0.02 | S18: 0.09724 | T18: 0.28625 | U18: 0.4145 | V18: 0.5 | W18: 12441.6 | X18: 60491.059 | Y18: 178070.4 | Z18: 257852.16 | AA18: 311040
A19: Tru by Hilton Denver Downtown Convention Center | B19: Hotel | C19: NO | D19: 176 | F19: 60 | G19: 912384 | H19: 3 | I19: 3 | J19: 3 | K19: 4 | L19: 2 | M19: 0.15 | N19: Brand familiarity (historical): Hilton_family | O19: 3 | P19: 3.15 | Q19: C — Opportunistic | R19: 0.02 | S19: 0.09724 | T19: 0.28625 | U19: 0.4145 | V19: 0.5 | W19: 18247.68 | X19: 88720.22 | Y19: 261169.92 | Z19: 378183.17 | AA19: 456192
A20: Home2 Suites by Hilton Denver Downtown Convention Center | B20: Hotel | C20: NO | D20: 206 | F20: 60 | G20: 1067904 | H20: 3 | I20: 3 | J20: 3 | K20: 4 | L20: 2 | M20: 0.15 | N20: Brand familiarity (historical): Hilton_family | O20: 3 | P20: 3.15 | Q20: C — Opportunistic | R20: 0.02 | S20: 0.09724 | T20: 0.28625 | U20: 0.4145 | V20: 0.5 | W20: 21358.08 | X20: 103842.98 | Y20: 305687.52 | Z20: 442646.21 | AA20: 533952
A21: Homewood Suites by Hilton Denver Downtown-Convention Center | B21: Hotel | C21: NO | D21: 182 | F21: 60 | G21: 943488 | H21: 3 | I21: 3 | J21: 3 | K21: 4 | L21: 2 | M21: 0.15 | N21: Brand familiarity (historical): Hilton_family | O21: 3 | P21: 3.15 | Q21: C — Opportunistic | R21: 0.02 | S21: 0.09724 | T21: 0.28625 | U21: 0.4145 | V21: 0.5 | W21: 18869.76 | X21: 91744.773 | Y21: 270073.44 | Z21: 391075.78 | AA21: 471744
A22: Hotel Clio, a Luxury Collection Hotel, Denver Cherry Creek | B22: Hotel | C22: NO | D22: 199 | E22: Pro Park | F22: 59 | G22: 380408.4 | H22: 3 | I22: 2 | J22: 2 | K22: 3 | L22: 2 | M22: 0 | O22: 2.4 | P22: 2.4 | Q22: D — Deprioritized | R22: 0 | S22: 0.018 | T22: 0.055 | U22: 0.082 | V22: 0.1 | W22: 0 | X22: 6847.3512 | Y22: 20922.462 | Z22: 31193.489 | AA22: 38040.84
A23: Clayton Hotel & Members Club | B23: Hotel | C23: NO | D23: 63 | F23: 59 | G23: 120430.8 | H23: 2 | I23: 1 | J23: 2 | K23: 4 | L23: 2 | M23: 0 | O23: 2.05 | P23: 2.05 | Q23: D — Deprioritized | R23: 0 | S23: 0.018 | T23: 0.055 | U23: 0.082 | V23: 0.1 | W23: 0 | X23: 2167.7544 | Y23: 6623.694 | Z23: 9875.3256 | AA23: 12043.08
A24: The Slate Hotel Denver Downtown, Tapestry by Hilton | B24: Hotel | C24: YES | D24: 251 | F24: 59 | G24: 799686 | H24: 4 | I24: 3 | J24: 3 | K24: 4 | L24: 4 | M24: 0.15 | N24: Brand familiarity (historical): Hilton_family | O24: 3.55 | P24: 3.7 | Q24: B — Core | R24: 0.08 | S24: 0.22066 | T24: 0.560625 | U24: 0.78675 | V24: 0.9375 | W24: 63974.88 | X24: 176458.71 | Y24: 448323.96 | Z24: 629152.96 | AA24: 749705.62
A25: Kimpton Hotel Monaco Denver | B25: Hotel | C25: YES | D25: 189 | E25: Towne Park | F25: 59 | G25: 602154 | H25: 4 | I25: 2 | J25: 3 | K25: 2 | L25: 4 | M25: 0 | O25: 3 | P25: 3 | Q25: C — Opportunistic | R25: 0.02 | S25: 0.09724 | T25: 0.28625 | U25: 0.4145 | V25: 0.5 | W25: 12043.08 | X25: 58553.455 | Y25: 172366.58 | Z25: 249592.83 | AA25: 301077
A26: Magnolia Hotel Denver, a Tribute Portfolio Hotel | B26: Hotel | C26: YES | D26: 297 | F26: 59 | G26: 946242 | H26: 4 | I26: 3 | J26: 2 | K26: 4 | L26: 4 | M26: 0.3 | N26: Brand familiarity (current): Marriott_family | O26: 3.35 | P26: 3.65 | Q26: B — Core | R26: 0.08 | S26: 0.22066 | T26: 0.560625 | U26: 0.78675 | V26: 0.9375 | W26: 75699.36 | X26: 208797.76 | Y26: 530486.92 | Z26: 744455.89 | AA26: 887101.87
A27: Hyatt Centric Downtown Denver | B27: Hotel | C27: YES | D27: 264 | F27: 59 | G27: 841104 | H27: 4 | I27: 3 | J27: 3 | K27: 4 | L27: 4 | M27: 0 | O27: 3.55 | P27: 3.55 | Q27: B — Core | R27: 0.08 | S27: 0.22066 | T27: 0.560625 | U27: 0.78675 | V27: 0.9375 | W27: 67288.32 | X27: 185598.01 | Y27: 471543.93 | Z27: 661738.57 | AA27: 788535
A28: Hotel Indigo Denver Downtown-Union Station | B28: Hotel | C28: NO | D28: 180 | F28: 55 | G28: 534600 | H28: 3 | I28: 2 | J28: 2 | K28: 4 | L28: 2 | M28: 0 | O28: 2.55 | P28: 2.55 | Q28: C — Opportunistic | R28: 0.02 | S28: 0.09724 | T28: 0.28625 | U28: 0.4145 | V28: 0.5 | W28: 10692 | X28: 51984.504 | Y28: 153029.25 | Z28: 221591.7 | AA28: 267300
A29: Hotel Teatro | B29: Hotel | C29: NO | D29: 111 | E29: LAZ | F29: 55 | G29: 329670 | H29: 3 | I29: 2 | J29: 2 | K29: 2 | L29: 2 | M29: 0 | O29: 2.25 | P29: 2.25 | Q29: D — Deprioritized | R29: 0 | S29: 0.018 | T29: 0.055 | U29: 0.082 | V29: 0.1 | W29: 0 | X29: 5934.06 | Y29: 18131.85 | Z29: 27032.94 | AA29: 32967
A30: Kimpton Claret Hotel | B30: Hotel | C30: NO | D30: 190 | F30: 55 | G30: 338580 | H30: 3 | I30: 2 | J30: 3 | K30: 4 | L30: 2 | M30: 0 | O30: 2.75 | P30: 2.75 | Q30: C — Opportunistic | R30: 0.02 | S30: 0.09724 | T30: 0.28625 | U30: 0.4145 | V30: 0.5 | W30: 6771.6 | X30: 32923.519 | Y30: 96918.525 | Z30: 140341.41 | AA30: 169290
A31: Apiary Hotel Belleview Station | B31: Hotel | C31: NO | D31: 175 | F31: 55 | G31: 311850 | H31: 3 | I31: 2 | J31: 2 | K31: 4 | L31: 2 | M31: 0 | O31: 2.55 | P31: 2.55 | Q31: C — Opportunistic | R31: 0.02 | S31: 0.09724 | T31: 0.28625 | U31: 0.4145 | V31: 0.5 | W31: 6237 | X31: 30324.294 | Y31: 89267.062 | Z31: 129261.82 | AA31: 155925
A32: The Art Hotel Denver, Curio Collection by Hilton | B32: Hotel | C32: NO | D32: 165 | F32: 54 | G32: 481140 | H32: 3 | I32: 2 | J32: 3 | K32: 4 | L32: 2 | M32: 0.15 | N32: Brand familiarity (historical): Hilton_family | O32: 2.75 | P32: 2.9 | Q32: C — Opportunistic | R32: 0.02 | S32: 0.09724 | T32: 0.28625 | U32: 0.4145 | V32: 0.5 | W32: 9622.8 | X32: 46786.054 | Y32: 137726.33 | Z32: 199432.53 | AA32: 240570
A33: The Westin Denver Downtown | B33: Hotel | C33: NO | D33: 432 | F33: 54 | G33: 2015539.2 | H33: 4 | I33: 4 | J33: 3 | K33: 4 | L33: 2 | M33: 0.3 | N33: Brand familiarity (current): Marriott_family | O33: 3.5 | P33: 3.8 | Q33: B — Core | R33: 0.08 | S33: 0.22066 | T33: 0.560625 | U33: 0.78675 | V33: 0.9375 | W33: 161243.14 | X33: 444748.88 | Y33: 1129961.7 | Z33: 1585725.5 | AA33: 1889568
A34: The Westin Denver International Airport | B34: Hotel | C34: NO | D34: 519 | E34: Pro Park | F34: 54 | G34: 908042.4 | H34: 5 | I34: 3 | J34: 3 | K34: 3 | L34: 2 | M34: 0.3 | N34: Brand familiarity (current): Marriott_family | O34: 3.35 | P34: 3.65 | Q34: B — Core | R34: 0.08 | S34: 0.22066 | T34: 0.560625 | U34: 0.78675 | V34: 0.9375 | W34: 72643.392 | X34: 200368.64 | Y34: 509071.27 | Z34: 714402.36 | AA34: 851289.75
A35: The Maven Hotel at Dairy Block | B35: Hotel | C35: NO | D35: 172 | F35: 53 | G35: 492264 | H35: 3 | I35: 2 | J35: 2 | K35: 4 | L35: 2 | M35: 0 | O35: 2.55 | P35: 2.55 | Q35: C — Opportunistic | R35: 0.02 | S35: 0.09724 | T35: 0.28625 | U35: 0.4145 | V35: 0.5 | W35: 9845.28 | X35: 47867.751 | Y35: 140910.57 | Z35: 204043.43 | AA35: 246132
A36: Catbird Hotel | B36: Hotel | C36: NO | D36: 165 | F36: 52 | G36: 463320 | H36: 3 | I36: 2 | J36: 2 | K36: 4 | L36: 2 | M36: 0 | O36: 2.55 | P36: 2.55 | Q36: C — Opportunistic | R36: 0.02 | S36: 0.09724 | T36: 0.28625 | U36: 0.4145 | V36: 0.5 | W36: 9266.4 | X36: 45053.237 | Y36: 132625.35 | Z36: 192046.14 | AA36: 231660
A37: Limelight Denver | B37: Hotel | C37: NO | D37: 200 | F37: 50 | G37: 324000 | H37: 3 | I37: 2 | J37: 2 | K37: 4 | L37: 2 | M37: 0 | O37: 2.55 | P37: 2.55 | Q37: C — Opportunistic | R37: 0.02 | S37: 0.09724 | T37: 0.28625 | U37: 0.4145 | V37: 0.5 | W37: 6480 | X37: 31505.76 | Y37: 92745 | Z37: 134298 | AA37: 162000
A38: The Crawford Hotel | B38: Hotel | C38: NO | D38: 112 | F38: 50 | G38: 302400 | H38: 3 | I38: 2 | J38: 2 | K38: 4 | L38: 2 | M38: 0 | O38: 2.55 | P38: 2.55 | Q38: C — Opportunistic | R38: 0.02 | S38: 0.09724 | T38: 0.28625 | U38: 0.4145 | V38: 0.5 | W38: 6048 | X38: 29405.376 | Y38: 86562 | Z38: 125344.8 | AA38: 151200
A39: Warwick Denver | B39: Hotel | C39: NO | D39: 216 | E39: SP+ | F39: 50 | G39: 349920 | H39: 3 | I39: 2 | J39: 2 | K39: 2 | L39: 2 | M39: 0 | O39: 2.25 | P39: 2.25 | Q39: D — Deprioritized | R39: 0 | S39: 0.018 | T39: 0.055 | U39: 0.082 | V39: 0.1 | W39: 0 | X39: 6298.56 | Y39: 19245.6 | Z39: 28693.44 | AA39: 34992
A40: Moxy Denver Cherry Creek | B40: Hotel | C40: NO | D40: 140 | F40: 49 | G40: 222264 | H40: 3 | I40: 1 | J40: 2 | K40: 4 | L40: 2 | M40: 0 | O40: 2.3 | P40: 2.3 | Q40: D — Deprioritized | R40: 0 | S40: 0.018 | T40: 0.055 | U40: 0.082 | V40: 0.1 | W40: 0 | X40: 4000.752 | Y40: 12224.52 | Z40: 18225.648 | AA40: 22226.4
A41: SpringHill Suites Denver Downtown | B41: Hotel | C41: NO | D41: 150 | F41: 49 | G41: 396900 | H41: 3 | I41: 2 | J41: 2 | K41: 4 | L41: 2 | M41: 0.3 | N41: Brand familiarity (current): Marriott_family | O41: 2.55 | P41: 2.85 | Q41: C — Opportunistic | R41: 0.02 | S41: 0.09724 | T41: 0.28625 | U41: 0.4145 | V41: 0.5 | W41: 7938 | X41: 38594.556 | Y41: 113612.62 | Z41: 164515.05 | AA41: 198450
A42: Hilton Garden Inn Denver Union Station | B42: Hotel | C42: YES | D42: 223 | F42: 49 | G42: 590058 | H42: 4 | I42: 2 | J42: 3 | K42: 4 | L42: 4 | M42: 0.15 | N42: Brand familiarity (historical): Hilton_family | O42: 3.3 | P42: 3.45 | Q42: C — Opportunistic | R42: 0.02 | S42: 0.09724 | T42: 0.28625 | U42: 0.4145 | V42: 0.5 | W42: 11801.16 | X42: 57377.24 | Y42: 168904.1 | Z42: 244579.04 | AA42: 295029
A43: Gaylord Rockies Resort & Convention Center | B43: Hotel | C43: NO | D43: 1501 | F43: 48 | G43: 7781184 | H43: 5 | I43: 5 | J43: 2 | K43: 4 | L43: 2 | M43: 0 | O43: 3.8 | P43: 3.8 | Q43: B — Core | R43: 0.08 | S43: 0.22066 | T43: 0.560625 | U43: 0.78675 | V43: 0.9375 | W43: 622494.72 | X43: 1716996.1 | Y43: 4362326.3 | Z43: 6121846.5 | AA43: 7294860
A44: The Rally Hotel at McGregor Square | B44: Hotel | C44: NO | D44: 182 | F44: 46 | G44: 452088 | H44: 3 | I44: 2 | J44: 2 | K44: 4 | L44: 2 | M44: 0 | O44: 2.55 | P44: 2.55 | Q44: C — Opportunistic | R44: 0.02 | S44: 0.09724 | T44: 0.28625 | U44: 0.4145 | V44: 0.5 | W44: 9041.76 | X44: 43961.037 | Y44: 129410.19 | Z44: 187390.48 | AA44: 226044
A45: Hampton Inn & Suites Denver-Downtown | B45: Hotel | C45: NO | D45: 156 | F45: 45 | G45: 379080 | H45: 3 | I45: 2 | J45: 3 | K45: 4 | L45: 2 | M45: 0.15 | N45: Brand familiarity (historical): Hilton_family | O45: 2.75 | P45: 2.9 | Q45: C — Opportunistic | R45: 0.02 | S45: 0.09724 | T45: 0.28625 | U45: 0.4145 | V45: 0.5 | W45: 7581.6 | X45: 36861.739 | Y45: 108511.65 | Z45: 157128.66 | AA45: 189540
A46: Renaissance Denver Downtown City Center Hotel | B46: Hotel | C46: YES | D46: 230 | F46: 43 | G46: 534060 | H46: 4 | I46: 2 | J46: 3 | K46: 4 | L46: 4 | M46: 0.3 | N46: Brand familiarity (current): Marriott_family | O46: 3.3 | P46: 3.6 | Q46: B — Core | R46: 0.08 | S46: 0.22066 | T46: 0.560625 | U46: 0.78675 | V46: 0.9375 | W46: 42724.8 | X46: 117845.68 | Y46: 299407.39 | Z46: 420171.71 | AA46: 500681.25
A47: Hyatt House Denver/Downtown | B47: Hotel | C47: NO | D47: 113 | F47: 42 | G47: 256284 | H47: 3 | I47: 2 | J47: 3 | K47: 4 | L47: 2 | M47: 0 | O47: 2.75 | P47: 2.75 | Q47: C — Opportunistic | R47: 0.02 | S47: 0.09724 | T47: 0.28625 | U47: 0.4145 | V47: 0.5 | W47: 5125.68 | X47: 24921.056 | Y47: 73361.295 | Z47: 106229.72 | AA47: 128142
A48: The Oxford Hotel | B48: Hotel | C48: YES | D48: 80 | E48: In House | F48: 40 | G48: 172800 | H48: 3 | I48: 1 | J48: 2 | K48: 5 | L48: 4 | M48: 0 | O48: 2.75 | P48: 2.75 | Q48: C — Opportunistic | R48: 0.02 | S48: 0.09724 | T48: 0.28625 | U48: 0.4145 | V48: 0.5 | W48: 3456 | X48: 16803.072 | Y48: 49464 | Z48: 71625.6 | AA48: 86400
A49: Benson Hotel & Faculty Club | B49: Hotel | C49: NO | D49: 106 | F49: 39 | G49: 223236 | H49: 3 | I49: 1 | J49: 2 | K49: 4 | L49: 2 | M49: 0 | O49: 2.3 | P49: 2.3 | Q49: D — Deprioritized | R49: 0 | S49: 0.018 | T49: 0.055 | U49: 0.082 | V49: 0.1 | W49: 0 | X49: 4018.248 | Y49: 12277.98 | Z49: 18305.352 | AA49: 22323.6
A50: The Ramble Hotel | B50: Hotel | C50: NO | D50: 50 | F50: 35 | G50: 56700 | H50: 2 | I50: 1 | J50: 2 | K50: 4 | L50: 2 | M50: 0 | O50: 2.05 | P50: 2.05 | Q50: D — Deprioritized | R50: 0 | S50: 0.018 | T50: 0.055 | U50: 0.082 | V50: 0.1 | W50: 0 | X50: 1020.6 | Y50: 3118.5 | Z50: 4649.4 | AA50: 5670
A51: Denver Marriott Tech Center | B51: Hotel | C51: NO | D51: 605 | F51: 25 | G51: 490050 | H51: 5 | I51: 2 | J51: 3 | K51: 4 | L51: 2 | M51: 0.3 | N51: Brand familiarity (current): Marriott_family | O51: 3.25 | P51: 3.55 | Q51: B — Core | R51: 0.08 | S51: 0.22066 | T51: 0.560625 | U51: 0.78675 | V51: 0.9375 | W51: 39204 | X51: 108134.43 | Y51: 274734.28 | Z51: 385546.84 | AA51: 459421.88
A52: Hyatt Regency Denver Tech Center | B52: Hotel | C52: NO | D52: 451 | F52: 25 | G52: 365310 | H52: 4 | I52: 2 | J52: 3 | K52: 4 | L52: 2 | M52: 0 | O52: 3 | P52: 3 | Q52: C — Opportunistic | R52: 0.02 | S52: 0.09724 | T52: 0.28625 | U52: 0.4145 | V52: 0.5 | W52: 7306.2 | X52: 35522.744 | Y52: 104569.99 | Z52: 151420.99 | AA52: 182655
A53: Renaissance Denver Hotel & Conference Center | B53: Hotel | C53: NO | D53: 399 | F53: 19 | G53: 245624.4 | H53: 4 | I53: 1 | J53: 3 | K53: 4 | L53: 2 | M53: 0.3 | N53: Brand familiarity (current): Marriott_family | O53: 2.75 | P53: 3.05 | Q53: C — Opportunistic | R53: 0.02 | S53: 0.09724 | T53: 0.28625 | U53: 0.4145 | V53: 0.5 | W53: 4912.488 | X53: 23884.517 | Y53: 70309.985 | Z53: 101811.31 | AA53: 122812.2
A54: DoubleTree by Hilton Hotel Denver | B54: Hotel | C54: NO | D54: 561 | F54: No Valet | G54: 0 | H54: 5 | I54: 1 | J54: 3 | K54: 4 | L54: 2 | M54: 0.15 | N54: Brand familiarity (historical): Hilton_family | O54: 3 | P54: 3.15 | Q54: C — Opportunistic | R54: 0.02 | S54: 0.09724 | T54: 0.28625 | U54: 0.4145 | V54: 0.5 | W54: 0 | X54: 0 | Y54: 0 | Z54: 0 | AA54: 0
A55: Courtyard Denver Central Park | B55: Hotel | C55: NO | D55: 146 | F55: No Valet | G55: 0 | H55: 3 | I55: 1 | J55: 3 | K55: 4 | L55: 2 | M55: 0 | O55: 2.5 | P55: 2.5 | Q55: C — Opportunistic | R55: 0.02 | S55: 0.09724 | T55: 0.28625 | U55: 0.4145 | V55: 0.5 | W55: 0 | X55: 0 | Y55: 0 | Z55: 0 | AA55: 0
A56: Hampton Inn & Suites Denver-Speer Boulevard | B56: Hotel | C56: NO | D56: 153 | F56: No Valet | G56: 0 | H56: 3 | I56: 1 | J56: 3 | K56: 4 | L56: 2 | M56: 0.15 | N56: Brand familiarity (historical): Hilton_family | O56: 2.5 | P56: 2.65 | Q56: C — Opportunistic | R56: 0.02 | S56: 0.09724 | T56: 0.28625 | U56: 0.4145 | V56: 0.5 | W56: 0 | X56: 0 | Y56: 0 | Z56: 0 | AA56: 0
A57: Drury Inn & Suites Denver Central Park | B57: Hotel | C57: NO | D57: 209 | F57: No Valet | G57: 0 | H57: 3 | I57: 1 | J57: 2 | K57: 4 | L57: 2 | M57: 0 | O57: 2.3 | P57: 2.3 | Q57: D — Deprioritized | R57: 0 | S57: 0.018 | T57: 0.055 | U57: 0.082 | V57: 0.1 | W57: 0 | X57: 0 | Y57: 0 | Z57: 0 | AA57: 0
A58: Cambria Hotel Denver Downtown RiNo | B58: Hotel | C58: NO | D58: 153 | F58: No Valet | G58: 0 | H58: 3 | I58: 1 | J58: 2 | K58: 4 | L58: 2 | M58: 0 | O58: 2.3 | P58: 2.3 | Q58: D — Deprioritized | R58: 0 | S58: 0.018 | T58: 0.055 | U58: 0.082 | V58: 0.1 | W58: 0 | X58: 0 | Y58: 0 | Z58: 0 | AA58: 0
A59: The Source Hotel | B59: Hotel | C59: NO | D59: 100 | F59: No Valet | G59: 0 | H59: 3 | I59: 1 | J59: 2 | K59: 4 | L59: 2 | M59: 0 | O59: 2.3 | P59: 2.3 | Q59: D — Deprioritized | R59: 0 | S59: 0.018 | T59: 0.055 | U59: 0.082 | V59: 0.1 | W59: 0 | X59: 0 | Y59: 0 | Z59: 0 | AA59: 0
A60: the Curtis Denver - a DoubleTree by Hilton Hotel | B60: Hotel | C60: YES | D60: 336 | F60: No Valet | G60: 0 | H60: 5 | I60: 1 | J60: 3 | K60: 4 | L60: 4 | M60: 0.15 | N60: Brand familiarity (historical): Hilton_family | O60: 3.3 | P60: 3.45 | Q60: C — Opportunistic | R60: 0.02 | S60: 0.09724 | T60: 0.28625 | U60: 0.4145 | V60: 0.5 | W60: 0 | X60: 0 | Y60: 0 | Z60: 0 | AA60: 0
A61: Courtyard Denver Downtown | B61: Hotel | C61: NO | D61: 177 | F61: No Valet | G61: 0 | H61: 3 | I61: 1 | J61: 3 | K61: 4 | L61: 2 | M61: 0 | O61: 2.5 | P61: 2.5 | Q61: C — Opportunistic | R61: 0.02 | S61: 0.09724 | T61: 0.28625 | U61: 0.4145 | V61: 0.5 | W61: 0 | X61: 0 | Y61: 0 | Z61: 0 | AA61: 0
A62: Hyatt Regency Aurora-Denver Conference Center | B62: Hotel | C62: NO | D62: 249 | G62: 0 | H62: 3 | I62: 1 | J62: 3 | K62: 4 | L62: 2 | M62: 0 | O62: 2.5 | P62: 2.5 | Q62: C — Opportunistic | R62: 0.02 | S62: 0.09724 | T62: 0.28625 | U62: 0.4145 | V62: 0.5 | W62: 0 | X62: 0 | Y62: 0 | Z62: 0 | AA62: 0
A63: Sonesta Denver Downtown | B63: Hotel | C63: YES | D63: 380 | F63: No Valet | G63: 0 | H63: 5 | I63: 1 | J63: 2 | K63: 4 | L63: 4 | M63: 0 | O63: 3.1 | P63: 3.1 | Q63: C — Opportunistic | R63: 0.02 | S63: 0.09724 | T63: 0.28625 | U63: 0.4145 | V63: 0.5 | W63: 0 | X63: 0 | Y63: 0 | Z63: 0 | AA63: 0
A64: Vīb Hotel by Best Western Denver RiNo | B64: Hotel | C64: NO | D64: 140 | F64: No Valet | G64: 0 | H64: 3 | I64: 1 | J64: 2 | K64: 4 | L64: 2 | M64: 0 | O64: 2.3 | P64: 2.3 | Q64: D — Deprioritized | R64: 0 | S64: 0.018 | T64: 0.055 | U64: 0.082 | V64: 0.1 | W64: 0 | X64: 0 | Y64: 0 | Z64: 0 | AA64: 0
A65: Element Denver Downtown East | B65: Hotel | C65: NO | D65: 157 | F65: No Valet | G65: 0 | H65: 3 | I65: 1 | J65: 2 | K65: 4 | L65: 2 | M65: 0 | O65: 2.3 | P65: 2.3 | Q65: D — Deprioritized | R65: 0 | S65: 0.018 | T65: 0.055 | U65: 0.082 | V65: 0.1 | W65: 0 | X65: 0 | Y65: 0 | Z65: 0 | AA65: 0
A66: DoubleTree by Hilton Hotel Denver Tech Center | B66: Hotel | C66: NO | D66: 305 | F66: No Valet | G66: 0 | H66: 4 | I66: 1 | J66: 3 | K66: 4 | L66: 2 | M66: 0.15 | N66: Brand familiarity (historical): Hilton_family | O66: 2.75 | P66: 2.9 | Q66: C — Opportunistic | R66: 0.02 | S66: 0.09724 | T66: 0.28625 | U66: 0.4145 | V66: 0.5 | W66: 0 | X66: 0 | Y66: 0 | Z66: 0 | AA66: 0
A67: Embassy Suites by Hilton Denver Tech Center | B67: Hotel | C67: NO | D67: 236 | F67: No Valet | G67: 0 | H67: 3 | I67: 1 | J67: 3 | K67: 4 | L67: 2 | M67: 0.15 | N67: Brand familiarity (historical): Hilton_family | O67: 2.5 | P67: 2.65 | Q67: C — Opportunistic | R67: 0.02 | S67: 0.09724 | T67: 0.28625 | U67: 0.4145 | V67: 0.5 | W67: 0 | X67: 0 | Y67: 0 | Z67: 0 | AA67: 0
A68: The Inverness Denver, a Hilton Golf & Spa Resort | B68: Hotel | C68: NO | D68: 302 | E68: In House | F68: Free (included in resort fee) | G68: 0 | H68: 4 | I68: 1 | J68: 3 | K68: 5 | L68: 2 | M68: 0.15 | N68: Brand familiarity (historical): Hilton_family | O68: 2.9 | P68: 3.05 | Q68: C — Opportunistic | R68: 0.02 | S68: 0.09724 | T68: 0.28625 | U68: 0.4145 | V68: 0.5 | W68: 0 | X68: 0 | Y68: 0 | Z68: 0 | AA68: 0
A69: Embassy Suites by Hilton Denver Tech Center North | B69: Hotel | C69: NO | D69: 205 | F69: No Valet | G69: 0 | H69: 3 | I69: 1 | J69: 3 | K69: 4 | L69: 2 | M69: 0.15 | N69: Brand familiarity (historical): Hilton_family | O69: 2.5 | P69: 2.65 | Q69: C — Opportunistic | R69: 0.02 | S69: 0.09724 | T69: 0.28625 | U69: 0.4145 | V69: 0.5 | W69: 0 | X69: 0 | Y69: 0 | Z69: 0 | AA69: 0
A70: Denver Marriott South at Park Meadows | B70: Hotel | C70: NO | D70: 279 | F70: No Valet | G70: 0 | H70: 4 | I70: 1 | J70: 3 | K70: 4 | L70: 2 | M70: 0.3 | N70: Brand familiarity (current): Marriott_family | O70: 2.75 | P70: 3.05 | Q70: C — Opportunistic | R70: 0.02 | S70: 0.09724 | T70: 0.28625 | U70: 0.4145 | V70: 0.5 | W70: 0 | X70: 0 | Y70: 0 | Z70: 0 | AA70: 0
A71: Hilton Garden Inn Denver Tech Center | B71: Hotel | C71: NO | D71: 180 | F71: No Valet | G71: 0 | H71: 3 | I71: 1 | J71: 3 | K71: 4 | L71: 2 | M71: 0.15 | N71: Brand familiarity (historical): Hilton_family | O71: 2.5 | P71: 2.65 | Q71: C — Opportunistic | R71: 0.02 | S71: 0.09724 | T71: 0.28625 | U71: 0.4145 | V71: 0.5 | W71: 0 | X71: 0 | Y71: 0 | Z71: 0 | AA71: 0
A72: DoubleTree by Hilton Hotel Denver - Aurora | B72: Hotel | C72: NO | D72: 248 | F72: No Valet | G72: 0 | H72: 3 | I72: 1 | J72: 3 | K72: 4 | L72: 2 | M72: 0.15 | N72: Brand familiarity (historical): Hilton_family | O72: 2.5 | P72: 2.65 | Q72: C — Opportunistic | R72: 0.02 | S72: 0.09724 | T72: 0.28625 | U72: 0.4145 | V72: 0.5 | W72: 0 | X72: 0 | Y72: 0 | Z72: 0 | AA72: 0
A73: Crowne Plaza Denver Airport Convention Center | B73: Hotel | C73: NO | D73: 255 | F73: No Valet | G73: 0 | H73: 4 | I73: 1 | J73: 3 | K73: 4 | L73: 2 | M73: 0 | O73: 2.75 | P73: 2.75 | Q73: C — Opportunistic | R73: 0.02 | S73: 0.09724 | T73: 0.28625 | U73: 0.4145 | V73: 0.5 | W73: 0 | X73: 0 | Y73: 0 | Z73: 0 | AA73: 0
A74: Courtyard Denver Downtown West (Stadium Area) | B74: Hotel | C74: NO | D74: 118 | F74: No Valet | G74: 0 | H74: 3 | I74: 1 | J74: 3 | K74: 4 | L74: 2 | M74: 0 | O74: 2.5 | P74: 2.5 | Q74: C — Opportunistic | R74: 0.02 | S74: 0.09724 | T74: 0.28625 | U74: 0.4145 | V74: 0.5 | W74: 0 | X74: 0 | Y74: 0 | Z74: 0 | AA74: 0
A75: Urban Cowboy Denver | B75: Hotel | C75: NO | D75: 9 | F75: No Valet | G75: 0 | H75: 2 | I75: 1 | J75: 2 | K75: 4 | L75: 2 | M75: 0 | O75: 2.05 | P75: 2.05 | Q75: D — Deprioritized | R75: 0 | S75: 0.018 | T75: 0.055 | U75: 0.082 | V75: 0.1 | W75: 0 | X75: 0 | Y75: 0 | Z75: 0 | AA75: 0
A76: Hyatt Place Denver/Cherry Creek | B76: Hotel | C76: NO | D76: 133 | F76: No Valet | G76: 0 | H76: 3 | I76: 1 | J76: 3 | K76: 4 | L76: 2 | M76: 0 | O76: 2.5 | P76: 2.5 | Q76: C — Opportunistic | R76: 0.02 | S76: 0.09724 | T76: 0.28625 | U76: 0.4145 | V76: 0.5 | W76: 0 | X76: 0 | Y76: 0 | Z76: 0 | AA76: 0
A77: Hyatt Place Denver Tech Center | B77: Hotel | C77: NO | D77: 126 | F77: No Valet | G77: 0 | H77: 3 | I77: 1 | J77: 3 | K77: 4 | L77: 2 | M77: 0 | O77: 2.5 | P77: 2.5 | Q77: C — Opportunistic | R77: 0.02 | S77: 0.09724 | T77: 0.28625 | U77: 0.4145 | V77: 0.5 | W77: 0 | X77: 0 | Y77: 0 | Z77: 0 | AA77: 0
A78: Hyatt Place Denver Airport | B78: Hotel | C78: NO | D78: 127 | F78: No Valet | G78: 0 | H78: 3 | I78: 1 | J78: 3 | K78: 4 | L78: 2 | M78: 0 | O78: 2.5 | P78: 2.5 | Q78: C — Opportunistic | R78: 0.02 | S78: 0.09724 | T78: 0.28625 | U78: 0.4145 | V78: 0.5 | W78: 0 | X78: 0 | Y78: 0 | Z78: 0 | AA78: 0
A79: Hyatt Place Peña Station / Denver Airport | B79: Hotel | C79: NO | D79: 150 | F79: No Valet | G79: 0 | H79: 3 | I79: 1 | J79: 3 | K79: 4 | L79: 2 | M79: 0 | O79: 2.5 | P79: 2.5 | Q79: C — Opportunistic | R79: 0.02 | S79: 0.09724 | T79: 0.28625 | U79: 0.4145 | V79: 0.5 | W79: 0 | X79: 0 | Y79: 0 | Z79: 0 | AA79: 0
A80: Aloft Denver Airport at Gateway Park | B80: Hotel | C80: NO | D80: 136 | F80: No Valet | G80: 0 | H80: 3 | I80: 1 | J80: 2 | K80: 4 | L80: 2 | M80: 0.3 | N80: Brand familiarity (current): Marriott_family | O80: 2.3 | P80: 2.6 | Q80: C — Opportunistic | R80: 0.02 | S80: 0.09724 | T80: 0.28625 | U80: 0.4145 | V80: 0.5 | W80: 0 | X80: 0 | Y80: 0 | Z80: 0 | AA80: 0
A81: Four Points by Sheraton Englewood Centennial Airport | B81: Hotel | C81: NO | D81: 132 | F81: No Valet | G81: 0 | H81: 3 | I81: 1 | J81: 3 | K81: 4 | L81: 2 | M81: 0.3 | N81: Brand familiarity (current): Marriott_family | O81: 2.5 | P81: 2.8 | Q81: C — Opportunistic | R81: 0.02 | S81: 0.09724 | T81: 0.28625 | U81: 0.4145 | V81: 0.5 | W81: 0 | X81: 0 | Y81: 0 | Z81: 0 | AA81: 0
A82: Mint House Denver - Downtown Union Station | B82: Hotel | C82: YES | D82: 40 | F82: No Valet | G82: 0 | H82: 2 | I82: 1 | J82: 2 | K82: 4 | L82: 4 | M82: 0 | O82: 2.35 | P82: 2.35 | Q82: D — Deprioritized | R82: 0 | S82: 0.018 | T82: 0.055 | U82: 0.082 | V82: 0.1 | W82: 0 | X82: 0 | Y82: 0 | Z82: 0 | AA82: 0
A83: Sonder at Skyline | B83: Hotel | C83: NO | D83: 93 | F83: No Valet | G83: 0 | H83: 2 | I83: 1 | J83: 2 | K83: 4 | L83: 2 | M83: 0 | O83: 2.05 | P83: 2.05 | Q83: D — Deprioritized | R83: 0 | S83: 0.018 | T83: 0.055 | U83: 0.082 | V83: 0.1 | W83: 0 | X83: 0 | Y83: 0 | Z83: 0 | AA83: 0
A84: Hyatt House Denver Tech Center | B84: Hotel | C84: NO | D84: 128 | F84: No Valet | G84: 0 | H84: 3 | I84: 1 | J84: 3 | K84: 4 | L84: 2 | M84: 0 | O84: 2.5 | P84: 2.5 | Q84: C — Opportunistic | R84: 0.02 | S84: 0.09724 | T84: 0.28625 | U84: 0.4145 | V84: 0.5 | W84: 0 | X84: 0 | Y84: 0 | Z84: 0 | AA84: 0
A85: Springhill Suites by Marriott Denver Airport at Gateway Park | B85: Hotel | C85: NO | D85: 124 | F85: No Valet | G85: 0 | H85: 3 | I85: 1 | J85: 3 | K85: 4 | L85: 2 | M85: 0.3 | N85: Brand familiarity (current): Marriott_family | O85: 2.5 | P85: 2.8 | Q85: C — Opportunistic | R85: 0.02 | S85: 0.09724 | T85: 0.28625 | U85: 0.4145 | V85: 0.5 | W85: 0 | X85: 0 | Y85: 0 | Z85: 0 | AA85: 0
A86: Hyatt House Denver Aurora Anschutz Medical Campus | B86: Hotel | C86: NO | D86: 124 | F86: No Valet | G86: 0 | H86: 3 | I86: 1 | J86: 3 | K86: 4 | L86: 2 | M86: 0 | O86: 2.5 | P86: 2.5 | Q86: C — Opportunistic | R86: 0.02 | S86: 0.09724 | T86: 0.28625 | U86: 0.4145 | V86: 0.5 | W86: 0 | X86: 0 | Y86: 0 | Z86: 0 | AA86: 0
A87: Home2 Suites by Hilton Denver Central Park | B87: Hotel | C87: NO | D87: 117 | F87: No Valet | G87: 0 | H87: 3 | I87: 1 | J87: 3 | K87: 4 | L87: 2 | M87: 0.15 | N87: Brand familiarity (historical): Hilton_family | O87: 2.5 | P87: 2.65 | Q87: C — Opportunistic | R87: 0.02 | S87: 0.09724 | T87: 0.28625 | U87: 0.4145 | V87: 0.5 | W87: 0 | X87: 0 | Y87: 0 | Z87: 0 | AA87: 0
A88: The Capital Grille - Denver | B88: Restaurant | D88: 0 | E88: Unknown (Darden Restaurants brand) | F88: Complimentary valet (free) for private dining; standard valet available at front | G88: 0 | H88: 3 | I88: 1 | J88: 2 | K88: 3 | L88: 2 | M88: 1 | N88: Current operator: Darden | O88: 2.15 | P88: 3.15 | Q88: C — Opportunistic | R88: 0.02 | S88: 0.09724 | T88: 0.28625 | U88: 0.4145 | V88: 0.5 | W88: 0 | X88: 0 | Y88: 0 | Z88: 0 | AA88: 0
A89: Ocean Prime - Denver (Larimer Square) | B89: Restaurant | D89: 0 | E89: Cameron Mitchell Restaurants | F89: $25 valet or $15 validated at host desk | G89: 227812.5 | H89: 3 | I89: 1 | J89: 2 | K89: 3 | L89: 2 | M89: 0 | O89: 2.15 | P89: 2.15 | Q89: D — Deprioritized | R89: 0 | S89: 0.018 | T89: 0.055 | U89: 0.082 | V89: 0.1 | W89: 0 | X89: 4100.625 | Y89: 12529.688 | Z89: 18680.625 | AA89: 22781.25
A90: Ruth's Chris Steak House - Denver | B90: Restaurant | D90: 0 | E90: Ruth's Hospitality Group | F90: Available (rate not published) | G90: 278437.5 | H90: 3 | I90: 2 | J90: 2 | K90: 3 | L90: 2 | M90: 1 | N90: Current operator: Darden | O90: 2.4 | P90: 3.4 | Q90: C — Opportunistic | R90: 0.02 | S90: 0.09724 | T90: 0.28625 | U90: 0.4145 | V90: 0.5 | W90: 5568.75 | X90: 27075.263 | Y90: 79702.734 | Z90: 115412.34 | AA90: 139218.75
A91: STK Steakhouse Denver | B91: Restaurant | D91: 0 | E91: ONE Group Hospitality | F91: No Valet | G91: 0 | H91: 3 | I91: 1 | J91: 2 | K91: 3 | L91: 2 | M91: 1 | N91: Current operator: The ONE Group | O91: 2.15 | P91: 3.15 | Q91: C — Opportunistic | R91: 0.02 | S91: 0.09724 | T91: 0.28625 | U91: 0.4145 | V91: 0.5 | W91: 0 | X91: 0 | Y91: 0 | Z91: 0 | AA91: 0
A92: Guard & Grace | B92: Restaurant | D92: 0 | E92: Chef/Owner Troy Guard (TAG Restaurant Group) | G92: 0 | H92: 3 | I92: 1 | J92: 2 | K92: 3 | L92: 2 | M92: 0 | O92: 2.15 | P92: 2.15 | Q92: D — Deprioritized | R92: 0 | S92: 0.018 | T92: 0.055 | U92: 0.082 | V92: 0.1 | W92: 0 | X92: 0 | Y92: 0 | Z92: 0 | AA92: 0
A93: Elway's Downtown | B93: Restaurant | D93: 0 | E93: John Elway Enterprises / Ritz-Carlton hotel valet | F93: Via Ritz-Carlton Denver hotel valet (adjacent) | G93: 0 | H93: 3 | I93: 1 | J93: 3 | K93: 3 | L93: 2 | M93: 0 | O93: 2.35 | P93: 2.35 | Q93: D — Deprioritized | R93: 0 | S93: 0.018 | T93: 0.055 | U93: 0.082 | V93: 0.1 | W93: 0 | X93: 0 | Y93: 0 | Z93: 0 | AA93: 0
A94: Elway's Cherry Creek | B94: Restaurant | D94: 0 | E94: John Elway Enterprises | F94: Not confirmed, parking available and validated | G94: 0 | H94: 3 | I94: 1 | J94: 2 | K94: 3 | L94: 2 | M94: 0 | O94: 2.15 | P94: 2.15 | Q94: D — Deprioritized | R94: 0 | S94: 0.018 | T94: 0.055 | U94: 0.082 | V94: 0.1 | W94: 0 | X94: 0 | Y94: 0 | Z94: 0 | AA94: 0
A95: Shanahan's Steakhouse | B95: Restaurant | D95: 0 | E95: Shanahan's Restaurant Group | F95: Available (rate not published) | G95: 202500 | H95: 3 | I95: 1 | J95: 2 | K95: 3 | L95: 2 | M95: 0 | O95: 2.15 | P95: 2.15 | Q95: D — Deprioritized | R95: 0 | S95: 0.018 | T95: 0.055 | U95: 0.082 | V95: 0.1 | W95: 0 | X95: 3645 | Y95: 11137.5 | Z95: 16605 | AA95: 20250
A96: Del Frisco's Double Eagle Steakhouse | B96: Restaurant | D96: 0 | E96: Del Frisco's Restaurant Group / Lone Star Funds | F96: Available (own parking lot and valet service) | G96: 455625 | H96: 3 | I96: 2 | J96: 2 | K96: 3 | L96: 2 | M96: 0 | O96: 2.4 | P96: 2.4 | Q96: D — Deprioritized | R96: 0 | S96: 0.018 | T96: 0.055 | U96: 0.082 | V96: 0.1 | W96: 0 | X96: 8201.25 | Y96: 25059.375 | Z96: 37361.25 | AA96: 45562.5
A97: Del Frisco's Grille - Cherry Creek | B97: Restaurant | D97: 0 | E97: Del Frisco's Restaurant Group | F97: No Valet | G97: 0 | H97: 3 | I97: 1 | J97: 2 | K97: 3 | L97: 2 | M97: 0 | O97: 2.15 | P97: 2.15 | Q97: D — Deprioritized | R97: 0 | S97: 0.018 | T97: 0.055 | U97: 0.082 | V97: 0.1 | W97: 0 | X97: 0 | Y97: 0 | Z97: 0 | AA97: 0
A98: Tavernetta | B98: Restaurant | D98: 0 | E98: Frasca Hospitality Group / Limelight Hotel valet | F98: $15 with restaurant validation at Limelight Hotel (1600 Wewatta St) | G98: 0 | H98: 3 | I98: 1 | J98: 2 | K98: 3 | L98: 2 | M98: 0 | O98: 2.15 | P98: 2.15 | Q98: D — Deprioritized | R98: 0 | S98: 0.018 | T98: 0.055 | U98: 0.082 | V98: 0.1 | W98: 0 | X98: 0 | Y98: 0 | Z98: 0 | AA98: 0
A99: Sunday Vinyl | B99: Restaurant | D99: 0 | E99: Frasca Hospitality Group | G99: 0 | H99: 3 | I99: 1 | J99: 2 | K99: 3 | L99: 2 | M99: 0 | O99: 2.15 | P99: 2.15 | Q99: D — Deprioritized | R99: 0 | S99: 0.018 | T99: 0.055 | U99: 0.082 | V99: 0.1 | W99: 0 | X99: 0 | Y99: 0 | Z99: 0 | AA99: 0
A100: Frasca Food and Wine | B100: Restaurant | D100: 0 | E100: Frasca Hospitality Group | F100: No Valet | G100: 0 | H100: 3 | I100: 1 | J100: 2 | K100: 3 | L100: 2 | M100: 0 | O100: 2.15 | P100: 2.15 | Q100: D — Deprioritized | R100: 0 | S100: 0.018 | T100: 0.055 | U100: 0.082 | V100: 0.1 | W100: 0 | X100: 0 | Y100: 0 | Z100: 0 | AA100: 0
...

Sheet SOM_Summary_v2
A1: SOPHI Denver — WAS v2 SOM Projection (state = COLD)
A2: Cold/Warm curves · S-curve ramp · Diversification multiplier · Relationship ledger
A4: Tier | B4: # Accts | C4: Total TAM | D4: Y1 | E4: Y2 | F4: Y3 | G4: Y4 | H4: Y5
A5: A — Beachhead | B5: 1 | C5: 7166534.4 | D5: 2866613.8 | E5: 3576100.7 | F5: 5034490.4 | G5: 6098720.8 | H5: 6808207.7
A6: B — Core | B6: 14 | C6: 30254256 | D6: 2420340.5 | E6: 6675904.1 | F6: 16961292 | G6: 23802536 | H6: 28363365
A7: C — Opportunistic | B7: 73 | C7: 18644518 | D7: 372890.36 | E7: 1812992.9 | F7: 5336993.2 | G7: 7728152.7 | H7: 9322258.9
A8: D — Deprioritized | B8: 47 | C8: 3221629.2 | D8: 0 | E8: 57989.326 | F8: 177189.61 | G8: 264173.59 | H8: 322162.92
A9: TOTAL (uncapped) | B9: 135 | C9: 59286938 | D9: 5659844.6 | E9: 12122987 | F9: 27509966 | G9: 37893583 | H9: 44815995
A11: CAPACITY-CAPPED SOM (single CM, 10 new accts/yr)
A12: Tier A+B, ranked by Y1 rev, cumulative 10/yr signing pace
B13: Accts Signed | D13: Y1 SOM | E13: Y2 SOM | F13: Y3 SOM | G13: Y4 SOM | H13: Y5 SOM
B14: End Y1: 10 | D14: 5010176.2
B15: End Y2: 20 | E15: 10876491
B16: End Y3: 30 | F16: 25762930
B17: End Y4: 40 | G17: 36984894
B18: End Y5: 50 | H18: 44493832
A20: BY ACCOUNT TYPE (uncapped)
A21: Type | B21: Count | C21: TAM | D21: Y1 | E21: Y3 | F21: Y5
A22: Hotel | B22: 86 | C22: 57469500 | D22: 5654275.8 | E22: 27345618 | F22: 44522876
A23: Restaurant | B23: 22 | C23: 1817437.5 | D23: 5568.75 | E23: 164347.73 | F23: 293118.75
A24: Hospital | B24: 12 | C24: 0 | D24: 0 | E24: 0 | F24: 0
A25: Event Venue | B25: 14 | C25: 0 | D25: 0 | E25: 0 | F25: 0
A26: Airport | B26: 1 | C26: 0 | D26: 0 | E26: 0 | F26: 0

Sheet Methodology_v2
A1: WAS v2 METHODOLOGY — SOPHI MOBILITY
A3: Market state: COLD (Warm = ≥3 current SOPHI anchor accounts in-market)
A5: CONVERSION CURVES (Y1 rate → Y5 rate per tier)
A6: Cold — A: 40% → 95%
A7: B: 8% → 75%
A8: C: 2% → 40%
A9: D: 0% → 10%
A10: Warm — A: 60% → 95%
A11: B: 25% → 80%
A12: C: 10% → 45%
A13: D: 0% → 15%
A15: S-CURVE ANNUAL RAMP (fraction of Y5-Y1 captured per year)
... A33: Source: config/relationships.yaml
