Workbook

Sheet Accounts
A1: =IFERROR(__xludf.DUMMYFUNCTION("if(eq(COUNTA(A2:A388) - COUNTUNIQUE(A2:A388),0),""Accounts"", CONCAT(""Accounts - Duplicate Found "",(COUNTA(A2:A388) - COUNTUNIQUE(A2:A388))))"),"Accounts") | B1: Account Type | C1: Active | D1: =IFERROR(__xludf.DUMMYFUNCTION("if(eq(COUNTA(D2:D388) - COUNTUNIQUE(D2:D388),0),""Address"", CONCAT(""Duplicate Found: "", (COUNTA(D2:D388) - COUNTUNIQUE(D2:D388))))"),"Duplicate Found: 6") | E1: Area | F1: Phone Number | G1: URL | H1: Self Parking Rate | I1: Valet Rate | J1: Room Count | K1: Parking Reviews | L1: Parking Reviews | M1: Management Group | N1: Linked Accounts | O1: Garage Operator | P1: Valet Operator | Q1: Location Notes | R1: POC | S1: Active Communications | T1: POC Name | U1: POC Role | V1: Email | W1: POC Phone Number | X1: Contact Preferences | Y1: Sales | Z1: Sales Notes Summary | AA1: 1. Linked In | AB1: 2. Cold Call | AC1: 3. In person visit | AD1: 4. First Email | AE1: 5. Cold Call | AF1: 6. Second follow up email | AG1: 7. Cold Call | AH1: 8. 2nd in person visit | AI1: 9. Cold Call or voicemail | AJ1: 10. Owner email | AK1: 11. 3rd email temp check | AM1: Notes | AN1: Sourcing Notes | AO1: a | AP1: b
A2: Kenect Phoenix | B2: Apartment | D2: 355 N Central Ave, Phoenix, AZ 85004 | E2: Downtown | F2: =16022582828 | G2: https://www.kenectphoenix.com/?utm_source=GBP&utm_medium=organic | I2: No Valet
A3: Sentral Sol Modern | B3: Apartment/Hotel | D3: 50 E Fillmore St, Phoenix, AZ 85004 | E3: Downtown | F3: =18449621670 | G3: https://sentral.com/phoenix/sol-modern/stay?utm_source=google&utm_medium=GMB-Website-Link&utm_campaign=GMB&utm_content=Sentral-Sol-Modern | H3: Included | I3: No Valet
A4: Sentral Alloy Midtown | B4: Apartment/Hotel | D4: 3010 N 2nd St, Phoenix, AZ 85012 | E4: Midtown | F4: (833) 584-1129 | G4: https://sentral.com/phoenix/alloy-midtown/stay?utm_source=google&utm_medium=gpm&utm_campaign=gpm&utm_content=phoenix-alloy-midtown | I4: No Valet
A5: Chateau Luxe Event Venue | B5: Event | C5: x | D5: 1175 E Lone Cactus Dr, Phoenix, AZ 85024 | E5: Cave Creek | F5: =16232668747 | S5: KA | T5: Ben COO | V5: info@chateauluxeaz.com | W5: Britanny
A6: Warehouse215 | B6: Event | D6: 215 E Grant St, Phoenix, AZ 85004 | E6: Downtown | G6: https://www.warehouse215.com/ | R6: Darnell- Events Manager | S6: KA | T6: Kathye Allen | U6: Executive Assitant | V6: Kathye.allen@warehouse215.com | Z6: Spoke with Kathye, they use their own service but also allow clients to bring in their own, going to send off information and she will share with Darnell who runs points on events
A7: 435 Collective | B7: Event | D7: 435 S 3rd Ave, Phoenix, AZ 85003 | E7: Downtown | F7: =14802668440 | G7: http://435collective.com/ | S7: KA | T7: Emily Bond | U7: Think owner? | V7: Ebond@arena.com
A8: The Boho Space | B8: Event | D8: 3201 N 16th St Suite 16, Phoenix, AZ 85016 | E8: Midtown | F8: =16234285577
A9: The Teapot | B9: Event | E9: Scottsdale | S9: KA | V9: no email provided, left inquiry on their website | Z9: Sent email inquiry
A10: monOrchid | B10: Event | D10: 214 E Roosevelt St, Phoenix, AZ 85004 | E10: Downtown | F10: =16024923235 | G10: https://monorchid.com/ | S10: KA | V10: event@monorchidphx.com | Z10: Sent email inquiry
A11: The Dauz Venue | B11: Event | D11: 750 W Polk St, Phoenix, AZ 85007 | E11: Downtown | F11: =16022570750 | G11: http://thedauz.com/ | S11: KA | V11: deedee@thedauz.com
A12: Antigua Garden | B12: Event | D12: 2645 N 16th St, Phoenix, AZ 85006 | E12: Downtown | F12: =16027590042 | G12: https://antiguagarden.com/ | W12: 602-759-0042
A13: The Icehouse | B13: Event | D13: 429 W Jackson St, Phoenix, AZ 85003 | E13: Downtown | F13: =14804286028 | G13: https://openvenues.com/venue/the-icehouse/ | V13: concierge@openvenues.com
A14: Encanto 18 | B14: Event | D14: 2775 N 15th Ave, Phoenix, AZ 85007 | E14: Downtown | F14: =16025344653 | U14: Event manager | V14: Michael.swartz@phoenix.gov | Y14: Owned by the city
A15: The Duce | B15: Event | D15: 525 S Central Ave, Phoenix, AZ 85004, USA | E15: Downtown
A16: Wedgewood Weddings | B16: Event | D16: 1742 N Lindsay Rd, Mesa, AZ 85213, USA | E16: Mesa | F16: 9805532210 | G16: https://www.wedgewoodweddings.com/lindsaygrove?matchtype=e&device=c&utm_source=google&utm_medium=cpc&utm_campaign={name}&utm_term=lindsay%20grove%20by%20wedgewood%20weddings&hsa_cam=11618124935&hsa_ad=774357435985&hsa_acc=1860597723&hsa_mt=e&hsa_net=adwords&hsa_ver=3&hsa_src=g&hsa_tgt=kwd-893510079835&hsa_grp=113660654112&hsa_kw=lindsay%20grove%20by%20wedgewood%20weddings&gad_source=1&gad_campaignid=11618124935&gbraid=0AAAAAD4sybBqp77uJaz5cPxSvqfv0aDIC&gclid=Cj0KCQiA6Y7KBhCkARIsAOxhqtMBkVtwqAaX4TF7kDJJWFt7CSWobTib9e3EcxKY0cwd2C9c87tjmdkaAgqAEALw_wcB | S16: KA | V16: events@wedgewoodweddings.com | Z16: Tons of locations across the country. Some in Charlotte and in Phoenix
A17: The Legacy Ballroom | B17: Event | D17: 4530 E Gold Dust Ave, Phoenix, AZ 85028 | R17: Sam | T17: info@thelegacyballroom.com
A18: TPC Scottsdale | B18: Golf | D18: 17020 Hayden Rd, Scottsdale, AZ 85255 | E18: North Scottsdale | F18: =14805854334 | G18: http://tpc.com/scottsdale | U18: Generic Email | V18: contactscottsdale@pgatourhq.com | Z18: Talked with Andrew on sales side, they have a vendor they are happy with at the moment | AA18: x
A19: Raven Golf Club | B19: Golf | D19: 3636 E Baseline Rd, Phoenix, AZ 85042 | E19: South Mountain | F19: =16022433636 | G19: https://www.ravenphx.com/ | S19: BT | T19: Chelsea- Event Manager, Matthew- GM | U19: Events and GM | V19: Cnavarrette@arcisgolf.com, Mphillips@arcisgolf.com | Z19: transfered to a sales member and he didnt know who to give my information to. He said he would ask around for me. He was excited to talk when i mentioned we have worked for qual hallow before
A20: Papago Golf Club | B20: Golf | D20: 5595 E Karsten Wy, Phoenix, AZ 85008 | E20: Tempe | F20: =16022758428 | G20: https://www.papagogolfclub.com/?utm_source=extnet&utm_medium=yext | U20: Kellil Meirick | V20: kmeirick@golfpapago.com
A21: Reliance Hospitality | B21: Hospitality Group | T21: Jason Moore VP of ops & Marcy Westrom CEO
A22: Integrity Lodging | B22: Hospitality Group | AA22: requested connecting
A23: Riot Hospitality Group | B23: Hospitality Group
A24: Heavlin Management Company (HMC) | B24: Hospitality Group
A25: Aligned Hospitality Management | B25: Hospitality Group
A26: Aimbridge Hospitality | B26: Hospitality Group
A27: Crescent Hotels & Resorts | B27: Hospitality Group
A28: Southwest Hospitality Management | B28: Hospitality Group
A29: Desert Hospitality Management | B29: Hospitality Group
A30: NCG Hospitality | B30: Hospitality Group
A31: Classic Hotels & Resorts | B31: Hospitality Group
A32: Carter Concepts Restaurant Group | B32: Hospitality Group
A33: Courtyard Phoenix Airport | B33: Hotel | D33: 2621 S 47th St, Phoenix, AZ 85034 | E33: Airport | F33: =14809664300 | G33: https://www.marriott.com/en-us/hotels/phxca-courtyard-phoenix-airport/overview/?scid=f2ae0541-1279-4f24-b197-a979c79310b0 | H33: 15 | I33: No Valet | J33: 145 | K33: 0.56 | L33: 18 | T33: Charles Padilla | U33: GM
A34: Hilton Phoenix Airport | B34: Hotel | D34: 2435 S 47th St, Phoenix, AZ 85034 | E34: Airport | F34: =14808941600 | G34: https://www.hilton.com/en/hotels/phxahhf-hilton-phoenix-airport/?SEO_id=GMB-AMER-HH-PHXAHHF&y_source=1_MTIyMDg0Ni03MTUtbG9jYXRpb24ud2Vic2l0ZQ%3D%3D | H34: 10 | I34: No Valet | J34: 259 | K34: 0.53 | L34: 51
A35: Marriott Phoenix Airport | B35: Hotel | D35: 1101 N 44th St, Phoenix, AZ 85008 | E35: Airport | F35: =16022737373 | G35: https://www.marriott.com/en-us/hotels/phxap-marriott-phoenix-airport/overview/?scid=f2ae0541-1279-4f24-b197-a979c79310b0 | H35: 10 | I35: No Valet | J35: 347 | K35: 0.65 | L35: 46
A36: Arizona Biltmore, LXR Hotels & Resorts | B36: Hotel | D36: 2400 E Missouri Ave, Phoenix, AZ 85016 | E36: Biltmore | F36: (602) 955-6600 | G36: https://www.hilton.com/en/hotels/phxbmol-arizona-biltmore/rooms/ | I36: valet only | J36: 750 | K36: 0.35 | L36: 156 | T36: Jessica Carlson | U36: Resort Manager
A37: Embassy Suites by Hilton Phoenix Biltmore | B37: Hotel | C37: x | D37: 2630 E Camelback Rd, Phoenix, AZ 85016 | E37: Blitmore | F37: =16029553992 | G37: https://www.hilton.com/en/hotels/phxcbes-embassy-suites-phoenix-biltmore/?SEO_id=GMB-AMER-ES-PHXCBES&y_source=1_MTExMDAzNC03MTUtbG9jYXRpb24ud2Vic2l0ZQ%3D%3D | H37: 14 | I37: No Valet | J37: 232 | K37: 0.2 | L37: 51 | T37: Vinnie Walia | U37: GM | V37: phxcb_embassy@hilton.com | Z37: called and talked to blake at front desk, said to call back monday for operations manager
A38: Hampton Inn Phoenix-Biltmore | B38: Hotel | D38: 2310 E Highland Ave, Phoenix, AZ 85016 | E38: Blitmore | F38: =16029565221 | G38: https://www.hilton.com/en/hotels/phxehhx-hampton-phoenix-biltmore/?SEO_id=GMB-AMER-HX-PHXEHHX&y_source=1_MjA4MzE5Ny03MTUtbG9jYXRpb24ud2Vic2l0ZQ%3D%3D | J38: 121 | K38: 0.42 | L38: 33
A39: The Camby, Autograph Collection | B39: Hotel | D39: 2401 E Camelback Rd, Phoenix, AZ 85016 | E39: Blitmore | F39: =16024680700 | G39: https://www.marriott.com/en-us/hotels/phxak-the-camby-autograph-collection/overview/?scid=f2ae0541-1279-4f24-b197-a979c79310b0 | I39: 40 | J39: 279 | K39: 0.45 | L39: 95 | T39: Christine Menzel | U39: GM | V39: Cmenzel@thecamby.com
A40: AC Hotel Phoenix Biltmore | B40: Hotel | D40: 2811 E Camelback Rd, Phoenix, AZ 85016 | E40: Blitmore | F40: =16028526500 | G40: https://www.marriott.com/en-us/hotels/phxab-ac-hotel-phoenix-biltmore/overview/?scid=f2ae0541-1279-4f24-b197-a979c79310b0 | H40: 12 | I40: No Valet | J40: 160 | K40: 0.68 | L40: 19 | T40: April Mosley | U40: GM | Z40: linked in message
A41: Sonesta Select Phoenix Camelback | B41: Hotel | D41: 2101 E Camelback Rd, Phoenix, AZ 85016 | E41: Blitmore | F41: =16029555200 | G41: https://www.sonesta.com/sonesta-select/az/phoenix/sonesta-select-phoenix-camelback | H41: Free | J41: 155 | K41: 0.71 | L41: 21 | T41: Rachel Fesler | U41: Area Gm | V41: Rachel.fesler@sonesta.com
A42: Hilton Garden Inn Chandler Downtown | B42: Hotel | C42: x | D42: 150 S Arizona Ave, Chandler, AZ 85225 | E42: Chandler | F42: =16234718400 | G42: https://www.hilton.com/en/hotels/phxazgi-hilton-garden-inn-chandler-downtown/?SEO_id=GMB-AMER-GI-PHXAZGI&y_source=1_MTU1MTEwNzctNzE1LWxvY2F0aW9uLndlYnNpdGU%3D | H42: 15 | I42: No Valet | J42: 110 | K42: 0.16 | L42: 31 | S42: KA | T42: Daron Brotherton | U42: GM | Z42: Called and jason no longer gm, left voicemail for Daron, must be new to the role at this property | AA42: Messaging him on linked in
A43: Element Chandler Fashion Center | B43: Hotel | D43: 44 S Chandler Village Dr, Chandler, AZ 85226 | E43: Chandler | F43: =14805537277 | G43: https://www.marriott.com/en-us/hotels/phxel-element-chandler-fashion-center/overview/?scid=f2ae0541-1279-4f24-b197-a979c79310b0 | H43: 10 | I43: No Valet | J43: 107 | K43: 0.56 | L43: 16
A44: AC Hotel Phoenix Downtown | B44: Hotel | C44: x | D44: 414 N 5th St, Phoenix, AZ 85004 | E44: Downtown | F44: (602) 258-1771 | G44: https://www.marriott.com/en-us/hotels/phxad-ac-hotel-phoenix-downtown/overview/?scid=f2ae0541-1279-4f24-b197-a979c79310b0 | H44: 34 | I44: No Valet | J44: 199 | K44: 0.3 | L44: 37 | S44: BT | T44: shayan - area gm | U44: Brian Hanus AGM | Z44: called left voicemail. explained that were new to area and wanted to get an introduction | AB44: front desk hung up on me
A45: Embassy Suites by Hilton Phoenix Downtown North | B45: Hotel | C45: x | D45: 10 E Thomas Rd, Phoenix, AZ 85012 | E45: Downtown | F45: =16022221111 | G45: https://www.hilton.com/en/hotels/phxeses-embassy-suites-phoenix-downtown-north/?SEO_id=GMB-AMER-ES-PHXESES&y_source=1_ODUzMzQzOC03MTUtbG9jYXRpb24ud2Vic2l0ZQ%3D%3D | H45: 32 | I45: No Valet | J45: 242 | K45: 0.32 | L45: 68 | S45: BT | T45: brian clark | V45: brian.clark@hilton.com | Z45: call but brian was ooo | AB45: Emailed Brian-korey
A46: Cambria Hotel Downtown Phoenix Convention Center | B46: Hotel | C46: x | D46: 222 E Portland St, Phoenix, AZ 85004 | E46: Downtown | F46: =16234628271 | G46: https://www.choicehotels.com/arizona/phoenix/cambria-hotels/az474?mc=llgoxxpx | H46: 25 | I46: 41 | J46: 127 | K46: 0.14 | L46: 113 | P46: Premium Parking | S46: BT | T46: Chris Rhoades | V46: Chris.rhoades@cambriadtphx.com | Z46: Monday Tuesdsay after 11am, and Friday? | AB46: Meeting with Monday
A47: Courtyard Phoenix Downtown | B47: Hotel | C47: x | D47: 132 S Central Ave, Phoenix, AZ 85004 | E47: Downtown | F47: =16026032001 | G47: https://www.marriott.com/en-us/hotels/phxxt-courtyard-phoenix-downtown/overview/?scid=f2ae0541-1279-4f24-b197-a979c79310b0 | I47: 45 | J47: 120 | K47: 0.2 | L47: 64 | P47: Laz | S47: KA | T47: Trent Collicott | U47: Dual GM | V47: trent.collicott@marriott.com | Z47: Left voicemail and just asked to possibly get time to introduce ourselves and showcase SOPHI and how we elevate current parking experience | AA47: x | AB47: Voicemail | AE47: called and left voicemail again, front desk said they didnt know his email
A48: Hilton Garden Inn Phoenix Downtown | B48: Hotel | C48: x | D48: 15 E Monroe St, Phoenix, AZ 85004 | E48: Downtown | F48: =16023430006 | G48: https://www.hilton.com/en/hotels/phxdogi-hilton-garden-inn-phoenix-downtown/?SEO_id=GMB-AMER-GI-PHXDOGI&y_source=1_MjY5OTI4MS03MTUtbG9jYXRpb24ud2Vic2l0ZQ%3D%3D | I48: 43 | J48: 170 | K48: 0.3 | L48: 136 | S48: KA | T48: Araceli | U48: GM | V48: Aaydogan@csmcorp.net | W48: Alex | Z48: Called talked to vivian at FD, she referred me to her AGM's email address | AB48: Called talked to vivian at FD, she referred me to her AGM's email address
A49: Residence Inn by Marriott Phoenix Downtown | B49: Hotel | C49: x | D49: 132 S Central Ave, Phoenix, AZ 85004 | E49: Downtown | F49: =16026032000 | G49: https://www.marriott.com/en-us/hotels/phxtw-residence-inn-phoenix-downtown/overview/?scid=f2ae0541-1279-4f24-b197-a979c79310b0 | I49: 45 | K49: 0.3 | L49: 87 | P49: Laz | S49: KA | T49: Trent Collicott | U49: Dual GM | V49: trent.collicott@marriott.com | Z49: Same POC as courtyard! | AA49: x | AB49: ** courtyard | AE49: called and left voicemail again, front desk said they didnt know his email
A50: Moxy Phoenix Downtown | B50: Hotel | C50: x | D50: 116 S Central Ave, Phoenix, AZ 85004 | E50: Downtown | F50: =16232911200 | G50: https://www.marriott.com/en-us/hotels/phxod-moxy-phoenix-downtown/overview/?scid=f2ae0541-1279-4f24-b197-a979c79310b0 | I50: 45 | J50: 164 | K50: 0.31 | L50: 13 | S50: KA | T50: Eren Bicakci | U50: GM | V50: Ebicakci@pegghospitalitygroup.com | Z50: Left Voicemail for Eren to call back and grabbed his email from FD | AD50: sent intro email
A51: Kimpton Hotel Palomar Phoenix | B51: Hotel | D51: 2 E Jefferson St, Phoenix, AZ 85004 | E51: Downtown | F51: =16022536633 | G51: https://www.hotelpalomar-phoenix.com/?&cm_mmc=WEB-_-KI-_-AMER-_-EN-_-EV-_-Google%20Business%20Profile-_-DD-_-palomar%20phoenix | H51: 30 | I51: 44 | J51: 242 | K51: 0.5 | L51: 131 | S51: KA
A52: Home2 Suites by Hilton Phoenix Downtown | B52: Hotel | C52: x | D52: 125 E Jackson St, Phoenix, AZ 85004 | E52: Downtown | F52: =16026031111 | G52: https://www.hilton.com/en/hotels/phxpxht-home2-suites-phoenix-downtown/?SEO_id=GMB-AMER-HT-PHXPXHT&y_source=1_OTgxMzcxMzgtNzE1LWxvY2F0aW9uLndlYnNpdGU%3D | I52: 45 | J52: 148 | K52: 0.34 | L52: 72 | S52: BT | T52: Kovava | U52: gm | V52: Kshipman@ih-corp.com | Z52: very happy with their current program and wouldnt consider changes, wild | AB52: x phone not working
A53: Renaissance Phoenix Downtown Hotel | B53: Hotel | C53: x | D53: 100 N 1st St, Phoenix, AZ 85004 | E53: Downtown | F53: =16023330000 | I53: 42 | J53: 518 | K53: 0.39 | L53: 150 | P53: TownePark | S53: BT | T53: Brittany | V53: brittany.a.raymond@marriott.com | Z53: she said theyre in contract with current provider. i asked if she knew when it renewed because we would love to get a proposal infront of them before the time comes. she said to email her some information about sophi and shed get back to me (could tell she just wanted to get me off the phone, she was typing the entire call) | AB53: x | AD53: sent her some information about sOPHI
A54: Sheraton Phoenix Downtown | B54: Hotel | C54: x | D54: 340 N 3rd St, Phoenix, AZ 85004 | E54: Downtown | F54: =16022622500 | G54: https://www.marriott.com/en-us/hotels/phxgp-sheraton-phoenix-downtown/overview/?scid=f2ae0541-1279-4f24-b197-a979c79310b0 | H54: 36 | I54: 46 | J54: 1000 | K54: 0.41 | L54: 219 | P54: TownePark | S54: BT | T54: Christopher Scott | U54: Director Rooms Op | AB54: Couldn't get through waiting on hold longer than 10 min, hung up will try later
A55: The Westin Phoenix Downtown | B55: Hotel | C55: x | D55: 333 N Central Ave, Phoenix, AZ 85004 | E55: Downtown | F55: =16024293500 | G55: https://www.marriott.com/en-us/hotels/phxiw-the-westin-phoenix-downtown/overview/?scid=f2ae0541-1279-4f24-b197-a979c79310b0 | H55: 35 | I55: 45 | J55: 242 | K55: 0.38 | L55: 131 | T55: Jeremy Raynor | U55: GM
A56: Hotel San Carlos | B56: Hotel | C56: x | D56: 202 N Central Ave, Phoenix, AZ 85004 | E56: Downtown | F56: =16022534121 | G56: https://hotelsancarlos.com/?utm_source=google-gbp&utm_medium=organic&utm_campaign=gbp | I56: No Valet | J56: 128 | K56: 0.24 | L56: 41 | T56: Angela Hentz | U56: GM | V56: Angela@hotelsancarlos.com | Z56: Angela is still the GM, left a voicemail and emailed
A57: Hampton Inn & Suites Phoenix Downtown | B57: Hotel | D57: 77 E Polk St, Phoenix, AZ 85004 | E57: Downtown | F57: =16027101240 | G57: https://www.hilton.com/en/hotels/phxcthx-hampton-suites-phoenix-downtown/?SEO_id=GMB-AMER-HX-PHXCTHX&y_source=1_OTQwMzQyNC03MTUtbG9jYXRpb24ud2Vic2l0ZQ%3D%3D | I57: 42 | J57: 210 | K57: 0.31 | L57: 153 | T57: Cory Gruber | U57: GM | V57: Cgruber@ncghospitality.com | Z57: Cory, connected with her on linked in, emailed and left voicemail
A58: Hyatt Place Phoenix / Downtown | B58: Hotel | D58: 150 W Adams St, Phoenix, AZ 85003 | E58: Downtown | F58: =16023884888 | H58: 34 | I58: 44 | J58: 238 | K58: 0.35 | L58: 78 | T58: Danielle Klus
A59: FOUND:RE Phoenix Hotel | B59: Hotel | D59: 1100 N Central Ave, Phoenix, AZ 85004 | E59: Downtown | F59: =16028758000 | G59: https://www.foundrehotels.com/ | H59: 35 | I59: 45 | J59: 104 | K59: 0.36 | L59: 78 | T59: chris genung
A60: Hyatt Regency Phoenix | B60: Hotel | D60: 122 N 2nd St, Phoenix, AZ 85004 | E60: Downtown | F60: 16022521234 | G60: https://www.hyatt.com/hyatt-regency/en-US/phxrp-hyatt-regency-phoenix?src=corp_lclb_google_seo_phxrp&utm_source=google&utm_medium=organic&utm_campaign=lmr | H60: 34 | I60: 44 | J60: 693 | K60: 0.37 | L60: 188 | T60: Eric Fink | U60: GM | Z60: linked in messages
A61: Egyptian Motor Hotel BW Signature Collection | B61: Hotel | D61: 765 Grand Ave, Phoenix, AZ 85007 | E61: Downtown | F61: (602) 807-5225 | G61: https://www.egyptianmotorhotel.com/eat-drink.htm | H61: Fee | I61: No Valet | J61: 49 | K61: 0.54 | L61: 13 | T61: Tamara Vildosola
A62: DoubleTree by Hilton Hotel Phoenix - Gilbert | B62: Hotel | D62: 1800 S Santan Village Pkwy, Gilbert, AZ 85295 | E62: Gilbert | F62: 14808094100 | G62: https://www.hilton.com/en/hotels/phxstdt-doubletree-phoenix-gilbert/?SEO_id=GMB-AMER-DT-PHXSTDT&y_source=1_MTM3MjY1Ny03MTUtbG9jYXRpb24ud2Vic2l0ZQ%3D%3D | H62: Free | I62: No Valet | J62: 121 | K62: 0.5 | L62: 22
A63: TownePlace Suites by Marriott Phoenix Glendale Sports & Entertainment District | B63: Hotel | D63: 7271 N Zanjero Blvd, Glendale, AZ 85305 | E63: Glendale | F63: =16238722100 | G63: https://www.marriott.com/en-us/hotels/phxtg-towneplace-suites-phoenix-glendale-sports-and-entertainment-district/overview/?scid=f2ae0541-1279-4f24-b197-a979c79310b0 | H63: 10 | I63: No Valet | K63: 0.17 | L63: 6
A64: SpringHill Suites by Marriott Phoenix Glendale Sports & Entertainment District | B64: Hotel | D64: 7370 N. Zanjero (Janjero) Boulevard, Glendale, AZ 85305 | E64: Glendale | F64: =16237729200 | G64: https://www.marriott.com/en-us/hotels/phxgl-springhill-suites-phoenix-glendale-sports-and-entertainment-district/overview/?scid=f2ae0541-1279-4f24-b197-a979c79310b0 | H64: 10 | I64: No Valet | J64: 120 | K64: 0.35 | L64: 17
A65: Tru by Hilton Phoenix Glendale Westgate | B65: Hotel | D65: 6610 N 95th Ave, Glendale, AZ 85305 | E65: Glendale | F65: =16232503551 | G65: https://www.hilton.com/en/hotels/phxpgru-tru-phoenix-glendale-westgate/?SEO_id=GMB-AMER-RU-PHXPGRU&y_source=1_MTkzMTU4MzYtNzE1LWxvY2F0aW9uLndlYnNpdGU%3D | H65: 18 | I65: No Valet | K65: 0.35 | L65: 17
A66: Residence Inn by Marriott Phoenix Glendale Sports & Entertainment District | B66: Hotel | D66: 7350 N Zanjero Blvd, Glendale, AZ 85305 | E66: Glendale | F66: =16237728900 | G66: https://www.marriott.com/en-us/hotels/phxgi-residence-inn-phoenix-glendale-sports-and-entertainment-district/overview/?scid=f2ae0541-1279-4f24-b197-a979c79310b0 | H66: 10 | I66: No Valet | K66: 0.43 | L66: 7
A67: Hampton Inn & Suites Phoenix Glendale-Westgate | B67: Hotel | D67: 6630 N 95th Ave, Glendale, AZ 85305 | E67: Glendale | F67: =16232717771 | G67: https://www.hilton.com/en/hotels/phxglhx-hampton-suites-phoenix-glendale-westgate/?SEO_id=GMB-AMER-HX-PHXGLHX&y_source=1_MjA4NDc3Ny03MTUtbG9jYXRpb24ud2Vic2l0ZQ%3D%3D | H67: 18 | I67: No Valet | J67: 149 | K67: 0.52 | L67: 25
A68: Staybridge Suites Phoenix - Glendale Sports Dist by IHG | B68: Hotel | D68: 9340 W Cabela Dr, Glendale, AZ 85305 | E68: Glendale | F68: =16238420000 | G68: https://www.ihg.com/staybridge/hotels/us/en/glendale/phxgz/hoteldetail?cm_mmc=GoogleMaps-_-SB-_-US-_-PHXGZ | H68: Free | I68: No Valet | J68: 116 | K68: 0.6 | L68: 5
A69: Renaissance Phoenix Glendale Hotel & Conference Center | B69: Hotel | D69: 9495 W Entertainment Blvd, Glendale, AZ 85305 | E69: Glendale | F69: 16239373700 | G69: https://www.marriott.com/en-us/hotels/phxgr-renaissance-phoenix-glendale-hotel-and-conference-center/overview/?scid=f2ae0541-1279-4f24-b197-a979c79310b0 | H69: 20 | I69: 26 | J69: 324 | K69: 0.78 | L69: 448
A70: Holiday Inn Express & Suites Phoenix - Glendale Sports Dist | B70: Hotel | D70: 9310 W Cabela Dr, Glendale, AZ 85305 | E70: Glendale | F70: =16239398888 | G70: https://www.ihg.com/holidayinnexpress/hotels/us/en/glendale/phxgg/hoteldetail?cm_mmc=GoogleMaps-_-EX-_-US-_-PHXGG | H70: Free | I70: No Valet | J70: 96 | K70: 0.78 | L70: 9
A71: Arizona Grand Resort & Spa | B71: Hotel | C71: x | D71: 8000 South Arizona Grand E, Phoenix, AZ 85044 | E71: Guadalupe | F71: =18778004888 | G71: https://www.arizonagrandresort.com/ | H71: Resort Fee | I71: No Valet | J71: 744 | K71: 0.29 | L71: 192 | T71: Paul | U71: GM
A72: Legacy Golf Resort | B72: Hotel | D72: 6808 S 32nd St, Phoenix, AZ 85042 | E72: Guadalupe | F72: =16023055500 | G72: https://www.extraholidays.com/phoenix-arizona/legacy-golf-resort?utm_medium=listing&utm_source=google-local&utm_campaign=na_gmb_na_locallisting_na_allusers&utm_content=svclegacygolf | H72: Free | I72: No Valet | K72: 0.43 | L72: 40
A73: WorldMark Phoenix - South Mountain Preserve | B73: Hotel | D73: 4647 E Francisco Dr, Phoenix, AZ 85044 | E73: Guadalupe | F73: =16023861900 | G73: https://www.extraholidays.com/phoenix-arizona/worldmark-phoenix?utm_medium=listing&utm_source=google-local&utm_campaign=na_gmb_na_locallisting_na_allusers&utm_content=wmphoenixsouthmountainpreserve | H73: Free | I73: No Valet | K73: 0.64 | L73: 66 | AN73: says parking is limited on website
A74: The Wigwam | B74: Hotel | D74: 300 E Wigwam Blvd, Litchfield Park, AZ 85340 | E74: Litchfield | F74: 18442391641 | G74: https://www.wigwamarizona.com/?utm_source=google&utm_medium=organic&utm_campaign=gbp_listing | H74: 42 | I74: 42 | J74: 331 | K74: 0.5 | L74: 62
A75: Sheraton Mesa Hotel at Wrigleyville West | B75: Hotel | D75: 860 N Riverview, Mesa, AZ 85201 | E75: Mesa | F75: =14806641221 | G75: https://www.marriott.com/en-us/hotels/phxww-sheraton-mesa-hotel-at-wrigleyville-west/overview/?scid=f2ae0541-1279-4f24-b197-a979c79310b0 | H75: Free | I75: No Valet | J75: 180 | K75: 0.38 | L75: 42 | T75: Kevin Thorpe | U75: GM
A76: Delta Hotels Phoenix Mesa | B76: Hotel | D76: 200 N Centennial Way, Mesa, AZ 85201 | E76: Mesa | F76: =14808988300 | G76: https://www.marriott.com/en-us/hotels/phxde-delta-hotels-phoenix-mesa/overview/?scid=f2ae0541-1279-4f24-b197-a979c79310b0 | H76: Free | I76: No Valet | J76: 274 | K76: 0.39 | L76: 41 | T76: Janet Woolf | U76: GM
A77: Courtyard by Marriott Phoenix Mesa | B77: Hotel | D77: 1221 S Westwood, Mesa, AZ 85210 | E77: Mesa | F77: =14804613000 | G77: https://www.marriott.com/en-us/hotels/phxme-courtyard-phoenix-mesa/overview/?scid=f2ae0541-1279-4f24-b197-a979c79310b0 | H77: 10 | I77: No Valet | J77: 149 | K77: 0.44 | L77: 18 | T77: Eric Valenzuela | U77: GM
A78: Four Points by Sheraton at Phoenix Mesa Gateway Airport | B78: Hotel | D78: 6850 E Williams Field Rd, Mesa, AZ 85212 | E78: Mesa | F78: =14805792100 | G78: https://www.marriott.com/en-us/hotels/phxma-four-points-at-phoenix-mesa-gateway-airport/overview/?scid=f2ae0541-1279-4f24-b197-a979c79310b0 | H78: 10 | I78: No Valet | J78: 134 | K78: 0.7 | L78: 20 | T78: Amanda Jones | U78: Ops Manager
A79: DoubleTree by Hilton Phoenix Mesa | B79: Hotel | D79: 1011 W Holmes Ave, Mesa, AZ 85210 | E79: Mesa | F79: 14808335555 | G79: https://www.hilton.com/en/hotels/meswhdt-doubletree-phoenix-mesa/?SEO_id=GMB-AMER-DT-MESWHDT&y_source=1_MTY1MDA5NzktNzE1LWxvY2F0aW9uLndlYnNpdGU%3D | H79: Free | I79: No Valet | J79: 262 | K79: 0.75 | L79: 32 | T79: Bryan Heintz | U79: GM
A80: Courtyard by Marriott Mesa at Wrigleyville West | B80: Hotel | D80: 2224 W Rio Salado Pkwy, Mesa, AZ 85201 | E80: Mesa | F80: =14805908000 | G80: https://www.marriott.com/en-us/hotels/phxce-courtyard-mesa-at-wrigleyville-west/overview/?scid=f2ae0541-1279-4f24-b197-a979c79310b0 | H80: Free | I80: No Valet | J80: 129 | K80: 1 | L80: 6 | T80: Charles Barron | U80: GM
A81: DoubleTree by Hilton Phoenix Midtown | B81: Hotel | C81: x | D81: 4000 N Central Ave, Phoenix, AZ 85012 | E81: Midtown | F81: =16022799811 | G81: https://www.hilton.com/en/hotels/phxardt-doubletree-phoenix-midtown/?SEO_id=GMB-AMER-DT-PHXARDT&y_source=1_MjA4Mzk4NS03MTUtbG9jYXRpb24ud2Vic2l0ZQ%3D%3D | H81: Free | J81: 156 | K81: 0.3 | L81: 70 | O81: Ace Parking | S81: BT | T81: Jack Wright | U81: GM | Z81: Called left voicemail | AB81: Called left voicemail | AN81: far away self parking terrible reviews
A82: Rise Uptown Hotel | B82: Hotel | C82: x | D82: 400 W Camelback Rd, Phoenix, AZ 85013 | E82: Midtown | F82: (480) 536-8900 | G82: https://www.google.com/aclk?sa=L&ai=DChsSEwj5ro-q_N2PAxULJEQIHSpsNvwYACICCAEQAxoCZHo&co=1&ase=2&gclid=CjwKCAjwlaTGBhANEiwAoRgXBceLXnbv5QWWVKOlNKgztmJ1y-EVIQDo-MotZrLXTyDgvElFh4BMzxoCtAIQAvD_BwE&ei=a7TJaOjPMfLOkPIPsJ2y4QM&cce=2&category=acrcp_v1_32&sig=AOD64_19cjeJIWDu7MzREcj1Mnmc2ElJiA&q&sqi=2&nis=4&adurl&ved=2ahUKEwiosYiq_N2PAxVyJ0QIHbCOLDwQ0Qx6BAhfEAQ | H82: Free | K82: 0.28 | L82: 29
A83: Home2 Suites by Hilton Phoenix Midtown | B83: Hotel | D83: 3150 N Central Ave, Phoenix, AZ 85012 | E83: Midtown | F83: =16022773150 | G83: https://www.hilton.com/en/hotels/phxmmht-home2-suites-phoenix-midtown/?SEO_id=GMB-AMER-HT-PHXMMHT&y_source=1_OTgxMzgwNzQtNzE1LWxvY2F0aW9uLndlYnNpdGU%3D | H83: 10 | J83: 103 | K83: 0.18 | L83: 6 | T83: Patricia Manzanares | U83: Dual GM | V83: Patricia.manzanares@hilton.com | Z83: Called again after first time, spoke with her, they haven't gotten valet approved yet to but has my contact written down
A84: The Clarendon Hotel and Spa | B84: Hotel | D84: 401 W Clarendon Ave, Phoenix, AZ 85013 | E84: Midtown | F84: 16022527363 | G84: http://www.goclarendon.com/ | I84: No Valet | J84: 105 | K84: 0.25 | L84: 130 | T84: Gill GM | U84: brent AGM | V84: brentjames@goclarendon.com | Z84: said no and i was like total understand, usually for smaller hotels they dont need valet but sometimes they want it to improve service, generate more money, improve reviews etc. gained his interest by disarminig and he ended up asking for more info
A85: Fairfield Inn & Suites Phoenix Midtown | B85: Hotel | D85: 2520 N Central Ave, Phoenix, AZ 85004 | E85: Midtown | F85: (602) 716-9900 | G85: https://www.marriott.com/en-us/hotels/phxas-fairfield-inn-and-suites-phoenix-midtown/overview/?scid=f2ae0541-1279-4f24-b197-a979c79310b0 | H85: 7 | I85: No Valet | J85: 107 | K85: 0.58 | L85: 24 | T85: Kassie Maloney | U85: GM
A86: Hilton Garden Inn Phoenix Midtown | B86: Hotel | D86: 4000 N Central Ave, Phoenix, AZ 85012 | E86: Midtown | F86: =16022799811 | G86: https://www.hilton.com/en/hotels/phxmdgi-hilton-garden-inn-phoenix-midtown/?SEO_id=GMB-AMER-GI-PHXMDGI&y_source=1_MjA4Mzk4NS03MTUtbG9jYXRpb24ud2Vic2l0ZQ%3D%3D | J86: 156
A87: JW Marriott Phoenix Desert Ridge Resort & Spa | B87: Hotel | C87: x | D87: 5350 E Marriott Dr, Phoenix, AZ 85054 | E87: North Scottsdale | F87: 14802935000 | G87: https://www.marriott.com/en-us/hotels/phxdr-jw-marriott-phoenix-desert-ridge-resort-and-spa/overview/?scid=f2ae0541-1279-4f24-b197-a979c79310b0 | H87: 29 | I87: 46 | J87: 950 | K87: 0.34 | L87: 154 | T87: Paige Lund | U87: paige-GM, Connie-asst | V87: Connie.ogden@marriott.com | Z87: spoke with connie, shes going to push our information to the right person who oversees valet and parking
A88: Marriott's Canyon Villas | B88: Hotel | D88: 5220 E Marriott Dr, Phoenix, AZ 85054 | E88: North Scottsdale | F88: 14806293200 | G88: https://www.marriott.com/en-us/hotels/phxcv-marriotts-canyon-villas/overview/?scid=f2ae0541-1279-4f24-b197-a979c79310b0 | H88: 25 | I88: No Valet | J88: 252 | K88: 0.5 | L88: 20 | T88: Sue Tan
A89: Fairmont Gold Lounge | B89: Hotel | D89: 7600 E Hartford Dr, Scottsdale, AZ 85255 | E89: North Scottsdale | F89: =14805854848 | G89: https://www.fairmont.com/en/fairmont-gold.html
A90: AC Hotel Scottsdale North | B90: Hotel | C90: x | D90: 15200 N Kierland Blvd, Scottsdale, AZ 85254 | E90: Scottsdale | F90: 14806075555 | G90: https://www.marriott.com/en-us/hotels/phxax-ac-hotel-scottsdale-north/overview/?scid=f2ae0541-1279-4f24-b197-a979c79310b0 | H90: 29 | I90: No Valet | J90: 165 | K90: 0.24 | L90: 17 | S90: BT | T90: Ximena Sanchez | U90: GM | V90: ximena.sanchez@marriott.com | Z90: called no voicemail, got email | AA90: x | AB90: called no voicemail, got email | AD90: sent email
A91: Courtyard Scottsdale Old Town | B91: Hotel | C91: x | D91: 3311 N Scottsdale Rd, Scottsdale, AZ 85251 | E91: Scottsdale | F91: =14804297785 | G91: https://www.marriott.com/en-us/hotels/phxsc-courtyard-scottsdale-old-town/overview/?scid=f2ae0541-1279-4f24-b197-a979c79310b0 | H91: 12 | I91: No Valet | J91: 180 | K91: 0.38 | L91: 24 | S91: BT | T91: Victoria gm and alli (soon to be agm) | Z91: called and left voicemail. | AB91: called and left voicemail.
A92: Scottsdale Marriott Old Town | B92: Hotel | C92: x | D92: 7325 E 3rd Ave, Scottsdale, AZ 85251 | E92: Scottsdale | F92: =14809451550 | G92: https://www.marriott.com/en-us/hotels/phxst-scottsdale-marriott-old-town/overview/?scid=f2ae0541-1279-4f24-b197-a979c79310b0 | H92: 30 | I92: No Valet | J92: 243 | K92: 0.44 | L92: 39 | S92: BT | T92: Erica Avila & Briana Naegeli | U92: Rooms operations manager & GM | W92: 4808746045
A93: The Monarch | B93: Hotel | D93: 4000 N Drinkwater Blvd, Scottsdale, AZ 85251 | E93: Scottsdale | F93: =16233527272 | G93: https://www.themonarchscottsdale.com/ | H93: 15 | I93: No Valet | J93: 194 | K93: 0.33 | L93: 57 | S93: BT | T93: Nate Lopez GM Bryce Milller AGM | Z93: said would be interested in pitching valet for events but rooms are too cheap to add valet services (had a room for $50)
A94: Hotel Adeline, Scottsdale, a Tribute Portfolio Hotel | B94: Hotel | C94: x | D94: 5101 N Scottsdale Rd, Scottsdale, AZ 85250 | E94: Scottsdale | F94: =14802847700 | G94: https://www.marriott.com/en-us/hotels/phxtx-hotel-adeline-scottsdale-a-tribute-portfolio-hotel/overview/?scid=f2ae0541-1279-4f24-b197-a979c79310b0 | H94: 25 | I94: No Valet | J94: 213 | K94: 0.39 | L94: 38 | S94: BT | T94: Trevor Curran | U94: GM | V94: trevor.curran@pyramidglobal.com | W94: 5413061305 | Z94: 1/26 just sent newemail trying to reconnect with maybe more security focus
A95: Embassy Suites by Hilton Scottsdale Resort | B95: Hotel | C95: x | D95: 5001 N Scottsdale Rd, Scottsdale, AZ 85250 | E95: Scottsdale | F95: =14809491414 | G95: https://www.hilton.com/en/hotels/scteses-embassy-suites-scottsdale-resort/?SEO_id=GMB-AMER-ES-SCTESES&y_source=1_MzM1NTM1NC03MTUtbG9jYXRpb24ud2Vic2l0ZQ%3D%3D | H95: Free | I95: No Valet | J95: 312 | K95: 0.44 | L95: 77 | S95: BT | T95: David Smith | U95: GM | Z95: got off the phone with him, said give him a call back in october or november. he said theyre struggling with room ocupancy rn and want to get it back to normal before potentially starting valet services. chatted about weather and moving from midwest (hes from ohio)
A96: Senna House Hotel Scottsdale, Curio Collection by Hilton | B96: Hotel | D96: 7501 E Camelback Rd, Scottsdale, AZ 85251 | E96: Scottsdale | F96: =14809465500 | G96: https://www.hilton.com/en/hotels/phxttqq-senna-house-hotel-scottsdale/?SEO_id=GMB-AMER-QQ-PHXTTQQ&y_source=1_Mjc3Mjk2MjQtNzE1LWxvY2F0aW9uLndlYnNpdGU%3D | I96: 40 | J96: 169 | K96: 0.5 | L96: 26 | P96: Epic | S96: BT | T96: Melissa Hall & Sam Kavathas | Z96: said theyve had same provider from launch and likes them
A97: The REMI Scottsdale, Autograph Collection | B97: Hotel | D97: 4415 N Buckboard Trail, Scottsdale, AZ 85251 | E97: Scottsdale | F97: 1 480-770-4415 | G97: https://www.marriott.com/en-us/hotels/phxda-the-remi-scottsdale-autograph-collection/overview/?scid=f2ae0541-1279-4f24-b197-a979c79310b0 | H97: None | I97: Valet Only | S97: BT | T97: Beth Brainard
A98: Caesars Republic Scottsdale, a Hilton Hotel | B98: Hotel | C98: x | D98: 4747 N Goldwater Blvd, Scottsdale, AZ 85251 | E98: Scottsdale | F98: (480) 903-4747 | G98: https://www.caesarsrepublicscottsdale.com/ | H98: 28 | I98: 40 | J98: 265 | K98: 0.23 | L98: 22 | T98: Ryan Kirby | U98: GM | V98: Ryan.kirby@hilton.com | Z98: emailed ryan and left vm
A99: DoubleTree Resort by Hilton Paradise Valley-Scottsdale | B99: Hotel | C99: x | D99: 5401 N Scottsdale Rd Scottsdale,Az 85250 | E99: Scottsdale | F99: 4809475400 | G99: https://www.hilton.com/en/hotels/phxsjdt-doubletree-resort-paradise-valley-scottsdale/?SEO_id=GMB-AMER-DT-PHXSJDT&y_source=1_MTM3Mjc3My03MTUtbG9jYXRpb24ud2Vic2l0ZQ%3D%3D | H99: Free | I99: 20 | J99: 378 | K99: 0.4 | L99: 75 | T99: Paul Hills | U99: GM | V99: paul.hills@hilton.com | Z99: emailed paul and left vm
A100: Home2 Suites by Hilton Scottsdale North | B100: Hotel | D100: 20001 N Scottsdale Rd, Scottsdale, AZ 85255 | E100: Scottsdale | F100: 14807411100 | G100: https://www.hilton.com/en/hotels/phxtsht-home2-suites-north-scottsdale-mayo-clinic/?SEO_id=GMB-AMER-HT-PHXTSHT&y_source=1_NDIyNTAwMzQtNzE1LWxvY2F0aW9uLndlYnNpdGU%3D | J100: 130 | K100: 0 | L100: 5
...

Sheet Analysis
A1: SOPHI's MARKET SCORE | B1: =G2 | C1: TAM | D1: SAM | E1: SOM | G1: Total | H1: Location | I1: Connections | J1: Garage | K1: Growth | L1: capacity | M1: cash flow | O1: Connection 3 | P1: Volume 2 170 + 2 100 + 1 | Q1: Location Downtown 1 Far -1 | R1: High End | S1: Garage Connection 2 location 1 | T1: Valet & Paid Self Park | U1: Points | V1: Priority
C2: =SUM(RevenueForecasting!H:H) | D2: =SUMIF(#REF!,1,RevenueForecasting!H2:H36) | E2: =D2/SUM(#REF!) | G2: =SUM(H2:L2)*2 & " /100" | H2: 7 | I2: 0 | J2: 8 | K2: 7
C3: sum of predicted revenues | D3: Guess of locations that I could see being interested in introducing valet | E3: SAM / # of locations in SAM. Representing 1 Hotel landed
C4: all valet, all parking contracts, additional services, bell etc | D4: realistically obtained | E4: going to get | H4: 257 miles | I4: locations? 0/7 | J4: public? 8/8 | K4: Population? 2/4 | L4: personal bandwidth 0/4 | M4: costs
H5: SB X | I5: 1 connection -> 5 2+ connections -> 7 | J5: yes or no | K5: small city, medium city, large city, metropolis
E6: Self Park | F6: Valet | H6: CH | I6: employees? 3 | J6: connection? 2 | K6: Events Space? 4 | L6: hire 0/3
A7: Average Self Park | B7: Average Valet | E7: Downtown | F7: Downtown | I7: # of possible employees | J7: yes or no | K7: # of markets
A8: =AVERAGE(Accounts!H:H) | B8: =AVERAGE(Accounts!I:I) | E8: =AVERAGEIF(Accounts!E:E,"Downtown",Accounts!H:H) | F8: =AVERAGEIF(Accounts!E:E,F7,Accounts!I:I) | H8: 0 -> 1000+ | K8: Parking? 2 | L8: management 0/3
H9: 3 -> 700 - 1000 | K9: reducing, steady, increasing
H10: 5 -> 500 - 700
H11: 7 -> 250 - 500
H12: 10 -> 0 - 250
G14: avg + reviews
G15: =AVERAGE(Accounts!K:K)
G17: avg + reviews downtown
G18: =AVERAGEIF(Accounts!E:E,"Downtown",Accounts!K:K)

Sheet Sales Candence
A1: =Accounts!A1 | B1: Contact Created? | C1: =Accounts!T1 | D1: Ideal method of contact | E1: GM Contact Info | F1: =Accounts!F1 | G1: =Accounts!O1 | H1: =Accounts!P1 | I1: =Accounts!H1 | J1: =Accounts!I1 | K1: =#REF! | L1: SALES NOTES | N1: 1. Linked In | O1: 2. Cold Call | P1: 3. In person visit | Q1: 4. First Email | R1: 5. Cold Call | S1: 6. Second follow up email (Cusom video email if top) | T1: 7. Cold Call | U1: 8. 2nd in person visit | V1: 9. Cold Call and leave a voicemail | W1: 10. video email - owner | X1: 11. 3rd email - temp check
A2: =Accounts!A2 | B2: FALSE | C2: =Accounts!T2 | E2: jack.miller@fairmont.com | F2: =Accounts!F2 | G2: =Accounts!O2 | H2: =Accounts!P2 | I2: =Accounts!H2 | J2: =Accounts!I2 | K2: =#REF! | L2: Wasn't able to connect to anyone worth the time, need to try and ping jack miller on indeed | N2: TRUE | O2: TRUE | P2: FALSE | Q2: TRUE | R2: FALSE | S2: FALSE | T2: FALSE | U2: FALSE | V2: FALSE | W2: FALSE
A3: =Accounts!A3 | B3: FALSE | C3: =Accounts!T3 | E3: connie.ogden@marriott.com | F3: =Accounts!F3 | G3: =Accounts!O3 | H3: =Accounts!P3 | I3: =Accounts!H3 | J3: =Accounts!I3 | K3: =#REF! | L3: Going to Connies vm paiges exec assistant- left a voicemail | N3: TRUE | O3: TRUE | P3: FALSE | Q3: TRUE | R3: FALSE | S3: FALSE | T3: FALSE | U3: FALSE | V3: FALSE | W3: FALSE
A4: =#REF! | B4: FALSE | C4: =#REF! | F4: =#REF! | G4: =#REF! | H4: =#REF! | I4: =#REF! | J4: =#REF! | K4: =#REF! | L4: Front desk stopped me and wouldn't push me to the voicemail, took a note down and explained to her all that we do so she could notorize it, left another message | N4: TRUE | O4: TRUE | P4: FALSE | Q4: TRUE | R4: FALSE | S4: FALSE | T4: FALSE | U4: FALSE | V4: FALSE | W4: FALSE
A5: =Accounts!A4 | B5: FALSE | C5: =Accounts!T4 | F5: =Accounts!F4 | G5: =Accounts!O4 | H5: =Accounts!P4 | I5: =Accounts!H4 | J5: =Accounts!I4 | K5: =#REF! | L5: Going to Marie vm Derek's exec assistant- left a voicemail | N5: TRUE | O5: TRUE | P5: FALSE | Q5: FALSE | R5: FALSE | S5: FALSE | T5: FALSE | U5: FALSE | V5: FALSE | W5: FALSE
A6: =Accounts!A5 | B6: FALSE | C6: =Accounts!T5 | F6: =Accounts!F5 | G6: =Accounts!O5 | H6: =Accounts!P5 | I6: free | J6: 25 | K6: =#REF! | L6: Left voicemail on Sally's voicemail | N6: TRUE | O6: TRUE | P6: FALSE | Q6: FALSE | R6: FALSE | S6: FALSE | T6: FALSE | U6: FALSE | V6: FALSE | W6: FALSE
A7: =Accounts!A6 | B7: FALSE | C7: =Accounts!T6 | F7: =Accounts!F6 | G7: =Accounts!O6 | H7: =Accounts!P6 | I7: =Accounts!H6 | J7: =Accounts!I6 | K7: =#REF! | L7: Left a voicemail on Donalei Smiths phone | N7: TRUE | O7: TRUE | P7: FALSE | Q7: FALSE | R7: FALSE | S7: FALSE | T7: FALSE | U7: FALSE | V7: FALSE | W7: FALSE
A8: =Accounts!A7 | B8: FALSE | C8: =Accounts!T7 | E8: Sue.tan@vacationclub.com | F8: =Accounts!F7 | G8: =Accounts!O7 | H8: =Accounts!P7 | I8: =Accounts!H7 | J8: =Accounts!I7 | L8: Got emails, Sue.tan@vacationclub.com, Lane.palma@vacationclub.com | N8: TRUE | O8: TRUE | P8: FALSE | Q8: FALSE | R8: FALSE | S8: FALSE | T8: FALSE | U8: FALSE | V8: FALSE | W8: FALSE
A9: =Accounts!A8 | B9: FALSE | C9: =Accounts!T8 | F9: =Accounts!F8 | G9: =Accounts!O8 | H9: =Accounts!P8 | I9: =Accounts!H8 | J9: =Accounts!I8 | K9: =#REF! | N9: FALSE | O9: FALSE | P9: FALSE | Q9: FALSE | R9: FALSE | S9: FALSE | T9: FALSE | U9: FALSE | V9: FALSE | W9: FALSE
A10: =Accounts!A9 | B10: FALSE | C10: =Accounts!T9 | F10: =Accounts!F9 | G10: =Accounts!O9 | H10: =Accounts!P9 | I10: =Accounts!H9 | J10: =Accounts!I9 | K10: =#REF! | N10: FALSE | O10: FALSE | P10: FALSE | Q10: FALSE | R10: FALSE | S10: FALSE | T10: FALSE | U10: FALSE | V10: FALSE | W10: FALSE
A11: =Accounts!A10 | B11: FALSE | C11: =#REF! | F11: =Accounts!F10 | G11: =Accounts!O10 | H11: =Accounts!P10 | I11: =Accounts!H10 | J11: =Accounts!I10 | K11: =#REF! | N11: FALSE | O11: FALSE | P11: FALSE | Q11: FALSE | R11: FALSE | S11: FALSE | T11: FALSE | U11: FALSE | V11: FALSE | W11: FALSE
A12: =Accounts!A11 | B12: FALSE | C12: =Accounts!T11 | F12: =Accounts!F11 | G12: =Accounts!O11 | H12: =Accounts!P11 | I12: =Accounts!H11 | J12: =Accounts!I11 | K12: =#REF! | N12: FALSE | O12: FALSE | P12: FALSE | Q12: FALSE | R12: FALSE | S12: FALSE | T12: FALSE | U12: FALSE | V12: FALSE | W12: FALSE
A13: =Accounts!A12 | B13: FALSE | C13: =Accounts!T12 | F13: =Accounts!F12 | G13: =Accounts!O12 | H13: =Accounts!P12 | I13: =Accounts!H12 | J13: =Accounts!I12 | K13: =#REF! | N13: FALSE | O13: FALSE | P13: FALSE | Q13: FALSE | R13: FALSE | S13: FALSE | T13: FALSE | U13: FALSE | V13: FALSE | W13: FALSE
A14: =Accounts!A13 | B14: FALSE | C14: =Accounts!T13 | F14: =Accounts!F13 | G14: =Accounts!O13 | H14: =Accounts!P13 | I14: =Accounts!H13 | J14: =Accounts!I13 | K14: =#REF! | N14: FALSE | O14: FALSE | P14: FALSE | Q14: FALSE | R14: FALSE | S14: FALSE | T14: FALSE | U14: FALSE | V14: FALSE | W14: FALSE
A15: =#REF! | B15: FALSE | C15: =#REF! | F15: =#REF! | G15: =#REF! | H15: =#REF! | I15: =#REF! | J15: =#REF! | K15: =#REF! | N15: FALSE | O15: FALSE | P15: FALSE | Q15: FALSE | R15: FALSE | S15: FALSE | T15: FALSE | U15: FALSE | V15: FALSE | W15: FALSE
A16: =Accounts!A14 | B16: FALSE | C16: =Accounts!T14 | F16: =Accounts!F14 | G16: =Accounts!O14 | H16: =Accounts!P14 | I16: =Accounts!H14 | J16: =Accounts!I14 | K16: =#REF! | L16: Left voicemail, POC is sexy | N16: TRUE | O16: FALSE | P16: FALSE | Q16: FALSE | R16: FALSE | S16: FALSE | T16: FALSE | U16: FALSE | V16: FALSE | W16: FALSE
A17: =Accounts!A15 | B17: FALSE | C17: =Accounts!T15 | F17: =Accounts!F15 | G17: =#REF! | H17: =Accounts!P15 | I17: =Accounts!H15 | J17: =Accounts!I15 | K17: =#REF! | N17: FALSE | O17: FALSE | P17: FALSE | Q17: FALSE | R17: FALSE | S17: FALSE | T17: FALSE | U17: FALSE | V17: FALSE | W17: FALSE
A18: =Accounts!A16 | B18: FALSE | C18: =Accounts!T16 | F18: =Accounts!F16 | G18: =Accounts!O16 | H18: =Accounts!P16 | I18: =Accounts!H16 | J18: =Accounts!I16 | K18: =#REF! | N18: FALSE | O18: FALSE | P18: FALSE | Q18: FALSE | R18: FALSE | S18: FALSE | T18: FALSE | U18: FALSE | V18: FALSE | W18: FALSE
A19: =Accounts!A17 | B19: FALSE | C19: =Accounts!T17 | F19: =Accounts!F17 | G19: =Accounts!O17 | H19: =Accounts!P17 | I19: =Accounts!H17 | J19: =Accounts!I17 | K19: =#REF! | N19: FALSE | O19: FALSE | P19: FALSE | Q19: FALSE | R19: FALSE | S19: FALSE | T19: FALSE | U19: FALSE | V19: FALSE | W19: FALSE
A20: =Accounts!A18 | B20: FALSE | C20: =Accounts!T18 | F20: =Accounts!F18 | G20: =Accounts!O18 | H20: =Accounts!P18 | I20: =Accounts!H18 | J20: =Accounts!I18 | K20: =#REF! | N20: FALSE | O20: FALSE | P20: FALSE | Q20: FALSE | R20: FALSE | S20: FALSE | T20: FALSE | U20: FALSE | V20: FALSE | W20: FALSE
A21: =Accounts!A19 | B21: FALSE | C21: =Accounts!T19 | E21: Brigitte.tueros@westin.com | F21: =Accounts!F19 | G21: =Accounts!O19 | H21: =Accounts!P19 | I21: =Accounts!H19 | J21: =Accounts!I19 | K21: =#REF! | L21: Not interested in valet but wanted to showcase sophi and sent to brigitte | N21: FALSE | O21: FALSE | P21: FALSE | Q21: FALSE | R21: FALSE | S21: FALSE | T21: FALSE | U21: FALSE | V21: FALSE | W21: FALSE
A22: =Accounts!A20 | B22: FALSE | C22: =Accounts!T20 | F22: =Accounts!F20 | G22: =Accounts!O20 | H22: =Accounts!P20 | I22: =Accounts!H20 | J22: =Accounts!I20 | K22: =#REF! | L22: Left voicemail for Adam, mutual connection with Linsday on linked inn. Called and they are happy with current service and I left my contact info | N22: TRUE | O22: TRUE | P22: FALSE | Q22: TRUE | R22: FALSE | S22: FALSE | T22: FALSE | U22: FALSE | V22: FALSE | W22: FALSE
A23: =Accounts!A21 | B23: FALSE | C23: =Accounts!T21 | E23: 4802144601-direct | F23: =Accounts!F21 | G23: =Accounts!O21 | H23: =Accounts!P21 | I23: =Accounts!H21 | J23: =Accounts!I21 | K23: =#REF! | L23: DOO-Amy.donovan@andaz.com Left a voicemail for carlos, will follow up with emails this week, left vm for carlos | N23: TRUE | O23: TRUE | P23: FALSE | Q23: TRUE | R23: FALSE | S23: FALSE | T23: FALSE | U23: FALSE | V23: FALSE | W23: FALSE
A24: =Accounts!A22 | B24: FALSE | C24: =Accounts!T22 | F24: =Accounts!F22 | G24: =Accounts!O22 | H24: =Accounts!P22 | I24: =Accounts!H22 | J24: =Accounts!I22 | K24: =#REF! | L24: Left a voicemail with Director of Rooms Leo Gianulis- Leo.gianulis@hyatt.com | N24: TRUE | O24: TRUE | P24: FALSE | Q24: FALSE | R24: FALSE | S24: FALSE | T24: FALSE | U24: FALSE | V24: FALSE | W24: FALSE
A25: =Accounts!A23 | B25: FALSE | C25: =Accounts!T23 | E25: Jeffrey.Herz@casinoaz.com | F25: =Accounts!F23 | G25: =Accounts!O23 | H25: =Accounts!P23 | I25: =Accounts!H23 | J25: =Accounts!I23 | K25: =#REF! | L25: Sent connect message on Linked Inn, Jeffrey is the contact for vendor partnerships | N25: TRUE | O25: TRUE | P25: FALSE | Q25: FALSE | R25: FALSE | S25: FALSE | T25: FALSE | U25: FALSE | V25: FALSE | W25: FALSE
A26: =Accounts!A24 | B26: FALSE | C26: =Accounts!T24 | F26: =Accounts!F24 | G26: =Accounts!O24 | H26: =Accounts!P24 | I26: =Accounts!H24 | J26: =Accounts!I24 | K26: =#REF! | L26: Connected with nicholas on linked in, messaged him, and left a voicemail | N26: TRUE | O26: FALSE | P26: FALSE | Q26: FALSE | R26: FALSE | S26: FALSE | T26: FALSE | U26: FALSE | V26: FALSE | W26: FALSE
A27: =Accounts!A25 | B27: FALSE | C27: =Accounts!T25 | F27: =Accounts!F25 | G27: =Accounts!O25 | H27: =Accounts!P25 | I27: =Accounts!H25 | J27: =Accounts!I25 | K27: =#REF! | N27: FALSE | O27: FALSE | P27: FALSE | Q27: FALSE | R27: FALSE | S27: FALSE | T27: FALSE | U27: FALSE | V27: FALSE | W27: FALSE
A28: =Accounts!A26 | B28: FALSE | C28: =Accounts!T26 | F28: =Accounts!F26 | G28: =Accounts!O26 | H28: =Accounts!P26 | I28: =Accounts!H26 | J28: =Accounts!I26 | K28: =#REF! | N28: FALSE | O28: FALSE | P28: FALSE | Q28: FALSE | R28: FALSE | S28: FALSE | T28: FALSE | U28: FALSE | V28: FALSE | W28: FALSE
A29: =Accounts!A27 | B29: FALSE | C29: =Accounts!T27 | F29: =Accounts!F27 | G29: =Accounts!O27 | H29: =Accounts!P27 | I29: =Accounts!H27 | J29: =Accounts!I27 | K29: =#REF! | N29: FALSE | O29: FALSE | P29: FALSE | Q29: FALSE | R29: FALSE | S29: FALSE | T29: FALSE | U29: FALSE | V29: FALSE | W29: FALSE
A30: =Accounts!A28 | B30: FALSE | C30: =Accounts!T28 | F30: =Accounts!F28 | G30: =Accounts!O28 | H30: =Accounts!P28 | I30: =Accounts!H28 | J30: =Accounts!I28 | K30: =#REF! | N30: FALSE | O30: FALSE | P30: FALSE | Q30: FALSE | R30: FALSE | S30: FALSE | T30: FALSE | U30: FALSE | V30: FALSE | W30: FALSE
A31: =Accounts!A29 | B31: FALSE | C31: =Accounts!T29 | F31: =Accounts!F29 | G31: =Accounts!O29 | H31: =Accounts!P29 | I31: =Accounts!H29 | J31: =Accounts!I29 | K31: =#REF! | N31: FALSE | O31: FALSE | P31: FALSE | Q31: FALSE | R31: FALSE | S31: FALSE | T31: FALSE | U31: FALSE | V31: FALSE | W31: FALSE
A32: =Accounts!A30 | B32: FALSE | C32: =Accounts!T30 | F32: =Accounts!F30 | G32: =Accounts!O30 | H32: =Accounts!P30 | I32: =Accounts!H30 | J32: =Accounts!I30 | K32: =#REF! | N32: FALSE | O32: FALSE | P32: FALSE | Q32: FALSE | R32: FALSE | S32: FALSE | T32: FALSE | U32: FALSE | V32: FALSE | W32: FALSE
A33: =Accounts!A31 | B33: FALSE | C33: =Accounts!T31 | F33: =Accounts!F31 | G33: =Accounts!O31 | H33: =Accounts!P31 | I33: =Accounts!H31 | J33: =Accounts!I31 | K33: =#REF! | N33: FALSE | O33: FALSE | P33: FALSE | Q33: FALSE | R33: FALSE | S33: FALSE | T33: FALSE | U33: FALSE | V33: FALSE | W33: FALSE
A34: =Accounts!A32 | B34: FALSE | C34: =Accounts!T32 | F34: =Accounts!F32 | G34: =Accounts!O32 | H34: =Accounts!P32 | I34: =Accounts!H32 | J34: =Accounts!I32 | K34: =#REF! | N34: FALSE | O34: FALSE | P34: FALSE | Q34: FALSE | R34: FALSE | S34: FALSE | T34: FALSE | U34: FALSE | V34: FALSE | W34: FALSE
A35: =Accounts!A33 | B35: FALSE | C35: =Accounts!T33 | F35: =Accounts!F33 | G35: =Accounts!O33 | H35: =Accounts!P33 | I35: =Accounts!H33 | J35: =Accounts!I33 | K35: =#REF! | N35: FALSE | O35: FALSE | P35: FALSE | Q35: FALSE | R35: FALSE | S35: FALSE | T35: FALSE | U35: FALSE | V35: FALSE | W35: FALSE
A36: =Accounts!A34 | B36: FALSE | C36: =Accounts!T34 | F36: =Accounts!F34 | G36: =Accounts!O34 | H36: =Accounts!P34 | I36: =Accounts!H34 | J36: =Accounts!I34 | K36: =#REF! | N36: FALSE | O36: FALSE | P36: FALSE | Q36: FALSE | R36: FALSE | S36: FALSE | T36: FALSE | U36: FALSE | V36: FALSE | W36: FALSE
A37: =Accounts!A35 | B37: FALSE | C37: =Accounts!T35 | F37: =Accounts!F35 | G37: =Accounts!O35 | H37: =Accounts!P35 | I37: =Accounts!H35 | J37: =Accounts!I35 | K37: =#REF! | L37: Left a voicemail for rebecca, reviews seem okay, they might be inhouse it seems if they are only charging $15 | N37: FALSE | O37: FALSE | P37: FALSE | Q37: FALSE | R37: FALSE | S37: FALSE | T37: FALSE | U37: FALSE | V37: FALSE | W37: FALSE
A38: =Accounts!A36 | B38: FALSE | C38: =Accounts!T36 | E38: Katy Powers | F38: =Accounts!F36 | G38: =Accounts!O36 | H38: =Accounts!P36 | I38: =Accounts!H36 | J38: =Accounts!I36 | K38: =#REF! | L38: Left voicemail for Katy | N38: TRUE | O38: TRUE | P38: FALSE | Q38: FALSE | R38: FALSE | S38: FALSE | T38: FALSE | U38: FALSE | V38: FALSE | W38: FALSE
A39: =Accounts!A37 | B39: FALSE | C39: =Accounts!T37 | E39: teri.owens@atriumhotels.com | F39: =Accounts!F37 | G39: =Accounts!O37 | H39: =Accounts!P37 | I39: =Accounts!H37 | J39: =Accounts!I37 | K39: =#REF! | L39: Actually talked to the GM Teri, said things are going well! Emailing her my contact incase | N39: TRUE | O39: TRUE | P39: FALSE | Q39: TRUE | R39: FALSE | S39: FALSE | T39: FALSE | U39: FALSE | V39: FALSE | W39: FALSE
A40: =Accounts!A38 | B40: FALSE | C40: =Accounts!T38 | F40: =Accounts!F38 | G40: =Accounts!O38 | H40: =Accounts!P38 | I40: =Accounts!H38 | J40: =Accounts!I38 | K40: =#REF! | N40: FALSE | O40: FALSE | P40: FALSE | Q40: FALSE | R40: FALSE | S40: FALSE | T40: FALSE | U40: FALSE | V40: FALSE | W40: FALSE
A41: =Accounts!A39 | B41: FALSE | C41: =Accounts!T39 | F41: =#REF! | G41: =Accounts!O39 | H41: =Accounts!P39 | I41: =#REF! | J41: =#REF! | K41: =#REF! | N41: FALSE | O41: FALSE | P41: FALSE | Q41: FALSE | R41: FALSE | S41: FALSE | T41: FALSE | U41: FALSE | V41: FALSE | W41: FALSE
A42: =Accounts!A40 | B42: FALSE | C42: =Accounts!T40 | F42: =Accounts!F39 | G42: =Accounts!O40 | H42: =Accounts!P40 | I42: =Accounts!H39 | J42: =Accounts!I39 | K42: =#REF! | N42: FALSE | O42: FALSE | P42: FALSE | Q42: FALSE | R42: FALSE | S42: FALSE | T42: FALSE | U42: FALSE | V42: FALSE | W42: FALSE
A43: =Accounts!A41 | B43: FALSE | C43: =Accounts!T41 | F43: =Accounts!F40 | G43: =Accounts!O41 | H43: =Accounts!P41 | I43: =Accounts!H40 | J43: =Accounts!I40 | K43: =#REF! | N43: FALSE | O43: FALSE | P43: FALSE | Q43: FALSE | R43: FALSE | S43: FALSE | T43: FALSE | U43: FALSE | V43: FALSE | W43: FALSE
A44: =Accounts!A42 | B44: FALSE | C44: =Accounts!T42 | E44: Rueben FOM | F44: =Accounts!F41 | G44: =#REF! | H44: =#REF! | I44: =Accounts!H41 | J44: =Accounts!I41 | K44: =#REF! | N44: TRUE | O44: FALSE | P44: FALSE | Q44: FALSE | R44: FALSE | S44: FALSE | T44: FALSE | U44: FALSE | V44: FALSE | W44: FALSE
A45: =Accounts!A43 | B45: FALSE | C45: =Accounts!T43 | F45: =Accounts!F42 | G45: =Accounts!O42 | H45: =Accounts!P42 | I45: =Accounts!H42 | J45: =Accounts!I42 | K45: =#REF! | N45: FALSE | O45: FALSE | P45: FALSE | Q45: FALSE | R45: FALSE | S45: FALSE | T45: FALSE | U45: FALSE | V45: FALSE | W45: FALSE
A46: =Accounts!A44 | B46: FALSE | C46: Kelly Sterling | E46: Kelly Gm assistant, kelly.osterling@renhotels.com | F46: =Accounts!F43 | G46: =Accounts!O43 | H46: =Accounts!P43 | I46: =Accounts!H43 | J46: =Accounts!I43 | K46: =#REF! | L46: Got informatio from the hotel front desk, currently doesn't have a shuttle service and feels like its lacking from that front, emailed kelly video and intro deck | N46: TRUE | O46: TRUE | P46: TRUE | Q46: TRUE | R46: TRUE | S46: TRUE | T46: FALSE | U46: FALSE | V46: FALSE | W46: FALSE
A47: =Accounts!A45 | B47: TRUE | C47: Carlos Zavala | F47: =Accounts!F44 | G47: =Accounts!O44 | H47: =Accounts!P44 | I47: =Accounts!H44 | J47: =Accounts!I44 | K47: =#REF! | L47: Talked with Carlos, they were in the talks with adding valet services. Sent him an email in hopes to connect soon. Will follow up Friday. | N47: TRUE | O47: TRUE | P47: TRUE | Q47: FALSE | R47: FALSE | S47: FALSE | T47: FALSE | U47: FALSE | V47: FALSE | W47: FALSE
A48: =Accounts!A46 | B48: FALSE | C48: =Accounts!T46 | F48: =Accounts!F45 | G48: =Accounts!O45 | H48: =Accounts!P45 | I48: =Accounts!H44 | J48: =Accounts!I44 | K48: =#REF! | L48: Tried to call and waited 15 min, moving on will call again next time | N48: TRUE | O48: TRUE | P48: TRUE | Q48: TRUE | R48: TRUE | S48: TRUE | T48: FALSE | U48: FALSE | V48: FALSE | W48: FALSE
A49: =Accounts!A47 | B49: FALSE | C49: Erin Bicaki | F49: =#REF! | G49: =#REF! | H49: =#REF! | I49: =#REF! | J49: =#REF! | K49: =#REF! | L49: Left a voicemail, reviews are unfavorable Erin is confirmed still the GM | N49: TRUE | O49: TRUE | P49: FALSE | Q49: FALSE | R49: FALSE | S49: FALSE | T49: FALSE | U49: FALSE | V49: FALSE | W49: FALSE
A50: =Accounts!A48 | B50: FALSE | C50: Trent Collicott | F50: =#REF! | G50: =#REF! | H50: =#REF! | I50: =#REF! | J50: =#REF! | K50: =#REF! | L50: Left a voicemail, Parking reviews are VERY unfavorable Trent is confirmed still the GM | N50: TRUE | O50: TRUE | P50: FALSE | Q50: FALSE | R50: FALSE | S50: FALSE | T50: FALSE | U50: FALSE | V50: FALSE | W50: FALSE
A51: =Accounts!A49 | B51: TRUE | C51: Kevin Shipman | F51: =Accounts!F46 | G51: =Accounts!O46 | H51: =Accounts!P46 | I51: =Accounts!H46 | J51: =Accounts!I46 | K51: =#REF! | L51: Kshipman@ih-corp.com | N51: FALSE | O51: TRUE | P51: FALSE | Q51: FALSE | R51: FALSE | S51: FALSE | T51: FALSE | U51: FALSE | V51: FALSE | W51: FALSE
A52: =Accounts!A50 | B52: FALSE | C52: Collin Walls | F52: =Accounts!F47 | G52: =Accounts!O47 | H52: =Accounts!P47 | I52: =Accounts!H47 | J52: =Accounts!I47 | K52: =#REF! | L52: Left message with collin walls | N52: TRUE | O52: TRUE | P52: FALSE | Q52: FALSE | R52: FALSE | S52: FALSE | T52: FALSE | U52: FALSE | V52: FALSE | W52: FALSE
A53: =Accounts!A51 | B53: FALSE | C53: =Accounts!T51 | F53: =Accounts!F48 | G53: =Accounts!O48 | H53: =Accounts!P48 | I53: =Accounts!H48 | J53: =Accounts!I48 | K53: =#REF! | L53: Left detailed voicemail | N53: TRUE | O53: TRUE | P53: FALSE | Q53: TRUE | R53: FALSE | S53: FALSE | T53: FALSE | U53: FALSE | V53: FALSE | W53: FALSE
A54: =Accounts!A52 | B54: TRUE | C54: =Accounts!T52 | F54: =Accounts!F49 | G54: =Accounts!O49 | H54: =Accounts!P49 | I54: =Accounts!H49 | J54: =Accounts!I49 | K54: =#REF! | N54: TRUE | O54: FALSE | P54: TRUE | Q54: TRUE | R54: FALSE | S54: FALSE | T54: FALSE | U54: FALSE | V54: FALSE | W54: FALSE
A55: =Accounts!A53 | B55: TRUE | C55: =Accounts!T53 | F55: =Accounts!F50 | G55: =Accounts!O50 | H55: =Accounts!P50 | I55: =Accounts!H50 | J55: =Accounts!I50 | K55: =#REF! | N55: TRUE | O55: FALSE | P55: FALSE | Q55: FALSE | R55: FALSE | S55: FALSE | T55: FALSE | U55: FALSE | V55: FALSE | W55: FALSE
A56: =Accounts!A54 | B56: FALSE | C56: =Accounts!T54 | F56: =Accounts!F51 | G56: =Accounts!O51 | H56: =Accounts!P51 | I56: =Accounts!H51 | J56: =Accounts!I51 | K56: =#REF! | L56: Called and left a voicemail | N56: FALSE | O56: TRUE | P56: TRUE | Q56: FALSE | R56: FALSE | S56: FALSE | T56: FALSE | U56: FALSE | V56: FALSE | W56: FALSE
A57: =Accounts!A55 | B57: FALSE | C57: =Accounts!T55 | F57: =Accounts!F52 | G57: =Accounts!O52 | H57: =Accounts!P52 | I57: =Accounts!H52 | J57: =Accounts!I52 | K57: =#REF! | N57: FALSE | O57: FALSE | P57: FALSE | Q57: FALSE | R57: FALSE | S57: FALSE | T57: FALSE | U57: FALSE | V57: FALSE | W57: FALSE
A58: =Accounts!A56 | B58: FALSE | C58: =Accounts!T56 | F58: =Accounts!F53 | G58: =Accounts!O53 | H58: =Accounts!P53 | I58: =Accounts!H53 | J58: =Accounts!I53 | K58: =#REF! | N58: FALSE | O58: FALSE | P58: FALSE | Q58: FALSE | R58: FALSE | S58: FALSE | T58: FALSE | U58: FALSE | V58: FALSE | W58: FALSE
A59: =Accounts!A57 | B59: FALSE | C59: =Accounts!T57 | F59: =Accounts!F54 | G59: =Accounts!O54 | H59: =Accounts!P54 | I59: =Accounts!H54 | J59: =Accounts!I54 | K59: =#REF! | L59: Told me to call back in a couple of hours | N59: FALSE | O59: TRUE | P59: FALSE | Q59: FALSE | R59: FALSE | S59: FALSE | T59: FALSE | U59: FALSE | V59: FALSE | W59: FALSE
A60: =Accounts!A58 | B60: FALSE | C60: Ursula Vanderwest | F60: =Accounts!F55 | G60: =Accounts!O55 | H60: =Accounts!P55 | I60: =Accounts!H55 | J60: =Accounts!I55 | K60: =#REF! | L60: Ursula.vanderwest@marriott.com Bethany gave me contact, they currently dont have a general manager sent an email | N60: FALSE | O60: FALSE | P60: FALSE | Q60: FALSE | R60: FALSE | S60: FALSE | T60: FALSE | U60: FALSE | V60: FALSE | W60: FALSE
A61: =Accounts!A59 | B61: FALSE | C61: =Accounts!T59 | F61: =Accounts!F56 | G61: =Accounts!O56 | H61: =Accounts!P56 | I61: =Accounts!H56 | J61: =Accounts!I56 | K61: =#REF! | N61: FALSE | O61: FALSE | P61: FALSE | Q61: FALSE | R61: FALSE | S61: FALSE | T61: FALSE | U61: FALSE | V61: FALSE | W61: FALSE
A62: =Accounts!A60 | B62: FALSE | C62: =Accounts!T60 | F62: =Accounts!F57 | G62: =Accounts!O57 | H62: =Accounts!P57 | I62: =Accounts!H57 | J62: =Accounts!I57 | K62: =#REF! | N62: FALSE | O62: FALSE | P62: FALSE | Q62: FALSE | R62: FALSE | S62: FALSE | T62: FALSE | U62: FALSE | V62: FALSE | W62: FALSE
A63: =Accounts!A61 | B63: FALSE | C63: =Accounts!T61 | F63: =Accounts!F58 | G63: =Accounts!O58 | H63: =Accounts!P58 | I63: =Accounts!H58 | J63: =Accounts!I58 | K63: =#REF! | N63: FALSE | O63: FALSE | P63: FALSE | Q63: FALSE | R63: FALSE | S63: FALSE | T63: FALSE | U63: FALSE | V63: FALSE | W63: FALSE
A64: =Accounts!A62 | B64: FALSE | C64: =Accounts!T62 | F64: =Accounts!F59 | G64: =Accounts!O59 | H64: =Accounts!P59 | I64: =Accounts!H59 | J64: =Accounts!I59 | K64: =#REF! | N64: FALSE | O64: FALSE | P64: FALSE | Q64: FALSE | R64: FALSE | S64: FALSE | T64: FALSE | U64: FALSE | V64: FALSE | W64: FALSE
A65: =Accounts!A63 | B65: FALSE | C65: =Accounts!T63 | F65: =Accounts!F60 | G65: =Accounts!O60 | H65: =Accounts!P60 | I65: =Accounts!H60 | J65: =Accounts!I60 | K65: =#REF! | N65: FALSE | O65: FALSE | P65: FALSE | Q65: FALSE | R65: FALSE | S65: FALSE | T65: FALSE | U65: FALSE | V65: FALSE | W65: FALSE
A66: =Accounts!A64 | B66: FALSE | C66: =Accounts!T64 | F66: =Accounts!F61 | G66: =Accounts!O61 | H66: =Accounts!P61 | I66: =Accounts!H61 | J66: =Accounts!I61 | K66: =#REF! | N66: FALSE | O66: FALSE | P66: FALSE | Q66: FALSE | R66: FALSE | S66: FALSE | T66: FALSE | U66: FALSE | V66: FALSE | W66: FALSE
A67: =Accounts!A65 | B67: FALSE | C67: =Accounts!T65 | F67: =Accounts!F62 | G67: =Accounts!O62 | H67: =Accounts!P62 | I67: =Accounts!H62 | J67: =Accounts!I62 | K67: =#REF! | N67: FALSE | O67: FALSE | P67: FALSE | Q67: FALSE | R67: FALSE | S67: FALSE | T67: FALSE | U67: FALSE | V67: FALSE | W67: FALSE
A68: =#REF! | B68: FALSE | C68: =#REF! | F68: =Accounts!F63 | G68: =Accounts!O63 | H68: =Accounts!P63 | I68: =Accounts!H63 | J68: =Accounts!I63 | K68: =#REF! | N68: FALSE | O68: FALSE | P68: FALSE | Q68: FALSE | R68: FALSE | S68: FALSE | T68: FALSE | U68: FALSE | V68: FALSE | W68: FALSE
A69: =Accounts!A66 | B69: FALSE | C69: =Accounts!T66 | F69: =Accounts!F64 | G69: =Accounts!O64 | H69: =Accounts!P64 | I69: =Accounts!H64 | J69: =Accounts!I64 | K69: =#REF! | N69: FALSE | O69: FALSE | P69: FALSE | Q69: FALSE | R69: FALSE | S69: FALSE | T69: FALSE | U69: FALSE | V69: FALSE | W69: FALSE
A70: =Accounts!A67 | B70: FALSE | C70: =Accounts!T67 | F70: =Accounts!F65 | G70: =Accounts!O65 | H70: =Accounts!P65 | I70: =Accounts!H65 | J70: =Accounts!I65 | K70: =#REF! | N70: FALSE | O70: FALSE | P70: FALSE | Q70: FALSE | R70: FALSE | S70: FALSE | T70: FALSE | U70: FALSE | V70: FALSE | W70: FALSE
A71: =Accounts!A68 | B71: FALSE | C71: =Accounts!T68 | F71: =#REF! | G71: =#REF! | H71: =#REF! | I71: =#REF! | J71: =#REF! | K71: =#REF! | N71: FALSE | O71: FALSE | P71: FALSE | Q71: FALSE | R71: FALSE | S71: FALSE | T71: FALSE | U71: FALSE | V71: FALSE | W71: FALSE
A72: =Accounts!A69 | B72: FALSE | C72: =Accounts!T69 | F72: =Accounts!F66 | G72: =Accounts!O66 | H72: =Accounts!P66 | I72: =Accounts!H66 | J72: =Accounts!I66 | K72: =#REF! | N72: FALSE | O72: FALSE | P72: FALSE | Q72: FALSE | R72: FALSE | S72: FALSE | T72: FALSE | U72: FALSE | V72: FALSE | W72: FALSE
A73: =Accounts!A70 | B73: FALSE | C73: =Accounts!T70 | F73: =Accounts!F67 | G73: =Accounts!O67 | H73: =Accounts!P67 | I73: =Accounts!H67 | J73: =Accounts!I67 | K73: =#REF! | N73: FALSE | O73: FALSE | P73: FALSE | Q73: FALSE | R73: FALSE | S73: FALSE | T73: FALSE | U73: FALSE | V73: FALSE | W73: FALSE
A74: =Accounts!A71 | B74: FALSE | C74: =Accounts!T71 | F74: =Accounts!F68 | G74: =Accounts!O68 | H74: =Accounts!P68 | I74: =Accounts!H68 | J74: =Accounts!I68 | K74: =#REF! | N74: FALSE | O74: FALSE | P74: FALSE | Q74: FALSE | R74: FALSE | S74: FALSE | T74: FALSE | U74: FALSE | V74: FALSE | W74: FALSE
A75: =Accounts!A72 | B75: FALSE | C75: Travis Linquist | F75: =Accounts!F69 | G75: =Accounts!O69 | H75: =Accounts!P69 | I75: =Accounts!H69 | J75: =Accounts!I69 | K75: =#REF! | L75: Left Travis a voicemail | N75: FALSE | O75: FALSE | P75: FALSE | Q75: FALSE | R75: FALSE | S75: FALSE | T75: FALSE | U75: FALSE | V75: FALSE | W75: FALSE
A76: =Accounts!A73 | B76: FALSE | C76: =Accounts!T73 | F76: =Accounts!F70 | G76: =Accounts!O70 | H76: =Accounts!P70 | I76: =Accounts!H70 | J76: =Accounts!I70 | K76: =#REF! | N76: FALSE | O76: FALSE | P76: FALSE | Q76: FALSE | R76: FALSE | S76: FALSE | T76: FALSE | U76: FALSE | V76: FALSE | W76: FALSE
A77: =Accounts!A74 | B77: FALSE | C77: =Accounts!T74 | F77: =Accounts!F71 | G77: =Accounts!O71 | H77: =Accounts!P71 | I77: =Accounts!H71 | J77: =Accounts!I71 | K77: =#REF! | N77: FALSE | O77: FALSE | P77: FALSE | Q77: FALSE | R77: FALSE | S77: FALSE | T77: FALSE | U77: FALSE | V77: FALSE | W77: FALSE
A78: =Accounts!A75 | B78: TRUE | C78: =Accounts!T75 | F78: =Accounts!F72 | G78: =Accounts!O72 | H78: =Accounts!P72 | I78: =Accounts!H72 | J78: =Accounts!I72 | K78: =#REF! | L78: Briana is new GM, guessed her email | N78: TRUE | O78: TRUE | P78: TRUE | Q78: TRUE | R78: TRUE | S78: TRUE | T78: TRUE | U78: FALSE | V78: FALSE | W78: FALSE
A79: =Accounts!A76 | B79: FALSE | C79: =Accounts!T76 | F79: =Accounts!F73 | G79: =Accounts!O73 | H79: =Accounts!P73 | I79: =Accounts!H73 | J79: =Accounts!I73 | K79: =#REF! | N79: FALSE | O79: FALSE | P79: FALSE | Q79: FALSE | R79: FALSE | S79: FALSE | T79: FALSE | U79: FALSE | V79: FALSE | W79: FALSE
A80: =Accounts!A77 | B80: TRUE | C80: =Accounts!T77 | F80: =Accounts!F74 | G80: =Accounts!O74 | H80: =Accounts!P74 | I80: =Accounts!H74 | J80: =Accounts!I74 | K80: =#REF! | N80: TRUE | O80: FALSE | P80: TRUE | Q80: TRUE | R80: FALSE | S80: FALSE | T80: FALSE | U80: FALSE | V80: FALSE | W80: FALSE
A81: =Accounts!A78 | B81: FALSE | C81: =Accounts!T78 | F81: =Accounts!F75 | G81: =Accounts!O75 | H81: =Accounts!P75 | I81: =Accounts!H75 | J81: =Accounts!I75 | K81: =#REF! | N81: FALSE | O81: FALSE | P81: FALSE | Q81: FALSE | R81: FALSE | S81: FALSE | T81: FALSE | U81: FALSE | V81: FALSE | W81: FALSE
A82: =Accounts!A79 | B82: FALSE | C82: =Accounts!T79 | F82: =Accounts!F76 | G82: =Accounts!O76 | H82: =Accounts!P76 | I82: =Accounts!H76 | J82: =Accounts!I76 | K82: =#REF! | N82: FALSE | O82: FALSE | P82: FALSE | Q82: FALSE | R82: FALSE | S82: FALSE | T82: FALSE | U82: FALSE | V82: FALSE | W82: FALSE
A83: =Accounts!A80 | B83: FALSE | C83: =Accounts!T80 | F83: =Accounts!F77 | G83: =Accounts!O77 | H83: =Accounts!P77 | I83: =Accounts!H77 | J83: =Accounts!I77 | K83: =#REF! | N83: FALSE | O83: FALSE | P83: FALSE | Q83: FALSE | R83: FALSE | S83: FALSE | T83: FALSE | U83: FALSE | V83: FALSE | W83: FALSE
A84: =Accounts!A81 | B84: TRUE | C84: =Accounts!T81 | F84: =Accounts!F78 | G84: =Accounts!O78 | H84: =Accounts!P78 | I84: =Accounts!H78 | J84: =Accounts!I78 | K84: =#REF! | L84: service seemed really bad but she wasnt interested in connecting us with anyone to implement a change from inhouse | N84: TRUE | O84: FALSE | P84: TRUE | Q84: FALSE | R84: FALSE | S84: FALSE | T84: FALSE | U84: FALSE | V84: FALSE | W84: FALSE
A85: =Accounts!A82 | B85: TRUE | C85: =Accounts!T82 | F85: =Accounts!F79 | G85: =Accounts!O79 | H85: =Accounts!P79 | I85: =Accounts!H79 | J85: =Accounts!I79 | K85: =#REF! | N85: TRUE | O85: FALSE | P85: TRUE | Q85: TRUE | R85: TRUE | S85: TRUE | T85: FALSE | U85: FALSE | V85: FALSE | W85: FALSE
A86: =Accounts!A83 | B86: TRUE | C86: =Accounts!T83 | F86: =Accounts!F80 | G86: =Accounts!O80 | H86: =Accounts!P80 | I86: =Accounts!H80 | J86: =Accounts!I80 | K86: =#REF! | N86: TRUE | O86: FALSE | P86: TRUE | Q86: TRUE | R86: TRUE | S86: TRUE | T86: FALSE | U86: FALSE | V86: FALSE | W86: FALSE
A87: =Accounts!A84 | B87: FALSE | C87: =Accounts!T84 | F87: =Accounts!F81 | G87: =Accounts!O81 | H87: =Accounts!P81 | I87: =Accounts!H81 | J87: =Accounts!I81 | K87: =#REF! | N87: FALSE | O87: FALSE | P87: FALSE | Q87: FALSE | R87: FALSE | S87: FALSE | T87: FALSE | U87: FALSE | V87: FALSE | W87: FALSE
A88: =Accounts!A85 | B88: TRUE | C88: =Accounts!T85 | F88: =Accounts!F82 | G88: =Accounts!O82 | H88: =Accounts!P82 | I88: =Accounts!H82 | J88: =Accounts!I82 | K88: =#REF! | N88: FALSE | O88: FALSE | P88: TRUE | Q88: FALSE | R88: FALSE | S88: FALSE | T88: FALSE | U88: FALSE | V88: FALSE | W88: FALSE
A89: =#REF! | B89: FALSE | C89: =#REF! | F89: =Accounts!F83 | G89: =Accounts!O83 | H89: =Accounts!P83 | I89: =Accounts!H83 | J89: =Accounts!I83 | K89: =#REF! | N89: FALSE | O89: FALSE | P89: FALSE | Q89: FALSE | R89: FALSE | S89: FALSE | T89: FALSE | U89: FALSE | V89: FALSE | W89: FALSE
A90: =Accounts!A86 | B90: FALSE | C90: =Accounts!T86 | F90: =Accounts!F84 | G90: =Accounts!O84 | H90: =Accounts!P84 | I90: =Accounts!H84 | J90: =Accounts!I84 | K90: =#REF! | N90: FALSE | O90: FALSE | P90: FALSE | Q90: FALSE | R90: FALSE | S90: FALSE | T90: FALSE | U90: FALSE | V90: FALSE | W90: FALSE
A91: =Accounts!A87 | B91: TRUE | C91: =Accounts!T87 | F91: =Accounts!F85 | G91: =Accounts!O85 | H91: =Accounts!P85 | I91: =Accounts!H85 | J91: =Accounts!I85 | K91: =#REF! | N91: TRUE | O91: FALSE | P91: TRUE | Q91: TRUE | R91: TRUE | S91: TRUE | T91: FALSE | U91: FALSE | V91: FALSE | W91: FALSE
A92: =Accounts!A88 | B92: FALSE | C92: =Accounts!T88 | F92: =#REF! | G92: =#REF! | H92: =#REF! | I92: =#REF! | J92: =#REF! | K92: =#REF! | N92: FALSE | O92: FALSE | P92: FALSE | Q92: FALSE | R92: FALSE | S92: FALSE | T92: FALSE | U92: FALSE | V92: FALSE | W92: FALSE
A93: =Accounts!A89 | B93: FALSE | C93: =Accounts!T89 | F93: =Accounts!F86 | G93: =Accounts!O86 | H93: =Accounts!P86 | I93: =Accounts!H86 | J93: =Accounts!I86 | K93: =#REF! | N93: FALSE | O93: FALSE | P93: FALSE | Q93: FALSE | R93: FALSE | S93: FALSE | T93: FALSE | U93: FALSE | V93: FALSE | W93: FALSE
A94: =Accounts!A90 | B94: FALSE | C94: =Accounts!T90 | F94: =Accounts!F87 | G94: =Accounts!O87 | H94: =Accounts!P87 | I94: =Accounts!H87 | J94: =Accounts!I87 | K94: =#REF! | N94: TRUE | O94: TRUE | P94: FALSE | Q94: FALSE | R94: FALSE | S94: FALSE | T94: FALSE | U94: FALSE | V94: FALSE | W94: FALSE
A95: =Accounts!A91 | B95: FALSE | C95: =Accounts!T91 | F95: =Accounts!F88 | G95: =Accounts!O88 | H95: =Accounts!P88 | I95: =Accounts!H88 | J95: =Accounts!I88 | K95: =#REF! | N95: FALSE | O95: FALSE | P95: FALSE | Q95: FALSE | R95: FALSE | S95: FALSE | T95: FALSE | U95: FALSE | V95: FALSE | W95: FALSE
A96: =Accounts!A92 | B96: FALSE | C96: =Accounts!T92 | F96: =Accounts!F89 | G96: =Accounts!O89 | H96: =Accounts!P89 | I96: =Accounts!H89 | J96: =Accounts!I89 | K96: =#REF! | N96: FALSE | O96: FALSE | P96: FALSE | Q96: FALSE | R96: FALSE | S96: FALSE | T96: FALSE | U96: FALSE | V96: FALSE | W96: FALSE
A97: =Accounts!A93 | B97: FALSE | C97: =Accounts!T93 | F97: =Accounts!F90 | G97: =Accounts!O90 | H97: =Accounts!P90 | I97: =Accounts!H90 | J97: =Accounts!I90 | K97: =#REF! | N97: FALSE | O97: FALSE | P97: FALSE | Q97: FALSE | R97: FALSE | S97: FALSE | T97: FALSE | U97: FALSE | V97: FALSE | W97: FALSE
A98: =Accounts!A94 | B98: FALSE | C98: =Accounts!T94 | F98: =Accounts!F91 | G98: =Accounts!O91 | H98: =Accounts!P91 | I98: =Accounts!H91 | J98: =Accounts!I91 | K98: =#REF! | N98: FALSE | O98: FALSE | P98: FALSE | Q98: FALSE | R98: FALSE | S98: FALSE | T98: FALSE | U98: FALSE | V98: FALSE | W98: FALSE
A99: =#REF! | B99: FALSE | C99: =Accounts!T92 | F99: =Accounts!F92 | G99: =Accounts!O92 | H99: =Accounts!P92 | I99: =Accounts!H92 | J99: =Accounts!I92 | K99: =#REF! | N99: FALSE | O99: FALSE | P99: FALSE | Q99: FALSE | R99: FALSE | S99: FALSE | T99: FALSE | U99: FALSE | V99: FALSE | W99: FALSE
A100: =Accounts!A95 | B100: FALSE | C100: =Accounts!T93 | F100: =Accounts!F93 | G100: =Accounts!O93 | H100: =Accounts!P93 | I100: =Accounts!H93 | J100: =Accounts!I93 | K100: =#REF! | N100: FALSE | O100: FALSE | P100: FALSE | Q100: FALSE | R100: FALSE | S100: FALSE | T100: FALSE | U100: FALSE | V100: FALSE | W100: FALSE
...

Sheet Parking
A1: Loaction ID | B1: Location Name | C1: Location Type | D1: Location Area | E1: Address | F1: # Spaces | G1: Hourly Rate | H1: Unreserved Monthly Rate | I1: Operator | J1: Point of Contact | K1: POC Number | L1: URL | M1: Notes | N1: PARCs Equipment Notes | O1: Account Associated
A2: 1 | B2: Novus Place Structure | C2: Garage | D2: Tempe | E2: 747 S Packard Dr, Tempe, AZ 85281 | F2: 1801 | G2: 4 | I2: ASU | O2: North Italia & Blanco in Tempe
A3: 2 | B3: Chase Centerpoint Facility | C3: Garage | D3: Tempe | E3: 725 Ash Ave, Tempe, AZ 85281 | F3: 750 | G3: 6 | H3: NA | I3: SP+ | J3: Monthly Parking Specialists | K3: (602)-802-5487 | L3: https://parking.com/national/parking-near/33.42302890000001/-111.9418086/725-s-ash-ave?lot_id=20719&showListOnly=1&view=daily&facility&valet&general=&displayFullCity=0&start=2026-02-24T11%3A00&stop=2026-02-24T13%3A00&sw=33.42082970431528,-111.94714598144415&ne=33.42560564999984,-111.93767239855623 | O3: Flithy Animal or Other Mill Ave
A4: 3 | B4: Hayden Ferry Lakeside | C4: Garage | D4: Tempe | E4: 68 E Rio Salado Pkwy, Tempe, AZ 85281 | F4: 2704 | G4: 3 | O4: Roman (Pre Open)
A5: 4 | B5: CityScape West | C5: Garage | D5: Downtown | E5: 1 E Washington St Phoenix, AZ 85004 | G5: 5 | I5: Ace | L5: https://www.reddevelopment.com/cityscape/directory/ | M5: Garage has valet | O5: Rosso Italian, Arrogant Butcher
A6: 5 | B6: City of Phoenix Plaza Garage | C6: Garage | D6: Downtown | E6: 100 W Washington St Phoenix, AZ 85003 | F6: 1405 | G6: 4 | I6: Ace
A7: 6 | B7: Chase Tower Garage | C7: Garage | D7: Downtown | E7: 201 N 1st St Phoenix, AZ 85004 | F7: 1950 | G7: 5 | I7: Ace
A8: 7 | B8: 21 W Van Buren St | C8: Garage | D8: Downtown | E8: 21 W Van Buren St Phoenix, AZ 85004 | F8: 461 | G8: 4 | I8: LAZ
A9: 8 | B9: Ten-0-One | C9: Garage | D9: Downtown | E9: 1001 N Central Ave Phoenix, AZ 85004 | F9: 350 | I9: Ace ( I think) | O9: Palma, Churchill, Monorchid, Cambria
A10: 9 | B10: Collier Center | C10: Garage | D10: Downtown | E10: 201 E Washington St Phoenix, AZ 85004 | F10: 1476 | G10: 5 | I10: Ace | O10: Potentially Pre Open STK
A11: 10 | B11: Galleria Garage | C11: Garage | D11: Scottsdale | E11: 4301-4343 N Scottsdale Rd Scottsdale, AZ 85251 | F11: 700 | G11: Free | I11: City of Scottsdale | K11: 1 480-312-3111
A12: 11 | B12: Scottsdale Waterfront | C12: Garage | D12: Scottsdale | E12: 7135 E Camelback Rd Scottsdale, AZ 85251 | F12: 300 | G12: Free | I12: City of Scottsdale | M12: Has Valet | O12: Maple & Ash, Culinary Dropout
A13: 12 | B13: 5th Avenue Garage | C13: Garage | D13: Scottsdale | E13: 7143 E 5th Ave Scottsdale, AZ 85251 | F13: 409 | G13: Free | I13: City of Scottsdale
A14: 13 | B14: Scottsdale Mall - Pepperwood Lot | C14: Not Covered | D14: Scottsdale | E14: 7319 E 1st Ave Scottsdale, AZ 85251 | F14: 123 | G14: Free | I14: City of Scottsdale | O14: Hulas
A15: 14 | B15: Parking Corral | C15: Partially Covered | D15: Scottsdale | E15: 3806 N Brown Ave Scottsdale, AZ 85251 | F15: 224 | G15: Free | I15: City of Scottsdale | O15: STK, Mission, Uchi
A16: 15 | B16: Center for the Arts Parking Garage | C16: Garage | D16: Scottsdale | E16: 3888 N Wells Fargo Ave Scottsdale, AZ 85251 | F16: 368 | G16: Free | I16: City of Scottsdale | K16: 1 480-312-3111
A17: 16
A18: 17
A19: 18
A20: 19
A21: 20
A22: 21
A23: 22
A24: 23
A25: 24
A26: 25
A27: 26
A28: 27
... A32: 31

Sheet RevenueForecasting
A1: Account | B1: # of Rooms | C1: Occupancy Rate | D1: Forecast | E1: Valet Conversion Rate | F1: Estimated Daily Valet Count | G1: Estimated Daily Revenue | H1: Estimated Annual Revenue | I1: Estimate Net Operating Income Annually | J1: Total Daily Rev | K1: Total Annual Rev | L1: Total Annual NOI
A2: =Accounts!A2 | B2: =Accounts!J2 | C2: 0.6 | D2: =Accounts!J2*C2 | E2: 0.4 | F2: =D2*E2 | G2: =if(or(eq(Accounts!I2,"No Valet"),eq(Accounts!I2,"Has Valet")), F2 * AVERAGE(Accounts!I$2:I$34),F2*Accounts!I2) | H2: =iferror(G2*360,"") | I2: =H2*0.1 | J2: =sum(G2:G72) | K2: =sum(H2:H72) | L2: =sum(I2:I72)
A3: =Accounts!A3 | B3: =Accounts!J3 | C3: 0.6 | D3: =Accounts!J3*C3 | E3: 0.4 | F3: =D3*E3 | G3: =if(or(eq(Accounts!I3,"No Valet"),eq(Accounts!I3,"Has Valet")), F3 * AVERAGE(Accounts!I$2:I$34),F3*Accounts!I3) | H3: =iferror(G3*360,"") | I3: =H3*0.1
A4: =#REF! | B4: =#REF! | C4: 0.6 | D4: =#REF!*C4 | E4: 0.4 | F4: =D4*E4 | G4: =if(or(eq(#REF!,"No Valet"),eq(#REF!,"Has Valet")), F4 * AVERAGE(Accounts!I$2:I$34),F4*#REF!) | H4: =iferror(G4*360,"") | I4: =H4*0.1
A5: =Accounts!A4 | B5: =Accounts!J4 | C5: 0.6 | D5: =Accounts!J4*C5 | E5: 0.4 | F5: =D5*E5 | G5: =if(or(eq(Accounts!I4,"No Valet"),eq(Accounts!I4,"Has Valet")), F5 * AVERAGE(Accounts!I$2:I$34),F5*Accounts!I4) | H5: =iferror(G5*360,"") | I5: =H5*0.1
A6: =Accounts!A5 | B6: =Accounts!J5 | C6: 0.6 | D6: =Accounts!J5*C6 | E6: 0.4 | F6: =D6*E6 | G6: =if(or(eq(Accounts!I5,"No Valet"),eq(Accounts!I5,"Has Valet")), F6 * AVERAGE(Accounts!I$2:I$34),F6*Accounts!I5) | H6: =iferror(G6*360,"") | I6: =H6*0.1
A7: =Accounts!A6 | B7: =Accounts!J6 | C7: 0.6 | D7: =Accounts!J6*C7 | E7: 0.4 | F7: =D7*E7 | G7: =if(or(eq(Accounts!I6,"No Valet"),eq(Accounts!I6,"Has Valet")), F7 * AVERAGE(Accounts!I$2:I$34),F7*Accounts!I6) | H7: =iferror(G7*360,"") | I7: =H7*0.1
A8: =Accounts!A7 | B8: =Accounts!J7 | C8: 0.6 | D8: =Accounts!J7*C8 | E8: 0.4 | F8: =D8*E8 | G8: =if(or(eq(Accounts!I7,"No Valet"),eq(Accounts!I7,"Has Valet")), F8 * AVERAGE(Accounts!I$2:I$34),F8*Accounts!I7) | H8: =iferror(G8*360,"") | I8: =H8*0.1
A9: =Accounts!A8 | B9: =Accounts!J8 | C9: 0.6 | D9: =Accounts!J8*C9 | E9: 0.4 | F9: =D9*E9 | G9: =if(or(eq(Accounts!I8,"No Valet"),eq(Accounts!I8,"Has Valet")), F9 * AVERAGE(Accounts!I$2:I$34),F9*Accounts!I8) | H9: =iferror(G9*360,"") | I9: =H9*0.1
A10: =Accounts!A9 | B10: =Accounts!J9 | C10: 0.6 | D10: =Accounts!J9*C10 | E10: 0.4 | F10: =D10*E10 | G10: =if(or(eq(Accounts!I9,"No Valet"),eq(Accounts!I9,"Has Valet")), F10 * AVERAGE(Accounts!I$2:I$34),F10*Accounts!I9) | H10: =iferror(G10*360,"") | I10: =H10*0.1
A11: =Accounts!A10 | B11: =Accounts!J10 | C11: 0.6 | D11: =Accounts!J10*C11 | E11: 0.4 | F11: =D11*E11 | G11: =if(or(eq(Accounts!I10,"No Valet"),eq(Accounts!I10,"Has Valet")), F11 * AVERAGE(Accounts!I$2:I$34),F11*Accounts!I10) | H11: =iferror(G11*360,"") | I11: =H11*0.1
A12: =Accounts!A11 | B12: =Accounts!J11 | C12: 0.6 | D12: =Accounts!J11*C12 | E12: 0.4 | F12: =D12*E12 | G12: =if(or(eq(Accounts!I11,"No Valet"),eq(Accounts!I11,"Has Valet")), F12 * AVERAGE(Accounts!I$2:I$34),F12*Accounts!I11) | H12: =iferror(G12*360,"") | I12: =H12*0.1
A13: =Accounts!A12 | B13: =Accounts!J12 | C13: 0.6 | D13: =Accounts!J12*C13 | E13: 0.4 | F13: =D13*E13 | G13: =if(or(eq(Accounts!I12,"No Valet"),eq(Accounts!I12,"Has Valet")), F13 * AVERAGE(Accounts!I$2:I$34),F13*Accounts!I12) | H13: =iferror(G13*360,"") | I13: =H13*0.1
A14: =Accounts!A13 | B14: =Accounts!J13 | C14: 0.6 | D14: =Accounts!J13*C14 | E14: 0.4 | F14: =D14*E14 | G14: =if(or(eq(Accounts!I13,"No Valet"),eq(Accounts!I13,"Has Valet")), F14 * AVERAGE(Accounts!I$2:I$34),F14*Accounts!I13) | H14: =iferror(G14*360,"") | I14: =H14*0.1
A15: =#REF! | B15: =#REF! | C15: 0.6 | D15: =#REF!*C15 | E15: 0.4 | F15: =D15*E15 | G15: =if(or(eq(#REF!,"No Valet"),eq(#REF!,"Has Valet")), F15 * AVERAGE(Accounts!I$2:I$34),F15*#REF!) | H15: =iferror(G15*360,"") | I15: =H15*0.1
A16: =Accounts!A14 | B16: =Accounts!J14 | C16: 0.6 | D16: =Accounts!J14*C16 | E16: 0.4 | F16: =D16*E16 | G16: =if(or(eq(Accounts!I14,"No Valet"),eq(Accounts!I14,"Has Valet")), F16 * AVERAGE(Accounts!I$2:I$34),F16*Accounts!I14) | H16: =iferror(G16*360,"") | I16: =H16*0.1
A17: =Accounts!A15 | B17: =Accounts!J15 | C17: 0.6 | D17: =Accounts!J15*C17 | E17: 0.4 | F17: =D17*E17 | G17: =if(or(eq(Accounts!I15,"No Valet"),eq(Accounts!I15,"Has Valet")), F17 * AVERAGE(Accounts!I$2:I$34),F17*Accounts!I15) | H17: =iferror(G17*360,"") | I17: =H17*0.1
A18: =Accounts!A16 | B18: =Accounts!J16 | C18: 0.6 | D18: =Accounts!J16*C18 | E18: 0.4 | F18: =D18*E18 | G18: =if(or(eq(Accounts!I16,"No Valet"),eq(Accounts!I16,"Has Valet")), F18 * AVERAGE(Accounts!I$2:I$34),F18*Accounts!I16) | H18: =iferror(G18*360,"") | I18: =H18*0.1
A19: =Accounts!A17 | B19: =Accounts!J17 | C19: 0.6 | D19: =Accounts!J17*C19 | E19: 0.4 | F19: =D19*E19 | G19: =if(or(eq(Accounts!I17,"No Valet"),eq(Accounts!I17,"Has Valet")), F19 * AVERAGE(Accounts!I$2:I$34),F19*Accounts!I17) | H19: =iferror(G19*360,"") | I19: =H19*0.1
A20: =Accounts!A18 | B20: =Accounts!J18 | C20: 0.6 | D20: =Accounts!J18*C20 | E20: 0.4 | F20: =D20*E20 | G20: =if(or(eq(Accounts!I18,"No Valet"),eq(Accounts!I18,"Has Valet")), F20 * AVERAGE(Accounts!I$2:I$34),F20*Accounts!I18) | H20: =iferror(G20*360,"") | I20: =H20*0.1
A21: =Accounts!A19 | B21: =Accounts!J19 | C21: 0.6 | D21: =Accounts!J19*C21 | E21: 0.4 | F21: =D21*E21 | G21: =if(or(eq(Accounts!I19,"No Valet"),eq(Accounts!I19,"Has Valet")), F21 * AVERAGE(Accounts!I$2:I$34),F21*Accounts!I19) | H21: =iferror(G21*360,"") | I21: =H21*0.1
A22: =Accounts!A20 | B22: =Accounts!J20 | C22: 0.6 | D22: =Accounts!J20*C22 | E22: 0.4 | F22: =D22*E22 | G22: =if(or(eq(Accounts!I20,"No Valet"),eq(Accounts!I20,"Has Valet")), F22 * AVERAGE(Accounts!I$2:I$34),F22*Accounts!I20) | H22: =iferror(G22*360,"") | I22: =H22*0.1
A23: =Accounts!A21 | B23: =Accounts!J21 | C23: 0.6 | D23: =Accounts!J21*C23 | E23: 0.4 | F23: =D23*E23 | G23: =if(or(eq(Accounts!I21,"No Valet"),eq(Accounts!I21,"Has Valet")), F23 * AVERAGE(Accounts!I$2:I$34),F23*Accounts!I21) | H23: =iferror(G23*360,"") | I23: =H23*0.1
A24: =Accounts!A22 | B24: =Accounts!J22 | C24: 0.6 | D24: =Accounts!J22*C24 | E24: 0.4 | F24: =D24*E24 | G24: =if(or(eq(Accounts!I22,"No Valet"),eq(Accounts!I22,"Has Valet")), F24 * AVERAGE(Accounts!I$2:I$34),F24*Accounts!I22) | H24: =iferror(G24*360,"") | I24: =H24*0.1
A25: =Accounts!A23 | B25: =Accounts!J23 | C25: 0.6 | D25: =Accounts!J23*C25 | E25: 0.4 | F25: =D25*E25 | G25: =if(or(eq(Accounts!I23,"No Valet"),eq(Accounts!I23,"Has Valet")), F25 * AVERAGE(Accounts!I$2:I$34),F25*Accounts!I23) | H25: =iferror(G25*360,"") | I25: =H25*0.1
A26: =Accounts!A24 | B26: =Accounts!J24 | C26: 0.6 | D26: =Accounts!J24*C26 | E26: 0.4 | F26: =D26*E26 | G26: =if(or(eq(Accounts!I24,"No Valet"),eq(Accounts!I24,"Has Valet")), F26 * AVERAGE(Accounts!I$2:I$34),F26*Accounts!I24) | H26: =iferror(G26*360,"") | I26: =H26*0.1
A27: =Accounts!A25 | B27: =Accounts!J25 | C27: 0.6 | D27: =Accounts!J25*C27 | E27: 0.4 | F27: =D27*E27 | G27: =if(or(eq(Accounts!I25,"No Valet"),eq(Accounts!I25,"Has Valet")), F27 * AVERAGE(Accounts!I$2:I$34),F27*Accounts!I25) | H27: =iferror(G27*360,"") | I27: =H27*0.1
... A40: =Accounts!A38 | B40: =Accounts!J38 | C40: 0.6 | D40: =Accounts!J38*C40 | E40: 0.4 | F40: =D40*E40 | G40: =if(or(eq(Accounts!I38,"No Valet"),eq(Accounts!I38,"Has Valet")), F40 * AVERAGE(Accounts!I$2:I$34),F40*Accounts!I38) | H40: =iferror(G40*360,"") | I40: =H40*0.1
A41: =Accounts!A39 | B41: =Accounts!J39 | C41: 0.6 | D41: =#REF!*C41 | E41: 0.4 | F41: =D41*E41 | G41: =if(or(eq(#REF!,"No Valet"),eq(#REF!,"Has Valet")), F41 * AVERAGE(Accounts!I$2:I$34),F41*#REF!) | H41: =iferror(G41*360,"") | I41: =H41*0.1
A42: =Accounts!A40 | B42: =Accounts!J40 | C42: 0.6 | D42: =Accounts!J39*C42 | E42: 0.4 | F42: =D42*E42 | G42: =if(or(eq(Accounts!I39,"No Valet"),eq(Accounts!I39,"Has Valet")), F42 * AVERAGE(Accounts!I$2:I$34),F42*Accounts!I39) | H42: =iferror(G42*360,"") | I42: =H42*0.1
A43: =Accounts!A41 | B43: =Accounts!J41 | C43: 0.6 | D43: =Accounts!J40*C43 | E43: 0.4 | F43: =D43*E43 | G43: =if(or(eq(Accounts!I40,"No Valet"),eq(Accounts!I40,"Has Valet")), F43 * AVERAGE(Accounts!I$2:I$34),F43*Accounts!I40) | H43: =iferror(G43*360,"") | I43: =H43*0.1
A44: =Accounts!A42 | B44: =Accounts!J42 | C44: 0.6 | D44: =Accounts!J41*C44 | E44: 0.4 | F44: =D44*E44 | G44: =if(or(eq(Accounts!I41,"No Valet"),eq(Accounts!I41,"Has Valet")), F44 * AVERAGE(Accounts!I$2:I$34),F44*Accounts!I41) | H44: =iferror(G44*360,"") | I44: =H44*0.1
A45: =Accounts!A43 | B45: =Accounts!J43 | C45: 0.6 | D45: =Accounts!J42*C45 | E45: 0.4 | F45: =D45*E45 | G45: =if(or(eq(Accounts!I42,"No Valet"),eq(Accounts!I42,"Has Valet")), F45 * AVERAGE(Accounts!I$2:I$34),F45*Accounts!I42) | H45: =iferror(G45*360,"") | I45: =H45*0.1
A46: =Accounts!A44 | B46: =Accounts!J44 | C46: 0.6 | D46: =Accounts!J43*C46 | E46: 0.4 | F46: =D46*E46 | G46: =if(or(eq(Accounts!I43,"No Valet"),eq(Accounts!I43,"Has Valet")), F46 * AVERAGE(Accounts!I$2:I$34),F46*Accounts!I43) | H46: =iferror(G46*360,"") | I46: =H46*0.1
A47: =Accounts!A45 | B47: =Accounts!J45 | C47: 0.6 | D47: =Accounts!J44*C47 | E47: 0.4 | F47: =D47*E47 | G47: =if(or(eq(#REF!,"No Valet"),eq(#REF!,"Has Valet")), F47 * AVERAGE(Accounts!I$2:I$34),F47*#REF!) | H47: =iferror(G47*360,"") | I47: =H47*0.1
A48: =Accounts!A46 | B48: =Accounts!J46 | C48: 0.6 | D48: =Accounts!J45*C48 | E48: 0.4 | F48: =D48*E48 | G48: =if(or(eq(Accounts!I44,"No Valet"),eq(Accounts!I44,"Has Valet")), F48 * AVERAGE(Accounts!I$2:I$34),F48*Accounts!I44) | H48: =iferror(G48*360,"") | I48: =H48*0.1
A49: =Accounts!A47 | B49: =Accounts!J47 | C49: 0.6 | D49: =#REF!*C49 | E49: 0.4 | F49: =D49*E49 | G49: =if(or(eq(#REF!,"No Valet"),eq(#REF!,"Has Valet")), F49 * AVERAGE(Accounts!I$2:I$34),F49*#REF!) | H49: =iferror(G49*360,"") | I49: =H49*0.1
A50: =Accounts!A48 | B50: =Accounts!J48 | C50: 0.6 | D50: =#REF!*C50 | E50: 0.4 | F50: =D50*E50 | G50: =if(or(eq(#REF!,"No Valet"),eq(#REF!,"Has Valet")), F50 * AVERAGE(Accounts!I$2:I$34),F50*#REF!) | H50: =iferror(G50*360,"") | I50: =H50*0.1
A51: =Accounts!A49 | B51: =Accounts!J49 | C51: 0.6 | D51: =Accounts!J46*C51 | E51: 0.4 | F51: =D51*E51 | G51: =if(or(eq(Accounts!I46,"No Valet"),eq(Accounts!I46,"Has Valet")), F51 * AVERAGE(Accounts!I$2:I$34),F51*Accounts!I46) | H51: =iferror(G51*360,"") | I51: =H51*0.1
A52: =Accounts!A50 | B52: =Accounts!J50 | C52: 0.6 | D52: =Accounts!J47*C52 | E52: 0.4 | F52: =D52*E52 | G52: =if(or(eq(Accounts!I47,"No Valet"),eq(Accounts!I47,"Has Valet")), F52 * AVERAGE(Accounts!I$2:I$34),F52*Accounts!I47) | H52: =iferror(G52*360,"") | I52: =H52*0.1
A53: =Accounts!A51 | B53: =Accounts!J51 | C53: 0.6 | D53: =Accounts!J48*C53 | E53: 0.4 | F53: =D53*E53 | G53: =if(or(eq(Accounts!I48,"No Valet"),eq(Accounts!I48,"Has Valet")), F53 * AVERAGE(Accounts!I$2:I$34),F53*Accounts!I48) | H53: =iferror(G53*360,"") | I53: =H53*0.1
A54: =Accounts!A52 | B54: =Accounts!J52 | C54: 0.6 | D54: =Accounts!J49*C54 | E54: 0.4 | F54: =D54*E54 | G54: =if(or(eq(Accounts!I49,"No Valet"),eq(Accounts!I49,"Has Valet")), F54 * AVERAGE(Accounts!I$2:I$34),F54*Accounts!I49) | H54: =iferror(G54*360,"") | I54: =H54*0.1
A55: =Accounts!A53 | B55: =Accounts!J53 | C55: 0.6 | D55: =Accounts!J50*C55 | E55: 0.4 | F55: =D55*E55 | G55: =if(or(eq(Accounts!I50,"No Valet"),eq(Accounts!I50,"Has Valet")), F55 * AVERAGE(Accounts!I$2:I$34),F55*Accounts!I50) | H55: =iferror(G55*360,"") | I55: =H55*0.1
A56: =Accounts!A54 | B56: =Accounts!J54 | C56: 0.6 | D56: =Accounts!J51*C56 | E56: 0.4 | F56: =D56*E56 | G56: =if(or(eq(Accounts!I51,"No Valet"),eq(Accounts!I51,"Has Valet")), F56 * AVERAGE(Accounts!I$2:I$34),F56*Accounts!I51) | H56: =iferror(G56*360,"") | I56: =H56*0.1
A57: =Accounts!A55 | B57: =Accounts!J55 | C57: 0.6 | D57: =Accounts!J52*C57 | E57: 0.4 | F57: =D57*E57 | G57: =if(or(eq(Accounts!I52,"No Valet"),eq(Accounts!I52,"Has Valet")), F57 * AVERAGE(Accounts!I$2:I$34),F57*Accounts!I52) | H57: =iferror(G57*360,"") | I57: =H57*0.1
A58: =Accounts!A56 | B58: =Accounts!J56 | C58: 0.6 | D58: =Accounts!J53*C58 | E58: 0.4 | F58: =D58*E58 | G58: =if(or(eq(Accounts!I53,"No Valet"),eq(Accounts!I53,"Has Valet")), F58 * AVERAGE(Accounts!I$2:I$34),F58*Accounts!I53) | H58: =iferror(G58*360,"") | I58: =H58*0.1
A59: =Accounts!A57 | B59: =Accounts!J57 | C59: 0.6 | D59: =Accounts!J54*C59 | E59: 0.4 | F59: =D59*E59 | G59: =if(or(eq(Accounts!I54,"No Valet"),eq(Accounts!I54,"Has Valet")), F59 * AVERAGE(Accounts!I$2:I$34),F59*Accounts!I54) | H59: =iferror(G59*360,"") | I59: =H59*0.1
A60: =Accounts!A58 | B60: =Accounts!J58 | C60: 0.6 | D60: =Accounts!J55*C60 | E60: 0.4 | F60: =D60*E60 | G60: =if(or(eq(Accounts!I55,"No Valet"),eq(Accounts!I55,"Has Valet")), F60 * AVERAGE(Accounts!I$2:I$34),F60*Accounts!I55) | H60: =iferror(G60*360,"") | I60: =H60*0.1
A61: =Accounts!A59 | B61: =Accounts!J59 | C61: 0.6 | D61: =Accounts!J56*C61 | E61: 0.4 | F61: =D61*E61 | G61: =if(or(eq(Accounts!I56,"No Valet"),eq(Accounts!I56,"Has Valet")), F61 * AVERAGE(Accounts!I$2:I$34),F61*Accounts!I56) | H61: =iferror(G61*360,"") | I61: =H61*0.1
A62: =Accounts!A60 | B62: =Accounts!J60 | C62: 0.6 | D62: =Accounts!J57*C62 | E62: 0.4 | F62: =D62*E62 | G62: =if(or(eq(Accounts!I57,"No Valet"),eq(Accounts!I57,"Has Valet")), F62 * AVERAGE(Accounts!I$2:I$34),F62*Accounts!I57) | H62: =iferror(G62*360,"") | I62: =H62*0.1
... A67: =Accounts!A65 | B67: =Accounts!J65 | C67: 0.6 | D67: =Accounts!J62*C67 | E67: 0.4 | F67: =D67*E67 | G67: =if(or(eq(Accounts!I62,"No Valet"),eq(Accounts!I62,"Has Valet")), F67 * AVERAGE(Accounts!I$2:I$34),F67*Accounts!I62) | H67: =iferror(G67*360,"") | I67: =H67*0.1
A68: =#REF! | B68: =#REF! | C68: 0.6 | D68: =Accounts!J63*C68 | E68: 0.4 | F68: =D68*E68 | G68: =if(or(eq(Accounts!I63,"No Valet"),eq(Accounts!I63,"Has Valet")), F68 * AVERAGE(Accounts!I$2:I$34),F68*Accounts!I63) | H68: =iferror(G68*360,"") | I68: =H68*0.1
A69: =Accounts!A66 | B69: =Accounts!J66 | C69: 0.6 | D69: =Accounts!J64*C69 | E69: 0.4 | F69: =D69*E69 | G69: =if(or(eq(Accounts!I64,"No Valet"),eq(Accounts!I64,"Has Valet")), F69 * AVERAGE(Accounts!I$2:I$34),F69*Accounts!I64) | H69: =iferror(G69*360,"") | I69: =H69*0.1
A70: =Accounts!A67 | B70: =Accounts!J67 | C70: 0.6 | D70: =Accounts!J65*C70 | E70: 0.4 | F70: =D70*E70 | G70: =if(or(eq(Accounts!I65,"No Valet"),eq(Accounts!I65,"Has Valet")), F70 * AVERAGE(Accounts!I$2:I$34),F70*Accounts!I65) | H70: =iferror(G70*360,"") | I70: =H70*0.1
A71: =Accounts!A68 | B71: =Accounts!J68 | C71: 0.6 | D71: =#REF!*C71 | E71: 0.4 | F71: =D71*E71 | G71: =if(or(eq(#REF!,"No Valet"),eq(#REF!,"Has Valet")), F71 * AVERAGE(Accounts!I$2:I$34),F71*#REF!) | H71: =iferror(G71*360,"") | I71: =H71*0.1
A72: =Accounts!A69 | B72: =Accounts!J69 | C72: 0.6 | D72: =Accounts!J66*C72 | E72: 0.4 | F72: =D72*E72 | G72: =if(or(eq(Accounts!I66,"No Valet"),eq(Accounts!I66,"Has Valet")), F72 * AVERAGE(Accounts!I$2:I$34),F72*Accounts!I66) | H72: =iferror(G72*360,"") | I72: =H72*0.1
A73: =Accounts!A70 | B73: =Accounts!J70 | C73: 0.6 | D73: =Accounts!J67*C73 | E73: 0.4 | F73: =D73*E73 | G73: =if(or(eq(Accounts!I67,"No Valet"),eq(Accounts!I67,"Has Valet")), F73 * AVERAGE(Accounts!I$2:I$34),F73*Accounts!I67) | H73: =iferror(G73*360,"") | I73: =H73*0.1
A74: =Accounts!A71 | B74: =Accounts!J71 | C74: 0.6 | D74: =Accounts!J68*C74 | E74: 0.4 | F74: =D74*E74 | G74: =if(or(eq(Accounts!I68,"No Valet"),eq(Accounts!I68,"Has Valet")), F74 * AVERAGE(Accounts!I$2:I$34),F74*Accounts!I68) | H74: =iferror(G74*360,"") | I74: =H74*0.1
A75: =Accounts!A72 | B75: =Accounts!J72 | C75: 0.6 | D75: =Accounts!J69*C75 | E75: 0.4 | F75: =D75*E75 | G75: =if(or(eq(Accounts!I69,"No Valet"),eq(Accounts!I69,"Has Valet")), F75 * AVERAGE(Accounts!I$2:I$34),F75*Accounts!I69) | H75: =iferror(G75*360,"") | I75: =H75*0.1
A76: =Accounts!A73 | B76: =Accounts!J73 | C76: 0.6 | D76: =Accounts!J70*C76 | E76: 0.4 | F76: =D76*E76 | G76: =if(or(eq(Accounts!I70,"No Valet"),eq(Accounts!I70,"Has Valet")), F76 * AVERAGE(Accounts!I$2:I$34),F76*Accounts!I70) | H76: =iferror(G76*360,"") | I76: =H76*0.1
A77: =Accounts!A74 | B77: =Accounts!J74 | C77: 0.6 | D77: =Accounts!J71*C77 | E77: 0.4 | F77: =D77*E77 | G77: =if(or(eq(Accounts!I71,"No Valet"),eq(Accounts!I71,"Has Valet")), F77 * AVERAGE(Accounts!I$2:I$34),F77*Accounts!I71) | H77: =iferror(G77*360,"") | I77: =H77*0.1
A78: =Accounts!A75 | B78: =Accounts!J75 | C78: 0.6 | D78: =Accounts!J72*C78 | E78: 0.4 | F78: =D78*E78 | G78: =if(or(eq(Accounts!I72,"No Valet"),eq(Accounts!I72,"Has Valet")), F78 * AVERAGE(Accounts!I$2:I$34),F78*Accounts!I72) | H78: =iferror(G78*360,"") | I78: =H78*0.1
A79: =Accounts!A76 | B79: =Accounts!J76 | C79: 0.6 | D79: =Accounts!J73*C79 | E79: 0.4 | F79: =D79*E79 | G79: =if(or(eq(Accounts!I73,"No Valet"),eq(Accounts!I73,"Has Valet")), F79 * AVERAGE(Accounts!I$2:I$34),F79*Accounts!I73) | H79: =iferror(G79*360,"") | I79: =H79*0.1
A80: =Accounts!A77 | B80: =Accounts!J77 | C80: 0.6 | D80: =Accounts!J74*C80 | E80: 0.4 | F80: =D80*E80 | G80: =if(or(eq(Accounts!I74,"No Valet"),eq(Accounts!I74,"Has Valet")), F80 * AVERAGE(Accounts!I$2:I$34),F80*Accounts!I74) | H80: =iferror(G80*360,"") | I80: =H80*0.1
A81: =Accounts!A78 | B81: =Accounts!J78 | C81: 0.6 | D81: =Accounts!J75*C81 | E81: 0.4 | F81: =D81*E81 | G81: =if(or(eq(Accounts!I75,"No Valet"),eq(Accounts!I75,"Has Valet")), F81 * AVERAGE(Accounts!I$2:I$34),F81*Accounts!I75) | H81: =iferror(G81*360,"") | I81: =H81*0.1
A82: =Accounts!A79 | B82: =Accounts!J79 | C82: 0.6 | D82: =Accounts!J76*C82 | E82: 0.4 | F82: =D82*E82 | G82: =if(or(eq(Accounts!I76,"No Valet"),eq(Accounts!I76,"Has Valet")), F82 * AVERAGE(Accounts!I$2:I$34),F82*Accounts!I76) | H82: =iferror(G82*360,"") | I82: =H82*0.1
A83: =Accounts!A80 | B83: =Accounts!J80 | C83: 0.6 | D83: =Accounts!J77*C83 | E83: 0.4 | F83: =D83*E83 | G83: =if(or(eq(Accounts!I77,"No Valet"),eq(Accounts!I77,"Has Valet")), F83 * AVERAGE(Accounts!I$2:I$34),F83*Accounts!I77) | H83: =iferror(G83*360,"") | I83: =H83*0.1
... A88: =Accounts!A85 | B88: =Accounts!J85 | C88: 0.6 | D88: =Accounts!J82*C88 | E88: 0.4 | F88: =D88*E88 | G88: =if(or(eq(Accounts!I82,"No Valet"),eq(Accounts!I82,"Has Valet")), F88 * AVERAGE(Accounts!I$2:I$34),F88*Accounts!I82) | H88: =iferror(G88*360,"") | I88: =H88*0.1
A89: =#REF! | B89: =#REF! | C89: 0.6 | D89: =Accounts!J83*C89 | E89: 0.4 | F89: =D89*E89 | G89: =if(or(eq(Accounts!I83,"No Valet"),eq(Accounts!I83,"Has Valet")), F89 * AVERAGE(Accounts!I$2:I$34),F89*Accounts!I83) | H89: =iferror(G89*360,"") | I89: =H89*0.1
A90: =Accounts!A86 | B90: =Accounts!J86 | C90: 0.6 | D90: =Accounts!J84*C90 | E90: 0.4 | F90: =D90*E90 | G90: =if(or(eq(Accounts!I84,"No Valet"),eq(Accounts!I84,"Has Valet")), F90 * AVERAGE(Accounts!I$2:I$34),F90*Accounts!I84) | H90: =iferror(G90*360,"") | I90: =H90*0.1
A91: =Accounts!A87 | B91: =Accounts!J87 | C91: 0.6 | D91: =Accounts!J85*C91 | E91: 0.4 | F91: =D91*E91 | G91: =if(or(eq(Accounts!I85,"No Valet"),eq(Accounts!I85,"Has Valet")), F91 * AVERAGE(Accounts!I$2:I$34),F91*Accounts!I85) | H91: =iferror(G91*360,"") | I91: =H91*0.1
A92: =Accounts!A88 | B92: =Accounts!J88 | C92: 0.6 | D92: =#REF!*C92 | E92: 0.4 | F92: =D92*E92 | G92: =if(or(eq(#REF!,"No Valet"),eq(#REF!,"Has Valet")), F92 * AVERAGE(Accounts!I$2:I$34),F92*#REF!) | H92: =iferror(G92*360,"") | I92: =H92*0.1
A93: =Accounts!A89 | B93: =Accounts!J89 | C93: 0.6 | D93: =Accounts!J86*C93 | E93: 0.4 | F93: =D93*E93 | G93: =if(or(eq(Accounts!I86,"No Valet"),eq(Accounts!I86,"Has Valet")), F93 * AVERAGE(Accounts!I$2:I$34),F93*Accounts!I86) | H93: =iferror(G93*360,"") | I93: =H93*0.1
A94: =Accounts!A90 | B94: =Accounts!J90 | C94: 0.6 | D94: =Accounts!J87*C94 | E94: 0.4 | F94: =D94*E94 | G94: =if(or(eq(Accounts!I87,"No Valet"),eq(Accounts!I87,"Has Valet")), F94 * AVERAGE(Accounts!I$2:I$34),F94*Accounts!I87) | H94: =iferror(G94*360,"") | I94: =H94*0.1
A95: =Accounts!A91 | B95: =Accounts!J91 | C95: 0.6 | D95: =Accounts!J88*C95 | E95: 0.4 | F95: =D95*E95 | G95: =if(or(eq(Accounts!I88,"No Valet"),eq(Accounts!I88,"Has Valet")), F95 * AVERAGE(Accounts!I$2:I$34),F95*Accounts!I88) | H95: =iferror(G95*360,"") | I95: =H95*0.1
A96: =Accounts!A92 | B96: =Accounts!J92 | C96: 0.6 | D96: =Accounts!J89*C96 | E96: 0.4 | F96: =D96*E96 | G96: =if(or(eq(Accounts!I89,"No Valet"),eq(Accounts!I89,"Has Valet")), F96 * AVERAGE(Accounts!I$2:I$34),F96*Accounts!I89) | H96: =iferror(G96*360,"") | I96: =H96*0.1
A97: =Accounts!A93 | B97: =Accounts!J93 | C97: 0.6 | D97: =Accounts!J90*C97 | E97: 0.4 | F97: =D97*E97 | G97: =if(or(eq(Accounts!I90,"No Valet"),eq(Accounts!I90,"Has Valet")), F97 * AVERAGE(Accounts!I$2:I$34),F97*Accounts!I90) | H97: =iferror(G97*360,"") | I97: =H97*0.1
A98: =Accounts!A94 | B98: =Accounts!J94 | C98: 0.6 | D98: =Accounts!J91*C98 | E98: 0.4 | F98: =D98*E98 | G98: =if(or(eq(Accounts!I91,"No Valet"),eq(Accounts!I91,"Has Valet")), F98 * AVERAGE(Accounts!I$2:I$34),F98*Accounts!I91) | H98: =iferror(G98*360,"") | I98: =H98*0.1
A99: =#REF! | B99: =#REF! | C99: 0.6 | D99: =Accounts!J92*C99 | E99: 0.4 | F99: =D99*E99 | G99: =if(or(eq(Accounts!I92,"No Valet"),eq(Accounts!I92,"Has Valet")), F99 * AVERAGE(Accounts!I$2:I$34),F99*Accounts!I92) | H99: =iferror(G99*360,"") | I99: =H99*0.1
A100: =Accounts!A95 | B100: =Accounts!J95 | C100: 0.6 | D100: =Accounts!J93*C100 | E100: 0.4 | F100: =D100*E100 | G100: =if(or(eq(Accounts!I93,"No Valet"),eq(Accounts!I93,"Has Valet")), F100 * AVERAGE(Accounts!I$2:I$34),F100*Accounts!I93) | H100: =iferror(G100*360,"") | I100: =H100*0.1
A101: =Accounts!A96 | B101: =Accounts!J96 | C101: 0.6 | D101: =Accounts!J94*C101 | E101: 0.4 | F101: =D101*E101 | G101: =if(or(eq(Accounts!I94,"No Valet"),eq(Accounts!I94,"Has Valet")), F101 * AVERAGE(Accounts!I$2:I$34),F101*Accounts!I94) | H101: =iferror(G101*360,"") | I101: =H101*0.1
A102: =Accounts!A97 | B102: =Accounts!J97 | C102: 0.6 | D102: =#REF!*C102 | E102: 0.4 | F102: =D102*E102 | G102: =if(or(eq(#REF!,"No Valet"),eq(#REF!,"Has Valet")), F102 * AVERAGE(Accounts!I$2:I$34),F102*#REF!) | H102: =iferror(G102*360,"") | I102: =H102*0.1
A103: =#REF! | B103: =#REF! | C103: 0.6 | D103: =Accounts!J95*C103 | E103: 0.4 | F103: =D103*E103 | G103: =if(or(eq(Accounts!I95,"No Valet"),eq(Accounts!I95,"Has Valet")), F103 * AVERAGE(Accounts!I$2:I$34),F103*Accounts!I95) | H103: =iferror(G103*360,"") | I103: =H103*0.1
A104: =Accounts!A98 | B104: =Accounts!J98 | C104: 0.6 | D104: =Accounts!J96*C104 | E104: 0.4 | F104: =D104*E104 | G104: =if(or(eq(Accounts!I96,"No Valet"),eq(Accounts!I96,"Has Valet")), F104 * AVERAGE(Accounts!I$2:I$34),F104*Accounts!I96) | H104: =iferror(G104*360,"") | I104: =H104*0.1
A105: =Accounts!A99 | B105: =Accounts!J99 | C105: 0.6 | D105: =Accounts!J97*C105 | E105: 0.4 | F105: =D105*E105 | G105: =if(or(eq(Accounts!I97,"No Valet"),eq(Accounts!I97,"Has Valet")), F105 * AVERAGE(Accounts!I$2:I$34),F105*Accounts!I97) | H105: =iferror(G105*360,"") | I105: =H105*0.1
A106: =Accounts!A100 | B106: =Accounts!J100 | C106: 0.6 | D106: =#REF!*C106 | E106: 0.4 | F106: =D106*E106 | G106: =if(or(eq(#REF!,"No Valet"),eq(#REF!,"Has Valet")), F106 * AVERAGE(Accounts!I$2:I$34),F106*#REF!) | H106: =iferror(G106*360,"") | I106: =H106*0.1
A107: =Accounts!A101 | B107: =Accounts!J101 | C107: 0.6 | D107: =Accounts!J98*C107 | E107: 0.4 | F107: =D107*E107 | G107: =if(or(eq(Accounts!I98,"No Valet"),eq(Accounts!I98,"Has Valet")), F107 * AVERAGE(Accounts!I$2:I$34),F107*Accounts!I98) | H107: =iferror(G107*360,"") | I107: =H107*0.1
A108: =Accounts!A102 | B108: =Accounts!J102 | C108: 0.6 | D108: =Accounts!J99*C108 | E108: 0.4 | F108: =D108*E108 | G108: =if(or(eq(Accounts!I99,"No Valet"),eq(Accounts!I99,"Has Valet")), F108 * AVERAGE(Accounts!I$2:I$34),F108*Accounts!I99) | H108: =iferror(G108*360,"") | I108: =H108*0.1
A109: =Accounts!A103 | B109: =Accounts!J103 | C109: 0.6 | D109: =Accounts!J100*C109 | E109: 0.4 | F109: =D109*E109 | G109: =if(or(eq(Accounts!I100,"No Valet"),eq(Accounts!I100,"Has Valet")), F109 * AVERAGE(Accounts!I$2:I$34),F109*Accounts!I100) | H109: =iferror(G109*360,"") | I109: =H109*0.1
A110: =Accounts!A104 | B110: =Accounts!J104 | C110: 0.6 | D110: =Accounts!J101*C110 | E110: 0.4 | F110: =D110*E110 | G110: =if(or(eq(Accounts!I101,"No Valet"),eq(Accounts!I101,"Has Valet")), F110 * AVERAGE(Accounts!I$2:I$34),F110*Accounts!I101) | H110: =iferror(G110*360,"") | I110: =H110*0.1
A111: =Accounts!A105 | B111: =Accounts!J105 | C111: 0.6 | D111: =Accounts!J102*C111 | E111: 0.4 | F111: =D111*E111 | G111: =if(or(eq(Accounts!I102,"No Valet"),eq(Accounts!I102,"Has Valet")), F111 * AVERAGE(Accounts!I$2:I$34),F111*Accounts!I102) | H111: =iferror(G111*360,"") | I111: =H111*0.1
A112: =Accounts!A106 | B112: =Accounts!J106 | C112: 0.6 | D112: =Accounts!J103*C112 | E112: 0.4 | F112: =D112*E112 | G112: =if(or(eq(Accounts!I103,"No Valet"),eq(Accounts!I103,"Has Valet")), F112 * AVERAGE(Accounts!I$2:I$34),F112*Accounts!I103) | H112: =iferror(G112*360,"") | I112: =H112*0.1
A113: =Accounts!A107 | B113: =Accounts!J107 | C113: 0.6 | D113: =Accounts!J104*C113 | E113: 0.4 | F113: =D113*E113 | G113: =if(or(eq(Accounts!I104,"No Valet"),eq(Accounts!I104,"Has Valet")), F113 * AVERAGE(Accounts!I$2:I$34),F113*Accounts!I104) | H113: =iferror(G113*360,"") | I113: =H113*0.1
A114: =Accounts!A108 | B114: =Accounts!J108 | C114: 0.6 | D114: =Accounts!J105*C114 | E114: 0.4 | F114: =D114*E114 | G114: =if(or(eq(Accounts!I105,"No Valet"),eq(Accounts!I105,"Has Valet")), F114 * AVERAGE(Accounts!I$2:I$34),F114*Accounts!I105) | H114: =iferror(G114*360,"") | I114: =H114*0.1
A115: =Accounts!A109 | B115: =Accounts!J109 | C115: 0.6 | D115: =Accounts!J106*C115 | E115: 0.4 | F115: =D115*E115 | G115: =if(or(eq(Accounts!I106,"No Valet"),eq(Accounts!I106,"Has Valet")), F115 * AVERAGE(Accounts!I$2:I$34),F115*Accounts!I106) | H115: =iferror(G115*360,"") | I115: =H115*0.1
A116: =Accounts!A110 | B116: =Accounts!J110 | C116: 0.6 | D116: =Accounts!J107*C116 | E116: 0.4 | F116: =D116*E116 | G116: =if(or(eq(Accounts!I107,"No Valet"),eq(Accounts!I107,"Has Valet")), F116 * AVERAGE(Accounts!I$2:I$34),F116*Accounts!I107) | H116: =iferror(G116*360,"") | I116: =H116*0.1
A117: =Accounts!A111 | B117: =Accounts!J111 | C117: 0.6 | D117: =Accounts!J108*C117 | E117: 0.4 | F117: =D117*E117 | G117: =if(or(eq(Accounts!I108,"No Valet"),eq(Accounts!I108,"Has Valet")), F117 * AVERAGE(Accounts!I$2:I$34),F117*Accounts!I108) | H117: =iferror(G117*360,"") | I117: =H117*0.1
A118: =Accounts!A112 | B118: =Accounts!J112 | C118: 0.6 | D118: =Accounts!J109*C118 | E118: 0.4 | F118: =D118*E118 | G118: =if(or(eq(Accounts!I109,"No Valet"),eq(Accounts!I109,"Has Valet")), F118 * AVERAGE(Accounts!I$2:I$34),F118*Accounts!I109) | H118: =iferror(G118*360,"") | I118: =H118*0.1
... A121: =Accounts!A115 | B121: =Accounts!J115 | C121: 0.6 | D121: =Accounts!J112*C121 | E121: 0.4 | F121: =D121*E121 | G121: =if(or(eq(Accounts!I112,"No Valet"),eq(Accounts!I112,"Has Valet")), F121 * AVERAGE(Accounts!I$2:I$34),F121*Accounts!I112) | H121: =iferror(G121*360,"") | I121: =H121*0.1
A122: =#REF! | B122: =#REF! | C122: 0.6 | D122: =Accounts!J113*C122 | E122: 0.4 | F122: =D122*E122 | G122: =if(or(eq(Accounts!I113,"No Valet"),eq(Accounts!I113,"Has Valet")), F122 * AVERAGE(Accounts!I$2:I$34),F122*Accounts!I113) | H122: =iferror(G122*360,"") | I122: =H122*0.1
...

Sheet Competition Analysis
A1: Company | B1: Role | C1: Low Pay | D1: High Play | E1: Type | F1: SOPHI role Equivalance | G1: Benefits | H1: Bonus?
A2: Crescent | B2: PT Overnight Valet Attendant | C2: 13.5 | D2: 17.5 | E2: PT | F2: Overnight | G2: Retirement, PTO | J2: OVERNIGHT SUPER | K2: OVERNIGHT ASSOC | L2: ASSOCIATE | M2: SUPERVISOR
A3: PMC | B3: Overnight Valet Attendant | C3: 14.69 | D3: 14.69 | E3: PT | F3: Overnight | J3: =AVERAGE(D2:D7) | K3: =AVERAGE(C2:C7) | L3: =AVERAGE(C8:C17) | M3: =AVERAGE(D8:D17)
A4: Crescent | B4: FT Overnight Valet Attendant | C4: 13.5 | D4: 18 | E4: FT | F4: Overnight
A5: SP+ | B5: Overnight Valet Driver | C5: 16.5 | D5: 16.5 | E5: FT | F5: Overnight
A6: PMC | B6: Overnight Valet Attendant | C6: 14.69 | D6: 14.69 | E6: FT | F6: Overnight
A7: SP+ | B7: Valet Driver Overnight | C7: 15 | D7: 20 | E7: FT | F7: Overnight
A8: FreedomPark | B8: Valet - Sky Harbor Airport | C8: 16.5 | D8: 18.5 | E8: FT
A9: EPIC | B9: Valet Parking Attendant | C9: 13.5 | D9: 17.75 | E9: PT
A10: Elevate Parking | B10: Valet | C10: 20 | D10: 35 | E10: FT
A11: Hyatt Andaz | B11: Bellman/Valet | C11: 14 | D11: 18.75 | E11: FT | G11: Medical Dental Vision Retirement
A12: PRS Management | B12: Driver/Valet | C12: 13.5 | D12: 18 | E12: FT | G12: Retirement, PTO
A13: Desert Mountain | B13: Valet Attendant | C13: 14 | D13: 18.25 | E13: PT | G13: Medical Dental Vision PTO 401k match
A14: ACE Parking | B14: VALET | C14: 15 | D14: 19.75 | E14: FT | G14: Medical Dental Vision PTO 401k match
A15: Desert Highlands | B15: Seasonal Valet | C15: 20 | D15: 23 | E15: FT
A16: PMC | B16: Valet Attendant | C16: 11.7 | D16: 11.7 | E16: PT/FT | G16: Medical Dental Vision PTO 401k match
A17: Troon Golf | B17: Valet Parking Attendant | C17: 17 | D17: 17 | E17: PT | H17: NO TIPS

Sheet Employees
A1: Employees | B1: Contacted | C1: Avalibility | D1: Contact Info | E1: Interested? | F1: Notes
B2: FALSE | E2: FALSE
B3: FALSE | E3: FALSE
B4: FALSE | E4: FALSE
B5: FALSE | E5: FALSE
B6: FALSE | E6: FALSE
B7: FALSE | E7: FALSE
B8: FALSE | E8: FALSE
B9: FALSE | E9: FALSE
B10: FALSE | E10: FALSE
B11: FALSE | E11: FALSE
B12: FALSE | E12: FALSE
B13: FALSE | E13: FALSE
... B36: FALSE | E36: FALSE

Sheet Market Notes
A1: NOTES
A2: Hospitality Groups | B2: Partners | C2: POC

Sheet TAM_Conservative
A1: Account | B1: Account Type | C1: TAM Class | D1: Rooms/Beds | E1: Seats | F1: Occupancy % | G1: Turnover | H1: Valet Conv % | I1: Valet Rate | J1: Op Days | K1: Peak Mod | L1: Daily Rev | M1: TAM | N1: TAM Status | O1: Notes / Source
A2: Kenect Phoenix | B2: Apartment | C2: Unknown type: Apartment | N2: REVIEW
A3: Sentral Sol Modern | B3: Apartment/Hotel | C3: Hotel — Downtown Select-Service | F3: 0.6 | H3: 0.25 | J3: 360 | N3: No Valet / TAM = $0 | O3: Hotel has no valet (rate field: 'No Valet'). Auto-class: downtown full-service <300 rooms. Qualitative pipeline only.
A4: Sentral Alloy Midtown | B4: Apartment/Hotel | C4: Hotel — Suburban/Airport | F4: 0.6 | H4: 0.15 | J4: 360 | N4: No Valet / TAM = $0 | O4: Hotel has no valet (rate field: 'No Valet'). Auto-class: not downtown (by flag or name). Qualitative pipeline only.
A5: Chateau Luxe Event Venue | B5: Event | C5: Unknown type: Event | N5: REVIEW
A6: Warehouse215 | B6: Event | C6: Unknown type: Event | N6: REVIEW
A7: 435 Collective | B7: Event | C7: Unknown type: Event | N7: REVIEW
A8: The Boho Space | B8: Event | C8: Unknown type: Event | N8: REVIEW
A9: The Teapot | B9: Event | C9: Unknown type: Event | N9: REVIEW
A10: monOrchid | B10: Event | C10: Unknown type: Event | N10: REVIEW
A11: The Dauz Venue | B11: Event | C11: Unknown type: Event | N11: REVIEW
A12: Antigua Garden | B12: Event | C12: Unknown type: Event | N12: REVIEW
A13: The Icehouse | B13: Event | C13: Unknown type: Event | N13: REVIEW
A14: Encanto 18 | B14: Event | C14: Unknown type: Event | N14: REVIEW
A15: The Duce | B15: Event | C15: Unknown type: Event | N15: REVIEW
A16: Wedgewood Weddings | B16: Event | C16: Unknown type: Event | N16: REVIEW
... A20: Papago Golf Club | B20: Golf | C20: Unknown type: Golf | N20: REVIEW
A21: Reliance Hospitality | B21: Hospitality Group | C21: Hospital — Qualitative | N21: PIPELINE ONLY | O21: Hospital deals are RFP/profit-share; excluded from TAM until IU Health benchmark formalized
A22: Integrity Lodging | B22: Hospitality Group | C22: Hospital — Qualitative | N22: PIPELINE ONLY | O22: Hospital deals are RFP/profit-share; excluded from TAM until IU Health benchmark formalized
A23: Riot Hospitality Group | B23: Hospitality Group | C23: Hospital — Qualitative | N23: PIPELINE ONLY | O23: Hospital deals are RFP/profit-share; excluded from TAM until IU Health benchmark formalized
A24: Heavlin Management Company (HMC) | B24: Hospitality Group | C24: Hospital — Qualitative | N24: PIPELINE ONLY | O24: Hospital deals are RFP/profit-share; excluded from TAM until IU Health benchmark formalized
A25: Aligned Hospitality Management | B25: Hospitality Group | C25: Hospital — Qualitative | N25: PIPELINE ONLY | O25: Hospital deals are RFP/profit-share; excluded from TAM until IU Health benchmark formalized
A26: Aimbridge Hospitality | B26: Hospitality Group | C26: Hospital — Qualitative | N26: PIPELINE ONLY | O26: Hospital deals are RFP/profit-share; excluded from TAM until IU Health benchmark formalized
A27: Crescent Hotels & Resorts | B27: Hospitality Group | C27: Hospital — Qualitative | N27: PIPELINE ONLY | O27: Hospital deals are RFP/profit-share; excluded from TAM until IU Health benchmark formalized
A28: Southwest Hospitality Management | B28: Hospitality Group | C28: Hospital — Qualitative | N28: PIPELINE ONLY | O28: Hospital deals are RFP/profit-share; excluded from TAM until IU Health benchmark formalized
A29: Desert Hospitality Management | B29: Hospitality Group | C29: Hospital — Qualitative | N29: PIPELINE ONLY | O29: Hospital deals are RFP/profit-share; excluded from TAM until IU Health benchmark formalized
A30: NCG Hospitality | B30: Hospitality Group | C30: Hospital — Qualitative | N30: PIPELINE ONLY | O30: Hospital deals are RFP/profit-share; excluded from TAM until IU Health benchmark formalized
A31: Classic Hotels & Resorts | B31: Hospitality Group | C31: Hospital — Qualitative | N31: PIPELINE ONLY | O31: Hospital deals are RFP/profit-share; excluded from TAM until IU Health benchmark formalized
A32: Carter Concepts Restaurant Group | B32: Hospitality Group | C32: Hospital — Qualitative | N32: PIPELINE ONLY | O32: Hospital deals are RFP/profit-share; excluded from TAM until IU Health benchmark formalized
A33: Courtyard Phoenix Airport | B33: Hotel | C33: Hotel — Suburban/Airport | D33: 145 | F33: 0.6 | H33: 0.15 | J33: 360 | N33: No Valet / TAM = $0 | O33: Hotel has no valet (rate field: 'No Valet'). Auto-class: not downtown (by flag or name). Qualitative pipeline only.
A34: Hilton Phoenix Airport | B34: Hotel | C34: Hotel — Suburban/Airport | D34: 259 | F34: 0.6 | H34: 0.15 | J34: 360 | N34: No Valet / TAM = $0 | O34: Hotel has no valet (rate field: 'No Valet'). Auto-class: not downtown (by flag or name). Qualitative pipeline only.
A35: Marriott Phoenix Airport | B35: Hotel | C35: Hotel — Suburban/Airport | D35: 347 | F35: 0.6 | H35: 0.15 | J35: 360 | N35: No Valet / TAM = $0 | O35: Hotel has no valet (rate field: 'No Valet'). Auto-class: not downtown (by flag or name). Qualitative pipeline only.
A36: Arizona Biltmore, LXR Hotels & Resorts | B36: Hotel | C36: Hotel — Resort | D36: 750 | F36: 0.6 | H36: 0.5 | I36: 30 | J36: 360 | L36: 6750 | M36: 2430000 | N36: Active TAM | O36: Auto-class: resort keyword: 'resort'. Occ 60% flat (refine w/STR).
A37: Embassy Suites by Hilton Phoenix Biltmore | B37: Hotel | C37: Hotel — Suburban/Airport | D37: 232 | F37: 0.6 | H37: 0.15 | J37: 360 | N37: No Valet / TAM = $0 | O37: Hotel has no valet (rate field: 'No Valet'). Auto-class: not downtown (by flag or name). Qualitative pipeline only.
A38: Hampton Inn Phoenix-Biltmore | B38: Hotel | C38: Hotel — Suburban/Airport | D38: 121 | F38: 0.6 | H38: 0.15 | J38: 360 | N38: No Valet / TAM = $0 | O38: Hotel has no valet (rate field: None). Auto-class: not downtown (by flag or name). Qualitative pipeline only.
A39: The Camby, Autograph Collection | B39: Hotel | C39: Hotel — Suburban/Airport | D39: 279 | F39: 0.6 | H39: 0.15 | I39: 40 | J39: 360 | L39: 1004.4 | M39: 361584 | N39: Active TAM | O39: Auto-class: not downtown (by flag or name). Occ 60% flat (refine w/STR).
A40: AC Hotel Phoenix Biltmore | B40: Hotel | C40: Hotel — Suburban/Airport | D40: 160 | F40: 0.6 | H40: 0.15 | J40: 360 | N40: No Valet / TAM = $0 | O40: Hotel has no valet (rate field: 'No Valet'). Auto-class: not downtown (by flag or name). Qualitative pipeline only.
A41: Sonesta Select Phoenix Camelback | B41: Hotel | C41: Hotel — Suburban/Airport | D41: 155 | F41: 0.6 | H41: 0.15 | J41: 360 | N41: No Valet / TAM = $0 | O41: Hotel has no valet (rate field: None). Auto-class: not downtown (by flag or name). Qualitative pipeline only.
A42: Hilton Garden Inn Chandler Downtown | B42: Hotel | C42: Hotel — Downtown Select-Service | D42: 110 | F42: 0.6 | H42: 0.25 | J42: 360 | N42: No Valet / TAM = $0 | O42: Hotel has no valet (rate field: 'No Valet'). Auto-class: downtown full-service <300 rooms [name-inferred downtown]. Qualitative pipeline only.
A43: Element Chandler Fashion Center | B43: Hotel | C43: Hotel — Suburban/Airport | D43: 107 | F43: 0.6 | H43: 0.15 | J43: 360 | N43: No Valet / TAM = $0 | O43: Hotel has no valet (rate field: 'No Valet'). Auto-class: not downtown (by flag or name). Qualitative pipeline only.
A44: AC Hotel Phoenix Downtown | B44: Hotel | C44: Hotel — Downtown Select-Service | D44: 199 | F44: 0.6 | H44: 0.25 | J44: 360 | N44: No Valet / TAM = $0 | O44: Hotel has no valet (rate field: 'No Valet'). Auto-class: downtown + select-service flag. Qualitative pipeline only.
A45: Embassy Suites by Hilton Phoenix Downtown North | B45: Hotel | C45: Hotel — Downtown Select-Service | D45: 242 | F45: 0.6 | H45: 0.25 | J45: 360 | N45: No Valet / TAM = $0 | O45: Hotel has no valet (rate field: 'No Valet'). Auto-class: downtown full-service <300 rooms. Qualitative pipeline only.
A46: Cambria Hotel Downtown Phoenix Convention Center | B46: Hotel | C46: Hotel — Downtown+Convention | D46: 127 | F46: 0.6 | H46: 0.4 | I46: 41 | J46: 360 | L46: 1249.68 | M46: 449884.8 | N46: Active TAM | O46: Auto-class: convention keyword in name. Occ 60% flat (refine w/STR).
A47: Courtyard Phoenix Downtown | B47: Hotel | C47: Hotel — Downtown Select-Service | D47: 120 | F47: 0.6 | H47: 0.25 | I47: 45 | J47: 360 | L47: 810 | M47: 291600 | N47: Active TAM | O47: Auto-class: downtown + select-service flag. Occ 60% flat (refine w/STR).
A48: Hilton Garden Inn Phoenix Downtown | B48: Hotel | C48: Hotel — Downtown Select-Service | D48: 170 | F48: 0.6 | H48: 0.25 | I48: 43 | J48: 360 | L48: 1096.5 | M48: 394740 | N48: Active TAM | O48: Auto-class: downtown full-service <300 rooms. Occ 60% flat (refine w/STR).
A49: Residence Inn by Marriott Phoenix Downtown | B49: Hotel | C49: Hotel — Downtown Select-Service | F49: 0.6 | H49: 0.25 | I49: 45 | J49: 360 | N49: Active TAM | O49: Auto-class: downtown + select-service flag. Occ 60% flat (refine w/STR).
A50: Moxy Phoenix Downtown | B50: Hotel | C50: Hotel — Downtown Select-Service | D50: 164 | F50: 0.6 | H50: 0.25 | I50: 45 | J50: 360 | L50: 1107 | M50: 398520 | N50: Active TAM | O50: Auto-class: downtown + select-service flag. Occ 60% flat (refine w/STR).
A51: Kimpton Hotel Palomar Phoenix | B51: Hotel | C51: Hotel — Downtown Select-Service | D51: 242 | F51: 0.6 | H51: 0.25 | I51: 44 | J51: 360 | L51: 1597.2 | M51: 574992 | N51: Active TAM | O51: Auto-class: downtown full-service <300 rooms. Occ 60% flat (refine w/STR).
A52: Home2 Suites by Hilton Phoenix Downtown | B52: Hotel | C52: Hotel — Downtown Select-Service | D52: 148 | F52: 0.6 | H52: 0.25 | I52: 45 | J52: 360 | L52: 999 | M52: 359640 | N52: Active TAM | O52: Auto-class: downtown + select-service flag. Occ 60% flat (refine w/STR).
A53: Renaissance Phoenix Downtown Hotel | B53: Hotel | C53: Hotel — Downtown+Convention | D53: 518 | F53: 0.6 | H53: 0.4 | I53: 42 | J53: 360 | L53: 5221.44 | M53: 1879718.4 | N53: Active TAM | O53: Auto-class: downtown + 518 rooms (>=400). Occ 60% flat (refine w/STR).
A54: Sheraton Phoenix Downtown | B54: Hotel | C54: Hotel — Downtown+Convention | D54: 1000 | F54: 0.6 | H54: 0.4 | I54: 46 | J54: 360 | L54: 11040 | M54: 3974400 | N54: Active TAM | O54: Auto-class: downtown + 1000 rooms (>=400). Occ 60% flat (refine w/STR).
A55: The Westin Phoenix Downtown | B55: Hotel | C55: Hotel — Downtown Select-Service | D55: 242 | F55: 0.6 | H55: 0.25 | I55: 45 | J55: 360 | L55: 1633.5 | M55: 588060 | N55: Active TAM | O55: Auto-class: downtown full-service <300 rooms. Occ 60% flat (refine w/STR).
A56: Hotel San Carlos | B56: Hotel | C56: Hotel — Downtown Select-Service | D56: 128 | F56: 0.6 | H56: 0.25 | J56: 360 | N56: No Valet / TAM = $0 | O56: Hotel has no valet (rate field: 'No Valet'). Auto-class: downtown full-service <300 rooms. Qualitative pipeline only.
A57: Hampton Inn & Suites Phoenix Downtown | B57: Hotel | C57: Hotel — Downtown Select-Service | D57: 210 | F57: 0.6 | H57: 0.25 | I57: 42 | J57: 360 | L57: 1323 | M57: 476280 | N57: Active TAM | O57: Auto-class: downtown + select-service flag. Occ 60% flat (refine w/STR).
A58: Hyatt Place Phoenix / Downtown | B58: Hotel | C58: Hotel — Downtown Select-Service | D58: 238 | F58: 0.6 | H58: 0.25 | I58: 44 | J58: 360 | L58: 1570.8 | M58: 565488 | N58: Active TAM | O58: Auto-class: downtown + select-service flag. Occ 60% flat (refine w/STR).
A59: FOUND:RE Phoenix Hotel | B59: Hotel | C59: Hotel — Downtown Select-Service | D59: 104 | F59: 0.6 | H59: 0.25 | I59: 45 | J59: 360 | L59: 702 | M59: 252720 | N59: Active TAM | O59: Auto-class: downtown full-service <300 rooms. Occ 60% flat (refine w/STR).
A60: Hyatt Regency Phoenix | B60: Hotel | C60: Hotel — Downtown+Convention | D60: 693 | F60: 0.6 | H60: 0.4 | I60: 44 | J60: 360 | L60: 7318.08 | M60: 2634508.8 | N60: Active TAM | O60: Auto-class: downtown + 693 rooms (>=400). Occ 60% flat (refine w/STR).
A61: Egyptian Motor Hotel BW Signature Collection | B61: Hotel | C61: Hotel — Downtown Select-Service | D61: 49 | F61: 0.6 | H61: 0.25 | J61: 360 | N61: No Valet / TAM = $0 | O61: Hotel has no valet (rate field: 'No Valet'). Auto-class: downtown full-service <300 rooms. Qualitative pipeline only.
A62: DoubleTree by Hilton Hotel Phoenix - Gilbert | B62: Hotel | C62: Hotel — Suburban/Airport | D62: 121 | F62: 0.6 | H62: 0.15 | J62: 360 | N62: No Valet / TAM = $0 | O62: Hotel has no valet (rate field: 'No Valet'). Auto-class: not downtown (by flag or name). Qualitative pipeline only.
A63: TownePlace Suites by Marriott Phoenix Glendale Sports & Entertainment District | B63: Hotel | C63: Hotel — Suburban/Airport | F63: 0.6 | H63: 0.15 | J63: 360 | N63: No Valet / TAM = $0 | O63: Hotel has no valet (rate field: 'No Valet'). Auto-class: not downtown (by flag or name). Qualitative pipeline only.
A64: SpringHill Suites by Marriott Phoenix Glendale Sports & Entertainment District | B64: Hotel | C64: Hotel — Suburban/Airport | D64: 120 | F64: 0.6 | H64: 0.15 | J64: 360 | N64: No Valet / TAM = $0 | O64: Hotel has no valet (rate field: 'No Valet'). Auto-class: not downtown (by flag or name). Qualitative pipeline only.
A65: Tru by Hilton Phoenix Glendale Westgate | B65: Hotel | C65: Hotel — Suburban/Airport | F65: 0.6 | H65: 0.15 | J65: 360 | N65: No Valet / TAM = $0 | O65: Hotel has no valet (rate field: 'No Valet'). Auto-class: not downtown (by flag or name). Qualitative pipeline only.
A66: Residence Inn by Marriott Phoenix Glendale Sports & Entertainment District | B66: Hotel | C66: Hotel — Suburban/Airport | F66: 0.6 | H66: 0.15 | J66: 360 | N66: No Valet / TAM = $0 | O66: Hotel has no valet (rate field: 'No Valet'). Auto-class: not downtown (by flag or name). Qualitative pipeline only.
A67: Hampton Inn & Suites Phoenix Glendale-Westgate | B67: Hotel | C67: Hotel — Suburban/Airport | D67: 149 | F67: 0.6 | H67: 0.15 | J67: 360 | N67: No Valet / TAM = $0 | O67: Hotel has no valet (rate field: 'No Valet'). Auto-class: not downtown (by flag or name). Qualitative pipeline only.
A68: Staybridge Suites Phoenix - Glendale Sports Dist by IHG | B68: Hotel | C68: Hotel — Suburban/Airport | D68: 116 | F68: 0.6 | H68: 0.15 | J68: 360 | N68: No Valet / TAM = $0 | O68: Hotel has no valet (rate field: 'No Valet'). Auto-class: not downtown (by flag or name). Qualitative pipeline only.
A69: Renaissance Phoenix Glendale Hotel & Conference Center | B69: Hotel | C69: Hotel — Suburban/Airport | D69: 324 | F69: 0.6 | H69: 0.15 | I69: 26 | J69: 360 | L69: 758.16 | M69: 272937.6 | N69: Active TAM | O69: Auto-class: not downtown (by flag or name). Occ 60% flat (refine w/STR).
A70: Holiday Inn Express & Suites Phoenix - Glendale Sports Dist | B70: Hotel | C70: Hotel — Suburban/Airport | D70: 96 | F70: 0.6 | H70: 0.15 | J70: 360 | N70: No Valet / TAM = $0 | O70: Hotel has no valet (rate field: 'No Valet'). Auto-class: not downtown (by flag or name). Qualitative pipeline only.
A71: Arizona Grand Resort & Spa | B71: Hotel | C71: Hotel — Resort | D71: 744 | F71: 0.6 | H71: 0.5 | J71: 360 | N71: No Valet / TAM = $0 | O71: Hotel has no valet (rate field: 'No Valet'). Auto-class: resort keyword: 'resort'. Qualitative pipeline only.
A72: Legacy Golf Resort | B72: Hotel | C72: Hotel — Resort | F72: 0.6 | H72: 0.5 | J72: 360 | N72: No Valet / TAM = $0 | O72: Hotel has no valet (rate field: 'No Valet'). Auto-class: resort keyword: 'resort'. Qualitative pipeline only.
A73: WorldMark Phoenix - South Mountain Preserve | B73: Hotel | C73: Hotel — Suburban/Airport | F73: 0.6 | H73: 0.15 | J73: 360 | N73: No Valet / TAM = $0 | O73: Hotel has no valet (rate field: 'No Valet'). Auto-class: not downtown (by flag or name). Qualitative pipeline only.
A74: The Wigwam | B74: Hotel | C74: Hotel — Suburban/Airport | D74: 331 | F74: 0.6 | H74: 0.15 | I74: 42 | J74: 360 | L74: 1251.18 | M74: 450424.8 | N74: Active TAM | O74: Auto-class: not downtown (by flag or name). Occ 60% flat (refine w/STR).
A75: Sheraton Mesa Hotel at Wrigleyville West | B75: Hotel | C75: Hotel — Suburban/Airport | D75: 180 | F75: 0.6 | H75: 0.15 | J75: 360 | N75: No Valet / TAM = $0 | O75: Hotel has no valet (rate field: 'No Valet'). Auto-class: not downtown (by flag or name). Qualitative pipeline only.
A76: Delta Hotels Phoenix Mesa | B76: Hotel | C76: Hotel — Suburban/Airport | D76: 274 | F76: 0.6 | H76: 0.15 | J76: 360 | N76: No Valet / TAM = $0 | O76: Hotel has no valet (rate field: 'No Valet'). Auto-class: not downtown (by flag or name). Qualitative pipeline only.
A77: Courtyard by Marriott Phoenix Mesa | B77: Hotel | C77: Hotel — Suburban/Airport | D77: 149 | F77: 0.6 | H77: 0.15 | J77: 360 | N77: No Valet / TAM = $0 | O77: Hotel has no valet (rate field: 'No Valet'). Auto-class: not downtown (by flag or name). Qualitative pipeline only.
A78: Four Points by Sheraton at Phoenix Mesa Gateway Airport | B78: Hotel | C78: Hotel — Suburban/Airport | D78: 134 | F78: 0.6 | H78: 0.15 | J78: 360 | N78: No Valet / TAM = $0 | O78: Hotel has no valet (rate field: 'No Valet'). Auto-class: not downtown (by flag or name). Qualitative pipeline only.
A79: DoubleTree by Hilton Phoenix Mesa | B79: Hotel | C79: Hotel — Suburban/Airport | D79: 262 | F79: 0.6 | H79: 0.15 | J79: 360 | N79: No Valet / TAM = $0 | O79: Hotel has no valet (rate field: 'No Valet'). Auto-class: not downtown (by flag or name). Qualitative pipeline only.
A80: Courtyard by Marriott Mesa at Wrigleyville West | B80: Hotel | C80: Hotel — Suburban/Airport | D80: 129 | F80: 0.6 | H80: 0.15 | J80: 360 | N80: No Valet / TAM = $0 | O80: Hotel has no valet (rate field: 'No Valet'). Auto-class: not downtown (by flag or name). Qualitative pipeline only.
A81: DoubleTree by Hilton Phoenix Midtown | B81: Hotel | C81: Hotel — Suburban/Airport | D81: 156 | F81: 0.6 | H81: 0.15 | J81: 360 | N81: No Valet / TAM = $0 | O81: Hotel has no valet (rate field: None). Auto-class: not downtown (by flag or name). Qualitative pipeline only.
A82: Rise Uptown Hotel | B82: Hotel | C82: Hotel — Suburban/Airport | F82: 0.6 | H82: 0.15 | J82: 360 | N82: No Valet / TAM = $0 | O82: Hotel has no valet (rate field: None). Auto-class: not downtown (by flag or name). Qualitative pipeline only.
A83: Home2 Suites by Hilton Phoenix Midtown | B83: Hotel | C83: Hotel — Suburban/Airport | D83: 103 | F83: 0.6 | H83: 0.15 | J83: 360 | N83: No Valet / TAM = $0 | O83: Hotel has no valet (rate field: None). Auto-class: not downtown (by flag or name). Qualitative pipeline only.
A84: The Clarendon Hotel and Spa | B84: Hotel | C84: Hotel — Resort | D84: 105 | F84: 0.6 | H84: 0.5 | J84: 360 | N84: No Valet / TAM = $0 | O84: Hotel has no valet (rate field: 'No Valet'). Auto-class: resort keyword: 'spa'. Qualitative pipeline only.
A85: Fairfield Inn & Suites Phoenix Midtown | B85: Hotel | C85: Hotel — Suburban/Airport | D85: 107 | F85: 0.6 | H85: 0.15 | J85: 360 | N85: No Valet / TAM = $0 | O85: Hotel has no valet (rate field: 'No Valet'). Auto-class: not downtown (by flag or name). Qualitative pipeline only.
A86: Hilton Garden Inn Phoenix Midtown | B86: Hotel | C86: Hotel — Suburban/Airport | D86: 156 | F86: 0.6 | H86: 0.15 | J86: 360 | N86: No Valet / TAM = $0 | O86: Hotel has no valet (rate field: None). Auto-class: not downtown (by flag or name). Qualitative pipeline only.
A87: JW Marriott Phoenix Desert Ridge Resort & Spa | B87: Hotel | C87: Hotel — Resort | D87: 950 | F87: 0.6 | H87: 0.5 | I87: 46 | J87: 360 | L87: 13110 | M87: 4719600 | N87: Active TAM | O87: Auto-class: resort keyword: 'resort'. Occ 60% flat (refine w/STR).
A88: Marriott's Canyon Villas | B88: Hotel | C88: Hotel — Suburban/Airport | D88: 252 | F88: 0.6 | H88: 0.15 | J88: 360 | N88: No Valet / TAM = $0 | O88: Hotel has no valet (rate field: 'No Valet'). Auto-class: not downtown (by flag or name). Qualitative pipeline only.
A89: Fairmont Gold Lounge | B89: Hotel | C89: Hotel — Suburban/Airport | F89: 0.6 | H89: 0.15 | J89: 360 | N89: No Valet / TAM = $0 | O89: Hotel has no valet (rate field: None). Auto-class: not downtown (by flag or name). Qualitative pipeline only.
A90: AC Hotel Scottsdale North | B90: Hotel | C90: Hotel — Suburban/Airport | D90: 165 | F90: 0.6 | H90: 0.15 | J90: 360 | N90: No Valet / TAM = $0 | O90: Hotel has no valet (rate field: 'No Valet'). Auto-class: not downtown (by flag or name). Qualitative pipeline only.
A91: Courtyard Scottsdale Old Town | B91: Hotel | C91: Hotel — Suburban/Airport | D91: 180 | F91: 0.6 | H91: 0.15 | J91: 360 | N91: No Valet / TAM = $0 | O91: Hotel has no valet (rate field: 'No Valet'). Auto-class: not downtown (by flag or name). Qualitative pipeline only.
A92: Scottsdale Marriott Old Town | B92: Hotel | C92: Hotel — Suburban/Airport | D92: 243 | F92: 0.6 | H92: 0.15 | J92: 360 | N92: No Valet / TAM = $0 | O92: Hotel has no valet (rate field: 'No Valet'). Auto-class: not downtown (by flag or name). Qualitative pipeline only.
A93: The Monarch | B93: Hotel | C93: Hotel — Suburban/Airport | D93: 194 | F93: 0.6 | H93: 0.15 | J93: 360 | N93: No Valet / TAM = $0 | O93: Hotel has no valet (rate field: 'No Valet'). Auto-class: not downtown (by flag or name). Qualitative pipeline only.
A94: Hotel Adeline, Scottsdale, a Tribute Portfolio Hotel | B94: Hotel | C94: Hotel — Suburban/Airport | D94: 213 | F94: 0.6 | H94: 0.15 | J94: 360 | N94: No Valet / TAM = $0 | O94: Hotel has no valet (rate field: 'No Valet'). Auto-class: not downtown (by flag or name). Qualitative pipeline only.
A95: Embassy Suites by Hilton Scottsdale Resort | B95: Hotel | C95: Hotel — Resort | D95: 312 | F95: 0.6 | H95: 0.5 | J95: 360 | N95: No Valet / TAM = $0 | O95: Hotel has no valet (rate field: 'No Valet'). Auto-class: resort keyword: 'resort'. Qualitative pipeline only.
A96: Senna House Hotel Scottsdale, Curio Collection by Hilton | B96: Hotel | C96: Hotel — Suburban/Airport | D96: 169 | F96: 0.6 | H96: 0.15 | I96: 40 | J96: 360 | L96: 608.4 | M96: 219024 | N96: Active TAM | O96: Auto-class: not downtown (by flag or name). Occ 60% flat (refine w/STR).
A97: The REMI Scottsdale, Autograph Collection | B97: Hotel | C97: Hotel — Suburban/Airport | F97: 0.6 | H97: 0.15 | I97: 30 | J97: 360 | N97: Active TAM | O97: Auto-class: not downtown (by flag or name). Occ 60% flat (refine w/STR).
A98: Caesars Republic Scottsdale, a Hilton Hotel | B98: Hotel | C98: Hotel — Suburban/Airport | D98: 265 | F98: 0.6 | H98: 0.15 | I98: 40 | J98: 360 | L98: 954 | M98: 343440 | N98: Active TAM | O98: Auto-class: not downtown (by flag or name). Occ 60% flat (refine w/STR).
A99: DoubleTree Resort by Hilton Paradise Valley-Scottsdale | B99: Hotel | C99: Hotel — Resort | D99: 378 | F99: 0.6 | H99: 0.5 | I99: 20 | J99: 360 | L99: 2268 | M99: 816480 | N99: Active TAM | O99: Auto-class: resort keyword: 'resort'. Occ 60% flat (refine w/STR).
A100: Home2 Suites by Hilton Scottsdale North | B100: Hotel | C100: Hotel — Suburban/Airport | D100: 130 | F100: 0.6 | H100: 0.15 | J100: 360 | N100: No Valet / TAM = $0 | O100: Hotel has no valet (rate field: None). Auto-class: not downtown (by flag or name). Qualitative pipeline only.
A101: Courtyard Scottsdale North | B101: Hotel | C101: Hotel — Suburban/Airport | D101: 153 | F101: 0.6 | H101: 0.15 | J101: 360 | N101: No Valet / TAM = $0 | O101: Hotel has no valet (rate field: 'No Valet'). Auto-class: not downtown (by flag or name). Qualitative pipeline only.
A102: Cambria Hotel Phoenix - North Scottsdale | B102: Hotel | C102: Hotel — Suburban/Airport | D102: 130 | F102: 0.6 | H102: 0.15 | J102: 360 | N102: No Valet / TAM = $0 | O102: Hotel has no valet (rate field: 'No Valet'). Auto-class: not downtown (by flag or name). Qualitative pipeline only.
A103: Great Wolf Lodge Water Park | Arizona | B103: Hotel | C103: Hotel — Suburban/Airport | F103: 0.6 | H103: 0.15 | J103: 360 | N103: No Valet / TAM = $0 | O103: Hotel has no valet (rate field: 'No Valet'). Auto-class: not downtown (by flag or name). Qualitative pipeline only.
...

Sheet TAM_Summary
A1: Phoenix — Conservative TAM Summary
A3: Account Type | B3: # Accounts | C3: TAM | D3: Status
A4: Hotel | B4: 239 | C4: 37116392 | D4: Active TAM
A5: Restaurant | B5: 8 | C5: 1913625 | D5: Active TAM
A6: Hospital | B6: 12 | C6: 0 | D6: Qualitative pipeline only
A7: Unknown | B7: 28 | C7: 0 | D7: ⚠️ Review
A8: TOTAL | B8: 287 | C8: 39030017
A10: HOTEL BREAKDOWN BY CLASS
A11: Class | B11: # Hotels | C11: Conv %
A12: Downtown+Convention | B12: 4 | C12: 0.4
A13: Downtown Select-Service | B13: 21 | C13: 0.25
A14: Resort | B14: 35 | C14: 0.5
A15: Suburban/Airport | B15: 179 | C15: 0.15
A17: RESTAURANTS WITH ACTIVE TAM
A18: Restaurant | B18: Seats | C18: TAM
A19: Maple & Ash | B19: 350 | C19: 318937.5
A20: Ocean 44 | B20: 325 | C20: 296156.25
A21: North Italia | B21: 300 | C21: 273375
A22: STK Steakhouse - Scottsdale | B22: 275 | C22: 250593.75
A23: Toca Madera Scottsdale | B23: 275 | C23: 250593.75
A24: Three Thirty Three Restaurant | B24: 200 | C24: 182250
A25: Montauk | B25: 200 | C25: 182250
A26: Diego Pops | B26: 175 | C26: 159468.75

Sheet TAM_Methodology
A1: SOPHI CONSERVATIVE TAM METHODOLOGY
A3: Replaces original RevenueForecasting formulas. Hospitals / Venues / Airports now qualitative only.
A5: HOTEL FORMULA
A6: TAM = Rooms × Occupancy × Valet Conversion (tiered) × Valet Rate × 360 days
A7: Occupancy: 60% flat across all hotels
A8: ⚠️ FLAG: Refine with STR actuals per-submarket before finalizing fundraise model
A9: Valet Conversion by archetype (auto-classified — review recommended):
A10: Downtown+Convention: 40%
A11: Downtown Select-Service: 25%
A12: Resort: 50%
A13: Suburban/Airport: 15%
A14: Operating Days: 360 (captures soft-closures / transition days)
... A35: 4. Hospital/venue/airport TAM dropped to $0 → build IU Health-benchmarked KPI proxy

Sheet WAS_Scoring_v2
A1: Account | B1: Type | C1: Downtown | D1: Rooms | E1: Valet Op (incumbent) | F1: Valet Rate | G1: Est. Annual Rev (TAM) | H1: Fit (25%) | I1: Size (25%) | J1: Owner Base (20%) | K1: Addr (15%) | L1: Adj (15%) | M1: Rel Lift | N1: Rel Tag | O1: WAS Raw | P1: WAS Final | Q1: Tier | R1: Y1 % | S1: Y2 % | T1: Y3 % | U1: Y4 % | V1: Y5 % | W1: Y1 Rev | X1: Y2 Rev | Y1: Y3 Rev | Z1: Y4 Rev | AA1: Y5 Rev
A2: Kenect Phoenix | B2: Apartment | C2: YES | D2: 0 | F2: No Valet | G2: 0 | H2: 2 | I2: 1 | J2: 2 | K2: 4 | L2: 4 | M2: 0 | O2: 2.35 | P2: 2.35 | Q2: D — Deprioritized | R2: 0 | S2: 0.018 | T2: 0.055 | U2: 0.082 | V2: 0.1 | W2: 0 | X2: 0 | Y2: 0 | Z2: 0 | AA2: 0
A3: Sentral Sol Modern | B3: Apartment/Hotel | C3: YES | D3: 0 | F3: No Valet | G3: 0 | H3: 2 | I3: 1 | J3: 2 | K3: 4 | L3: 4 | M3: 0 | O3: 2.35 | P3: 2.35 | Q3: D — Deprioritized | R3: 0 | S3: 0.018 | T3: 0.055 | U3: 0.082 | V3: 0.1 | W3: 0 | X3: 0 | Y3: 0 | Z3: 0 | AA3: 0
A4: Sentral Alloy Midtown | B4: Apartment/Hotel | C4: NO | D4: 0 | F4: No Valet | G4: 0 | H4: 2 | I4: 1 | J4: 2 | K4: 4 | L4: 2 | M4: 0 | O4: 2.05 | P4: 2.05 | Q4: D — Deprioritized | R4: 0 | S4: 0.018 | T4: 0.055 | U4: 0.082 | V4: 0.1 | W4: 0 | X4: 0 | Y4: 0 | Z4: 0 | AA4: 0
A5: Chateau Luxe Event Venue | B5: Event | C5: NO | D5: 0 | G5: 0 | H5: 2 | I5: 1 | J5: 2 | K5: 4 | L5: 2 | M5: 0 | O5: 2.05 | P5: 2.05 | Q5: D — Deprioritized | R5: 0 | S5: 0.018 | T5: 0.055 | U5: 0.082 | V5: 0.1 | W5: 0 | X5: 0 | Y5: 0 | Z5: 0 | AA5: 0
A6: Warehouse215 | B6: Event | C6: YES | D6: 0 | G6: 0 | H6: 2 | I6: 1 | J6: 2 | K6: 4 | L6: 4 | M6: 0 | O6: 2.35 | P6: 2.35 | Q6: D — Deprioritized | R6: 0 | S6: 0.018 | T6: 0.055 | U6: 0.082 | V6: 0.1 | W6: 0 | X6: 0 | Y6: 0 | Z6: 0 | AA6: 0
A7: 435 Collective | B7: Event | C7: YES | D7: 0 | G7: 0 | H7: 2 | I7: 1 | J7: 2 | K7: 4 | L7: 4 | M7: 0 | O7: 2.35 | P7: 2.35 | Q7: D — Deprioritized | R7: 0 | S7: 0.018 | T7: 0.055 | U7: 0.082 | V7: 0.1 | W7: 0 | X7: 0 | Y7: 0 | Z7: 0 | AA7: 0
A8: The Boho Space | B8: Event | C8: NO | D8: 0 | G8: 0 | H8: 2 | I8: 1 | J8: 2 | K8: 4 | L8: 2 | M8: 0 | O8: 2.05 | P8: 2.05 | Q8: D — Deprioritized | R8: 0 | S8: 0.018 | T8: 0.055 | U8: 0.082 | V8: 0.1 | W8: 0 | X8: 0 | Y8: 0 | Z8: 0 | AA8: 0
A9: The Teapot | B9: Event | C9: NO | D9: 0 | G9: 0 | H9: 2 | I9: 1 | J9: 2 | K9: 4 | L9: 2 | M9: 0 | O9: 2.05 | P9: 2.05 | Q9: D — Deprioritized | R9: 0 | S9: 0.018 | T9: 0.055 | U9: 0.082 | V9: 0.1 | W9: 0 | X9: 0 | Y9: 0 | Z9: 0 | AA9: 0
A10: monOrchid | B10: Event | C10: YES | D10: 0 | G10: 0 | H10: 2 | I10: 1 | J10: 2 | K10: 4 | L10: 4 | M10: 0 | O10: 2.35 | P10: 2.35 | Q10: D — Deprioritized | R10: 0 | S10: 0.018 | T10: 0.055 | U10: 0.082 | V10: 0.1 | W10: 0 | X10: 0 | Y10: 0 | Z10: 0 | AA10: 0
A11: The Dauz Venue | B11: Event | C11: YES | D11: 0 | G11: 0 | H11: 2 | I11: 1 | J11: 2 | K11: 4 | L11: 4 | M11: 0 | O11: 2.35 | P11: 2.35 | Q11: D — Deprioritized | R11: 0 | S11: 0.018 | T11: 0.055 | U11: 0.082 | V11: 0.1 | W11: 0 | X11: 0 | Y11: 0 | Z11: 0 | AA11: 0
A12: Antigua Garden | B12: Event | C12: YES | D12: 0 | G12: 0 | H12: 2 | I12: 1 | J12: 2 | K12: 4 | L12: 4 | M12: 0 | O12: 2.35 | P12: 2.35 | Q12: D — Deprioritized | R12: 0 | S12: 0.018 | T12: 0.055 | U12: 0.082 | V12: 0.1 | W12: 0 | X12: 0 | Y12: 0 | Z12: 0 | AA12: 0
A13: The Icehouse | B13: Event | C13: YES | D13: 0 | G13: 0 | H13: 2 | I13: 1 | J13: 2 | K13: 4 | L13: 4 | M13: 0 | O13: 2.35 | P13: 2.35 | Q13: D — Deprioritized | R13: 0 | S13: 0.018 | T13: 0.055 | U13: 0.082 | V13: 0.1 | W13: 0 | X13: 0 | Y13: 0 | Z13: 0 | AA13: 0
A14: Encanto 18 | B14: Event | C14: YES | D14: 0 | G14: 0 | H14: 2 | I14: 1 | J14: 2 | K14: 4 | L14: 4 | M14: 0 | O14: 2.35 | P14: 2.35 | Q14: D — Deprioritized | R14: 0 | S14: 0.018 | T14: 0.055 | U14: 0.082 | V14: 0.1 | W14: 0 | X14: 0 | Y14: 0 | Z14: 0 | AA14: 0
A15: The Duce | B15: Event | C15: YES | D15: 0 | G15: 0 | H15: 2 | I15: 1 | J15: 2 | K15: 4 | L15: 4 | M15: 0 | O15: 2.35 | P15: 2.35 | Q15: D — Deprioritized | R15: 0 | S15: 0.018 | T15: 0.055 | U15: 0.082 | V15: 0.1 | W15: 0 | X15: 0 | Y15: 0 | Z15: 0 | AA15: 0
A16: Wedgewood Weddings | B16: Event | C16: NO | D16: 0 | G16: 0 | H16: 2 | I16: 1 | J16: 2 | K16: 4 | L16: 2 | M16: 0 | O16: 2.05 | P16: 2.05 | Q16: D — Deprioritized | R16: 0 | S16: 0.018 | T16: 0.055 | U16: 0.082 | V16: 0.1 | W16: 0 | X16: 0 | Y16: 0 | Z16: 0 | AA16: 0
... A32: Carter Concepts Restaurant Group | B32: Hospitality Group | C32: NO | D32: 0 | G32: 0 | H32: 3 | I32: 1 | J32: 2 | K32: 4 | L32: 2 | M32: 0 | O32: 2.3 | P32: 2.3 | Q32: D — Deprioritized | R32: 0 | S32: 0.018 | T32: 0.055 | U32: 0.082 | V32: 0.1 | W32: 0 | X32: 0 | Y32: 0 | Z32: 0 | AA32: 0
A33: Courtyard Phoenix Airport | B33: Hotel | C33: NO | D33: 145 | F33: No Valet | G33: 0 | H33: 3 | I33: 1 | J33: 3 | K33: 4 | L33: 2 | M33: 0 | O33: 2.5 | P33: 2.5 | Q33: C — Opportunistic | R33: 0.02 | S33: 0.09724 | T33: 0.28625 | U33: 0.4145 | V33: 0.5 | W33: 0 | X33: 0 | Y33: 0 | Z33: 0 | AA33: 0
A34: Hilton Phoenix Airport | B34: Hotel | C34: NO | D34: 259 | F34: No Valet | G34: 0 | H34: 4 | I34: 1 | J34: 3 | K34: 4 | L34: 2 | M34: 0.15 | N34: Brand familiarity (historical): Hilton_family | O34: 2.75 | P34: 2.9 | Q34: C — Opportunistic | R34: 0.02 | S34: 0.09724 | T34: 0.28625 | U34: 0.4145 | V34: 0.5 | W34: 0 | X34: 0 | Y34: 0 | Z34: 0 | AA34: 0
A35: Marriott Phoenix Airport | B35: Hotel | C35: NO | D35: 347 | F35: No Valet | G35: 0 | H35: 4 | I35: 1 | J35: 3 | K35: 4 | L35: 2 | M35: 0.3 | N35: Brand familiarity (current): Marriott_family | O35: 2.75 | P35: 3.05 | Q35: C — Opportunistic | R35: 0.02 | S35: 0.09724 | T35: 0.28625 | U35: 0.4145 | V35: 0.5 | W35: 0 | X35: 0 | Y35: 0 | Z35: 0 | AA35: 0
A36: Arizona Biltmore, LXR Hotels & Resorts | B36: Hotel | C36: NO | D36: 750 | F36: valet only | G36: 2430000 | H36: 5 | I36: 4 | J36: 2 | K36: 4 | L36: 2 | M36: 0.15 | N36: Brand familiarity (historical): Hilton_family | O36: 3.55 | P36: 3.7 | Q36: B — Core | R36: 0.08 | S36: 0.22066 | T36: 0.560625 | U36: 0.78675 | V36: 0.9375 | W36: 194400 | X36: 536203.8 | Y36: 1362318.8 | Z36: 1911802.5 | AA36: 2278125
A37: Embassy Suites by Hilton Phoenix Biltmore | B37: Hotel | C37: NO | D37: 232 | F37: No Valet | G37: 0 | H37: 3 | I37: 1 | J37: 3 | K37: 4 | L37: 2 | M37: 0.15 | N37: Brand familiarity (historical): Hilton_family | O37: 2.5 | P37: 2.65 | Q37: C — Opportunistic | R37: 0.02 | S37: 0.09724 | T37: 0.28625 | U37: 0.4145 | V37: 0.5 | W37: 0 | X37: 0 | Y37: 0 | Z37: 0 | AA37: 0
A38: Hampton Inn Phoenix-Biltmore | B38: Hotel | C38: NO | D38: 121 | G38: 0 | H38: 3 | I38: 1 | J38: 3 | K38: 4 | L38: 2 | M38: 0.15 | N38: Brand familiarity (historical): Hilton_family | O38: 2.5 | P38: 2.65 | Q38: C — Opportunistic | R38: 0.02 | S38: 0.09724 | T38: 0.28625 | U38: 0.4145 | V38: 0.5 | W38: 0 | X38: 0 | Y38: 0 | Z38: 0 | AA38: 0
A39: The Camby, Autograph Collection | B39: Hotel | C39: NO | D39: 279 | F39: 40 | G39: 361584 | H39: 4 | I39: 2 | J39: 3 | K39: 4 | L39: 2 | M39: 0.3 | N39: Brand familiarity (current): Marriott_family | O39: 3 | P39: 3.3 | Q39: C — Opportunistic | R39: 0.02 | S39: 0.09724 | T39: 0.28625 | U39: 0.4145 | V39: 0.5 | W39: 7231.68 | X39: 35160.428 | Y39: 103503.42 | Z39: 149876.57 | AA39: 180792
A40: AC Hotel Phoenix Biltmore | B40: Hotel | C40: NO | D40: 160 | F40: No Valet | G40: 0 | H40: 3 | I40: 1 | J40: 2 | K40: 4 | L40: 2 | M40: 0 | O40: 2.3 | P40: 2.3 | Q40: D — Deprioritized | R40: 0 | S40: 0.018 | T40: 0.055 | U40: 0.082 | V40: 0.1 | W40: 0 | X40: 0 | Y40: 0 | Z40: 0 | AA40: 0
A41: Sonesta Select Phoenix Camelback | B41: Hotel | C41: NO | D41: 155 | G41: 0 | H41: 3 | I41: 1 | J41: 2 | K41: 4 | L41: 2 | M41: 0 | O41: 2.3 | P41: 2.3 | Q41: D — Deprioritized | R41: 0 | S41: 0.018 | T41: 0.055 | U41: 0.082 | V41: 0.1 | W41: 0 | X41: 0 | Y41: 0 | Z41: 0 | AA41: 0
A42: Hilton Garden Inn Chandler Downtown | B42: Hotel | C42: NO | D42: 110 | F42: No Valet | G42: 0 | H42: 3 | I42: 1 | J42: 3 | K42: 4 | L42: 2 | M42: 0.15 | N42: Brand familiarity (historical): Hilton_family | O42: 2.5 | P42: 2.65 | Q42: C — Opportunistic | R42: 0.02 | S42: 0.09724 | T42: 0.28625 | U42: 0.4145 | V42: 0.5 | W42: 0 | X42: 0 | Y42: 0 | Z42: 0 | AA42: 0
A43: Element Chandler Fashion Center | B43: Hotel | C43: NO | D43: 107 | F43: No Valet | G43: 0 | H43: 3 | I43: 1 | J43: 2 | K43: 4 | L43: 2 | M43: 0 | O43: 2.3 | P43: 2.3 | Q43: D — Deprioritized | R43: 0 | S43: 0.018 | T43: 0.055 | U43: 0.082 | V43: 0.1 | W43: 0 | X43: 0 | Y43: 0 | Z43: 0 | AA43: 0
A44: AC Hotel Phoenix Downtown | B44: Hotel | C44: YES | D44: 199 | F44: No Valet | G44: 0 | H44: 4 | I44: 1 | J44: 2 | K44: 4 | L44: 4 | M44: 0 | O44: 2.85 | P44: 2.85 | Q44: C — Opportunistic | R44: 0.02 | S44: 0.09724 | T44: 0.28625 | U44: 0.4145 | V44: 0.5 | W44: 0 | X44: 0 | Y44: 0 | Z44: 0 | AA44: 0
A45: Embassy Suites by Hilton Phoenix Downtown North | B45: Hotel | C45: YES | D45: 242 | F45: No Valet | G45: 0 | H45: 4 | I45: 1 | J45: 3 | K45: 4 | L45: 4 | M45: 0.15 | N45: Brand familiarity (historical): Hilton_family | O45: 3.05 | P45: 3.2 | Q45: C — Opportunistic | R45: 0.02 | S45: 0.09724 | T45: 0.28625 | U45: 0.4145 | V45: 0.5 | W45: 0 | X45: 0 | Y45: 0 | Z45: 0 | AA45: 0
A46: Cambria Hotel Downtown Phoenix Convention Center | B46: Hotel | C46: YES | D46: 127 | E46: Premium Parking | F46: 41 | G46: 449884.8 | H46: 3 | I46: 2 | J46: 2 | K46: 3 | L46: 4 | M46: 0 | O46: 2.7 | P46: 2.7 | Q46: C — Opportunistic | R46: 0.02 | S46: 0.09724 | T46: 0.28625 | U46: 0.4145 | V46: 0.5 | W46: 8997.696 | X46: 43746.798 | Y46: 128779.52 | Z46: 186477.25 | AA46: 224942.4
A47: Courtyard Phoenix Downtown | B47: Hotel | C47: YES | D47: 120 | E47: Laz | F47: 45 | G47: 291600 | H47: 3 | I47: 2 | J47: 3 | K47: 2 | L47: 4 | M47: 0 | O47: 2.75 | P47: 2.75 | Q47: C — Opportunistic | R47: 0.02 | S47: 0.09724 | T47: 0.28625 | U47: 0.4145 | V47: 0.5 | W47: 5832 | X47: 28355.184 | Y47: 83470.5 | Z47: 120868.2 | AA47: 145800
A48: Hilton Garden Inn Phoenix Downtown | B48: Hotel | C48: YES | D48: 170 | F48: 43 | G48: 394740 | H48: 4 | I48: 2 | J48: 3 | K48: 4 | L48: 4 | M48: 0.15 | N48: Brand familiarity (historical): Hilton_family | O48: 3.3 | P48: 3.45 | Q48: C — Opportunistic | R48: 0.02 | S48: 0.09724 | T48: 0.28625 | U48: 0.4145 | V48: 0.5 | W48: 7894.8 | X48: 38384.518 | Y48: 112994.32 | Z48: 163619.73 | AA48: 197370
A49: Residence Inn by Marriott Phoenix Downtown | B49: Hotel | C49: YES | D49: 0 | E49: Laz | F49: 45 | G49: 0 | H49: 2 | I49: 1 | J49: 3 | K49: 2 | L49: 4 | M49: 0.3 | N49: Brand familiarity (current): Marriott_family | O49: 2.25 | P49: 2.55 | Q49: C — Opportunistic | R49: 0.02 | S49: 0.09724 | T49: 0.28625 | U49: 0.4145 | V49: 0.5 | W49: 0 | X49: 0 | Y49: 0 | Z49: 0 | AA49: 0
A50: Moxy Phoenix Downtown | B50: Hotel | C50: YES | D50: 164 | F50: 45 | G50: 398520 | H50: 4 | I50: 2 | J50: 2 | K50: 4 | L50: 4 | M50: 0 | O50: 3.1 | P50: 3.1 | Q50: C — Opportunistic | R50: 0.02 | S50: 0.09724 | T50: 0.28625 | U50: 0.4145 | V50: 0.5 | W50: 7970.4 | X50: 38752.085 | Y50: 114076.35 | Z50: 165186.54 | AA50: 199260
A51: Kimpton Hotel Palomar Phoenix | B51: Hotel | C51: YES | D51: 242 | F51: 44 | G51: 574992 | H51: 4 | I51: 2 | J51: 3 | K51: 4 | L51: 4 | M51: 0 | O51: 3.3 | P51: 3.3 | Q51: C — Opportunistic | R51: 0.02 | S51: 0.09724 | T51: 0.28625 | U51: 0.4145 | V51: 0.5 | W51: 11499.84 | X51: 55912.222 | Y51: 164591.46 | Z51: 238334.18 | AA51: 287496
A52: Home2 Suites by Hilton Phoenix Downtown | B52: Hotel | C52: YES | D52: 148 | F52: 45 | G52: 359640 | H52: 3 | I52: 2 | J52: 3 | K52: 4 | L52: 4 | M52: 0.15 | N52: Brand familiarity (historical): Hilton_family | O52: 3.05 | P52: 3.2 | Q52: C — Opportunistic | R52: 0.02 | S52: 0.09724 | T52: 0.28625 | U52: 0.4145 | V52: 0.5 | W52: 7192.8 | X52: 34971.394 | Y52: 102946.95 | Z52: 149070.78 | AA52: 179820
A53: Renaissance Phoenix Downtown Hotel | B53: Hotel | C53: YES | D53: 518 | E53: TownePark | F53: 42 | G53: 1879718.4 | H53: 5 | I53: 4 | J53: 3 | K53: 3 | L53: 4 | M53: 0.3 | N53: Brand familiarity (current): Marriott_family | O53: 3.9 | P53: 4.2 | Q53: B — Core | R53: 0.08 | S53: 0.22066 | T53: 0.560625 | U53: 0.78675 | V53: 0.9375 | W53: 150377.47 | X53: 414778.66 | Y53: 1053817.1 | Z53: 1478868.5 | AA53: 1762236
A54: Sheraton Phoenix Downtown | B54: Hotel | C54: YES | D54: 1000 | E54: TownePark | F54: 46 | G54: 3974400 | H54: 5 | I54: 5 | J54: 3 | K54: 3 | L54: 4 | M54: 0.3 | N54: Brand familiarity (current): Marriott_family | O54: 4.15 | P54: 4.45 | Q54: B — Core | R54: 0.08 | S54: 0.22066 | T54: 0.560625 | U54: 0.78675 | V54: 0.9375 | W54: 317952 | X54: 876991.1 | Y54: 2228148 | Z54: 3126859.2 | AA54: 3726000
A55: The Westin Phoenix Downtown | B55: Hotel | C55: YES | D55: 242 | F55: 45 | G55: 588060 | H55: 4 | I55: 2 | J55: 3 | K55: 4 | L55: 4 | M55: 0.3 | N55: Brand familiarity (current): Marriott_family | O55: 3.3 | P55: 3.6 | Q55: B — Core | R55: 0.08 | S55: 0.22066 | T55: 0.560625 | U55: 0.78675 | V55: 0.9375 | W55: 47044.8 | X55: 129761.32 | Y55: 329681.14 | Z55: 462656.2 | AA55: 551306.25
A56: Hotel San Carlos | B56: Hotel | C56: YES | D56: 128 | F56: No Valet | G56: 0 | H56: 3 | I56: 1 | J56: 2 | K56: 4 | L56: 4 | M56: 0 | O56: 2.6 | P56: 2.6 | Q56: C — Opportunistic | R56: 0.02 | S56: 0.09724 | T56: 0.28625 | U56: 0.4145 | V56: 0.5 | W56: 0 | X56: 0 | Y56: 0 | Z56: 0 | AA56: 0
A57: Hampton Inn & Suites Phoenix Downtown | B57: Hotel | C57: YES | D57: 210 | F57: 42 | G57: 476280 | H57: 4 | I57: 2 | J57: 3 | K57: 4 | L57: 4 | M57: 0.15 | N57: Brand familiarity (historical): Hilton_family | O57: 3.3 | P57: 3.45 | Q57: C — Opportunistic | R57: 0.02 | S57: 0.09724 | T57: 0.28625 | U57: 0.4145 | V57: 0.5 | W57: 9525.6 | X57: 46313.467 | Y57: 136335.15 | Z57: 197418.06 | AA57: 238140
A58: Hyatt Place Phoenix / Downtown | B58: Hotel | C58: YES | D58: 238 | F58: 44 | G58: 565488 | H58: 4 | I58: 2 | J58: 3 | K58: 4 | L58: 4 | M58: 0 | O58: 3.3 | P58: 3.3 | Q58: C — Opportunistic | R58: 0.02 | S58: 0.09724 | T58: 0.28625 | U58: 0.4145 | V58: 0.5 | W58: 11309.76 | X58: 54988.053 | Y58: 161870.94 | Z58: 234394.78 | AA58: 282744
A59: FOUND:RE Phoenix Hotel | B59: Hotel | C59: YES | D59: 104 | F59: 45 | G59: 252720 | H59: 3 | I59: 2 | J59: 2 | K59: 4 | L59: 4 | M59: 0 | O59: 2.85 | P59: 2.85 | Q59: C — Opportunistic | R59: 0.02 | S59: 0.09724 | T59: 0.28625 | U59: 0.4145 | V59: 0.5 | W59: 5054.4 | X59: 24574.493 | Y59: 72341.1 | Z59: 104752.44 | AA59: 126360
A60: Hyatt Regency Phoenix | B60: Hotel | C60: YES | D60: 693 | F60: 44 | G60: 2634508.8 | H60: 5 | I60: 5 | J60: 3 | K60: 4 | L60: 4 | M60: 0 | O60: 4.3 | P60: 4.3 | Q60: B — Core | R60: 0.08 | S60: 0.22066 | T60: 0.560625 | U60: 0.78675 | V60: 0.9375 | W60: 210760.7 | X60: 581330.71 | Y60: 1476971.5 | Z60: 2072699.8 | AA60: 2469852
A61: Egyptian Motor Hotel BW Signature Collection | B61: Hotel | C61: YES | D61: 49 | F61: No Valet | G61: 0 | H61: 2 | I61: 1 | J61: 2 | K61: 4 | L61: 4 | M61: 0 | O61: 2.35 | P61: 2.35 | Q61: D — Deprioritized | R61: 0 | S61: 0.018 | T61: 0.055 | U61: 0.082 | V61: 0.1 | W61: 0 | X61: 0 | Y61: 0 | Z61: 0 | AA61: 0
A62: DoubleTree by Hilton Hotel Phoenix - Gilbert | B62: Hotel | C62: NO | D62: 121 | F62: No Valet | G62: 0 | H62: 3 | I62: 1 | J62: 3 | K62: 4 | L62: 2 | M62: 0.15 | N62: Brand familiarity (historical): Hilton_family | O62: 2.5 | P62: 2.65 | Q62: C — Opportunistic | R62: 0.02 | S62: 0.09724 | T62: 0.28625 | U62: 0.4145 | V62: 0.5 | W62: 0 | X62: 0 | Y62: 0 | Z62: 0 | AA62: 0
A63: TownePlace Suites by Marriott Phoenix Glendale Sports & Entertainment District | B63: Hotel | C63: NO | D63: 0 | F63: No Valet | G63: 0 | H63: 2 | I63: 1 | J63: 3 | K63: 4 | L63: 2 | M63: 0.3 | N63: Brand familiarity (current): Marriott_family | O63: 2.25 | P63: 2.55 | Q63: C — Opportunistic | R63: 0.02 | S63: 0.09724 | T63: 0.28625 | U63: 0.4145 | V63: 0.5 | W63: 0 | X63: 0 | Y63: 0 | Z63: 0 | AA63: 0
A64: SpringHill Suites by Marriott Phoenix Glendale Sports & Entertainment District | B64: Hotel | C64: NO | D64: 120 | F64: No Valet | G64: 0 | H64: 3 | I64: 1 | J64: 3 | K64: 4 | L64: 2 | M64: 0.3 | N64: Brand familiarity (current): Marriott_family | O64: 2.5 | P64: 2.8 | Q64: C — Opportunistic | R64: 0.02 | S64: 0.09724 | T64: 0.28625 | U64: 0.4145 | V64: 0.5 | W64: 0 | X64: 0 | Y64: 0 | Z64: 0 | AA64: 0
A65: Tru by Hilton Phoenix Glendale Westgate | B65: Hotel | C65: NO | D65: 0 | F65: No Valet | G65: 0 | H65: 2 | I65: 1 | J65: 3 | K65: 4 | L65: 2 | M65: 0.15 | N65: Brand familiarity (historical): Hilton_family | O65: 2.25 | P65: 2.4 | Q65: D — Deprioritized | R65: 0 | S65: 0.018 | T65: 0.055 | U65: 0.082 | V65: 0.1 | W65: 0 | X65: 0 | Y65: 0 | Z65: 0 | AA65: 0
A66: Residence Inn by Marriott Phoenix Glendale Sports & Entertainment District | B66: Hotel | C66: NO | D66: 0 | F66: No Valet | G66: 0 | H66: 2 | I66: 1 | J66: 3 | K66: 4 | L66: 2 | M66: 0.3 | N66: Brand familiarity (current): Marriott_family | O66: 2.25 | P66: 2.55 | Q66: C — Opportunistic | R66: 0.02 | S66: 0.09724 | T66: 0.28625 | U66: 0.4145 | V66: 0.5 | W66: 0 | X66: 0 | Y66: 0 | Z66: 0 | AA66: 0
A67: Hampton Inn & Suites Phoenix Glendale-Westgate | B67: Hotel | C67: NO | D67: 149 | F67: No Valet | G67: 0 | H67: 3 | I67: 1 | J67: 3 | K67: 4 | L67: 2 | M67: 0.15 | N67: Brand familiarity (historical): Hilton_family | O67: 2.5 | P67: 2.65 | Q67: C — Opportunistic | R67: 0.02 | S67: 0.09724 | T67: 0.28625 | U67: 0.4145 | V67: 0.5 | W67: 0 | X67: 0 | Y67: 0 | Z67: 0 | AA67: 0
A68: Staybridge Suites Phoenix - Glendale Sports Dist by IHG | B68: Hotel | C68: NO | D68: 116 | F68: No Valet | G68: 0 | H68: 3 | I68: 1 | J68: 3 | K68: 4 | L68: 2 | M68: 0 | O68: 2.5 | P68: 2.5 | Q68: C — Opportunistic | R68: 0.02 | S68: 0.09724 | T68: 0.28625 | U68: 0.4145 | V68: 0.5 | W68: 0 | X68: 0 | Y68: 0 | Z68: 0 | AA68: 0
A69: Renaissance Phoenix Glendale Hotel & Conference Center | B69: Hotel | C69: NO | D69: 324 | F69: 26 | G69: 272937.6 | H69: 4 | I69: 2 | J69: 3 | K69: 4 | L69: 2 | M69: 0.3 | N69: Brand familiarity (current): Marriott_family | O69: 3 | P69: 3.3 | Q69: C — Opportunistic | R69: 0.02 | S69: 0.09724 | T69: 0.28625 | U69: 0.4145 | V69: 0.5 | W69: 5458.752 | X69: 26540.452 | Y69: 78128.388 | Z69: 113132.64 | AA69: 136468.8
A70: Holiday Inn Express & Suites Phoenix - Glendale Sports Dist | B70: Hotel | C70: NO | D70: 96 | F70: No Valet | G70: 0 | H70: 2 | I70: 1 | J70: 3 | K70: 4 | L70: 2 | M70: 0 | O70: 2.25 | P70: 2.25 | Q70: D — Deprioritized | R70: 0 | S70: 0.018 | T70: 0.055 | U70: 0.082 | V70: 0.1 | W70: 0 | X70: 0 | Y70: 0 | Z70: 0 | AA70: 0
A71: Arizona Grand Resort & Spa | B71: Hotel | C71: NO | D71: 744 | F71: No Valet | G71: 0 | H71: 5 | I71: 1 | J71: 2 | K71: 4 | L71: 2 | M71: 0 | O71: 2.8 | P71: 2.8 | Q71: C — Opportunistic | R71: 0.02 | S71: 0.09724 | T71: 0.28625 | U71: 0.4145 | V71: 0.5 | W71: 0 | X71: 0 | Y71: 0 | Z71: 0 | AA71: 0
A72: Legacy Golf Resort | B72: Hotel | C72: NO | D72: 0 | F72: No Valet | G72: 0 | H72: 2 | I72: 1 | J72: 2 | K72: 4 | L72: 2 | M72: 0 | O72: 2.05 | P72: 2.05 | Q72: D — Deprioritized | R72: 0 | S72: 0.018 | T72: 0.055 | U72: 0.082 | V72: 0.1 | W72: 0 | X72: 0 | Y72: 0 | Z72: 0 | AA72: 0
A73: WorldMark Phoenix - South Mountain Preserve | B73: Hotel | C73: NO | D73: 0 | F73: No Valet | G73: 0 | H73: 2 | I73: 1 | J73: 2 | K73: 4 | L73: 2 | M73: 0 | O73: 2.05 | P73: 2.05 | Q73: D — Deprioritized | R73: 0 | S73: 0.018 | T73: 0.055 | U73: 0.082 | V73: 0.1 | W73: 0 | X73: 0 | Y73: 0 | Z73: 0 | AA73: 0
A74: The Wigwam | B74: Hotel | C74: NO | D74: 331 | F74: 42 | G74: 450424.8 | H74: 4 | I74: 2 | J74: 2 | K74: 4 | L74: 2 | M74: 0 | O74: 2.8 | P74: 2.8 | Q74: C — Opportunistic | R74: 0.02 | S74: 0.09724 | T74: 0.28625 | U74: 0.4145 | V74: 0.5 | W74: 9008.496 | X74: 43799.308 | Y74: 128934.1 | Z74: 186701.08 | AA74: 225212.4
A75: Sheraton Mesa Hotel at Wrigleyville West | B75: Hotel | C75: NO | D75: 180 | F75: No Valet | G75: 0 | H75: 3 | I75: 1 | J75: 3 | K75: 4 | L75: 2 | M75: 0.3 | N75: Brand familiarity (current): Marriott_family | O75: 2.5 | P75: 2.8 | Q75: C — Opportunistic | R75: 0.02 | S75: 0.09724 | T75: 0.28625 | U75: 0.4145 | V75: 0.5 | W75: 0 | X75: 0 | Y75: 0 | Z75: 0 | AA75: 0
A76: Delta Hotels Phoenix Mesa | B76: Hotel | C76: NO | D76: 274 | F76: No Valet | G76: 0 | H76: 4 | I76: 1 | J76: 2 | K76: 4 | L76: 2 | M76: 0.3 | N76: Brand familiarity (current): Marriott_family | O76: 2.55 | P76: 2.85 | Q76: C — Opportunistic | R76: 0.02 | S76: 0.09724 | T76: 0.28625 | U76: 0.4145 | V76: 0.5 | W76: 0 | X76: 0 | Y76: 0 | Z76: 0 | AA76: 0
A77: Courtyard by Marriott Phoenix Mesa | B77: Hotel | C77: NO | D77: 149 | F77: No Valet | G77: 0 | H77: 3 | I77: 1 | J77: 3 | K77: 4 | L77: 2 | M77: 0.3 | N77: Brand familiarity (current): Marriott_family | O77: 2.5 | P77: 2.8 | Q77: C — Opportunistic | R77: 0.02 | S77: 0.09724 | T77: 0.28625 | U77: 0.4145 | V77: 0.5 | W77: 0 | X77: 0 | Y77: 0 | Z77: 0 | AA77: 0
A78: Four Points by Sheraton at Phoenix Mesa Gateway Airport | B78: Hotel | C78: NO | D78: 134 | F78: No Valet | G78: 0 | H78: 3 | I78: 1 | J78: 3 | K78: 4 | L78: 2 | M78: 0.3 | N78: Brand familiarity (current): Marriott_family | O78: 2.5 | P78: 2.8 | Q78: C — Opportunistic | R78: 0.02 | S78: 0.09724 | T78: 0.28625 | U78: 0.4145 | V78: 0.5 | W78: 0 | X78: 0 | Y78: 0 | Z78: 0 | AA78: 0
A79: DoubleTree by Hilton Phoenix Mesa | B79: Hotel | C79: NO | D79: 262 | F79: No Valet | G79: 0 | H79: 4 | I79: 1 | J79: 3 | K79: 4 | L79: 2 | M79: 0.15 | N79: Brand familiarity (historical): Hilton_family | O79: 2.75 | P79: 2.9 | Q79: C — Opportunistic | R79: 0.02 | S79: 0.09724 | T79: 0.28625 | U79: 0.4145 | V79: 0.5 | W79: 0 | X79: 0 | Y79: 0 | Z79: 0 | AA79: 0
A80: Courtyard by Marriott Mesa at Wrigleyville West | B80: Hotel | C80: NO | D80: 129 | F80: No Valet | G80: 0 | H80: 3 | I80: 1 | J80: 3 | K80: 4 | L80: 2 | M80: 0.3 | N80: Brand familiarity (current): Marriott_family | O80: 2.5 | P80: 2.8 | Q80: C — Opportunistic | R80: 0.02 | S80: 0.09724 | T80: 0.28625 | U80: 0.4145 | V80: 0.5 | W80: 0 | X80: 0 | Y80: 0 | Z80: 0 | AA80: 0
A81: DoubleTree by Hilton Phoenix Midtown | B81: Hotel | C81: NO | D81: 156 | G81: 0 | H81: 3 | I81: 1 | J81: 3 | K81: 4 | L81: 2 | M81: 0.15 | N81: Brand familiarity (historical): Hilton_family | O81: 2.5 | P81: 2.65 | Q81: C — Opportunistic | R81: 0.02 | S81: 0.09724 | T81: 0.28625 | U81: 0.4145 | V81: 0.5 | W81: 0 | X81: 0 | Y81: 0 | Z81: 0 | AA81: 0
A82: Rise Uptown Hotel | B82: Hotel | C82: NO | D82: 0 | G82: 0 | H82: 2 | I82: 1 | J82: 2 | K82: 4 | L82: 2 | M82: 0 | O82: 2.05 | P82: 2.05 | Q82: D — Deprioritized | R82: 0 | S82: 0.018 | T82: 0.055 | U82: 0.082 | V82: 0.1 | W82: 0 | X82: 0 | Y82: 0 | Z82: 0 | AA82: 0
A83: Home2 Suites by Hilton Phoenix Midtown | B83: Hotel | C83: NO | D83: 103 | G83: 0 | H83: 3 | I83: 1 | J83: 3 | K83: 4 | L83: 2 | M83: 0.15 | N83: Brand familiarity (historical): Hilton_family | O83: 2.5 | P83: 2.65 | Q83: C — Opportunistic | R83: 0.02 | S83: 0.09724 | T83: 0.28625 | U83: 0.4145 | V83: 0.5 | W83: 0 | X83: 0 | Y83: 0 | Z83: 0 | AA83: 0
A84: The Clarendon Hotel and Spa | B84: Hotel | C84: NO | D84: 105 | F84: No Valet | G84: 0 | H84: 3 | I84: 1 | J84: 2 | K84: 4 | L84: 2 | M84: 0 | O84: 2.3 | P84: 2.3 | Q84: D — Deprioritized | R84: 0 | S84: 0.018 | T84: 0.055 | U84: 0.082 | V84: 0.1 | W84: 0 | X84: 0 | Y84: 0 | Z84: 0 | AA84: 0
A85: Fairfield Inn & Suites Phoenix Midtown | B85: Hotel | C85: NO | D85: 107 | F85: No Valet | G85: 0 | H85: 3 | I85: 1 | J85: 2 | K85: 4 | L85: 2 | M85: 0.3 | N85: Brand familiarity (current): Marriott_family | O85: 2.3 | P85: 2.6 | Q85: C — Opportunistic | R85: 0.02 | S85: 0.09724 | T85: 0.28625 | U85: 0.4145 | V85: 0.5 | W85: 0 | X85: 0 | Y85: 0 | Z85: 0 | AA85: 0
A86: Hilton Garden Inn Phoenix Midtown | B86: Hotel | C86: NO | D86: 156 | G86: 0 | H86: 3 | I86: 1 | J86: 3 | K86: 4 | L86: 2 | M86: 0.15 | N86: Brand familiarity (historical): Hilton_family | O86: 2.5 | P86: 2.65 | Q86: C — Opportunistic | R86: 0.02 | S86: 0.09724 | T86: 0.28625 | U86: 0.4145 | V86: 0.5 | W86: 0 | X86: 0 | Y86: 0 | Z86: 0 | AA86: 0
A87: JW Marriott Phoenix Desert Ridge Resort & Spa | B87: Hotel | C87: NO | D87: 950 | F87: 46 | G87: 4719600 | H87: 5 | I87: 5 | J87: 3 | K87: 4 | L87: 2 | M87: 0.3 | N87: Brand familiarity (current): Marriott_family | O87: 4 | P87: 4.3 | Q87: B — Core | R87: 0.08 | S87: 0.22066 | T87: 0.560625 | U87: 0.78675 | V87: 0.9375 | W87: 377568 | X87: 1041426.9 | Y87: 2645925.8 | Z87: 3713145.3 | AA87: 4424625
A88: Marriott's Canyon Villas | B88: Hotel | C88: NO | D88: 252 | F88: No Valet | G88: 0 | H88: 4 | I88: 1 | J88: 3 | K88: 4 | L88: 2 | M88: 0.3 | N88: Brand familiarity (current): Marriott_family | O88: 2.75 | P88: 3.05 | Q88: C — Opportunistic | R88: 0.02 | S88: 0.09724 | T88: 0.28625 | U88: 0.4145 | V88: 0.5 | W88: 0 | X88: 0 | Y88: 0 | Z88: 0 | AA88: 0
A89: Fairmont Gold Lounge | B89: Hotel | C89: NO | D89: 0 | G89: 0 | H89: 2 | I89: 1 | J89: 2 | K89: 4 | L89: 2 | M89: 0 | O89: 2.05 | P89: 2.05 | Q89: D — Deprioritized | R89: 0 | S89: 0.018 | T89: 0.055 | U89: 0.082 | V89: 0.1 | W89: 0 | X89: 0 | Y89: 0 | Z89: 0 | AA89: 0
A90: AC Hotel Scottsdale North | B90: Hotel | C90: NO | D90: 165 | F90: No Valet | G90: 0 | H90: 3 | I90: 1 | J90: 2 | K90: 4 | L90: 2 | M90: 0 | O90: 2.3 | P90: 2.3 | Q90: D — Deprioritized | R90: 0 | S90: 0.018 | T90: 0.055 | U90: 0.082 | V90: 0.1 | W90: 0 | X90: 0 | Y90: 0 | Z90: 0 | AA90: 0
A91: Courtyard Scottsdale Old Town | B91: Hotel | C91: NO | D91: 180 | F91: No Valet | G91: 0 | H91: 3 | I91: 1 | J91: 3 | K91: 4 | L91: 2 | M91: 0 | O91: 2.5 | P91: 2.5 | Q91: C — Opportunistic | R91: 0.02 | S91: 0.09724 | T91: 0.28625 | U91: 0.4145 | V91: 0.5 | W91: 0 | X91: 0 | Y91: 0 | Z91: 0 | AA91: 0
A92: Scottsdale Marriott Old Town | B92: Hotel | C92: NO | D92: 243 | F92: No Valet | G92: 0 | H92: 3 | I92: 1 | J92: 3 | K92: 4 | L92: 2 | M92: 0.3 | N92: Brand familiarity (current): Marriott_family | O92: 2.5 | P92: 2.8 | Q92: C — Opportunistic | R92: 0.02 | S92: 0.09724 | T92: 0.28625 | U92: 0.4145 | V92: 0.5 | W92: 0 | X92: 0 | Y92: 0 | Z92: 0 | AA92: 0
A93: The Monarch | B93: Hotel | C93: NO | D93: 194 | F93: No Valet | G93: 0 | H93: 3 | I93: 1 | J93: 2 | K93: 4 | L93: 2 | M93: 0 | O93: 2.3 | P93: 2.3 | Q93: D — Deprioritized | R93: 0 | S93: 0.018 | T93: 0.055 | U93: 0.082 | V93: 0.1 | W93: 0 | X93: 0 | Y93: 0 | Z93: 0 | AA93: 0
A94: Hotel Adeline, Scottsdale, a Tribute Portfolio Hotel | B94: Hotel | C94: NO | D94: 213 | F94: No Valet | G94: 0 | H94: 3 | I94: 1 | J94: 2 | K94: 4 | L94: 2 | M94: 0.3 | N94: Brand familiarity (current): Marriott_family | O94: 2.3 | P94: 2.6 | Q94: C — Opportunistic | R94: 0.02 | S94: 0.09724 | T94: 0.28625 | U94: 0.4145 | V94: 0.5 | W94: 0 | X94: 0 | Y94: 0 | Z94: 0 | AA94: 0
A95: Embassy Suites by Hilton Scottsdale Resort | B95: Hotel | C95: NO | D95: 312 | F95: No Valet | G95: 0 | H95: 4 | I95: 1 | J95: 3 | K95: 4 | L95: 2 | M95: 0.15 | N95: Brand familiarity (historical): Hilton_family | O95: 2.75 | P95: 2.9 | Q95: C — Opportunistic | R95: 0.02 | S95: 0.09724 | T95: 0.28625 | U95: 0.4145 | V95: 0.5 | W95: 0 | X95: 0 | Y95: 0 | Z95: 0 | AA95: 0
A96: Senna House Hotel Scottsdale, Curio Collection by Hilton | B96: Hotel | C96: NO | D96: 169 | E96: Epic | F96: 40 | G96: 219024 | H96: 3 | I96: 1 | J96: 3 | K96: 3 | L96: 2 | M96: 0.15 | N96: Brand familiarity (historical): Hilton_family | O96: 2.35 | P96: 2.5 | Q96: C — Opportunistic | R96: 0.02 | S96: 0.09724 | T96: 0.28625 | U96: 0.4145 | V96: 0.5 | W96: 4380.48 | X96: 21297.894 | Y96: 62695.62 | Z96: 90785.448 | AA96: 109512
A97: The REMI Scottsdale, Autograph Collection | B97: Hotel | C97: NO | D97: 0 | F97: Valet Only | G97: 0 | H97: 2 | I97: 1 | J97: 3 | K97: 4 | L97: 2 | M97: 0.3 | N97: Brand familiarity (current): Marriott_family | O97: 2.25 | P97: 2.55 | Q97: C — Opportunistic | R97: 0.02 | S97: 0.09724 | T97: 0.28625 | U97: 0.4145 | V97: 0.5 | W97: 0 | X97: 0 | Y97: 0 | Z97: 0 | AA97: 0
A98: Caesars Republic Scottsdale, a Hilton Hotel | B98: Hotel | C98: NO | D98: 265 | F98: 40 | G98: 343440 | H98: 4 | I98: 2 | J98: 3 | K98: 4 | L98: 2 | M98: 0.15 | N98: Brand familiarity (historical): Hilton_family | O98: 3 | P98: 3.15 | Q98: C — Opportunistic | R98: 0.02 | S98: 0.09724 | T98: 0.28625 | U98: 0.4145 | V98: 0.5 | W98: 6868.8 | X98: 33396.106 | Y98: 98309.7 | Z98: 142355.88 | AA98: 171720
A99: DoubleTree Resort by Hilton Paradise Valley-Scottsdale | B99: Hotel | C99: NO | D99: 378 | F99: 20 | G99: 816480 | H99: 4 | I99: 3 | J99: 3 | K99: 4 | L99: 2 | M99: 0.15 | N99: Brand familiarity (historical): Hilton_family | O99: 3.25 | P99: 3.4 | Q99: C — Opportunistic | R99: 0.02 | S99: 0.09724 | T99: 0.28625 | U99: 0.4145 | V99: 0.5 | W99: 16329.6 | X99: 79394.515 | Y99: 233717.4 | Z99: 338430.96 | AA99: 408240
A100: Home2 Suites by Hilton Scottsdale North | B100: Hotel | C100: NO | D100: 130 | G100: 0 | H100: 3 | I100: 1 | J100: 3 | K100: 4 | L100: 2 | M100: 0.15 | N100: Brand familiarity (historical): Hilton_family | O100: 2.5 | P100: 2.65 | Q100: C — Opportunistic | R100: 0.02 | S100: 0.09724 | T100: 0.28625 | U100: 0.4145 | V100: 0.5 | W100: 0 | X100: 0 | Y100: 0 | Z100: 0 | AA100: 0
A101: Courtyard Scottsdale North | B101: Hotel | C101: NO | D101: 153 | F101: No Valet | G101: 0 | H101: 3 | I101: 1 | J101: 3 | K101: 4 | L101: 2 | M101: 0 | O101: 2.5 | P101: 2.5 | Q101: C — Opportunistic | R101: 0.02 | S101: 0.09724 | T101: 0.28625 | U101: 0.4145 | V101: 0.5 | W101: 0 | X101: 0 | Y101: 0 | Z101: 0 | AA101: 0
A102: Cambria Hotel Phoenix - North Scottsdale | B102: Hotel | C102: NO | D102: 130 | F102: No Valet | G102: 0 | H102: 3 | I102: 1 | J102: 2 | K102: 4 | L102: 2 | M102: 0 | O102: 2.3 | P102: 2.3 | Q102: D — Deprioritized | R102: 0 | S102: 0.018 | T102: 0.055 | U102: 0.082 | V102: 0.1 | W102: 0 | X102: 0 | Y102: 0 | Z102: 0 | AA102: 0
A103: Great Wolf Lodge Water Park | Arizona | B103: Hotel | C103: NO | D103: 0 | F103: No Valet | G103: 0 | H103: 2 | I103: 1 | J103: 2 | K103: 4 | L103: 2 | M103: 0 | O103: 2.05 | P103: 2.05 | Q103: D — Deprioritized | R103: 0 | S103: 0.018 | T103: 0.055 | U103: 0.082 | V103: 0.1 | W103: 0 | X103: 0 | Y103: 0 | Z103: 0 | AA103: 0
A104: Residence Inn Scottsdale North | B104: Hotel | C104: NO | D104: 120 | F104: No Valet | G104: 0 | H104: 3 | I104: 1 | J104: 3 | K104: 4 | L104: 2 | M104: 0.3 | N104: Brand familiarity (current): Marriott_family | O104: 2.5 | P104: 2.8 | Q104: C — Opportunistic | R104: 0.02 | S104: 0.09724 | T104: 0.28625 | U104: 0.4145 | V104: 0.5 | W104: 0 | X104: 0 | Y104: 0 | Z104: 0 | AA104: 0
A105: Orange Tree Resort | B105: Hotel | C105: NO | D105: 0 | F105: No Valet | G105: 0 | H105: 2 | I105: 1 | J105: 2 | K105: 4 | L105: 2 | M105: 0 | O105: 2.05 | P105: 2.05 | Q105: D — Deprioritized | R105: 0 | S105: 0.018 | T105: 0.055 | U105: 0.082 | V105: 0.1 | W105: 0 | X105: 0 | Y105: 0 | Z105: 0 | AA105: 0
A106: The Westin Kierland Resort & Spa | B106: Hotel | C106: NO | D106: 735 | F106: 40 | G106: 3175200 | H106: 5 | I106: 5 | J106: 3 | K106: 4 | L106: 2 | M106: 0.3 | N106: Brand familiarity (current): Marriott_family | O106: 4 | P106: 4.3 | Q106: B — Core | R106: 0.08 | S106: 0.22066 | T106: 0.560625 | U106: 0.78675 | V106: 0.9375 | W106: 254016 | X106: 700639.63 | Y106: 1780096.5 | Z106: 2498088.6 | AA106: 2976750
A107: Fairmont Scottsdale Princess | B107: Hotel | C107: NO | D107: 750 | F107: 40 | G107: 972000 | H107: 5 | I107: 3 | J107: 2 | K107: 4 | L107: 2 | M107: 0 | O107: 3.3 | P107: 3.3 | Q107: C — Opportunistic | R107: 0.02 | S107: 0.09724 | T107: 0.28625 | U107: 0.4145 | V107: 0.5 | W107: 19440 | X107: 94517.28 | Y107: 278235 | Z107: 402894 | AA107: 486000
A108: Grand Hyatt Scottsdale Resort | B108: Hotel | C108: NO | D108: 496 | F108: Has Valet | G108: 1607040 | H108: 4 | I108: 4 | J108: 3 | K108: 4 | L108: 2 | M108: 0 | O108: 3.5 | P108: 3.5 | Q108: B — Core | R108: 0.08 | S108: 0.22066 | T108: 0.560625 | U108: 0.78675 | V108: 0.9375 | W108: 128563.2 | X108: 354609.45 | Y108: 900946.8 | Z108: 1264338.7 | AA108: 1506600
A109: The Global Ambassador | B109: Hotel | C109: NO | D109: 141 | F109: 35 | G109: 159894 | H109: 3 | I109: 1 | J109: 2 | K109: 4 | L109: 2 | M109: 0 | O109: 2.3 | P109: 2.3 | Q109: D — Deprioritized | R109: 0 | S109: 0.018 | T109: 0.055 | U109: 0.082 | V109: 0.1 | W109: 0 | X109: 2878.092 | Y109: 8794.17 | Z109: 13111.308 | AA109: 15989.4
A110: SpringHill Suites Scottsdale North | B110: Hotel | C110: NO | D110: 121 | F110: No Valet | G110: 0 | H110: 3 | I110: 1 | J110: 2 | K110: 4 | L110: 2 | M110: 0.3 | N110: Brand familiarity (current): Marriott_family | O110: 2.3 | P110: 2.6 | Q110: C — Opportunistic | R110: 0.02 | S110: 0.09724 | T110: 0.28625 | U110: 0.4145 | V110: 0.5 | W110: 0 | X110: 0 | Y110: 0 | Z110: 0 | AA110: 0
A111: SpringHill Suites Phoenix Scottsdale | B111: Hotel | C111: NO | D111: 0 | G111: 0 | H111: 2 | I111: 1 | J111: 2 | K111: 4 | L111: 2 | M111: 0.3 | N111: Brand familiarity (current): Marriott_family | O111: 2.05 | P111: 2.35 | Q111: D — Deprioritized | R111: 0 | S111: 0.018 | T111: 0.055 | U111: 0.082 | V111: 0.1 | W111: 0 | X111: 0 | Y111: 0 | Z111: 0 | AA111: 0
A112: Hilton Garden Inn Scottsdale Old Town | B112: Hotel | C112: NO | D112: 199 | G112: 0 | H112: 3 | I112: 1 | J112: 3 | K112: 4 | L112: 2 | M112: 0.15 | N112: Brand familiarity (historical): Hilton_family | O112: 2.5 | P112: 2.65 | Q112: C — Opportunistic | R112: 0.02 | S112: 0.09724 | T112: 0.28625 | U112: 0.4145 | V112: 0.5 | W112: 0 | X112: 0 | Y112: 0 | Z112: 0 | AA112: 0
A113: The Scott Resort & Spa | B113: Hotel | C113: NO | D113: 204 | F113: No Valet | G113: 0 | H113: 3 | I113: 1 | J113: 2 | K113: 4 | L113: 2 | M113: 0 | O113: 2.3 | P113: 2.3 | Q113: D — Deprioritized | R113: 0 | S113: 0.018 | T113: 0.055 | U113: 0.082 | V113: 0.1 | W113: 0 | X113: 0 | Y113: 0 | Z113: 0 | AA113: 0
A114: Hyatt Place Scottsdale - North | B114: Hotel | C114: NO | D114: 136 | F114: No Valet | G114: 0 | H114: 3 | I114: 1 | J114: 3 | K114: 4 | L114: 2 | M114: 0 | O114: 2.5 | P114: 2.5 | Q114: C — Opportunistic | R114: 0.02 | S114: 0.09724 | T114: 0.28625 | U114: 0.4145 | V114: 0.5 | W114: 0 | X114: 0 | Y114: 0 | Z114: 0 | AA114: 0
A115: The McCormick Scottsdale | B115: Hotel | C115: NO | D115: 125 | F115: No Valet | G115: 0 | H115: 3 | I115: 1 | J115: 2 | K115: 4 | L115: 2 | M115: 0 | O115: 2.3 | P115: 2.3 | Q115: D — Deprioritized | R115: 0 | S115: 0.018 | T115: 0.055 | U115: 0.082 | V115: 0.1 | W115: 0 | X115: 0 | Y115: 0 | Z115: 0 | AA115: 0
...

Sheet SOM_Summary_v2
A1: Phoenix — WAS v2 SOM Projection (state = COLD)
A2: Cold/Warm curves · S-curve ramp · Diversification multiplier · Relationship ledger
A4: Tier | B4: # Accts | C4: Total TAM | D4: Y1 | E4: Y2 | F4: Y3 | G4: Y4 | H4: Y5
A5: A — Beachhead | B5: 0 | C5: 0 | D5: 0 | E5: 0 | F5: 0 | G5: 0 | H5: 0
A6: B — Core | B6: 11 | C6: 22726841 | D6: 1818147.3 | E6: 5014904.7 | F6: 12741235 | G6: 17880342 | H6: 21306413
A7: C — Opportunistic | B7: 132 | C7: 15400678 | D7: 308013.57 | E7: 1497562 | F7: 4408444.2 | G7: 6383581.2 | H7: 7700339.2
A8: D — Deprioritized | B8: 222 | C8: 902497.95 | D8: 0 | E8: 16244.963 | F8: 49637.387 | G8: 74004.832 | H8: 90249.795
A9: TOTAL (uncapped) | B9: 365 | C9: 39030017 | D9: 2126160.8 | E9: 6528711.7 | F9: 17199317 | G9: 24337928 | H9: 29097002
A11: CAPACITY-CAPPED SOM (single CM, 10 new accts/yr)
A12: Tier A+B, ranked by Y1 rev, cumulative 10/yr signing pace
B13: Accts Signed | D13: Y1 SOM | E13: Y2 SOM | F13: Y3 SOM | G13: Y4 SOM | H13: Y5 SOM
B14: End Y1: 10 | D14: 1818147.3
B15: End Y2: 20 | E15: 5690692.8
B16: End Y3: 30 | F16: 15967596
B17: End Y4: 40 | G17: 23862784
B18: End Y5: 50 | H18: 29006753
A20: BY ACCOUNT TYPE (uncapped)
A21: Type | B21: Count | C21: TAM | D21: Y1 | E21: Y3 | F21: Y5
A22: Hotel | B22: 237 | C22: 37116392 | D22: 2083332.1 | E22: 16703953 | F22: 28240143
A23: Restaurant | B23: 86 | C23: 1913625 | D23: 42828.75 | E23: 495364.04 | F23: 856859.77
A24: Apartment | B24: 1 | C24: 0 | D24: 0 | E24: 0 | F24: 0
A25: Apartment/Hotel | B25: 2 | C25: 0 | D25: 0 | E25: 0 | F25: 0
A26: Event | B26: 13 | C26: 0 | D26: 0 | E26: 0 | F26: 0
A27: Golf | B27: 3 | C27: 0 | D27: 0 | E27: 0 | F27: 0
A28: Hospitality Group | B28: 12 | C28: 0 | D28: 0 | E28: 0 | F28: 0
A29: Villas | B29: 2 | C29: 0 | D29: 0 | E29: 0 | F29: 0
A30: Wedding Planner | B30: 9 | C30: 0 | D30: 0 | E30: 0 | F30: 0

Sheet Methodology_v2
A1: WAS v2 METHODOLOGY — SOPHI MOBILITY
A3: Market state: COLD (Warm = ≥3 current SOPHI anchor accounts in-market)
A5: CONVERSION CURVES (Y1 rate → Y5 rate per tier)
A6: Cold — A: 40% → 95%
A7: B: 8% → 75%
A8: C: 2% → 40%
A9: D: 0% → 10%
A10: Warm — A: 60% → 95%
A11: B: 25% → 80%
A12: C: 10% → 45%
A13: D: 0% → 15%
A15: S-CURVE ANNUAL RAMP (fraction of Y5-Y1 captured per year)
... A33: Source: config/relationships.yaml
